Workbook

Sheet Processed_Ratios
A1: DILUTED EPS | B1: 2025 | C1: 2024 | D1: 2023 | E1: 2022 | F1: 2021 | G1: 2020 | H1: 2019 | I1: 2018 | J1: 2017 | K1: 2016 | L1: 2015 | M1: 2014
A2: Adani Ports and Special Economic Zone Ltd | B2: 51.35 | C2: 37.55 | D2: 24.58 | E2: 22.39 | F2: 24.58 | G2: 18.35 | H2: 19.27 | I2: 17.74 | J2: 18.89 | K2: 13.99 | L2: 11.18 | M2: 8.45
A3: Asian Paints Ltd | B3: 38.25 | C3: 56.94 | D3: 42.82 | E3: 31.59 | F3: 32.73 | G3: 28.2 | H3: 22.48 | I3: 21.26 | J3: 20.22 | K3: 18.19 | L3: 14.54 | M3: 12.71
A4: AXIS Bank Ltd | B4: 90.18 | C4: 85.01 | D4: 35.04 | E4: 45.91 | F4: 24.19 | G4: 6.8 | H4: 19.49 | I4: 2.1015 | J4: 16.48 | K4: 34.93 | L4: 31.23 | M4: 134.2
A5: Bajaj Finserv Ltd | B5: 9.7 | C5: 7.3 | D5: 4.6 | E5: 26.6 | F5: 11.2 | G5: 41.9 | H5: 19.3 | I5: 8.9 | J5: 4.4 | K5: 10.3 | L5: 7.9 | M5: 5.2
A6: Bajaj Finance Ltd | B6: 187.439 | C6: 187.439 | D6: 187.439 | E6: 115.79 | F6: 73 | G6: 89.07 | H6: 68.75 | I6: 47.05 | J6: 33.67 | K6: 187.439 | L6: 177.7 | M6: 143.65
A7: Bharat Electronics Ltd | B7: 7.28 | C7: 5.45 | D7: 4.09 | E7: 9.85 | F7: 8.62 | G7: 7.49 | H7: 7.74 | I7: 5.83 | J7: 5.94 | K7: 5.57 | L7: 149.65 | M7: 118.91
A8: Bharti Airtel Ltd | B8: 56.04 | C8: 12.8 | D8: 14.57 | E8: 7.63 | F8: 2.1015 | G8: 2.1015 | H8: 2.1015 | I8: 2.75 | J8: 9.51 | K8: 15.2 | L8: 11.56 | M8: 7.01
A9: HCL Technologies Ltd | B9: 64.09 | C9: 57.86 | D9: 54.79 | E9: 49.77 | F9: 41.07 | G9: 40.75 | H9: 73.55 | I9: 62.19 | J9: 60.27 | K9: 39.69 | L9: 51.79 | M9: 91.93
A10: HDFC Bank Ltd | B10: 92.39 | C10: 90.01 | D10: 82.27 | E10: 68.31 | F10: 57.61 | G10: 49.46 | H10: 82.51 | I10: 70.76 | J10: 59.16 | K10: 50.24 | L10: 43.6 | M10: 36.31
A11: Hindustan Unilever Ltd | B11: 45.32 | C11: 43.74 | D11: 43.07 | E11: 37.79 | F11: 34.03 | G11: 31.17 | H11: 27.96 | I11: 24.08 | J11: 20.67 | K11: 19.09 | L11: 20.16 | M11: 18.23
A12: ICICI Bank Ltd | B12: 71.14 | C12: 61.96 | D12: 47.84 | E12: 35.44 | F12: 26.83 | G12: 14.55 | H12: 6.53 | I12: 11.89 | J12: 15.84 | K12: 17.41 | L12: 21.17 | M12: 95.65
... A30: UltraTech Cement Ltd | B30: 187.439 | C30: 187.439 | D30: 175.54 | E30: 187.439 | F30: 187.439 | G30: 187.439 | H30: 84 | I30: 80.92 | J30: 98.88 | K30: 90.25 | L30: 76.44 | M30: 80.42
A32: Max | B32: =MAX(E2:M30) -> 187.439
A34: PAYOUT RATIO | B34: (PR)2025 | C34: (PR)2024 | D34: (PR)2023 | E34: (PR)2022 | F34: (PR)2021 | G34: (PR)2020 | H34: (PR)2019 | I34: (PR)2018 | J34: (PR)2017 | K34: (PR)2016 | L34: (PR)2015 | M34: (PR)2014
A35: Adani Ports and Special Economic Zone Ltd | B35: 11.68 | C35: 13.31 | D35: 19.88 | E35: 21.59 | F35: 0 | G35: 18.37 | H35: 10.38 | I35: 7.32 | J35: 0 | K35: 15.72 | L35: 9.83 | M35: 12.28
A36: Asian Paints Ltd | B36: 84.74 | C36: 46.37 | D36: 46.48 | E36: 57.44 | F36: 10.23 | G36: 64.35 | H36: 39.59 | I36: 48.45 | J36: 39.31 | K36: 35.72 | L36: 41.93 | M36: 41.71
A37: AXIS Bank Ltd | B37: 1.19 | C37: 1.25 | D37: 3.25 | E37: 1.24 | F37: 1.52 | G37: 1.25 | H37: 2.33 | I37: 1.39 | J37: 1.53 | K37: 1.09 | L37: 1.005 | M37: 1.32
A38: Bajaj Finserv Ltd | B38: 1.79 | C38: 1.56 | D38: 0.99 | E38: 1.04 | F38: 0 | G38: 3.54 | H38: 0.86 | I38: 1.05 | J38: 0 | K38: 1.49 | L38: 1.64 | M38: 1.8
A39: Bajaj Finance Ltd | B39: 13.38 | C39: 12.56 | D39: 10.49 | E39: 8.57 | F39: 0 | G39: 18.04 | H39: 5.78 | I39: 7.4 | J39: 0 | K39: 10.99 | L39: 10.05 | M39: 11.15
A40: Bharat Electronics Ltd | B40: 31.59 | C40: 36.69 | D40: 41.63 | E40: 42.65 | F40: 48.75 | G40: 41.41 | H40: 27.12 | I40: 43.83 | J40: 40.43 | K40: 18.36 | L40: 19.51 | M40: 19.59
A41: Bharti Airtel Ltd | B41: 13.79 | C41: 30.47 | D41: 20.34 | E41: 0 | F41: 0 | G41: 0 | H41: 87.981 | I41: 87.981 | J41: 17.21 | K41: 17.57 | L41: 33.3 | M41: 0
A42: HCL Technologies Ltd | B42: 87.981 | C42: 87.981 | D42: 87.5 | E42: 84.38 | F42: 29.22 | G42: 12.27 | H42: 10.85 | I42: 19.4 | J42: 39.34 | K42: 48.15 | L42: 32.6 | M42: 10.75
A43: HDFC Bank Ltd | B43: 25.05 | C43: 24.38 | D43: 24.07 | E43: 23.28 | F43: 11.54 | G43: 0 | H43: 18.63 | I43: 19.32 | J43: 20.84 | K43: 20.67 | L43: 0 | M43: 0
A44: Hindustan Unilever Ltd | B44: 87.981 | C44: 87.981 | D44: 83.58 | E44: 84.68 | F44: 87.981 | G44: 77 | H44: 75.09 | I44: 74.72 | J44: 79.78 | K44: 81.03 | L44: 74.38 | M44: 71.25
A45: ICICI Bank Ltd | B45: 15.4 | C45: 15.9 | D45: 16.4 | E45: 13.8 | F45: 7.5 | G45: 0 | H45: 15 | I45: 12 | J45: 14 | K45: 29 | L45: 24 | M45: 24
A46: Infosys Ltd | B46: 75.97 | C46: 56 | D46: 56.57 | E46: 57.23 | F46: 47.12 | G46: 57.35 | H46: 87.981 | I46: 46.59 | J46: 48.43 | K46: 50.51 | L46: 41.14 | M46: 33.83
... A63: UltraTech Cement Ltd | B63: 33.4 | C63: 15.63 | D63: 21.57 | E63: 14.52 | F63: 6.86 | G63: 6.61 | H63: 14.46 | I63: 14.86 | J63: 9.6 | K63: 11.83 | L63: 11.77 | M63: 11.18
A65: Max | B65: =MAX(E35:M63) -> 87.981
A67: PROFIT MARGIN | B67: (PM)2025 | C67: (PM)2024 | D67: (PM)2023 | E67: (PM)2022 | F67: (PM)2021 | G67: (PM)2020 | H67: (PM)2019 | I67: (PM)2018 | J67: (PM)2017 | K67: (PM)2016 | L67: (PM)2015 | M67: (PM)2014
A68: Adani Ports and Special Economic Zone Ltd | B68: 8.22 | C68: 8.7525 | D68: 6.55 | E68: 8.7525 | F68: 8.7525 | G68: 4.3 | H68: 7.17 | I68: 6.49 | J68: 8.34 | K68: 7.22 | L68: 8.7525 | M68: 8.05
A69: Asian Paints Ltd | B69: 6.61 | C69: 7.69 | D69: 7.68 | E69: 8.7525 | F69: 8.7525 | G69: 7.91 | H69: 7.44 | I69: 6.39 | J69: 6.82 | K69: 5.84 | L69: 5.47 | M69: 4.12
A70: AXIS Bank Ltd | B70: 2.68 | C70: 2.87 | D70: 3.02 | E70: 3.39 | F70: 3.3 | G70: 1.68 | H70: 3.56 | I70: 2.8 | J70: 2.6 | K70: 2.56 | L70: 3.72 | M70: 2.23
A71: Bajaj Finserv Ltd | B71: 2.39 | C71: 2.37 | D71: 2.46 | E71: 3.97 | F71: 2.54 | G71: 1.34 | H71: 2.63 | I71: 2.51 | J71: 2.65 | K71: 2.87 | L71: 2.91 | M71: 2.09
A72: Bajaj Finance Ltd | B72: 7.97 | C72: 8.14 | D72: 8.2 | E72: 8.7525 | F72: 8.7525 | G72: 5.04 | H72: 8.7525 | I72: 7.57 | J72: 6.44 | K72: 5.08 | L72: 3.81 | M72: 2.05
A73: Bharat Electronics Ltd | B73: 8.7525 | C73: 7.27 | D73: 4.02 | E73: 3.34 | F73: 2.16 | G73: 1.4 | H73: 1.87 | I73: 3.33 | J73: 4.03 | K73: 3.98 | L73: 3.78 | M73: 1.4
A74: Bharti Airtel Ltd | B74: 5.8 | C74: 4.71 | D74: 3.05 | E74: 3.62 | F74: 2.82 | G74: 2.75 | H74: 1.65 | I74: 1.9 | J74: 1.46 | K74: 1.45 | L74: 1.64 | M74: 1.46
A75: HCL Technologies Ltd | B75: 3.69 | C75: 3.81 | D75: 2.91 | E75: 3.69 | F75: 3.54 | G75: 1.68 | H75: 2.44 | I75: 2.66 | J75: 2.62 | K75: 3.69 | L75: 3.53 | M75: 3.26
A76: HDFC Bank Ltd | B76: 4.66 | C76: 4.26 | D76: 5.56 | E76: 6.38 | F76: 6.81 | G76: 4.12 | H76: 6.37 | I76: 6.12 | J76: 5.33 | K76: 4.5 | L76: 5.29 | M76: 4.37
A77: Hindustan Unilever Ltd | B77: 8.41 | C77: 8.61 | D77: 8.7525 | E77: 8.7525 | F77: 8.7525 | G77: 8.7525 | H77: 8.7525 | I77: 8.12 | J77: 5.93 | K77: 5.84 | L77: 5.91 | M77: 4.47
A78: ICICI Bank Ltd | B78: 5.15 | C78: 4.82 | D78: 5.06 | E78: 5.32 | F78: 4.51 | G78: 2.48 | H78: 3.57 | I78: 2.88 | J78: 2.65 | K78: 2.32 | L78: 3.33 | M78: 2.91
A79: Infosys Ltd | B79: 3.99 | C79: 4.04 | D79: 4.03 | E79: 6.58 | F79: 5.78 | G79: 2.99 | H79: 3.9 | I79: 3.5 | J79: 3.41 | K79: 4.46 | L79: 4.76 | M79: 3.74
... A96: UltraTech Cement Ltd | B96: 4.46 | C96: 3.97 | D96: 3.48 | E96: 3.62 | F96: 4.35 | G96: 2.21 | H96: 2.64 | I96: 3.5 | J96: 4.32 | K96: 3.52 | L96: 3.24 | M96: 2.77
A98: Max | B98: =MAX(E68:M96) -> 8.7525
A100: DEBT TO EQUITY | B100: 2025 | C100: 2024 | D100: 2023 | E100: 2022 | F100: 2021 | G100: 2020 | H100: 2019 | I100: 2018 | J100: 2017 | K100: 2016 | L100: 2015 | M100: 2014
A101: Adani Ports and Special Economic Zone Ltd | B101: 0.54812141 | C101: 0.62593843 | D101: 0.73716407 | E101: 0.78390154 | F101: 0.75612198 | G101: 0.73716407 | H101: 0.72754861 | I101: 0.69813472 | J101: 0.78845736 | K101: 0.87546874 | L101: 0.87962675 | M101: 0.84586827
A102: Asian Paints Ltd | B102: 0.039220713 | C102: 0.058268908 | D102: 0.058268908 | E102: 0.058268908 | F102: 0.029558802 | G102: 0.029558802 | H102: 0.067658648 | I102: 0.058268908 | J102: 0.067658648 | K102: 0.048790164 | L102: 0.086177696 | M102: 0.058268908
A103: AXIS Bank Ltd | B103: 2.1838016 | C103: 2.2710944 | D103: 2.3408438 | E103: 2.3145137 | F103: 2.2679936 | G103: 2.1972246 | H103: 2.484073 | I103: 2.3721112 | J103: 2.3786198 | K103: 2.2905125 | L103: 2.3350523 | M103: 2.3085672
A104: Bajaj Finserv Ltd | B104: 1.773256 | C104: 1.7526721 | D104: 1.7155981 | E104: 1.6074359 | F104: 1.5195132 | G104: 1.6174061 | H104: 1.6486586 | I104: 1.4447642 | J104: 1.4447642 | K104: 1.4447642 | L104: 1.4447642 | M104: 1.4447642
A105: Bajaj Finance Ltd | B105: 1.5560371 | C105: 1.5727739 | D105: 1.6074359 | E105: 1.5644405 | F105: 1.5195132 | G105: 1.6134299 | H105: 1.8180768 | I105: 1.4861397 | J105: 1.6826884 | K105: 1.7900914 | L105: 1.742219 | M105: 1.8196988
A106: Bharat Electronics Ltd | B106: 0.78845736 | C106: 0.75612198 | D106: 0.74193734 | E106: 0.65752 | F106: 0.5988365 | G106: 0.87962675 | H106: 0.81536481 | I106: 0.48858001 | J106: 0.54812141 | K106: 0.44468582 | L106: 0.53062825 | M106: 0.57661336
A107: Bharti Airtel Ltd | B107: 0.75612198 | C107: 0.91629073 | D107: 1.0367369 | E107: 1.0986123 | F107: 1.1391037 | G107: 0.9242589 | H107: 0.98954119 | I107: 0.87962675 | J107: 0.9242589 | K107: 0.91629073 | L107: 1.0152307 | M107: 0.81977983
A108: HCL Technologies Ltd | B108: 0.029558802 | C108: 0.029558802 | D108: 0.029558802 | E108: 0.058268908 | F108: 0.058268908 | G108: 0.086177696 | H108: 0.086177696 | I108: 0.029558802 | J108: 0.029558802 | K108: 0.029558802 | L108: 0.029558802 | M108: 0.029558802
A109: HDFC Bank Ltd | B109: 1.9837563 | C109: 2.0943302 | D109: 2.1747517 | E109: 2.1494339 | F109: 2.1494339 | G109: 2.1882959 | H109: 2.1317968 | I109: 2.3194422 | J109: 2.1994443 | K109: 2.184927 | L109: 2.2628042 | M109: 2.4300984
A110: Hindustan Unilever Ltd | B110: 0.44468582 | C110: 0.45107562 | D110: 0.43178242 | E110: 0.41871033 | F110: 0.39877612 | G110: 0.97077892 | H110: 0.86710049 | I110: 0.87962675 | J110: 0.9439059 | K110: 0.85015093 | L110: 1.0784096 | M110: 1.1391037
A111: ICICI Bank Ltd | B111: 2.2894999 | C111: 2.2945529 | D111: 2.1598688 | E111: 2.2115657 | F111: 2.2310891 | G111: 2.3398809 | H111: 2.3155013 | I111: 2.2648832 | J111: 2.2192035 | K111: 2.2181159 | L111: 2.2353763 | M111: 2.2289386
... A129: UltraTech Cement Ltd | B129: 0.28517894 | C129: 0.15700375 | D129: 0.16551444 | E129: 0.18232156 | F129: 0.33647224 | G129: 0.43825493 | H129: 0.62057649 | I129: 0.53649337 | J129: 0.27002714 | K129: 0.29266961 | L129: 0.33647224 | M129: 0.3435897
A131: max | B131: =MAX(E101:M129) -> 2.8068995

Sheet Fuzzy_Inputs_10
A1: DILUTED EPS | B1: 2025 | C1: 2024 | D1: 2023 | E1: 2022 | F1: 2021 | G1: 2020 | H1: 2019 | I1: 2018 | J1: 2017 | K1: 2016 | L1: 2015 | M1: 2014
A2: Adani Ports and Special Economic Zone Ltd | B2: =(Processed_Ratios!B2 / Processed_Ratios!$B$32) * 10 -> 2.7395579 | C2: =(Processed_Ratios!C2 / Processed_Ratios!$B$32) * 10 -> 2.0033184 | D2: =(Processed_Ratios!D2 / Processed_Ratios!$B$32) * 10 -> 1.31136 | E2: =(Processed_Ratios!E2 / Processed_Ratios!$B$32) * 10 -> 1.194522 | F2: =(Processed_Ratios!F2 / Processed_Ratios!$B$32) * 10 -> 1.31136 | G2: =(Processed_Ratios!G2 / Processed_Ratios!$B$32) * 10 -> 0.97898516 | H2: =(Processed_Ratios!H2 / Processed_Ratios!$B$32) * 10 -> 1.0280678 | I2: =(Processed_Ratios!I2 / Processed_Ratios!$B$32) * 10 -> 0.94644124 | ... M2: =(Processed_Ratios!M2 / Processed_Ratios!$B$32) * 10 -> 0.45081333
A3: Asian Paints Ltd | B3: =(Processed_Ratios!B3 / Processed_Ratios!$B$32) * 10 -> 2.0406639 | C3: =(Processed_Ratios!C3 / Processed_Ratios!$B$32) * 10 -> 3.0377883 | D3: =(Processed_Ratios!D3 / Processed_Ratios!$B$32) * 10 -> 2.2844765 | E3: =(Processed_Ratios!E3 / Processed_Ratios!$B$32) * 10 -> 1.6853483 | F3: =(Processed_Ratios!F3 / Processed_Ratios!$B$32) * 10 -> 1.7461681 | G3: =(Processed_Ratios!G3 / Processed_Ratios!$B$32) * 10 -> 1.5044895 | H3: =(Processed_Ratios!H3 / Processed_Ratios!$B$32) * 10 -> 1.1993235 | I3: =(Processed_Ratios!I3 / Processed_Ratios!$B$32) * 10 -> 1.1342357 | ... M3: =(Processed_Ratios!M3 / Processed_Ratios!$B$32) * 10 -> 0.67808727
A4: AXIS Bank Ltd | B4: =(Processed_Ratios!B4 / Processed_Ratios!$B$32) * 10 -> 4.8111652 | C4: =(Processed_Ratios!C4 / Processed_Ratios!$B$32) * 10 -> 4.5353422 | D4: =(Processed_Ratios!D4 / Processed_Ratios!$B$32) * 10 -> 1.8694082 | E4: =(Processed_Ratios!E4 / Processed_Ratios!$B$32) * 10 -> 2.4493302 | F4: =(Processed_Ratios!F4 / Processed_Ratios!$B$32) * 10 -> 1.2905532 | G4: =(Processed_Ratios!G4 / Processed_Ratios!$B$32) * 10 -> 0.36278469 | H4: =(Processed_Ratios!H4 / Processed_Ratios!$B$32) * 10 -> 1.0398049 | I4: =(Processed_Ratios!I4 / Processed_Ratios!$B$32) * 10 -> 0.11211648 | ... M4: =(Processed_Ratios!M4 / Processed_Ratios!$B$32) * 10 -> 7.1596626
A5: Bajaj Finserv Ltd | B5: =(Processed_Ratios!B5 / Processed_Ratios!$B$32) * 10 -> 0.51750169 | C5: =(Processed_Ratios!C5 / Processed_Ratios!$B$32) * 10 -> 0.38946004 | D5: =(Processed_Ratios!D5 / Processed_Ratios!$B$32) * 10 -> 0.24541317 | E5: =(Processed_Ratios!E5 / Processed_Ratios!$B$32) * 10 -> 1.4191284 | F5: =(Processed_Ratios!F5 / Processed_Ratios!$B$32) * 10 -> 0.59752773 | G5: =(Processed_Ratios!G5 / Processed_Ratios!$B$32) * 10 -> 2.2353939 | H5: =(Processed_Ratios!H5 / Processed_Ratios!$B$32) * 10 -> 1.0296683 | I5: =(Processed_Ratios!I5 / Processed_Ratios!$B$32) * 10 -> 0.47482114 | ... M5: =(Processed_Ratios!M5 / Processed_Ratios!$B$32) * 10 -> 0.27742359
A6: Bajaj Finance Ltd | B6: =(Processed_Ratios!B6 / Processed_Ratios!$B$32) * 10 -> 10 | C6: =(Processed_Ratios!C6 / Processed_Ratios!$B$32) * 10 -> 10 | D6: =(Processed_Ratios!D6 / Processed_Ratios!$B$32) * 10 -> 10 | E6: =(Processed_Ratios!E6 / Processed_Ratios!$B$32) * 10 -> 6.1774764 | F6: =(Processed_Ratios!F6 / Processed_Ratios!$B$32) * 10 -> 3.8946004 | G6: =(Processed_Ratios!G6 / Processed_Ratios!$B$32) * 10 -> 4.751946 | H6: =(Processed_Ratios!H6 / Processed_Ratios!$B$32) * 10 -> 3.6678599 | I6: =(Processed_Ratios!I6 / Processed_Ratios!$B$32) * 10 -> 2.51015 | ... M6: =(Processed_Ratios!M6 / Processed_Ratios!$B$32) * 10 -> 7.6638266
A7: Bharat Electronics Ltd | B7: =(Processed_Ratios!B7 / Processed_Ratios!$B$32) * 10 -> 0.38839302 | C7: =(Processed_Ratios!C7 / Processed_Ratios!$B$32) * 10 -> 0.29076126 | D7: =(Processed_Ratios!D7 / Processed_Ratios!$B$32) * 10 -> 0.21820432 | E7: =(Processed_Ratios!E7 / Processed_Ratios!$B$32) * 10 -> 0.5255043 | F7: =(Processed_Ratios!F7 / Processed_Ratios!$B$32) * 10 -> 0.45988295 | G7: =(Processed_Ratios!G7 / Processed_Ratios!$B$32) * 10 -> 0.39959667 | H7: =(Processed_Ratios!H7 / Processed_Ratios!$B$32) * 10 -> 0.41293434 | I7: =(Processed_Ratios!I7 / Processed_Ratios!$B$32) * 10 -> 0.31103452 | ... M7: =(Processed_Ratios!M7 / Processed_Ratios!$B$32) * 10 -> 6.3439306
A8: Bharti Airtel Ltd | B8: =(Processed_Ratios!B8 / Processed_Ratios!$B$32) * 10 -> 2.9897727 | C8: =(Processed_Ratios!C8 / Processed_Ratios!$B$32) * 10 -> 0.68288883 | D8: =(Processed_Ratios!D8 / Processed_Ratios!$B$32) * 10 -> 0.77731955 | E8: =(Processed_Ratios!E8 / Processed_Ratios!$B$32) * 10 -> 0.40706577 | F8: =(Processed_Ratios!F8 / Processed_Ratios!$B$32) * 10 -> 0.11211648 | G8: =(Processed_Ratios!G8 / Processed_Ratios!$B$32) * 10 -> 0.11211648 | H8: =(Processed_Ratios!H8 / Processed_Ratios!$B$32) * 10 -> 0.11211648 | I8: =(Processed_Ratios!I8 / Processed_Ratios!$B$32) * 10 -> 0.1467144 | ... M8: =(Processed_Ratios!M8 / Processed_Ratios!$B$32) * 10 -> 0.37398834
A9: HCL Technologies Ltd | B9: =(Processed_Ratios!B9 / Processed_Ratios!$B$32) * 10 -> 3.4192457 | C9: =(Processed_Ratios!C9 / Processed_Ratios!$B$32) * 10 -> 3.0868709 | D9: =(Processed_Ratios!D9 / Processed_Ratios!$B$32) * 10 -> 2.9230843 | E9: =(Processed_Ratios!E9 / Processed_Ratios!$B$32) * 10 -> 2.6552638 | F9: =(Processed_Ratios!F9 / Processed_Ratios!$B$32) * 10 -> 2.1911128 | G9: =(Processed_Ratios!G9 / Processed_Ratios!$B$32) * 10 -> 2.1740406 | H9: =(Processed_Ratios!H9 / Processed_Ratios!$B$32) * 10 -> 3.9239433 | I9: =(Processed_Ratios!I9 / Processed_Ratios!$B$32) * 10 -> 3.3178794 | ... M9: =(Processed_Ratios!M9 / Processed_Ratios!$B$32) * 10 -> 4.9045289
A10: HDFC Bank Ltd | B10: =(Processed_Ratios!B10 / Processed_Ratios!$B$32) * 10 -> 4.9290703 | C10: =(Processed_Ratios!C10 / Processed_Ratios!$B$32) * 10 -> 4.8020956 | D10: =(Processed_Ratios!D10 / Processed_Ratios!$B$32) * 10 -> 4.3891613 | E10: =(Processed_Ratios!E10 / Processed_Ratios!$B$32) * 10 -> 3.6443856 | F10: =(Processed_Ratios!F10 / Processed_Ratios!$B$32) * 10 -> 3.0735333 | G10: =(Processed_Ratios!G10 / Processed_Ratios!$B$32) * 10 -> 2.6387251 | H10: =(Processed_Ratios!H10 / Processed_Ratios!$B$32) * 10 -> 4.4019654 | I10: =(Processed_Ratios!I10 / Processed_Ratios!$B$32) * 10 -> 3.7750948 | ... M10: =(Processed_Ratios!M10 / Processed_Ratios!$B$32) * 10 -> 1.9371636
A11: Hindustan Unilever Ltd | B11: =(Processed_Ratios!B11 / Processed_Ratios!$B$32) * 10 -> 2.4178533 | C11: =(Processed_Ratios!C11 / Processed_Ratios!$B$32) * 10 -> 2.3335592 | D11: =(Processed_Ratios!D11 / Processed_Ratios!$B$32) * 10 -> 2.2978142 | E11: =(Processed_Ratios!E11 / Processed_Ratios!$B$32) * 10 -> 2.0161226 | F11: =(Processed_Ratios!F11 / Processed_Ratios!$B$32) * 10 -> 1.815524 | G11: =(Processed_Ratios!G11 / Processed_Ratios!$B$32) * 10 -> 1.662941 | H11: =(Processed_Ratios!H11 / Processed_Ratios!$B$32) * 10 -> 1.4916853 | I11: =(Processed_Ratios!I11 / Processed_Ratios!$B$32) * 10 -> 1.2846846 | ... M11: =(Processed_Ratios!M11 / Processed_Ratios!$B$32) * 10 -> 0.97258308
A12: ICICI Bank Ltd | B12: =(Processed_Ratios!B12 / Processed_Ratios!$B$32) * 10 -> 3.7953681 | C12: =(Processed_Ratios!C12 / Processed_Ratios!$B$32) * 10 -> 3.3056088 | D12: =(Processed_Ratios!D12 / Processed_Ratios!$B$32) * 10 -> 2.552297 | E12: =(Processed_Ratios!E12 / Processed_Ratios!$B$32) * 10 -> 1.8907485 | F12: =(Processed_Ratios!F12 / Processed_Ratios!$B$32) * 10 -> 1.431399 | G12: =(Processed_Ratios!G12 / Processed_Ratios!$B$32) * 10 -> 0.77625254 | H12: =(Processed_Ratios!H12 / Processed_Ratios!$B$32) * 10 -> 0.34838001 | I12: =(Processed_Ratios!I12 / Processed_Ratios!$B$32) * 10 -> 0.63433971 | ... M12: =(Processed_Ratios!M12 / Processed_Ratios!$B$32) * 10 -> 5.1029935
A13: Infosys Ltd | B13: =(Processed_Ratios!B13 / Processed_Ratios!$B$32) * 10 -> 3.4325834 | C13: =(Processed_Ratios!C13 / Processed_Ratios!$B$32) * 10 -> 3.3819002 | D13: =(Processed_Ratios!D13 / Processed_Ratios!$B$32) * 10 -> 3.0697987 | E13: =(Processed_Ratios!E13 / Processed_Ratios!$B$32) * 10 -> 2.7961097 | F13: =(Processed_Ratios!F13 / Processed_Ratios!$B$32) * 10 -> 2.4285234 | G13: =(Processed_Ratios!G13 / Processed_Ratios!$B$32) * 10 -> 2.0758754 | H13: =(Processed_Ratios!H13 / Processed_Ratios!$B$32) * 10 -> 1.8875474 | I13: =(Processed_Ratios!I13 / Processed_Ratios!$B$32) * 10 -> 3.787899 | ... M13: =(Processed_Ratios!M13 / Processed_Ratios!$B$32) * 10 -> 9.9493702
... A30: UltraTech Cement Ltd | B30: =(Processed_Ratios!B30 / Processed_Ratios!$B$32) * 10 -> 10 | C30: =(Processed_Ratios!C30 / Processed_Ratios!$B$32) * 10 -> 10 | D30: =(Processed_Ratios!D30 / Processed_Ratios!$B$32) * 10 -> 9.3651801 | E30: =(Processed_Ratios!E30 / Processed_Ratios!$B$32) * 10 -> 10 | F30: =(Processed_Ratios!F30 / Processed_Ratios!$B$32) * 10 -> 10 | G30: =(Processed_Ratios!G30 / Processed_Ratios!$B$32) * 10 -> 10 | H30: =(Processed_Ratios!H30 / Processed_Ratios!$B$32) * 10 -> 4.481458 | I30: =(Processed_Ratios!I30 / Processed_Ratios!$B$32) * 10 -> 4.3171378 | ... M30: =(Processed_Ratios!M30 / Processed_Ratios!$B$32) * 10 -> 4.2904625
A34: PAYOUT RATIO | B34: (PR)2025 | C34: (PR)2024 | D34: (PR)2023 | E34: (PR)2022 | F34: (PR)2021 | G34: (PR)2020 | H34: (PR)2019 | I34: (PR)2018 | J34: (PR)2017 | K34: (PR)2016 | L34: (PR)2015 | M34: (PR)2014
A35: Adani Ports and Special Economic Zone Ltd | B35: =(Processed_Ratios!B35 / Processed_Ratios!$B$65) * 10 -> 1.3275594 | C35: =(Processed_Ratios!C35 / Processed_Ratios!$B$65) * 10 -> 1.5128266 | D35: =(Processed_Ratios!D35 / Processed_Ratios!$B$65) * 10 -> 2.2595788 | E35: =(Processed_Ratios!E35 / Processed_Ratios!$B$65) * 10 -> 2.4539389 | F35: =(Processed_Ratios!F35 / Processed_Ratios!$B$65) * 10 -> 0 | G35: =(Processed_Ratios!G35 / Processed_Ratios!$B$65) * 10 -> 2.0879508 | H35: =(Processed_Ratios!H35 / Processed_Ratios!$B$65) * 10 -> 1.1798002 | I35: =(Processed_Ratios!I35 / Processed_Ratios!$B$65) * 10 -> 0.83199782 | ... M35: =(Processed_Ratios!M35 / Processed_Ratios!$B$65) * 10 -> 1.3957559
A36: Asian Paints Ltd | B36: =(Processed_Ratios!B36 / Processed_Ratios!$B$65) * 10 -> 9.631625 | C36: =(Processed_Ratios!C36 / Processed_Ratios!$B$65) * 10 -> 5.2704561 | D36: =(Processed_Ratios!D36 / Processed_Ratios!$B$65) * 10 -> 5.2829588 | E36: =(Processed_Ratios!E36 / Processed_Ratios!$B$65) * 10 -> 6.5286823 | F36: =(Processed_Ratios!F36 / Processed_Ratios!$B$65) * 10 -> 1.162751 | G36: =(Processed_Ratios!G36 / Processed_Ratios!$B$65) * 10 -> 7.3140792 | H36: =(Processed_Ratios!H36 / Processed_Ratios!$B$65) * 10 -> 4.4998352 | I36: =(Processed_Ratios!I36 / Processed_Ratios!$B$65) * 10 -> 5.5068708 | ... M36: =(Processed_Ratios!M36 / Processed_Ratios!$B$65) * 10 -> 4.7407963
A37: AXIS Bank Ltd | B37: =(Processed_Ratios!B37 / Processed_Ratios!$B$65) * 10 -> 0.13525648 | C37: =(Processed_Ratios!C37 / Processed_Ratios!$B$65) * 10 -> 0.14207613 | D37: =(Processed_Ratios!D37 / Processed_Ratios!$B$65) * 10 -> 0.36939794 | E37: =(Processed_Ratios!E37 / Processed_Ratios!$B$65) * 10 -> 0.14093952 | F37: =(Processed_Ratios!F37 / Processed_Ratios!$B$65) * 10 -> 0.17276457 | G37: =(Processed_Ratios!G37 / Processed_Ratios!$B$65) * 10 -> 0.14207613 | H37: =(Processed_Ratios!H37 / Processed_Ratios!$B$65) * 10 -> 0.26482991 | I37: =(Processed_Ratios!I37 / Processed_Ratios!$B$65) * 10 -> 0.15798866 | ... M37: =(Processed_Ratios!M37 / Processed_Ratios!$B$65) * 10 -> 0.15003239
A38: Bajaj Finserv Ltd | B38: =(Processed_Ratios!B38 / Processed_Ratios!$B$65) * 10 -> 0.20345302 | C38: =(Processed_Ratios!C38 / Processed_Ratios!$B$65) * 10 -> 0.17731101 | D38: =(Processed_Ratios!D38 / Processed_Ratios!$B$65) * 10 -> 0.11252429 | E38: =(Processed_Ratios!E38 / Processed_Ratios!$B$65) * 10 -> 0.11820734 | F38: =(Processed_Ratios!F38 / Processed_Ratios!$B$65) * 10 -> 0 | G38: =(Processed_Ratios!G38 / Processed_Ratios!$B$65) * 10 -> 0.4023596 | H38: =(Processed_Ratios!H38 / Processed_Ratios!$B$65) * 10 -> 0.097748377 | I38: =(Processed_Ratios!I38 / Processed_Ratios!$B$65) * 10 -> 0.11934395 | ... M38: =(Processed_Ratios!M38 / Processed_Ratios!$B$65) * 10 -> 0.20458963
A39: Bajaj Finance Ltd | B39: =(Processed_Ratios!B39 / Processed_Ratios!$B$65) * 10 -> 1.5207829 | C39: =(Processed_Ratios!C39 / Processed_Ratios!$B$65) * 10 -> 1.427581 | D39: =(Processed_Ratios!D39 / Processed_Ratios!$B$65) * 10 -> 1.1923029 | E39: =(Processed_Ratios!E39 / Processed_Ratios!$B$65) * 10 -> 0.97407395 | F39: =(Processed_Ratios!F39 / Processed_Ratios!$B$65) * 10 -> 0 | G39: =(Processed_Ratios!G39 / Processed_Ratios!$B$65) * 10 -> 2.0504427 | H39: =(Processed_Ratios!H39 / Processed_Ratios!$B$65) * 10 -> 0.65696003 | I39: =(Processed_Ratios!I39 / Processed_Ratios!$B$65) * 10 -> 0.84109069 | ... M39: =(Processed_Ratios!M39 / Processed_Ratios!$B$65) * 10 -> 1.2673191
A40: Bharat Electronics Ltd | B40: =(Processed_Ratios!B40 / Processed_Ratios!$B$65) * 10 -> 3.590548 | C40: =(Processed_Ratios!C40 / Processed_Ratios!$B$65) * 10 -> 4.1702186 | D40: =(Processed_Ratios!D40 / Processed_Ratios!$B$65) * 10 -> 4.7317034 | E40: =(Processed_Ratios!E40 / Processed_Ratios!$B$65) * 10 -> 4.8476376 | F40: =(Processed_Ratios!F40 / Processed_Ratios!$B$65) * 10 -> 5.5409691 | G40: =(Processed_Ratios!G40 / Processed_Ratios!$B$65) * 10 -> 4.706698 | H40: =(Processed_Ratios!H40 / Processed_Ratios!$B$65) * 10 -> 3.0824837 | I40: =(Processed_Ratios!I40 / Processed_Ratios!$B$65) * 10 -> 4.9817574 | ... M40: =(Processed_Ratios!M40 / Processed_Ratios!$B$65) * 10 -> 2.2266171
A41: Bharti Airtel Ltd | B41: =(Processed_Ratios!B41 / Processed_Ratios!$B$65) * 10 -> 1.5673839 | C41: =(Processed_Ratios!C41 / Processed_Ratios!$B$65) * 10 -> 3.4632477 | D41: =(Processed_Ratios!D41 / Processed_Ratios!$B$65) * 10 -> 2.3118628 | E41: =(Processed_Ratios!E41 / Processed_Ratios!$B$65) * 10 -> 0 | F41: =(Processed_Ratios!F41 / Processed_Ratios!$B$65) * 10 -> 0 | G41: =(Processed_Ratios!G41 / Processed_Ratios!$B$65) * 10 -> 0 | H41: =(Processed_Ratios!H41 / Processed_Ratios!$B$65) * 10 -> 10 | I41: =(Processed_Ratios!I41 / Processed_Ratios!$B$65) * 10 -> 10 | ... M41: =(Processed_Ratios!M41 / Processed_Ratios!$B$65) * 10 -> 0
A42: HCL Technologies Ltd | B42: =(Processed_Ratios!B42 / Processed_Ratios!$B$65) * 10 -> 10 | C42: =(Processed_Ratios!C42 / Processed_Ratios!$B$65) * 10 -> 10 | D42: =(Processed_Ratios!D42 / Processed_Ratios!$B$65) * 10 -> 9.9453291 | E42: =(Processed_Ratios!E42 / Processed_Ratios!$B$65) * 10 -> 9.5907071 | F42: =(Processed_Ratios!F42 / Processed_Ratios!$B$65) * 10 -> 3.3211716 | G42: =(Processed_Ratios!G42 / Processed_Ratios!$B$65) * 10 -> 1.3946193 | H42: =(Processed_Ratios!H42 / Processed_Ratios!$B$65) * 10 -> 1.2332208 | I42: =(Processed_Ratios!I42 / Processed_Ratios!$B$65) * 10 -> 2.2050215 | ... M42: =(Processed_Ratios!M42 / Processed_Ratios!$B$65) * 10 -> 1.2218547
A43: HDFC Bank Ltd | B43: =(Processed_Ratios!B43 / Processed_Ratios!$B$65) * 10 -> 2.8472056 | C43: =(Processed_Ratios!C43 / Processed_Ratios!$B$65) * 10 -> 2.7710528 | D43: =(Processed_Ratios!D43 / Processed_Ratios!$B$65) * 10 -> 2.735818 | E43: =(Processed_Ratios!E43 / Processed_Ratios!$B$65) * 10 -> 2.6460258 | F43: =(Processed_Ratios!F43 / Processed_Ratios!$B$65) * 10 -> 1.3116468 | G43: =(Processed_Ratios!G43 / Processed_Ratios!$B$65) * 10 -> 0 | H43: =(Processed_Ratios!H43 / Processed_Ratios!$B$65) * 10 -> 2.1175026 | I43: =(Processed_Ratios!I43 / Processed_Ratios!$B$65) * 10 -> 2.1959287 | ... M43: =(Processed_Ratios!M43 / Processed_Ratios!$B$65) * 10 -> 0
A44: Hindustan Unilever Ltd | B44: =(Processed_Ratios!B44 / Processed_Ratios!$B$65) * 10 -> 10 | C44: =(Processed_Ratios!C44 / Processed_Ratios!$B$65) * 10 -> 10 | D44: =(Processed_Ratios!D44 / Processed_Ratios!$B$65) * 10 -> 9.4997784 | E44: =(Processed_Ratios!E44 / Processed_Ratios!$B$65) * 10 -> 9.6248054 | F44: =(Processed_Ratios!F44 / Processed_Ratios!$B$65) * 10 -> 10 | G44: =(Processed_Ratios!G44 / Processed_Ratios!$B$65) * 10 -> 8.7518896 | H44: =(Processed_Ratios!H44 / Processed_Ratios!$B$65) * 10 -> 8.5347973 | I44: =(Processed_Ratios!I44 / Processed_Ratios!$B$65) * 10 -> 8.4927428 | ... M44: =(Processed_Ratios!M44 / Processed_Ratios!$B$65) * 10 -> 8.0983394
A45: ICICI Bank Ltd | B45: =(Processed_Ratios!B45 / Processed_Ratios!$B$65) * 10 -> 1.7503779 | C45: =(Processed_Ratios!C45 / Processed_Ratios!$B$65) * 10 -> 1.8072084 | D45: =(Processed_Ratios!D45 / Processed_Ratios!$B$65) * 10 -> 1.8640388 | E45: =(Processed_Ratios!E45 / Processed_Ratios!$B$65) * 10 -> 1.5685205 | F45: =(Processed_Ratios!F45 / Processed_Ratios!$B$65) * 10 -> 0.85245678 | G45: =(Processed_Ratios!G45 / Processed_Ratios!$B$65) * 10 -> 0 | H45: =(Processed_Ratios!H45 / Processed_Ratios!$B$65) * 10 -> 1.7049136 | I45: =(Processed_Ratios!I45 / Processed_Ratios!$B$65) * 10 -> 1.3639308 | ... M45: =(Processed_Ratios!M45 / Processed_Ratios!$B$65) * 10 -> 2.7278617
A46: Infosys Ltd | B46: =(Processed_Ratios!B46 / Processed_Ratios!$B$65) * 10 -> 8.6348189 | C46: =(Processed_Ratios!C46 / Processed_Ratios!$B$65) * 10 -> 6.3650106 | D46: =(Processed_Ratios!D46 / Processed_Ratios!$B$65) * 10 -> 6.4297973 | E46: =(Processed_Ratios!E46 / Processed_Ratios!$B$65) * 10 -> 6.5048135 | F46: =(Processed_Ratios!F46 / Processed_Ratios!$B$65) * 10 -> 5.3557018 | G46: =(Processed_Ratios!G46 / Processed_Ratios!$B$65) * 10 -> 6.5184528 | H46: =(Processed_Ratios!H46 / Processed_Ratios!$B$65) * 10 -> 10 | I46: =(Processed_Ratios!I46 / Processed_Ratios!$B$65) * 10 -> 5.2954615 | ... M46: =(Processed_Ratios!M46 / Processed_Ratios!$B$65) * 10 -> 3.8451484
... A63: UltraTech Cement Ltd | B63: =(Processed_Ratios!B63 / Processed_Ratios!$B$65) * 10 -> 3.7962742 | C63: =(Processed_Ratios!C63 / Processed_Ratios!$B$65) * 10 -> 1.7765199 | D63: =(Processed_Ratios!D63 / Processed_Ratios!$B$65) * 10 -> 2.4516657 | E63: =(Processed_Ratios!E63 / Processed_Ratios!$B$65) * 10 -> 1.6503563 | F63: =(Processed_Ratios!F63 / Processed_Ratios!$B$65) * 10 -> 0.7797138 | G63: =(Processed_Ratios!G63 / Processed_Ratios!$B$65) * 10 -> 0.75129858 | H63: =(Processed_Ratios!H63 / Processed_Ratios!$B$65) * 10 -> 1.6435367 | I63: =(Processed_Ratios!I63 / Processed_Ratios!$B$65) * 10 -> 1.689001 | ... M63: =(Processed_Ratios!M63 / Processed_Ratios!$B$65) * 10 -> 1.2707289
A67: Price to sales | B67: (PM)2025 | C67: (PM)2024 | D67: (PM)2023 | E67: (PM)2022 | F67: (PM)2021 | G67: (PM)2020 | H67: (PM)2019 | I67: (PM)2018 | J67: (PM)2017 | K67: (PM)2016 | L67: (PM)2015 | M67: (PM)2014
A68: Adani Ports and Special Economic Zone Ltd | B68: =(Processed_Ratios!B68 / Processed_Ratios!$B$98) * 10 -> 9.3916024 | C68: =(Processed_Ratios!C68 / Processed_Ratios!$B$98) * 10 -> 10 | D68: =(Processed_Ratios!D68 / Processed_Ratios!$B$98) * 10 -> 7.4835761 | E68: =(Processed_Ratios!E68 / Processed_Ratios!$B$98) * 10 -> 10 | F68: =(Processed_Ratios!F68 / Processed_Ratios!$B$98) * 10 -> 10 | G68: =(Processed_Ratios!G68 / Processed_Ratios!$B$98) * 10 -> 4.912882 | H68: =(Processed_Ratios!H68 / Processed_Ratios!$B$98) * 10 -> 8.1919452 | I68: =(Processed_Ratios!I68 / Processed_Ratios!$B$98) * 10 -> 7.4150243 | ... M68: =(Processed_Ratios!M68 / Processed_Ratios!$B$98) * 10 -> 9.1973722
A69: Asian Paints Ltd | B69: =(Processed_Ratios!B69 / Processed_Ratios!$B$98) * 10 -> 7.552128 | C69: =(Processed_Ratios!C69 / Processed_Ratios!$B$98) * 10 -> 8.7860611 | D69: =(Processed_Ratios!D69 / Processed_Ratios!$B$98) * 10 -> 8.7746358 | E69: =(Processed_Ratios!E69 / Processed_Ratios!$B$98) * 10 -> 10 | F69: =(Processed_Ratios!F69 / Processed_Ratios!$B$98) * 10 -> 10 | G69: =(Processed_Ratios!G69 / Processed_Ratios!$B$98) * 10 -> 9.0374179 | H69: =(Processed_Ratios!H69 / Processed_Ratios!$B$98) * 10 -> 8.5004284 | I69: =(Processed_Ratios!I69 / Processed_Ratios!$B$98) * 10 -> 7.3007712 | ... M69: =(Processed_Ratios!M69 / Processed_Ratios!$B$98) * 10 -> 4.7072265
A70: AXIS Bank Ltd | B70: =(Processed_Ratios!B70 / Processed_Ratios!$B$98) * 10 -> 3.0619823 | C70: =(Processed_Ratios!C70 / Processed_Ratios!$B$98) * 10 -> 3.2790631 | D70: =(Processed_Ratios!D70 / Processed_Ratios!$B$98) * 10 -> 3.4504427 | E70: =(Processed_Ratios!E70 / Processed_Ratios!$B$98) * 10 -> 3.8731791 | F70: =(Processed_Ratios!F70 / Processed_Ratios!$B$98) * 10 -> 3.7703513 | G70: =(Processed_Ratios!G70 / Processed_Ratios!$B$98) * 10 -> 1.9194516 | H70: =(Processed_Ratios!H70 / Processed_Ratios!$B$98) * 10 -> 4.0674093 | I70: =(Processed_Ratios!I70 / Processed_Ratios!$B$98) * 10 -> 3.199086 | ... M70: =(Processed_Ratios!M70 / Processed_Ratios!$B$98) * 10 -> 2.5478435
A71: Bajaj Finserv Ltd | B71: =(Processed_Ratios!B71 / Processed_Ratios!$B$98) * 10 -> 2.7306484 | C71: =(Processed_Ratios!C71 / Processed_Ratios!$B$98) * 10 -> 2.7077978 | D71: =(Processed_Ratios!D71 / Processed_Ratios!$B$98) * 10 -> 2.8106255 | E71: =(Processed_Ratios!E71 / Processed_Ratios!$B$98) * 10 -> 4.5358469 | F71: =(Processed_Ratios!F71 / Processed_Ratios!$B$98) * 10 -> 2.902028 | G71: =(Processed_Ratios!G71 / Processed_Ratios!$B$98) * 10 -> 1.5309911 | H71: =(Processed_Ratios!H71 / Processed_Ratios!$B$98) * 10 -> 3.0048558 | I71: =(Processed_Ratios!I71 / Processed_Ratios!$B$98) * 10 -> 2.8677521 | ... M71: =(Processed_Ratios!M71 / Processed_Ratios!$B$98) * 10 -> 2.3878892
A72: Bajaj Finance Ltd | B72: =(Processed_Ratios!B72 / Processed_Ratios!$B$98) * 10 -> 9.1059697 | C72: =(Processed_Ratios!C72 / Processed_Ratios!$B$98) * 10 -> 9.3001999 | D72: =(Processed_Ratios!D72 / Processed_Ratios!$B$98) * 10 -> 9.3687518 | E72: =(Processed_Ratios!E72 / Processed_Ratios!$B$98) * 10 -> 10 | F72: =(Processed_Ratios!F72 / Processed_Ratios!$B$98) * 10 -> 10 | G72: =(Processed_Ratios!G72 / Processed_Ratios!$B$98) * 10 -> 5.7583548 | H72: =(Processed_Ratios!H72 / Processed_Ratios!$B$98) * 10 -> 10 | I72: =(Processed_Ratios!I72 / Processed_Ratios!$B$98) * 10 -> 8.6489574 | ... M72: =(Processed_Ratios!M72 / Processed_Ratios!$B$98) * 10 -> 2.3421879
A73: Bharat Electronics Ltd | B73: =(Processed_Ratios!B73 / Processed_Ratios!$B$98) * 10 -> 10 | C73: =(Processed_Ratios!C73 / Processed_Ratios!$B$98) * 10 -> 8.3061982 | D73: =(Processed_Ratios!D73 / Processed_Ratios!$B$98) * 10 -> 4.5929734 | E73: =(Processed_Ratios!E73 / Processed_Ratios!$B$98) * 10 -> 3.8160526 | F73: =(Processed_Ratios!F73 / Processed_Ratios!$B$98) * 10 -> 2.4678663 | G73: =(Processed_Ratios!G73 / Processed_Ratios!$B$98) * 10 -> 1.599543 | H73: =(Processed_Ratios!H73 / Processed_Ratios!$B$98) * 10 -> 2.1365324 | I73: =(Processed_Ratios!I73 / Processed_Ratios!$B$98) * 10 -> 3.8046272 | ... M73: =(Processed_Ratios!M73 / Processed_Ratios!$B$98) * 10 -> 1.599543
A74: Bharti Airtel Ltd | B74: =(Processed_Ratios!B74 / Processed_Ratios!$B$98) * 10 -> 6.6266781 | C74: =(Processed_Ratios!C74 / Processed_Ratios!$B$98) * 10 -> 5.3813196 | D74: =(Processed_Ratios!D74 / Processed_Ratios!$B$98) * 10 -> 3.4847187 | E74: =(Processed_Ratios!E74 / Processed_Ratios!$B$98) * 10 -> 4.1359612 | F74: =(Processed_Ratios!F74 / Processed_Ratios!$B$98) * 10 -> 3.2219366 | G74: =(Processed_Ratios!G74 / Processed_Ratios!$B$98) * 10 -> 3.1419594 | H74: =(Processed_Ratios!H74 / Processed_Ratios!$B$98) * 10 -> 1.8851757 | I74: =(Processed_Ratios!I74 / Processed_Ratios!$B$98) * 10 -> 2.1708083 | ... M74: =(Processed_Ratios!M74 / Processed_Ratios!$B$98) * 10 -> 1.6680948
A75: HCL Technologies Ltd | B75: =(Processed_Ratios!B75 / Processed_Ratios!$B$98) * 10 -> 4.2159383 | C75: =(Processed_Ratios!C75 / Processed_Ratios!$B$98) * 10 -> 4.353042 | D75: =(Processed_Ratios!D75 / Processed_Ratios!$B$98) * 10 -> 3.3247644 | E75: =(Processed_Ratios!E75 / Processed_Ratios!$B$98) * 10 -> 4.2159383 | F75: =(Processed_Ratios!F75 / Processed_Ratios!$B$98) * 10 -> 4.0445587 | G75: =(Processed_Ratios!G75 / Processed_Ratios!$B$98) * 10 -> 1.9194516 | H75: =(Processed_Ratios!H75 / Processed_Ratios!$B$98) * 10 -> 2.7877749 | I75: =(Processed_Ratios!I75 / Processed_Ratios!$B$98) * 10 -> 3.0391317 | ... M75: =(Processed_Ratios!M75 / Processed_Ratios!$B$98) * 10 -> 3.7246501
A76: HDFC Bank Ltd | B76: =(Processed_Ratios!B76 / Processed_Ratios!$B$98) * 10 -> 5.3241931 | C76: =(Processed_Ratios!C76 / Processed_Ratios!$B$98) * 10 -> 4.8671808 | D76: =(Processed_Ratios!D76 / Processed_Ratios!$B$98) * 10 -> 6.3524707 | E76: =(Processed_Ratios!E76 / Processed_Ratios!$B$98) * 10 -> 7.2893459 | F76: =(Processed_Ratios!F76 / Processed_Ratios!$B$98) * 10 -> 7.7806341 | G76: =(Processed_Ratios!G76 / Processed_Ratios!$B$98) * 10 -> 4.7072265 | H76: =(Processed_Ratios!H76 / Processed_Ratios!$B$98) * 10 -> 7.2779206 | I76: =(Processed_Ratios!I76 / Processed_Ratios!$B$98) * 10 -> 6.9922879 | ... M76: =(Processed_Ratios!M76 / Processed_Ratios!$B$98) * 10 -> 4.9928592
A77: Hindustan Unilever Ltd | B77: =(Processed_Ratios!B77 / Processed_Ratios!$B$98) * 10 -> 9.6086832 | C77: =(Processed_Ratios!C77 / Processed_Ratios!$B$98) * 10 -> 9.8371894 | D77: =(Processed_Ratios!D77 / Processed_Ratios!$B$98) * 10 -> 10 | E77: =(Processed_Ratios!E77 / Processed_Ratios!$B$98) * 10 -> 10 | F77: =(Processed_Ratios!F77 / Processed_Ratios!$B$98) * 10 -> 10 | G77: =(Processed_Ratios!G77 / Processed_Ratios!$B$98) * 10 -> 10 | H77: =(Processed_Ratios!H77 / Processed_Ratios!$B$98) * 10 -> 10 | I77: =(Processed_Ratios!I77 / Processed_Ratios!$B$98) * 10 -> 9.2773493 | ... M77: =(Processed_Ratios!M77 / Processed_Ratios!$B$98) * 10 -> 5.1071123
A78: ICICI Bank Ltd | B78: =(Processed_Ratios!B78 / Processed_Ratios!$B$98) * 10 -> 5.8840331 | C78: =(Processed_Ratios!C78 / Processed_Ratios!$B$98) * 10 -> 5.506998 | D78: =(Processed_Ratios!D78 / Processed_Ratios!$B$98) * 10 -> 5.7812054 | E78: =(Processed_Ratios!E78 / Processed_Ratios!$B$98) * 10 -> 6.0782634 | F78: =(Processed_Ratios!F78 / Processed_Ratios!$B$98) * 10 -> 5.1528135 | G78: =(Processed_Ratios!G78 / Processed_Ratios!$B$98) * 10 -> 2.8334762 | H78: =(Processed_Ratios!H78 / Processed_Ratios!$B$98) * 10 -> 4.0788346 | I78: =(Processed_Ratios!I78 / Processed_Ratios!$B$98) * 10 -> 3.2904884 | ... M78: =(Processed_Ratios!M78 / Processed_Ratios!$B$98) * 10 -> 3.3247644
A79: Infosys Ltd | B79: =(Processed_Ratios!B79 / Processed_Ratios!$B$98) * 10 -> 4.5586975 | C79: =(Processed_Ratios!C79 / Processed_Ratios!$B$98) * 10 -> 4.615824 | D79: =(Processed_Ratios!D79 / Processed_Ratios!$B$98) * 10 -> 4.6043987 | E79: =(Processed_Ratios!E79 / Processed_Ratios!$B$98) * 10 -> 7.517852 | F79: =(Processed_Ratios!F79 / Processed_Ratios!$B$98) * 10 -> 6.6038275 | G79: =(Processed_Ratios!G79 / Processed_Ratios!$B$98) * 10 -> 3.4161668 | H79: =(Processed_Ratios!H79 / Processed_Ratios!$B$98) * 10 -> 4.4558698 | I79: =(Processed_Ratios!I79 / Processed_Ratios!$B$98) * 10 -> 3.9988575 | ... M79: =(Processed_Ratios!M79 / Processed_Ratios!$B$98) * 10 -> 4.2730648
... A96: UltraTech Cement Ltd | B96: =(Processed_Ratios!B96 / Processed_Ratios!$B$98) * 10 -> 5.0956869 | C96: =(Processed_Ratios!C96 / Processed_Ratios!$B$98) * 10 -> 4.5358469 | D96: =(Processed_Ratios!D96 / Processed_Ratios!$B$98) * 10 -> 3.9760069 | E96: =(Processed_Ratios!E96 / Processed_Ratios!$B$98) * 10 -> 4.1359612 | F96: =(Processed_Ratios!F96 / Processed_Ratios!$B$98) * 10 -> 4.9700086 | G96: =(Processed_Ratios!G96 / Processed_Ratios!$B$98) * 10 -> 2.5249929 | H96: =(Processed_Ratios!H96 / Processed_Ratios!$B$98) * 10 -> 3.0162811 | I96: =(Processed_Ratios!I96 / Processed_Ratios!$B$98) * 10 -> 3.9988575 | ... M96: =(Processed_Ratios!M96 / Processed_Ratios!$B$98) * 10 -> 3.1648101
A100: DEBT TO EQUITY | B100: 2025 | C100: 2024 | D100: 2023 | E100: 2022 | F100: 2021 | G100: 2020 | H100: 2019 | I100: 2018 | J100: 2017 | K100: 2016 | L100: 2015 | M100: 2014
A101: Adani Ports and Special Economic Zone Ltd | B101: =(Processed_Ratios!B101 / Processed_Ratios!$B$131) * 10 -> 1.9527646 | C101: =(Processed_Ratios!C101 / Processed_Ratios!$B$131) * 10 -> 2.2299994 | D101: =(Processed_Ratios!D101 / Processed_Ratios!$B$131) * 10 -> 2.6262574 | E101: =(Processed_Ratios!E101 / Processed_Ratios!$B$131) * 10 -> 2.7927667 | F101: =(Processed_Ratios!F101 / Processed_Ratios!$B$131) * 10 -> 2.6937978 | G101: =(Processed_Ratios!G101 / Processed_Ratios!$B$131) * 10 -> 2.6262574 | H101: =(Processed_Ratios!H101 / Processed_Ratios!$B$131) * 10 -> 2.5920009 | I101: =(Processed_Ratios!I101 / Processed_Ratios!$B$131) * 10 -> 2.4872095 | ... M101: =(Processed_Ratios!M101 / Processed_Ratios!$B$131) * 10 -> 3.0135324
A102: Asian Paints Ltd | B102: =(Processed_Ratios!B102 / Processed_Ratios!$B$131) * 10 -> 0.13972966 | C102: =(Processed_Ratios!C102 / Processed_Ratios!$B$131) * 10 -> 0.20759171 | D102: =(Processed_Ratios!D102 / Processed_Ratios!$B$131) * 10 -> 0.20759171 | E102: =(Processed_Ratios!E102 / Processed_Ratios!$B$131) * 10 -> 0.20759171 | F102: =(Processed_Ratios!F102 / Processed_Ratios!$B$131) * 10 -> 0.10530766 | G102: =(Processed_Ratios!G102 / Processed_Ratios!$B$131) * 10 -> 0.10530766 | H102: =(Processed_Ratios!H102 / Processed_Ratios!$B$131) * 10 -> 0.24104407 | I102: =(Processed_Ratios!I102 / Processed_Ratios!$B$131) * 10 -> 0.20759171 | ... M102: =(Processed_Ratios!M102 / Processed_Ratios!$B$131) * 10 -> 0.20759171
A103: AXIS Bank Ltd | B103: =(Processed_Ratios!B103 / Processed_Ratios!$B$131) * 10 -> 7.7801201 | C103: =(Processed_Ratios!C103 / Processed_Ratios!$B$131) * 10 -> 8.091114 | D103: =(Processed_Ratios!D103 / Processed_Ratios!$B$131) * 10 -> 8.3396066 | E103: =(Processed_Ratios!E103 / Processed_Ratios!$B$131) * 10 -> 8.2458016 | F103: =(Processed_Ratios!F103 / Processed_Ratios!$B$131) * 10 -> 8.080067 | G103: =(Processed_Ratios!G103 / Processed_Ratios!$B$131) * 10 -> 7.8279416 | H103: =(Processed_Ratios!H103 / Processed_Ratios!$B$131) * 10 -> 8.849882 | I103: =(Processed_Ratios!I103 / Processed_Ratios!$B$131) * 10 -> 8.4510013 | ... M103: =(Processed_Ratios!M103 / Processed_Ratios!$B$131) * 10 -> 8.2246163
A104: Bajaj Finserv Ltd | B104: =(Processed_Ratios!B104 / Processed_Ratios!$B$131) * 10 -> 6.3174901 | C104: =(Processed_Ratios!C104 / Processed_Ratios!$B$131) * 10 -> 6.2441568 | D104: =(Processed_Ratios!D104 / Processed_Ratios!$B$131) * 10 -> 6.1120752 | E104: =(Processed_Ratios!E104 / Processed_Ratios!$B$131) * 10 -> 5.7267312 | F104: =(Processed_Ratios!F104 / Processed_Ratios!$B$131) * 10 -> 5.4134934 | G104: =(Processed_Ratios!G104 / Processed_Ratios!$B$131) * 10 -> 5.7622514 | H104: =(Processed_Ratios!H104 / Processed_Ratios!$B$131) * 10 -> 5.8735933 | I104: =(Processed_Ratios!I104 / Processed_Ratios!$B$131) * 10 -> 5.1471889 | ... M104: =(Processed_Ratios!M104 / Processed_Ratios!$B$131) * 10 -> 5.1471889
A105: Bajaj Finance Ltd | B105: =(Processed_Ratios!B105 / Processed_Ratios!$B$131) * 10 -> 5.5436153 | C105: =(Processed_Ratios!C105 / Processed_Ratios!$B$131) * 10 -> 5.6032427 | D105: =(Processed_Ratios!D105 / Processed_Ratios!$B$131) * 10 -> 5.7267312 | E105: =(Processed_Ratios!E105 / Processed_Ratios!$B$131) * 10 -> 5.5735537 | F105: =(Processed_Ratios!F105 / Processed_Ratios!$B$131) * 10 -> 5.4134934 | G105: =(Processed_Ratios!G105 / Processed_Ratios!$B$131) * 10 -> 5.7480858 | H105: =(Processed_Ratios!H105 / Processed_Ratios!$B$131) * 10 -> 6.4771708 | I105: =(Processed_Ratios!I105 / Processed_Ratios!$B$131) * 10 -> 5.2945952 | ... M105: =(Processed_Ratios!M105 / Processed_Ratios!$B$131) * 10 -> 6.4829496
A106: Bharat Electronics Ltd | B106: =(Processed_Ratios!B106 / Processed_Ratios!$B$131) * 10 -> 2.8089974 | C106: =(Processed_Ratios!C106 / Processed_Ratios!$B$131) * 10 -> 2.6937978 | D106: =(Processed_Ratios!D106 / Processed_Ratios!$B$131) * 10 -> 2.6432629 | E106: =(Processed_Ratios!E106 / Processed_Ratios!$B$131) * 10 -> 2.3425135 | F106: =(Processed_Ratios!F106 / Processed_Ratios!$B$131) * 10 -> 2.1334447 | G106: =(Processed_Ratios!G106 / Processed_Ratios!$B$131) * 10 -> 3.133802 | H106: =(Processed_Ratios!H106 / Processed_Ratios!$B$131) * 10 -> 2.9048593 | I106: =(Processed_Ratios!I106 / Processed_Ratios!$B$131) * 10 -> 1.7406395 | ... M106: =(Processed_Ratios!M106 / Processed_Ratios!$B$131) * 10 -> 2.0542715
A107: Bharti Airtel Ltd | B107: =(Processed_Ratios!B107 / Processed_Ratios!$B$131) * 10 -> 2.6937978 | C107: =(Processed_Ratios!C107 / Processed_Ratios!$B$131) * 10 -> 3.264423 | D107: =(Processed_Ratios!D107 / Processed_Ratios!$B$131) * 10 -> 3.6935304 | E107: =(Processed_Ratios!E107 / Processed_Ratios!$B$131) * 10 -> 3.9139708 | F107: =(Processed_Ratios!F107 / Processed_Ratios!$B$131) * 10 -> 4.0582276 | G107: =(Processed_Ratios!G107 / Processed_Ratios!$B$131) * 10 -> 3.2928108 | H107: =(Processed_Ratios!H107 / Processed_Ratios!$B$131) * 10 -> 3.5253887 | I107: =(Processed_Ratios!I107 / Processed_Ratios!$B$131) * 10 -> 3.133802 | ... M107: =(Processed_Ratios!M107 / Processed_Ratios!$B$131) * 10 -> 2.9205884
A108: HCL Technologies Ltd | B108: =(Processed_Ratios!B108 / Processed_Ratios!$B$131) * 10 -> 0.10530766 | C108: =(Processed_Ratios!C108 / Processed_Ratios!$B$131) * 10 -> 0.10530766 | D108: =(Processed_Ratios!D108 / Processed_Ratios!$B$131) * 10 -> 0.10530766 | E108: =(Processed_Ratios!E108 / Processed_Ratios!$B$131) * 10 -> 0.20759171 | F108: =(Processed_Ratios!F108 / Processed_Ratios!$B$131) * 10 -> 0.20759171 | G108: =(Processed_Ratios!G108 / Processed_Ratios!$B$131) * 10 -> 0.30702095 | H108: =(Processed_Ratios!H108 / Processed_Ratios!$B$131) * 10 -> 0.30702095 | I108: =(Processed_Ratios!I108 / Processed_Ratios!$B$131) * 10 -> 0.10530766 | ... M108: =(Processed_Ratios!M108 / Processed_Ratios!$B$131) * 10 -> 0.10530766
A109: HDFC Bank Ltd | B109: =(Processed_Ratios!B109 / Processed_Ratios!$B$131) * 10 -> 7.0674289 | C109: =(Processed_Ratios!C109 / Processed_Ratios!$B$131) * 10 -> 7.4613648 | D109: =(Processed_Ratios!D109 / Processed_Ratios!$B$131) * 10 -> 7.7478787 | E109: =(Processed_Ratios!E109 / Processed_Ratios!$B$131) * 10 -> 7.6576802 | F109: =(Processed_Ratios!F109 / Processed_Ratios!$B$131) * 10 -> 7.6576802 | G109: =(Processed_Ratios!G109 / Processed_Ratios!$B$131) * 10 -> 7.796132 | H109: =(Processed_Ratios!H109 / Processed_Ratios!$B$131) * 10 -> 7.5948453 | I109: =(Processed_Ratios!I109 / Processed_Ratios!$B$131) * 10 -> 8.2633602 | ... M109: =(Processed_Ratios!M109 / Processed_Ratios!$B$131) * 10 -> 8.6575895
A110: Hindustan Unilever Ltd | B110: =(Processed_Ratios!B110 / Processed_Ratios!$B$131) * 10 -> 1.5842598 | C110: =(Processed_Ratios!C110 / Processed_Ratios!$B$131) * 10 -> 1.6070244 | D110: =(Processed_Ratios!D110 / Processed_Ratios!$B$131) * 10 -> 1.5382895 | E110: =(Processed_Ratios!E110 / Processed_Ratios!$B$131) * 10 -> 1.4917183 | F110: =(Processed_Ratios!F110 / Processed_Ratios!$B$131) * 10 -> 1.4206997 | G110: =(Processed_Ratios!G110 / Processed_Ratios!$B$131) * 10 -> 3.4585453 | H110: =(Processed_Ratios!H110 / Processed_Ratios!$B$131) * 10 -> 3.0891754 | I110: =(Processed_Ratios!I110 / Processed_Ratios!$B$131) * 10 -> 3.133802 | ... M110: =(Processed_Ratios!M110 / Processed_Ratios!$B$131) * 10 -> 4.0582276
A111: ICICI Bank Ltd | B111: =(Processed_Ratios!B111 / Processed_Ratios!$B$131) * 10 -> 8.1566861 | C111: =(Processed_Ratios!C111 / Processed_Ratios!$B$131) * 10 -> 8.1746884 | D111: =(Processed_Ratios!D111 / Processed_Ratios!$B$131) * 10 -> 7.694856 | E111: =(Processed_Ratios!E111 / Processed_Ratios!$B$131) * 10 -> 7.879034 | F111: =(Processed_Ratios!F111 / Processed_Ratios!$B$131) * 10 -> 7.948589 | G111: =(Processed_Ratios!G111 / Processed_Ratios!$B$131) * 10 -> 8.3361761 | H111: =(Processed_Ratios!H111 / Processed_Ratios!$B$131) * 10 -> 8.2493202 | I111: =(Processed_Ratios!I111 / Processed_Ratios!$B$131) * 10 -> 8.0689857 | ... M111: =(Processed_Ratios!M111 / Processed_Ratios!$B$131) * 10 -> 7.9409274
A112: Infosys Ltd | B112: =(Processed_Ratios!B112 / Processed_Ratios!$B$131) * 10 -> 1.372555 | C112: =(Processed_Ratios!C112 / Processed_Ratios!$B$131) * 10 -> 1.4206997 | D112: =(Processed_Ratios!D112 / Processed_Ratios!$B$131) * 10 -> 1.6070244 | E112: =(Processed_Ratios!E112 / Processed_Ratios!$B$131) * 10 -> 1.5842598 | F112: =(Processed_Ratios!F112 / Processed_Ratios!$B$131) * 10 -> 1.2742688 | G112: =(Processed_Ratios!G112 / Processed_Ratios!$B$131) * 10 -> 1.2492676 | H112: =(Processed_Ratios!H112 / Processed_Ratios!$B$131) * 10 -> 0.879476 | I112: =(Processed_Ratios!I112 / Processed_Ratios!$B$131) * 10 -> 0.73751898 | ... M112: =(Processed_Ratios!M112 / Processed_Ratios!$B$131) * 10 -> 0.82337012
... A129: UltraTech Cement Ltd | B129: =(Processed_Ratios!B129 / Processed_Ratios!$B$131) * 10 -> 1.0159927 | C129: =(Processed_Ratios!C129 / Processed_Ratios!$B$131) * 10 -> 0.55934937 | D129: =(Processed_Ratios!D129 / Processed_Ratios!$B$131) * 10 -> 0.58966998 | E129: =(Processed_Ratios!E129 / Processed_Ratios!$B$131) * 10 -> 0.64954785 | F129: =(Processed_Ratios!F129 / Processed_Ratios!$B$131) * 10 -> 1.1987327 | G129: =(Processed_Ratios!G129 / Processed_Ratios!$B$131) * 10 -> 1.5613488 | H129: =(Processed_Ratios!H129 / Processed_Ratios!$B$131) * 10 -> 2.2108967 | I129: =(Processed_Ratios!I129 / Processed_Ratios!$B$131) * 10 -> 1.911338 | ... M129: =(Processed_Ratios!M129 / Processed_Ratios!$B$131) * 10 -> 1.2240898
P137: Larsen & Toubro Ltd | Q137: Mahindra & Mahindra Ltd | R137: Maruti Suzuki India Ltd | S137: NTPC Ltd | T137: Power Grid Corporation of India Ltd | U137: Reliance Industries Ltd | V137: State Bank of India | W137: Sun Pharmaceutical Industries Ltd | X137: Tata Motors Ltd | Y137: Tata Steel Ltd | Z137: Tata Consultancy Services Ltd | AA137: Tech Mahindra Ltd | AB137: Titan Company Ltd | AC137: Trent Ltd | AD137: UltraTech Cement Ltd
P141: 2.0568208 | Q141: 1.872114 | R141: 1.3148626 | S141: 3.759881 | T141: 10 | U141: 3.0210535 | V141: 3.9226736 | W141: 2.7580809 | X141: 0.20881271 | Y141: 5.2719731 | Z141: 6.2769038 | AA141: 3.9445879 | AB141: 2.3886671 | AC141: 0.20881271 | AD141: 4.3640917
P142: 2.9709634 | Q142: 0.20881271 | R142: 1.8752446 | S142: 4.0072004 | T142: 9.3355248 | U142: 3.5657823 | V142: 2.7330359 | W142: 2.1350865 | X142: 0.20881271 | Y142: 1.5715739 | Z142: 6.2080301 | AA142: 3.5970885 | AB142: 1.4150427 | AC142: 0.20881271 | AD142: 3.8193629
P143: 2.3291853 | Q143: 0.20881271 | R143: 2.297879 | S143: 3.2871566 | T143: 9.0443766 | U143: 2.0818659 | V143: 2.1069109 | W143: 3.9915473 | X143: 0.20881271 | Y143: 0.20881271 | Z143: 6.4710026 | AA143: 3.3122016 | AB143: 2.222744 | AC143: 1.2240745 | AD143: 4.2419973
P144: 2.3698834 | Q144: 1.3899977 | R144: 2.723644 | S144: 4.169993 | T144: 8.8440166 | U144: 2.1851765 | V144: 0.37880567 | W144: 3.4562104 | X144: 0.20881271 | Y144: 1.7594114 | Z144: 6.743367 | AA144: 3.9226736 | AB144: 2.2008296 | AC144: 1.2647726 | AD144: 1.8032402
P145: 2.2070909 | Q145: 2.3260546 | R145: 3.0241841 | S145: 3.5720435 | T145: 8.4182515 | U145: 2.8770447 | V145: 0.20881271 | W145: 3.1212335 | X145: 0.72317445 | Y145: 4.1637317 | Z145: 6.5805745 | AA145: 3.8506692 | AB145: 2.1444784 | AC145: 1.5903577 | AD145: 2.247789
P146: 1.9691633 | Q146: 1.1771151 | R146: 3.3716835 | S146: 3.8475385 | T146: 8.9034985 | U146: 3.0680128 | V146: 0.20881271 | W146: 7.8328246 | X146: 0.70126008 | Y146: 0.20881271 | Z146: 6.993817 | AA146: 3.0648822 | AB146: 1.6498396 | AC146: 1.6216639 | AD146: 3.3466385
P147: 1.7124521 | Q147: 1.1176332 | R147: 2.9208734 | S147: 4.5362761 | T147: 8.8565391 | U147: 3.384206 | V147: 1.8063708 | W147: 6.2142913 | X147: 1.2710339 | Y147: 0.20881271 | Z147: 7.0126008 | AA147: 3.5720435 | AB147: 1.8752446 | AC147: 0.92353448 | AD147: 3.083666
P148: 1.6780152 | Q148: 1.1270251 | R148: 2.3354465 | S148: 3.8788448 | T148: 8.9441966 | U148: 1.9691633 | V148: 2.6359865 | W148: 6.2612507 | X148: 1.6748846 | Y148: 0.20881271 | Z148: 6.6337951 | AA148: 3.6784848 | AB148: 2.1444784 | AC148: 1.7719339 | AD148: 2.7017297
P149: 1.7844564 | Q149: 1.8282852 | R149: 1.9942083 | S149: 4.520623 | T149: 9.0819441 | U149: 1.6216639 | V149: 2.398059 | W149: 7.5510683 | X149: 1.8940283 | Y149: 0.77013383 | Z149: 7.3976677 | AA149: 5.0903968 | AB149: 2.1037802 | AC149: 0.20881271 | AD149: 3.1963685
A150: DEBT TO EQUITY | B150: 2025 | C150: 2024 | D150: 2023 | E150: 2022 | F150: 2021 | G150: 2020 | H150: 2019 | I150: 2018 | J150: 2017 | K150: 2016 | L150: 2015 | M150: 2014 | P150: Larsen & Toubro Ltd | Q150: Mahindra & Mahindra Ltd | R150: Maruti Suzuki India Ltd | S150: NTPC Ltd | T150: Power Grid Corporation of India Ltd | U150: Reliance Industries Ltd | V150: State Bank of India | W150: Sun Pharmaceutical Industries Ltd | X150: Tata Motors Ltd | Y150: Tata Steel Ltd | Z150: Tata Consultancy Services Ltd | AA150: Tech Mahindra Ltd | AB150: Titan Company Ltd | AC150: Trent Ltd | AD150: UltraTech Cement Ltd
A151: Adani Ports and Special Economic Zone Ltd | B151: 1.9527646 | C151: 2.2299994 | D151: 2.6262574 | E151: 2.7927667 | F151: 2.6937978 | G151: 2.6262574 | H151: 2.5920009 | I151: 2.4872095 | J151: 2.8089974 | K151: 3.1189885 | L151: 3.133802 | M151: 3.0135324 | P151: 2.1632621 | Q151: 2.4700634 | R151: 2.9177428 | S151: 3.6158723 | T151: 10 | U151: 2.6203334 | V151: 5.0371762 | W151: 6.5367457 | X151: 1.9816858 | Y151: 0.42576505 | Z151: 5.982625 | AA151: 2.5076309 | AB151: 1.7249746 | AC151: 2.6453784 | AD151: 2.4919778
A152: Asian Paints Ltd | B152: 0.13972966 | C152: 0.20759171 | D152: 0.20759171 | E152: 0.20759171 | F152: 0.10530766 | G152: 0.10530766 | H152: 0.24104407 | I152: 0.20759171 | J152: 0.24104407 | K152: 0.17382227 | L152: 0.30702095 | M152: 0.20759171 | P152: 2.2039602 | Q152: 2.523284 | R152: 2.9177428 | S152: 3.4530798 | T152: 10 | U152: 2.7299053 | V152: 4.8555999 | W152: 6.2268138 | X152: 2.222744 | Y152: 0.20881271 | Z152: 5.9888863 | AA152: 1.4338264 | AB152: 2.1413477 | AC152: 3.4249041 | AD152: 3.0805353
A153: AXIS Bank Ltd | B153: 7.7801201 | C153: 8.091114 | D153: 8.3396066 | E153: 8.2458016 | F153: 8.080067 | G153: 7.8279416 | H153: 8.849882 | I153: 8.4510013 | J153: 8.4741892 | K153: 8.1602939 | L153: 8.3189735 | M153: 8.2246163 | P153: 2.1538702 | Q153: 2.5451984 | R153: 2.1382171 | S153: 2.9020897 | T153: 10 | U153: 2.6391172 | V153: 5.0465681 | W153: 6.1047194 | X153: 0.21288252 | Y153: 0.98301636 | Z153: 5.8730531 | AA153: 2.8676528 | AB153: 2.523284 | AC153: 1.1771151 | AD153: 2.5076309
A154: Bajaj Finserv Ltd | B154: 6.3174901 | C154: 6.2441568 | D154: 6.1120752 | E154: 5.7267312 | F154: 5.4134934 | G154: 5.7622514 | H154: 5.8735933 | I154: 5.1471889 | J154: 5.1471889 | K154: 5.1471889 | L154: 5.1471889 | M154: 5.1471889 | P154: 2.0568208 | Q154: 1.872114 | R154: 1.3148626 | S154: 3.759881 | T154: 10 | U154: 3.0210535 | V154: 3.9226736 | W154: 2.7580809 | X154: 0.20881271 | Y154: 5.2719731 | Z154: 6.2769038 | AA154: 3.9445879 | AB154: 2.3886671 | AC154: 0.20881271 | AD154: 4.3640917
A155: Bajaj Finance Ltd | B155: 5.5436153 | C155: 5.6032427 | D155: 5.7267312 | E155: 5.5735537 | F155: 5.4134934 | G155: 5.7480858 | H155: 6.4771708 | I155: 5.2945952 | J155: 5.9948293 | K155: 6.3774688 | L155: 6.2069162 | M155: 6.4829496 | P155: 2.9709634 | Q155: 0.20881271 | R155: 1.8752446 | S155: 4.0072004 | T155: 9.3355248 | U155: 3.5657823 | V155: 2.7330359 | W155: 2.1350865 | X155: 0.20881271 | Y155: 1.5715739 | Z155: 6.2080301 | AA155: 3.5970885 | AB155: 1.4150427 | AC155: 0.20881271 | AD155: 3.8193629
A156: Bharat Electronics Ltd | B156: 2.8089974 | C156: 2.6937978 | D156: 2.6432629 | E156: 2.3425135 | F156: 2.1334447 | G156: 3.133802 | H156: 2.9048593 | I156: 1.7406395 | J156: 1.9527646 | K156: 1.5842598 | L156: 1.8904426 | M156: 2.0542715 | P156: 2.3291853 | Q156: 0.20881271 | R156: 2.297879 | S156: 3.2871566 | T156: 9.0443766 | U156: 2.0818659 | V156: 2.1069109 | W156: 3.9915473 | X156: 0.20881271 | Y156: 0.20881271 | Z156: 6.4710026 | AA156: 3.3122016 | AB156: 2.222744 | AC156: 1.2240745 | AD156: 4.2419973
A157: Bharti Airtel Ltd | B157: 2.6937978 | C157: 3.264423 | D157: 3.6935304 | E157: 3.9139708 | F157: 4.0582276 | G157: 3.2928108 | H157: 3.5253887 | I157: 3.133802 | J157: 3.2928108 | K157: 3.264423 | L157: 3.6169113 | M157: 2.9205884 | P157: 2.3698834 | Q157: 1.3899977 | R157: 2.723644 | S157: 4.169993 | T157: 8.8440166 | U157: 2.1851765 | V157: 0.37880567 | W157: 3.4562104 | X157: 0.20881271 | Y157: 1.7594114 | Z157: 6.743367 | AA157: 3.9226736 | AB157: 2.2008296 | AC157: 1.2647726 | AD157: 1.8032402
A158: HCL Technologies Ltd | B158: 0.10530766 | C158: 0.10530766 | D158: 0.10530766 | E158: 0.20759171 | F158: 0.20759171 | G158: 0.30702095 | H158: 0.30702095 | I158: 0.10530766 | J158: 0.10530766 | K158: 0.10530766 | L158: 0.10530766 | M158: 0.10530766 | P158: 2.2070909 | Q158: 2.3260546 | R158: 3.0241841 | S158: 3.5720435 | T158: 8.4182515 | U158: 2.8770447 | V158: 0.20881271 | W158: 3.1212335 | X158: 0.72317445 | Y158: 4.1637317 | Z158: 6.5805745 | AA158: 3.8506692 | AB158: 2.1444784 | AC158: 1.5903577 | AD158: 2.247789
A159: HDFC Bank Ltd | B159: 7.0674289 | C159: 7.4613648 | D159: 7.7478787 | E159: 7.6576802 | F159: 7.6576802 | G159: 7.796132 | H159: 7.5948453 | I159: 8.2633603 | J159: 7.8358498 | K159: 7.7841298 | L159: 8.0615789 | M159: 8.6575895 | P159: 1.9691633 | Q159: 1.1771151 | R159: 3.3716835 | S159: 3.8475385 | T159: 8.9034985 | U159: 3.0680128 | V159: 0.20881271 | W159: 7.8328246 | X159: 0.70126008 | Y159: 0.20881271 | Z159: 6.993817 | AA159: 3.0648822 | AB159: 1.6498396 | AC159: 1.6216639 | AD159: 3.3466385
A160: Hindustan Unilever Ltd | B160: 1.5842598 | C160: 1.6070245 | D160: 1.5382895 | E160: 1.4917183 | F160: 1.4206997 | G160: 3.4585453 | H160: 3.0891754 | I160: 3.133802 | J160: 3.3628061 | K160: 3.02879 | L160: 3.8419956 | M160: 4.0582276 | P160: 1.7124521 | Q160: 1.1176332 | R160: 2.9208734 | S160: 4.5362761 | T160: 8.8565391 | U160: 3.384206 | V160: 1.8063708 | W160: 6.2142913 | X160: 1.2710339 | Y160: 0.20881271 | Z160: 7.0126008 | AA160: 3.5720435 | AB160: 1.8752446 | AC160: 0.92353448 | AD160: 3.083666
A161: ICICI Bank Ltd | B161: 8.1566861 | C161: 8.1746884 | D161: 7.694856 | E161: 7.879034 | F161: 7.948589 | G161: 8.3361761 | H161: 8.2493202 | I161: 8.0689857 | J161: 7.9062448 | K161: 7.9023702 | L161: 7.963863 | M161: 7.9409274 | P161: 1.6780152 | Q161: 1.1270251 | R161: 2.3354465 | S161: 3.8788448 | T161: 8.9441966 | U161: 1.9691633 | V161: 2.6359865 | W161: 6.2612507 | X161: 1.6748846 | Y161: 0.20881271 | Z161: 6.6337951 | AA161: 3.6784848 | AB161: 2.1444784 | AC161: 1.7719339 | AD161: 2.7017297
A162: Infosys Ltd | B162: 1.372555 | C162: 1.4206997 | D162: 1.6070245 | E162: 1.5842598 | F162: 1.2742688 | G162: 1.2492676 | H162: 0.879476 | I162: 0.73751898 | J162: 0.61973471 | K162: 0.64954785 | L162: 0.64954785 | M162: 0.82337012 | P162: 1.7844564 | Q162: 1.8282852 | R162: 1.9942083 | S162: 4.520623 | T162: 9.0819441 | U162: 1.6216639 | V162: 2.398059 | W162: 7.5510683 | X162: 1.8940283 | Y162: 0.77013383 | Z162: 7.3976677 | AA162: 5.0903968 | AB162: 2.1037802 | AC162: 0.20881271 | AD162: 3.1963685
A163: ITC Ltd | B163: 0.43541862 | C163: 0.46680781 | D163: 0.73751898 | E163: 0.76636651 | F163: 0.73751898 | G163: 0.67911358 | H163: 0.76636651 | I163: 0.73751898 | J163: 0.79498232 | K163: 1.2492676 | L163: 1.2990957 | M163: 1.3482365
A164: Kotak Mahindra Bank Ltd | B164: 6.0146402 | C164: 6.3295669 | D164: 6.0992368 | E164: 6.0992368 | F164: 6.1818711 | G164: 6.5685258 | H164: 6.8083053 | I164: 6.8606212 | J164: 7.0230493 | K164: 7.1015682 | L164: 6.9781099 | M164: 7.202066
A165: Larsen & Toubro Ltd | B165: 3.0135324 | C165: 2.9982091 | D165: 3.0135324 | E165: 3.264423 | F165: 3.5779749 | G165: 4.0192785 | H165: 3.937643 | I165: 3.4854333 | J165: 3.51212 | K165: 3.9020755 | L165: 3.9258266 | M165: 4.0582276
A166: Mahindra & Mahindra Ltd | B166: 3.3628061 | C166: 3.3489166 | D166: 3.3628061 | E166: 3.3766417 | F166: 3.1632456 | G166: 3.3489166 | H166: 3.0439826 | I166: 2.8572508 | J166: 3.0439826 | K166: 2.7436259 | L166: 2.7104847 | M166: 2.8251546
A167: Maruti Suzuki India Ltd | B167: 0.93471199 | C167: 1.0954603 | D167: 1.0954603 | E167: 1.0426793 | F167: 1.0159927 | G167: 0.8515335 | H167: 0.96201212 | I167: 1.0426793 | J167: 1.0691676 | K167: 1.2240898 | L167: 1.5382895 | M167: 1.7187154
A168: NTPC Ltd | B168: 2.7270938 | C168: 2.8731911 | D168: 3.0135324 | E168: 3.0135324 | F168: 3.0891754 | G168: 3.133802 | H168: 2.9048593 | I168: 2.6937978 | J168: 2.5399905 | K168: 2.3792422 | L168: 2.3974655 | M168: 1.9527646
A169: Power Grid Corporation of India Ltd | B169: 3.133802 | C169: 3.1485542 | D169: 3.2928108 | E169: 3.6297962 | F169: 3.7561445 | G169: 4.0582276 | H169: 4.0582276 | I169: 4.0582276 | J169: 4.0582276 | K169: 4.0582276 | L169: 4.0582276 | M169: 4.0582276
A170: Reliance Industries Ltd | B170: 1.2240898 | C170: 1.2240898 | D170: 1.2990957 | E170: 1.0426793 | F170: 0.98910464 | G170: 1.784087 | H170: 1.8904426 | I170: 1.7187154 | J170: 1.8904426 | K170: 1.9321115 | L170: 1.8482806 | M170: 1.8482806
A171: State Bank of India | B171: 9.643081 | C171: 9.9198198 | D171: 9.9981708 | E171: 10 | F171: 10 | G171: 10 | H171: 10 | I171: 9.8057874 | J171: 9.8397069 | K171: 9.9700757 | L171: 10 | M171: 9.9286111
A172: Sun Pharmaceutical Industries Ltd | B172: 0.8515335 | C172: 1.0426793 | D172: 1.1731939 | E172: 1.1731939 | F172: 1.1731939 | G172: 1.2742688 | H172: 1.1987327 | I172: 1.2240898 | J172: 1.0159927 | K172: 1.0159927 | L172: 1.2492676 | M172: 0.93471199
A173: Tata Motors Ltd | B173: 1.5382895 | C173: 2.7436259 | D173: 4.0582276 | E173: 4.0582276 | F173: 4.0077302 | G173: 3.3766417 | H173: 3.2786451 | I173: 2.1334447 | J173: 2.9362485 | K173: 2.0542715 | L173: 2.8572508 | M173: 2.1723812
A174: Tata Steel Ltd | B174: 2.4336348 | C174: 2.2679003 | D174: 2.0140151 | E174: 1.6744583 | F174: 2.6432629 | G174: 3.3904237 | H174: 3.0741747 | I174: 3.2786451 | J174: 4.0582276 | K174: 3.8419956 | L174: 4.0582276 | M174: 3.5253887
... A179: UltraTech Cement Ltd | B179: 1.0159927 | C179: 0.55934937 | D179: 0.58966998 | E179: 0.64954785 | F179: 1.1987327 | G179: 1.5613488 | H179: 2.2108967 | I179: 1.911338 | J179: 0.96201212 | K179: 1.0426793 | L179: 1.1987327 | M179: 1.2240898
A183: DEBT TO EQUITY | B183: Adani Ports and Special Economic Zone Ltd | C183: Asian Paints Ltd | D183: AXIS Bank Ltd | E183: Bajaj Finserv Ltd | F183: Bajaj Finance Ltd | G183: Bharat Electronics Ltd | H183: Bharti Airtel Ltd | I183: HCL Technologies Ltd | J183: HDFC Bank Ltd | K183: Hindustan Unilever Ltd | L183: ICICI Bank Ltd | M183: Infosys Ltd | N183: ITC Ltd | O183: Kotak Mahindra Bank Ltd | P183: Larsen & Toubro Ltd | Q183: Mahindra & Mahindra Ltd | R183: Maruti Suzuki India Ltd | S183: NTPC Ltd | T183: Power Grid Corporation of India Ltd | U183: Reliance Industries Ltd | V183: State Bank of India | W183: Sun Pharmaceutical Industries Ltd | X183: Tata Motors Ltd | Y183: Tata Steel Ltd | Z183: Tata Consultancy Services Ltd | AA183: Tech Mahindra Ltd | AB183: Titan Company Ltd | AC183: Trent Ltd | AD183: UltraTech Cement Ltd
A184: 2025 | X184: 1.5382895
A185: 2024 | X185: 2.7436259
A186: 2023 | X186: 4.0582276
A187: 2022 | B187: 2.7927667 | C187: 0.20759171 | D187: 8.2458016 | E187: 5.7267312 | F187: 5.5735537 | G187: 2.3425135 | H187: 3.9139708 | I187: 0.20759171 | J187: 7.6576802 | K187: 1.4917183 | L187: 7.879034 | M187: 1.5842598 | N187: 0.76636651 | O187: 6.0992368 | P187: 3.264423 | Q187: 3.3766417 | R187: 1.0426793 | S187: 3.0135324 | T187: 3.6297962 | U187: 1.0426793 | V187: 10 | W187: 1.1731939 | X187: 4.0582276 | Y187: 1.6744583 | Z187: 1.6296445 | AA187: 0.20759171 | AB187: 0.20759171 | AC187: 0.67911358 | AD187: 0.64954785
A188: 2021 | B188: 2.6937978 | C188: 0.10530766 | D188: 8.080067 | E188: 5.4134934 | F188: 5.4134934 | G188: 2.1334447 | H188: 4.0582276 | I188: 0.20759171 | J188: 7.6576802 | K188: 1.4206997 | L188: 7.948589 | M188: 1.2742688 | N188: 0.73751898 | O188: 6.1818711 | P188: 3.5779749 | Q188: 3.1632456 | R188: 1.0159927 | S188: 3.0891754 | T188: 3.7561445 | U188: 0.98910464 | V188: 10 | W188: 1.1731939 | X188: 4.0077302 | Y188: 2.6432629 | Z188: 1.4445302 | AA188: 0.24104407 | AB188: 1.6296445 | AC188: 0.10530766 | AD188: 1.1987327
A189: 2020 | B189: 2.6262574 | C189: 0.10530766 | D189: 7.8279416 | E189: 5.7622514 | F189: 5.7480858 | G189: 3.133802 | H189: 3.2928108 | I189: 0.30702095 | J189: 7.796132 | K189: 3.4585453 | L189: 8.3361761 | M189: 1.2492676 | N189: 0.67911358 | O189: 6.5685258 | P189: 4.0192785 | Q189: 3.3489166 | R189: 0.8515335 | S189: 3.133802 | T189: 4.0582276 | U189: 1.784087 | V189: 10 | W189: 1.2742688 | X189: 3.3766417 | Y189: 3.3904237 | Z189: 1.2492676 | AA189: 0.37179818 | AB189: 1.0691676 | AC189: 0.43541862 | AD189: 1.5613488
A190: 2019 | B190: 2.5920009 | C190: 0.24104407 | D190: 8.849882 | E190: 5.8735933 | F190: 6.4771708 | G190: 2.9048593 | H190: 3.5253887 | I190: 0.30702095 | J190: 7.5948453 | K190: 3.0891754 | L190: 8.2493202 | M190: 0.879476 | N190: 0.76636651 | O190: 6.8083053 | P190: 3.937643 | Q190: 3.0439826 | R190: 0.96201212 | S190: 2.9048593 | T190: 4.0582276 | U190: 1.8904426 | V190: 10 | W190: 1.1987327 | X190: 3.2786451 | Y190: 3.0741747 | Z190: 0.82337012 | AA190: 0.24104407 | AB190: 1.1731939 | AC190: 0.76636651 | AD190: 2.2108967
...

Sheet Fuzzy_Parameters
A1: DILUTED EPS
A2: TMF Coords
A3: a | B3: P20 | C3: =_xlfn.PERCENTILE.INC(Fuzzy_Inputs_10!$E$2:$M$30, 0.2) -> 0.54951211
A4: b | B4: P40 | C4: =_xlfn.PERCENTILE.INC(Fuzzy_Inputs_10!$E$2:$M$30, 0.4) -> 1.0280678
A5: c | B5: P60 | C5: =_xlfn.PERCENTILE.INC(Fuzzy_Inputs_10!$E$2:$M$30, 0.6) -> 2.1174889
A6: d | B6: P80 | C6: =_xlfn.PERCENTILE.INC(Fuzzy_Inputs_10!$E$2:$M$30, 0.8) -> 4.0125054
A9: PAYOUT RATIO
A10: TMF Coords
A11: a | B11: P20 | C11: =_xlfn.PERCENTILE.INC(Fuzzy_Inputs_10!$E$35:$M$63, 0.2) -> 0.39213012
A12: b | B12: P40 | C12: =_xlfn.PERCENTILE.INC(Fuzzy_Inputs_10!$E$35:$M$63, 0.4) -> 1.689001
A13: c | B13: P60 | C13: =_xlfn.PERCENTILE.INC(Fuzzy_Inputs_10!$E$35:$M$63, 0.6) -> 2.7960582
A14: d | B14: P80 | C14: =_xlfn.PERCENTILE.INC(Fuzzy_Inputs_10!$E$35:$M$63, 0.8) -> 4.8203589
A17: Price To SAles
A18: TMF Coords
A19: a | B19: P20 | C19: =_xlfn.PERCENTILE.INC(Fuzzy_Inputs_10!$E$68:$M$96, 0.2) -> 1.5766924
A20: b | B20: P40 | C20: =_xlfn.PERCENTILE.INC(Fuzzy_Inputs_10!$E$68:$M$96, 0.4) -> 2.9934304
A21: c | B21: P60 | C21: =_xlfn.PERCENTILE.INC(Fuzzy_Inputs_10!$E$68:$M$96, 0.6) -> 4.3187661
A22: d | B22: P80 | C22: =_xlfn.PERCENTILE.INC(Fuzzy_Inputs_10!$E$68:$M$96, 0.8) -> 6.7752071
A25: DEBT TO EQUITY
A26: TMF Coords
A27: a | B27: P20 | C27: =_xlfn.PERCENTILE.INC(Fuzzy_Inputs_10!$E$101:$M$129, 0.2) -> 0.82337012
A28: b | B28: P40 | C28: =_xlfn.PERCENTILE.INC(Fuzzy_Inputs_10!$E$101:$M$129, 0.4) -> 1.7406395
A29: c | B29: P60 | C29: =_xlfn.PERCENTILE.INC(Fuzzy_Inputs_10!$E$101:$M$129, 0.6) -> 3.1632456
A30: d | B30: P80 | C30: =_xlfn.PERCENTILE.INC(Fuzzy_Inputs_10!$E$101:$M$129, 0.8) -> 5.7480858

Sheet Membership_Functions
A1: Factors in terms of linguistic variables | B1: Linguistic Values | C1: Fuzzy Trapezoidal Membership (a,b,c,d)
A2: Diluted EPS | B2: Low | C2: (0,0,0.5495121079, 1.028067798)
B3: Standard | C3: (0.5495121079, 1.028067798, 2.11748889, 4.012505402)
B4: High | C4: (2.11748889, 4.012505402,10,10)
A5: Payout Ratio | B5: Low | C5: (0,0,0.392130119, 1.689001034)
B6: Standard | C6: (0.392130119, 1.689001034, 2.79605824, 4.820358941)
B7: High | C7: (2.79605824, 4.820358941,10,10)
A8: Price to Sales | B8: Low | C8: (0,0,1.576692374, 2.993430448) | E8: CHANGEEEE
B9: Standard | C9: (1.576692374, 2.993430448,4.318766067,6.775207084)
B10: High | C10: (4.318766067,6.775207084,10,10)
A11: Debt to Equity | B11: Low | C11: (0,0,0.8233701189, 1.740639476)
B12: Standard | C12: (0.8233701189, 1.740639476, 3.163245581, 5.748085778)
B13: High | C13: ( 3.163245581, 5.748085778,10,10)

Sheet Sheet6
A1: Stock | B1: Year | C1: EPS | D1: Payout | E1: PM | F1: DE
A2: Adani Ports and Special Economic Zone Ltd | B2: 2022 | C2: 1.194522 | D2: 2.453939 | E2: 10 | F2: 2.792767
A3: Adani Ports and Special Economic Zone Ltd | B3: 2021 | C3: 1.31136 | D3: 0 | E3: 10 | F3: 2.693798
A4: Adani Ports and Special Economic Zone Ltd | B4: 2020 | C4: 0.978985 | D4: 2.087951 | E4: 4.912882 | F4: 2.626257
A5: Adani Ports and Special Economic Zone Ltd | B5: 2019 | C5: 1.028068 | D5: 1.1798 | E5: 8.1919452 | F5: 2.592001
A6: Adani Ports and Special Economic Zone Ltd | B6: 2018 | C6: 0.946441 | D6: 0.831998 | E6: 7.4150243 | F6: 2.48721
A7: Adani Ports and Special Economic Zone Ltd | B7: 2017 | C7: 1.007795 | D7: 0 | E7: 9.5287061 | F7: 2.808997
A8: Adani Ports and Special Economic Zone Ltd | B8: 2016 | C8: 0.746376 | D8: 1.786749 | E8: 8.2490717 | F8: 3.118988
A9: Adani Ports and Special Economic Zone Ltd | B9: 2015 | C9: 0.596461 | D9: 1.117287 | E9: 10 | F9: 3.133802
A10: Adani Ports and Special Economic Zone Ltd | B10: 2014 | C10: 0.450813 | D10: 1.395756 | E10: 9.1973722 | F10: 3.013532
A11: Asian Paints Ltd | B11: 2022 | C11: 1.685348 | D11: 6.528682 | E11: 10 | F11: 0.207592
A12: Asian Paints Ltd | B12: 2021 | C12: 1.746168 | D12: 1.162751 | E12: 10 | F12: 0.105308
A13: Asian Paints Ltd | B13: 2020 | C13: 1.504489 | D13: 7.314079 | E13: 9.0374179 | F13: 0.105308
... A262: UltraTech Cement Ltd | B262: 2014 | C262: 4.290462 | D262: 1.270729 | E262: 3.1648101 | F262: 1.22409

Sheet Membership_Grades
A1: Stock | B1: Year | C1: EPS_L | D1: EPS_S | E1: EPS_H | F1: PAYOUT_L | G1: PAYOUT_S | H1: PAYOUT_H | I1: PS_L | J1: PS_S | K1: PS_H | L1: DE_L | M1: DE_S | N1: DE_H
A2: Adani Ports and Special Economic Zone Ltd | B2: 2022 | C2: =MAX(MIN(1, (Fuzzy_Parameters!$C$4 - Sheet6!C2)/(Fuzzy_Parameters!$C$4 - Fuzzy_Parameters!$C$3)), 0) -> 0 | D2: =MAX(MIN((Sheet6!C2 - Fuzzy_Parameters!$C$3)/(Fuzzy_Parameters!$C$4 - Fuzzy_Parameters!$C$3), 1, (Fuzzy_Parameters!$C$6 - Sheet6!C2)/(Fuzzy_Parameters!$C$6 - Fuzzy_Parameters!$C$5)), 0) -> 1 | E2: =MAX(MIN((Sheet6!C2 - Fuzzy_Parameters!$C$5)/(Fuzzy_Parameters!$C$6 - Fuzzy_Parameters!$C$5), 1), 0) -> 0 | F2: =MAX(MIN(1, (Fuzzy_Parameters!$C$12 - Sheet6!D2)/(Fuzzy_Parameters!$C$12 - Fuzzy_Parameters!$C$11)), 0) -> 0 | G2: =MAX(MIN((Sheet6!D2 - Fuzzy_Parameters!$C$11)/(Fuzzy_Parameters!$C$12 - Fuzzy_Parameters!$C$11), 1, (Fuzzy_Parameters!$C$14 - Sheet6!D2)/(Fuzzy_Parameters!$C$14 - Fuzzy_Parameters!$C$13)), 0) -> 1 | H2: =MAX(MIN((Sheet6!D2 - Fuzzy_Parameters!$C$13)/(Fuzzy_Parameters!$C$14 - Fuzzy_Parameters!$C$13), 1), 0) -> 0 | I2: =MAX(MIN(1, (Fuzzy_Parameters!$C$20 - Sheet6!E2)/(Fuzzy_Parameters!$C$20 - Fuzzy_Parameters!$C$19)), 0) -> 0 | J2: =MAX(MIN((Sheet6!E2 - Fuzzy_Parameters!$C$19)/(Fuzzy_Parameters!$C$20 - Fuzzy_Parameters!$C$19), 1, (Fuzzy_Parameters!$C$22 - Sheet6!E2)/(Fuzzy_Parameters!$C$22 - Fuzzy_Parameters!$C$21)), 0) -> 0 | K2: =MAX(MIN((Sheet6!E2 - Fuzzy_Parameters!$C$21)/(Fuzzy_Parameters!$C$22 - Fuzzy_Parameters!$C$21), 1), 0) -> 1 | L2: =MAX(MIN(1, (Fuzzy_Parameters!$C$28 - Sheet6!F2)/(Fuzzy_Parameters!$C$28 - Fuzzy_Parameters!$C$27)), 0) -> 0 | M2: =MAX(MIN((Sheet6!F2 - Fuzzy_Parameters!$C$27)/(Fuzzy_Parameters!$C$28 - Fuzzy_Parameters!$C$27), 1, (Fuzzy_Parameters!$C$30 - Sheet6!F2)/(Fuzzy_Parameters!$C$30 - Fuzzy_Parameters!$C$29)), 0) -> 1 | N2: =MAX(MIN((Sheet6!F2 - Fuzzy_Parameters!$C$29)/(Fuzzy_Parameters!$C$30 - Fuzzy_Parameters!$C$29), 1), 0) -> 0
A3: Adani Ports and Special Economic Zone Ltd | B3: 2021 | C3: =MAX(MIN(1, (Fuzzy_Parameters!$C$4 - Sheet6!C3)/(Fuzzy_Parameters!$C$4 - Fuzzy_Parameters!$C$3)), 0) -> 0 | D3: =MAX(MIN((Sheet6!C3 - Fuzzy_Parameters!$C$3)/(Fuzzy_Parameters!$C$4 - Fuzzy_Parameters!$C$3), 1, (Fuzzy_Parameters!$C$6 - Sheet6!C3)/(Fuzzy_Parameters!$C$6 - Fuzzy_Parameters!$C$5)), 0) -> 1 | E3: =MAX(MIN((Sheet6!C3 - Fuzzy_Parameters!$C$5)/(Fuzzy_Parameters!$C$6 - Fuzzy_Parameters!$C$5), 1), 0) -> 0 | F3: =MAX(MIN(1, (Fuzzy_Parameters!$C$12 - Sheet6!D3)/(Fuzzy_Parameters!$C$12 - Fuzzy_Parameters!$C$11)), 0) -> 1 | G3: =MAX(MIN((Sheet6!D3 - Fuzzy_Parameters!$C$11)/(Fuzzy_Parameters!$C$12 - Fuzzy_Parameters!$C$11), 1, (Fuzzy_Parameters!$C$14 - Sheet6!D3)/(Fuzzy_Parameters!$C$14 - Fuzzy_Parameters!$C$13)), 0) -> 0 | H3: =MAX(MIN((Sheet6!D3 - Fuzzy_Parameters!$C$13)/(Fuzzy_Parameters!$C$14 - Fuzzy_Parameters!$C$13), 1), 0) -> 0 | I3: =MAX(MIN(1, (Fuzzy_Parameters!$C$20 - Sheet6!E3)/(Fuzzy_Parameters!$C$20 - Fuzzy_Parameters!$C$19)), 0) -> 0 | J3: =MAX(MIN((Sheet6!E3 - Fuzzy_Parameters!$C$19)/(Fuzzy_Parameters!$C$20 - Fuzzy_Parameters!$C$19), 1, (Fuzzy_Parameters!$C$22 - Sheet6!E3)/(Fuzzy_Parameters!$C$22 - Fuzzy_Parameters!$C$21)), 0) -> 0 | K3: =MAX(MIN((Sheet6!E3 - Fuzzy_Parameters!$C$21)/(Fuzzy_Parameters!$C$22 - Fuzzy_Parameters!$C$21), 1), 0) -> 1 | L3: =MAX(MIN(1, (Fuzzy_Parameters!$C$28 - Sheet6!F3)/(Fuzzy_Parameters!$C$28 - Fuzzy_Parameters!$C$27)), 0) -> 0 | M3: =MAX(MIN((Sheet6!F3 - Fuzzy_Parameters!$C$27)/(Fuzzy_Parameters!$C$28 - Fuzzy_Parameters!$C$27), 1, (Fuzzy_Parameters!$C$30 - Sheet6!F3)/(Fuzzy_Parameters!$C$30 - Fuzzy_Parameters!$C$29)), 0) -> 1 | N3: =MAX(MIN((Sheet6!F3 - Fuzzy_Parameters!$C$29)/(Fuzzy_Parameters!$C$30 - Fuzzy_Parameters!$C$29), 1), 0) -> 0
A4: Adani Ports and Special Economic Zone Ltd | B4: 2020 | C4: =MAX(MIN(1, (Fuzzy_Parameters!$C$4 - Sheet6!C4)/(Fuzzy_Parameters!$C$4 - Fuzzy_Parameters!$C$3)), 0) -> 0.10256444 | D4: =MAX(MIN((Sheet6!C4 - Fuzzy_Parameters!$C$3)/(Fuzzy_Parameters!$C$4 - Fuzzy_Parameters!$C$3), 1, (Fuzzy_Parameters!$C$6 - Sheet6!C4)/(Fuzzy_Parameters!$C$6 - Fuzzy_Parameters!$C$5)), 0) -> 0.89743556 | E4: =MAX(MIN((Sheet6!C4 - Fuzzy_Parameters!$C$5)/(Fuzzy_Parameters!$C$6 - Fuzzy_Parameters!$C$5), 1), 0) -> 0 | F4: =MAX(MIN(1, (Fuzzy_Parameters!$C$12 - Sheet6!D4)/(Fuzzy_Parameters!$C$12 - Fuzzy_Parameters!$C$11)), 0) -> 0 | G4: =MAX(MIN((Sheet6!D4 - Fuzzy_Parameters!$C$11)/(Fuzzy_Parameters!$C$12 - Fuzzy_Parameters!$C$11), 1, (Fuzzy_Parameters!$C$14 - Sheet6!D4)/(Fuzzy_Parameters!$C$14 - Fuzzy_Parameters!$C$13)), 0) -> 1 | H4: =MAX(MIN((Sheet6!D4 - Fuzzy_Parameters!$C$13)/(Fuzzy_Parameters!$C$14 - Fuzzy_Parameters!$C$13), 1), 0) -> 0 | I4: =MAX(MIN(1, (Fuzzy_Parameters!$C$20 - Sheet6!E4)/(Fuzzy_Parameters!$C$20 - Fuzzy_Parameters!$C$19)), 0) -> 0 | J4: =MAX(MIN((Sheet6!E4 - Fuzzy_Parameters!$C$19)/(Fuzzy_Parameters!$C$20 - Fuzzy_Parameters!$C$19), 1, (Fuzzy_Parameters!$C$22 - Sheet6!E4)/(Fuzzy_Parameters!$C$22 - Fuzzy_Parameters!$C$21)), 0) -> 0.75813953 | K4: =MAX(MIN((Sheet6!E4 - Fuzzy_Parameters!$C$21)/(Fuzzy_Parameters!$C$22 - Fuzzy_Parameters!$C$21), 1), 0) -> 0.24186047 | L4: =MAX(MIN(1, (Fuzzy_Parameters!$C$28 - Sheet6!F4)/(Fuzzy_Parameters!$C$28 - Fuzzy_Parameters!$C$27)), 0) -> 0 | M4: =MAX(MIN((Sheet6!F4 - Fuzzy_Parameters!$C$27)/(Fuzzy_Parameters!$C$28 - Fuzzy_Parameters!$C$27), 1, (Fuzzy_Parameters!$C$30 - Sheet6!F4)/(Fuzzy_Parameters!$C$30 - Fuzzy_Parameters!$C$29)), 0) -> 1 | N4: =MAX(MIN((Sheet6!F4 - Fuzzy_Parameters!$C$29)/(Fuzzy_Parameters!$C$30 - Fuzzy_Parameters!$C$29), 1), 0) -> 0
A5: Adani Ports and Special Economic Zone Ltd | B5: 2019 | C5: =MAX(MIN(1, (Fuzzy_Parameters!$C$4 - Sheet6!C5)/(Fuzzy_Parameters!$C$4 - Fuzzy_Parameters!$C$3)), 0) -> 0 | D5: =MAX(MIN((Sheet6!C5 - Fuzzy_Parameters!$C$3)/(Fuzzy_Parameters!$C$4 - Fuzzy_Parameters!$C$3), 1, (Fuzzy_Parameters!$C$6 - Sheet6!C5)/(Fuzzy_Parameters!$C$6 - Fuzzy_Parameters!$C$5)), 0) -> 1 | E5: =MAX(MIN((Sheet6!C5 - Fuzzy_Parameters!$C$5)/(Fuzzy_Parameters!$C$6 - Fuzzy_Parameters!$C$5), 1), 0) -> 0 | F5: =MAX(MIN(1, (Fuzzy_Parameters!$C$12 - Sheet6!D5)/(Fuzzy_Parameters!$C$12 - Fuzzy_Parameters!$C$11)), 0) -> 0.39263818 | G5: =MAX(MIN((Sheet6!D5 - Fuzzy_Parameters!$C$11)/(Fuzzy_Parameters!$C$12 - Fuzzy_Parameters!$C$11), 1, (Fuzzy_Parameters!$C$14 - Sheet6!D5)/(Fuzzy_Parameters!$C$14 - Fuzzy_Parameters!$C$13)), 0) -> 0.60736182 | H5: =MAX(MIN((Sheet6!D5 - Fuzzy_Parameters!$C$13)/(Fuzzy_Parameters!$C$14 - Fuzzy_Parameters!$C$13), 1), 0) -> 0 | I5: =MAX(MIN(1, (Fuzzy_Parameters!$C$20 - Sheet6!E5)/(Fuzzy_Parameters!$C$20 - Fuzzy_Parameters!$C$19)), 0) -> 0 | J5: =MAX(MIN((Sheet6!E5 - Fuzzy_Parameters!$C$19)/(Fuzzy_Parameters!$C$20 - Fuzzy_Parameters!$C$19), 1, (Fuzzy_Parameters!$C$22 - Sheet6!E5)/(Fuzzy_Parameters!$C$22 - Fuzzy_Parameters!$C$21)), 0) -> 0 | K5: =MAX(MIN((Sheet6!E5 - Fuzzy_Parameters!$C$21)/(Fuzzy_Parameters!$C$22 - Fuzzy_Parameters!$C$21), 1), 0) -> 1 | L5: =MAX(MIN(1, (Fuzzy_Parameters!$C$28 - Sheet6!F5)/(Fuzzy_Parameters!$C$28 - Fuzzy_Parameters!$C$27)), 0) -> 0 | M5: =MAX(MIN((Sheet6!F5 - Fuzzy_Parameters!$C$27)/(Fuzzy_Parameters!$C$28 - Fuzzy_Parameters!$C$27), 1, (Fuzzy_Parameters!$C$30 - Sheet6!F5)/(Fuzzy_Parameters!$C$30 - Fuzzy_Parameters!$C$29)), 0) -> 1 | N5: =MAX(MIN((Sheet6!F5 - Fuzzy_Parameters!$C$29)/(Fuzzy_Parameters!$C$30 - Fuzzy_Parameters!$C$29), 1), 0) -> 0
A6: Adani Ports and Special Economic Zone Ltd | B6: 2018 | C6: =MAX(MIN(1, (Fuzzy_Parameters!$C$4 - Sheet6!C6)/(Fuzzy_Parameters!$C$4 - Fuzzy_Parameters!$C$3)), 0) -> 0.17056907 | D6: =MAX(MIN((Sheet6!C6 - Fuzzy_Parameters!$C$3)/(Fuzzy_Parameters!$C$4 - Fuzzy_Parameters!$C$3), 1, (Fuzzy_Parameters!$C$6 - Sheet6!C6)/(Fuzzy_Parameters!$C$6 - Fuzzy_Parameters!$C$5)), 0) -> 0.82943093 | E6: =MAX(MIN((Sheet6!C6 - Fuzzy_Parameters!$C$5)/(Fuzzy_Parameters!$C$6 - Fuzzy_Parameters!$C$5), 1), 0) -> 0 | F6: =MAX(MIN(1, (Fuzzy_Parameters!$C$12 - Sheet6!D6)/(Fuzzy_Parameters!$C$12 - Fuzzy_Parameters!$C$11)), 0) -> 0.6608237 | G6: =MAX(MIN((Sheet6!D6 - Fuzzy_Parameters!$C$11)/(Fuzzy_Parameters!$C$12 - Fuzzy_Parameters!$C$11), 1, (Fuzzy_Parameters!$C$14 - Sheet6!D6)/(Fuzzy_Parameters!$C$14 - Fuzzy_Parameters!$C$13)), 0) -> 0.3391763 | H6: =MAX(MIN((Sheet6!D6 - Fuzzy_Parameters!$C$13)/(Fuzzy_Parameters!$C$14 - Fuzzy_Parameters!$C$13), 1), 0) -> 0 | I6: =MAX(MIN(1, (Fuzzy_Parameters!$C$20 - Sheet6!E6)/(Fuzzy_Parameters!$C$20 - Fuzzy_Parameters!$C$19)), 0) -> 0 | J6: =MAX(MIN((Sheet6!E6 - Fuzzy_Parameters!$C$19)/(Fuzzy_Parameters!$C$20 - Fuzzy_Parameters!$C$19), 1, (Fuzzy_Parameters!$C$22 - Sheet6!E6)/(Fuzzy_Parameters!$C$22 - Fuzzy_Parameters!$C$21)), 0) -> 0 | K6: =MAX(MIN((Sheet6!E6 - Fuzzy_Parameters!$C$21)/(Fuzzy_Parameters!$C$22 - Fuzzy_Parameters!$C$21), 1), 0) -> 1 | L6: =MAX(MIN(1, (Fuzzy_Parameters!$C$28 - Sheet6!F6)/(Fuzzy_Parameters!$C$28 - Fuzzy_Parameters!$C$27)), 0) -> 0 | M6: =MAX(MIN((Sheet6!F6 - Fuzzy_Parameters!$C$27)/(Fuzzy_Parameters!$C$28 - Fuzzy_Parameters!$C$27), 1, (Fuzzy_Parameters!$C$30 - Sheet6!F6)/(Fuzzy_Parameters!$C$30 - Fuzzy_Parameters!$C$29)), 0) -> 1 | N6: =MAX(MIN((Sheet6!F6 - Fuzzy_Parameters!$C$29)/(Fuzzy_Parameters!$C$30 - Fuzzy_Parameters!$C$29), 1), 0) -> 0
A7: Adani Ports and Special Economic Zone Ltd | B7: 2017 | C7: =MAX(MIN(1, (Fuzzy_Parameters!$C$4 - Sheet6!C7)/(Fuzzy_Parameters!$C$4 - Fuzzy_Parameters!$C$3)), 0) -> 0.042362464 | D7: =MAX(MIN((Sheet6!C7 - Fuzzy_Parameters!$C$3)/(Fuzzy_Parameters!$C$4 - Fuzzy_Parameters!$C$3), 1, (Fuzzy_Parameters!$C$6 - Sheet6!C7)/(Fuzzy_Parameters!$C$6 - Fuzzy_Parameters!$C$5)), 0) -> 0.95763754 | E7: =MAX(MIN((Sheet6!C7 - Fuzzy_Parameters!$C$5)/(Fuzzy_Parameters!$C$6 - Fuzzy_Parameters!$C$5), 1), 0) -> 0 | F7: =MAX(MIN(1, (Fuzzy_Parameters!$C$12 - Sheet6!D7)/(Fuzzy_Parameters!$C$12 - Fuzzy_Parameters!$C$11)), 0) -> 1 | G7: =MAX(MIN((Sheet6!D7 - Fuzzy_Parameters!$C$11)/(Fuzzy_Parameters!$C$12 - Fuzzy_Parameters!$C$11), 1, (Fuzzy_Parameters!$C$14 - Sheet6!D7)/(Fuzzy_Parameters!$C$14 - Fuzzy_Parameters!$C$13)), 0) -> 0 | H7: =MAX(MIN((Sheet6!D7 - Fuzzy_Parameters!$C$13)/(Fuzzy_Parameters!$C$14 - Fuzzy_Parameters!$C$13), 1), 0) -> 0 | I7: =MAX(MIN(1, (Fuzzy_Parameters!$C$20 - Sheet6!E7)/(Fuzzy_Parameters!$C$20 - Fuzzy_Parameters!$C$19)), 0) -> 0 | J7: =MAX(MIN((Sheet6!E7 - Fuzzy_Parameters!$C$19)/(Fuzzy_Parameters!$C$20 - Fuzzy_Parameters!$C$19), 1, (Fuzzy_Parameters!$C$22 - Sheet6!E7)/(Fuzzy_Parameters!$C$22 - Fuzzy_Parameters!$C$21)), 0) -> 0 | K7: =MAX(MIN((Sheet6!E7 - Fuzzy_Parameters!$C$21)/(Fuzzy_Parameters!$C$22 - Fuzzy_Parameters!$C$21), 1), 0) -> 1 | L7: =MAX(MIN(1, (Fuzzy_Parameters!$C$28 - Sheet6!F7)/(Fuzzy_Parameters!$C$28 - Fuzzy_Parameters!$C$27)), 0) -> 0 | M7: =MAX(MIN((Sheet6!F7 - Fuzzy_Parameters!$C$27)/(Fuzzy_Parameters!$C$28 - Fuzzy_Parameters!$C$27), 1, (Fuzzy_Parameters!$C$30 - Sheet6!F7)/(Fuzzy_Parameters!$C$30 - Fuzzy_Parameters!$C$29)), 0) -> 1 | N7: =MAX(MIN((Sheet6!F7 - Fuzzy_Parameters!$C$29)/(Fuzzy_Parameters!$C$30 - Fuzzy_Parameters!$C$29), 1), 0) -> 0
A8: Adani Ports and Special Economic Zone Ltd | B8: 2016 | C8: =MAX(MIN(1, (Fuzzy_Parameters!$C$4 - Sheet6!C8)/(Fuzzy_Parameters!$C$4 - Fuzzy_Parameters!$C$3)), 0) -> 0.58862909 | D8: =MAX(MIN((Sheet6!C8 - Fuzzy_Parameters!$C$3)/(Fuzzy_Parameters!$C$4 - Fuzzy_Parameters!$C$3), 1, (Fuzzy_Parameters!$C$6 - Sheet6!C8)/(Fuzzy_Parameters!$C$6 - Fuzzy_Parameters!$C$5)), 0) -> 0.41137091 | E8: =MAX(MIN((Sheet6!C8 - Fuzzy_Parameters!$C$5)/(Fuzzy_Parameters!$C$6 - Fuzzy_Parameters!$C$5), 1), 0) -> 0 | F8: =MAX(MIN(1, (Fuzzy_Parameters!$C$12 - Sheet6!D8)/(Fuzzy_Parameters!$C$12 - Fuzzy_Parameters!$C$11)), 0) -> 0 | G8: =MAX(MIN((Sheet6!D8 - Fuzzy_Parameters!$C$11)/(Fuzzy_Parameters!$C$12 - Fuzzy_Parameters!$C$11), 1, (Fuzzy_Parameters!$C$14 - Sheet6!D8)/(Fuzzy_Parameters!$C$14 - Fuzzy_Parameters!$C$13)), 0) -> 1 | H8: =MAX(MIN((Sheet6!D8 - Fuzzy_Parameters!$C$13)/(Fuzzy_Parameters!$C$14 - Fuzzy_Parameters!$C$13), 1), 0) -> 0 | I8: =MAX(MIN(1, (Fuzzy_Parameters!$C$20 - Sheet6!E8)/(Fuzzy_Parameters!$C$20 - Fuzzy_Parameters!$C$19)), 0) -> 0 | J8: =MAX(MIN((Sheet6!E8 - Fuzzy_Parameters!$C$19)/(Fuzzy_Parameters!$C$20 - Fuzzy_Parameters!$C$19), 1, (Fuzzy_Parameters!$C$22 - Sheet6!E8)/(Fuzzy_Parameters!$C$22 - Fuzzy_Parameters!$C$21)), 0) -> 0 | K8: =MAX(MIN((Sheet6!E8 - Fuzzy_Parameters!$C$21)/(Fuzzy_Parameters!$C$22 - Fuzzy_Parameters!$C$21), 1), 0) -> 1 | L8: =MAX(MIN(1, (Fuzzy_Parameters!$C$28 - Sheet6!F8)/(Fuzzy_Parameters!$C$28 - Fuzzy_Parameters!$C$27)), 0) -> 0 | M8: =MAX(MIN((Sheet6!F8 - Fuzzy_Parameters!$C$27)/(Fuzzy_Parameters!$C$28 - Fuzzy_Parameters!$C$27), 1, (Fuzzy_Parameters!$C$30 - Sheet6!F8)/(Fuzzy_Parameters!$C$30 - Fuzzy_Parameters!$C$29)), 0) -> 1 | N8: =MAX(MIN((Sheet6!F8 - Fuzzy_Parameters!$C$29)/(Fuzzy_Parameters!$C$30 - Fuzzy_Parameters!$C$29), 1), 0) -> 0
A9: Adani Ports and Special Economic Zone Ltd | B9: 2015 | C9: =MAX(MIN(1, (Fuzzy_Parameters!$C$4 - Sheet6!C9)/(Fuzzy_Parameters!$C$4 - Fuzzy_Parameters!$C$3)), 0) -> 0.90189461 | D9: =MAX(MIN((Sheet6!C9 - Fuzzy_Parameters!$C$3)/(Fuzzy_Parameters!$C$4 - Fuzzy_Parameters!$C$3), 1, (Fuzzy_Parameters!$C$6 - Sheet6!C9)/(Fuzzy_Parameters!$C$6 - Fuzzy_Parameters!$C$5)), 0) -> 0.098105389 | E9: =MAX(MIN((Sheet6!C9 - Fuzzy_Parameters!$C$5)/(Fuzzy_Parameters!$C$6 - Fuzzy_Parameters!$C$5), 1), 0) -> 0 | F9: =MAX(MIN(1, (Fuzzy_Parameters!$C$12 - Sheet6!D9)/(Fuzzy_Parameters!$C$12 - Fuzzy_Parameters!$C$11)), 0) -> 0.44084113 | G9: =MAX(MIN((Sheet6!D9 - Fuzzy_Parameters!$C$11)/(Fuzzy_Parameters!$C$12 - Fuzzy_Parameters!$C$11), 1, (Fuzzy_Parameters!$C$14 - Sheet6!D9)/(Fuzzy_Parameters!$C$14 - Fuzzy_Parameters!$C$13)), 0) -> 0.55915887 | H9: =MAX(MIN((Sheet6!D9 - Fuzzy_Parameters!$C$13)/(Fuzzy_Parameters!$C$14 - Fuzzy_Parameters!$C$13), 1), 0) -> 0 | I9: =MAX(MIN(1, (Fuzzy_Parameters!$C$20 - Sheet6!E9)/(Fuzzy_Parameters!$C$20 - Fuzzy_Parameters!$C$19)), 0) -> 0 | J9: =MAX(MIN((Sheet6!E9 - Fuzzy_Parameters!$C$19)/(Fuzzy_Parameters!$C$20 - Fuzzy_Parameters!$C$19), 1, (Fuzzy_Parameters!$C$22 - Sheet6!E9)/(Fuzzy_Parameters!$C$22 - Fuzzy_Parameters!$C$21)), 0) -> 0 | K9: =MAX(MIN((Sheet6!E9 - Fuzzy_Parameters!$C$21)/(Fuzzy_Parameters!$C$22 - Fuzzy_Parameters!$C$21), 1), 0) -> 1 | L9: =MAX(MIN(1, (Fuzzy_Parameters!$C$28 - Sheet6!F9)/(Fuzzy_Parameters!$C$28 - Fuzzy_Parameters!$C$27)), 0) -> 0 | M9: =MAX(MIN((Sheet6!F9 - Fuzzy_Parameters!$C$27)/(Fuzzy_Parameters!$C$28 - Fuzzy_Parameters!$C$27), 1, (Fuzzy_Parameters!$C$30 - Sheet6!F9)/(Fuzzy_Parameters!$C$30 - Fuzzy_Parameters!$C$29)), 0) -> 1 | N9: =MAX(MIN((Sheet6!F9 - Fuzzy_Parameters!$C$29)/(Fuzzy_Parameters!$C$30 - Fuzzy_Parameters!$C$29), 1), 0) -> 0
A10: Adani Ports and Special Economic Zone Ltd | B10: 2014 | C10: =MAX(MIN(1, (Fuzzy_Parameters!$C$4 - Sheet6!C10)/(Fuzzy_Parameters!$C$4 - Fuzzy_Parameters!$C$3)), 0) -> 1 | D10: =MAX(MIN((Sheet6!C10 - Fuzzy_Parameters!$C$3)/(Fuzzy_Parameters!$C$4 - Fuzzy_Parameters!$C$3), 1, (Fuzzy_Parameters!$C$6 - Sheet6!C10)/(Fuzzy_Parameters!$C$6 - Fuzzy_Parameters!$C$5)), 0) -> 0 | E10: =MAX(MIN((Sheet6!C10 - Fuzzy_Parameters!$C$5)/(Fuzzy_Parameters!$C$6 - Fuzzy_Parameters!$C$5), 1), 0) -> 0 | F10: =MAX(MIN(1, (Fuzzy_Parameters!$C$12 - Sheet6!D10)/(Fuzzy_Parameters!$C$12 - Fuzzy_Parameters!$C$11)), 0) -> 0.22611737 | G10: =MAX(MIN((Sheet6!D10 - Fuzzy_Parameters!$C$11)/(Fuzzy_Parameters!$C$12 - Fuzzy_Parameters!$C$11), 1, (Fuzzy_Parameters!$C$14 - Sheet6!D10)/(Fuzzy_Parameters!$C$14 - Fuzzy_Parameters!$C$13)), 0) -> 0.77388263 | H10: =MAX(MIN((Sheet6!D10 - Fuzzy_Parameters!$C$13)/(Fuzzy_Parameters!$C$14 - Fuzzy_Parameters!$C$13), 1), 0) -> 0 | I10: =MAX(MIN(1, (Fuzzy_Parameters!$C$20 - Sheet6!E10)/(Fuzzy_Parameters!$C$20 - Fuzzy_Parameters!$C$19)), 0) -> 0 | J10: =MAX(MIN((Sheet6!E10 - Fuzzy_Parameters!$C$19)/(Fuzzy_Parameters!$C$20 - Fuzzy_Parameters!$C$19), 1, (Fuzzy_Parameters!$C$22 - Sheet6!E10)/(Fuzzy_Parameters!$C$22 - Fuzzy_Parameters!$C$21)), 0) -> 0 | K10: =MAX(MIN((Sheet6!E10 - Fuzzy_Parameters!$C$21)/(Fuzzy_Parameters!$C$22 - Fuzzy_Parameters!$C$21), 1), 0) -> 1 | L10: =MAX(MIN(1, (Fuzzy_Parameters!$C$28 - Sheet6!F10)/(Fuzzy_Parameters!$C$28 - Fuzzy_Parameters!$C$27)), 0) -> 0 | M10: =MAX(MIN((Sheet6!F10 - Fuzzy_Parameters!$C$27)/(Fuzzy_Parameters!$C$28 - Fuzzy_Parameters!$C$27), 1, (Fuzzy_Parameters!$C$30 - Sheet6!F10)/(Fuzzy_Parameters!$C$30 - Fuzzy_Parameters!$C$29)), 0) -> 1 | N10: =MAX(MIN((Sheet6!F10 - Fuzzy_Parameters!$C$29)/(Fuzzy_Parameters!$C$30 - Fuzzy_Parameters!$C$29), 1), 0) -> 0
A11: Asian Paints Ltd | B11: 2022 | C11: =MAX(MIN(1, (Fuzzy_Parameters!$C$4 - Sheet6!C11)/(Fuzzy_Parameters!$C$4 - Fuzzy_Parameters!$C$3)), 0) -> 0 | D11: =MAX(MIN((Sheet6!C11 - Fuzzy_Parameters!$C$3)/(Fuzzy_Parameters!$C$4 - Fuzzy_Parameters!$C$3), 1, (Fuzzy_Parameters!$C$6 - Sheet6!C11)/(Fuzzy_Parameters!$C$6 - Fuzzy_Parameters!$C$5)), 0) -> 1 | E11: =MAX(MIN((Sheet6!C11 - Fuzzy_Parameters!$C$5)/(Fuzzy_Parameters!$C$6 - Fuzzy_Parameters!$C$5), 1), 0) -> 0 | F11: =MAX(MIN(1, (Fuzzy_Parameters!$C$12 - Sheet6!D11)/(Fuzzy_Parameters!$C$12 - Fuzzy_Parameters!$C$11)), 0) -> 0 | G11: =MAX(MIN((Sheet6!D11 - Fuzzy_Parameters!$C$11)/(Fuzzy_Parameters!$C$12 - Fuzzy_Parameters!$C$11), 1, (Fuzzy_Parameters!$C$14 - Sheet6!D11)/(Fuzzy_Parameters!$C$14 - Fuzzy_Parameters!$C$13)), 0) -> 0 | H11: =MAX(MIN((Sheet6!D11 - Fuzzy_Parameters!$C$13)/(Fuzzy_Parameters!$C$14 - Fuzzy_Parameters!$C$13), 1), 0) -> 1 | I11: =MAX(MIN(1, (Fuzzy_Parameters!$C$20 - Sheet6!E11)/(Fuzzy_Parameters!$C$20 - Fuzzy_Parameters!$C$19)), 0) -> 0 | J11: =MAX(MIN((Sheet6!E11 - Fuzzy_Parameters!$C$19)/(Fuzzy_Parameters!$C$20 - Fuzzy_Parameters!$C$19), 1, (Fuzzy_Parameters!$C$22 - Sheet6!E11)/(Fuzzy_Parameters!$C$22 - Fuzzy_Parameters!$C$21)), 0) -> 0 | K11: =MAX(MIN((Sheet6!E11 - Fuzzy_Parameters!$C$21)/(Fuzzy_Parameters!$C$22 - Fuzzy_Parameters!$C$21), 1), 0) -> 1 | L11: =MAX(MIN(1, (Fuzzy_Parameters!$C$28 - Sheet6!F11)/(Fuzzy_Parameters!$C$28 - Fuzzy_Parameters!$C$27)), 0) -> 1 | M11: =MAX(MIN((Sheet6!F11 - Fuzzy_Parameters!$C$27)/(Fuzzy_Parameters!$C$28 - Fuzzy_Parameters!$C$27), 1, (Fuzzy_Parameters!$C$30 - Sheet6!F11)/(Fuzzy_Parameters!$C$30 - Fuzzy_Parameters!$C$29)), 0) -> 0 | N11: =MAX(MIN((Sheet6!F11 - Fuzzy_Parameters!$C$29)/(Fuzzy_Parameters!$C$30 - Fuzzy_Parameters!$C$29), 1), 0) -> 0
A12: Asian Paints Ltd | B12: 2021 | C12: =MAX(MIN(1, (Fuzzy_Parameters!$C$4 - Sheet6!C12)/(Fuzzy_Parameters!$C$4 - Fuzzy_Parameters!$C$3)), 0) -> 0 | D12: =MAX(MIN((Sheet6!C12 - Fuzzy_Parameters!$C$3)/(Fuzzy_Parameters!$C$4 - Fuzzy_Parameters!$C$3), 1, (Fuzzy_Parameters!$C$6 - Sheet6!C12)/(Fuzzy_Parameters!$C$6 - Fuzzy_Parameters!$C$5)), 0) -> 1 | E12: =MAX(MIN((Sheet6!C12 - Fuzzy_Parameters!$C$5)/(Fuzzy_Parameters!$C$6 - Fuzzy_Parameters!$C$5), 1), 0) -> 0 | F12: =MAX(MIN(1, (Fuzzy_Parameters!$C$12 - Sheet6!D12)/(Fuzzy_Parameters!$C$12 - Fuzzy_Parameters!$C$11)), 0) -> 0.40578444 | G12: =MAX(MIN((Sheet6!D12 - Fuzzy_Parameters!$C$11)/(Fuzzy_Parameters!$C$12 - Fuzzy_Parameters!$C$11), 1, (Fuzzy_Parameters!$C$14 - Sheet6!D12)/(Fuzzy_Parameters!$C$14 - Fuzzy_Parameters!$C$13)), 0) -> 0.59421556 | H12: =MAX(MIN((Sheet6!D12 - Fuzzy_Parameters!$C$13)/(Fuzzy_Parameters!$C$14 - Fuzzy_Parameters!$C$13), 1), 0) -> 0 | I12: =MAX(MIN(1, (Fuzzy_Parameters!$C$20 - Sheet6!E12)/(Fuzzy_Parameters!$C$20 - Fuzzy_Parameters!$C$19)), 0) -> 0 | J12: =MAX(MIN((Sheet6!E12 - Fuzzy_Parameters!$C$19)/(Fuzzy_Parameters!$C$20 - Fuzzy_Parameters!$C$19), 1, (Fuzzy_Parameters!$C$22 - Sheet6!E12)/(Fuzzy_Parameters!$C$22 - Fuzzy_Parameters!$C$21)), 0) -> 0 | K12: =MAX(MIN((Sheet6!E12 - Fuzzy_Parameters!$C$21)/(Fuzzy_Parameters!$C$22 - Fuzzy_Parameters!$C$21), 1), 0) -> 1 | L12: =MAX(MIN(1, (Fuzzy_Parameters!$C$28 - Sheet6!F12)/(Fuzzy_Parameters!$C$28 - Fuzzy_Parameters!$C$27)), 0) -> 1 | M12: =MAX(MIN((Sheet6!F12 - Fuzzy_Parameters!$C$27)/(Fuzzy_Parameters!$C$28 - Fuzzy_Parameters!$C$27), 1, (Fuzzy_Parameters!$C$30 - Sheet6!F12)/(Fuzzy_Parameters!$C$30 - Fuzzy_Parameters!$C$29)), 0) -> 0 | N12: =MAX(MIN((Sheet6!F12 - Fuzzy_Parameters!$C$29)/(Fuzzy_Parameters!$C$30 - Fuzzy_Parameters!$C$29), 1), 0) -> 0
A13: Asian Paints Ltd | B13: 2020 | C13: =MAX(MIN(1, (Fuzzy_Parameters!$C$4 - Sheet6!C13)/(Fuzzy_Parameters!$C$4 - Fuzzy_Parameters!$C$3)), 0) -> 0 | D13: =MAX(MIN((Sheet6!C13 - Fuzzy_Parameters!$C$3)/(Fuzzy_Parameters!$C$4 - Fuzzy_Parameters!$C$3), 1, (Fuzzy_Parameters!$C$6 - Sheet6!C13)/(Fuzzy_Parameters!$C$6 - Fuzzy_Parameters!$C$5)), 0) -> 1 | E13: =MAX(MIN((Sheet6!C13 - Fuzzy_Parameters!$C$5)/(Fuzzy_Parameters!$C$6 - Fuzzy_Parameters!$C$5), 1), 0) -> 0 | F13: =MAX(MIN(1, (Fuzzy_Parameters!$C$12 - Sheet6!D13)/(Fuzzy_Parameters!$C$12 - Fuzzy_Parameters!$C$11)), 0) -> 0 | G13: =MAX(MIN((Sheet6!D13 - Fuzzy_Parameters!$C$11)/(Fuzzy_Parameters!$C$12 - Fuzzy_Parameters!$C$11), 1, (Fuzzy_Parameters!$C$14 - Sheet6!D13)/(Fuzzy_Parameters!$C$14 - Fuzzy_Parameters!$C$13)), 0) -> 0 | H13: =MAX(MIN((Sheet6!D13 - Fuzzy_Parameters!$C$13)/(Fuzzy_Parameters!$C$14 - Fuzzy_Parameters!$C$13), 1), 0) -> 1 | I13: =MAX(MIN(1, (Fuzzy_Parameters!$C$20 - Sheet6!E13)/(Fuzzy_Parameters!$C$20 - Fuzzy_Parameters!$C$19)), 0) -> 0 | J13: =MAX(MIN((Sheet6!E13 - Fuzzy_Parameters!$C$19)/(Fuzzy_Parameters!$C$20 - Fuzzy_Parameters!$C$19), 1, (Fuzzy_Parameters!$C$22 - Sheet6!E13)/(Fuzzy_Parameters!$C$22 - Fuzzy_Parameters!$C$21)), 0) -> 0 | K13: =MAX(MIN((Sheet6!E13 - Fuzzy_Parameters!$C$21)/(Fuzzy_Parameters!$C$22 - Fuzzy_Parameters!$C$21), 1), 0) -> 1 | L13: =MAX(MIN(1, (Fuzzy_Parameters!$C$28 - Sheet6!F13)/(Fuzzy_Parameters!$C$28 - Fuzzy_Parameters!$C$27)), 0) -> 1 | M13: =MAX(MIN((Sheet6!F13 - Fuzzy_Parameters!$C$27)/(Fuzzy_Parameters!$C$28 - Fuzzy_Parameters!$C$27), 1, (Fuzzy_Parameters!$C$30 - Sheet6!F13)/(Fuzzy_Parameters!$C$30 - Fuzzy_Parameters!$C$29)), 0) -> 0 | N13: =MAX(MIN((Sheet6!F13 - Fuzzy_Parameters!$C$29)/(Fuzzy_Parameters!$C$30 - Fuzzy_Parameters!$C$29), 1), 0) -> 0
... A262: UltraTech Cement Ltd | B262: 2014 | C262: =MAX(MIN(1, (Fuzzy_Parameters!$C$4 - Sheet6!C262)/(Fuzzy_Parameters!$C$4 - Fuzzy_Parameters!$C$3)), 0) -> 0 | D262: =MAX(MIN((Sheet6!C262 - Fuzzy_Parameters!$C$3)/(Fuzzy_Parameters!$C$4 - Fuzzy_Parameters!$C$3), 1, (Fuzzy_Parameters!$C$6 - Sheet6!C262)/(Fuzzy_Parameters!$C$6 - Fuzzy_Parameters!$C$5)), 0) -> 0 | E262: =MAX(MIN((Sheet6!C262 - Fuzzy_Parameters!$C$5)/(Fuzzy_Parameters!$C$6 - Fuzzy_Parameters!$C$5), 1), 0) -> 1 | F262: =MAX(MIN(1, (Fuzzy_Parameters!$C$12 - Sheet6!D262)/(Fuzzy_Parameters!$C$12 - Fuzzy_Parameters!$C$11)), 0) -> 0.32252403 | G262: =MAX(MIN((Sheet6!D262 - Fuzzy_Parameters!$C$11)/(Fuzzy_Parameters!$C$12 - Fuzzy_Parameters!$C$11), 1, (Fuzzy_Parameters!$C$14 - Sheet6!D262)/(Fuzzy_Parameters!$C$14 - Fuzzy_Parameters!$C$13)), 0) -> 0.67747597 | H262: =MAX(MIN((Sheet6!D262 - Fuzzy_Parameters!$C$13)/(Fuzzy_Parameters!$C$14 - Fuzzy_Parameters!$C$13), 1), 0) -> 0 | I262: =MAX(MIN(1, (Fuzzy_Parameters!$C$20 - Sheet6!E262)/(Fuzzy_Parameters!$C$20 - Fuzzy_Parameters!$C$19)), 0) -> 0 | J262: =MAX(MIN((Sheet6!E262 - Fuzzy_Parameters!$C$19)/(Fuzzy_Parameters!$C$20 - Fuzzy_Parameters!$C$19), 1, (Fuzzy_Parameters!$C$22 - Sheet6!E262)/(Fuzzy_Parameters!$C$22 - Fuzzy_Parameters!$C$21)), 0) -> 1 | K262: =MAX(MIN((Sheet6!E262 - Fuzzy_Parameters!$C$21)/(Fuzzy_Parameters!$C$22 - Fuzzy_Parameters!$C$21), 1), 0) -> 0 | L262: =MAX(MIN(1, (Fuzzy_Parameters!$C$28 - Sheet6!F262)/(Fuzzy_Parameters!$C$28 - Fuzzy_Parameters!$C$27)), 0) -> 0.56313827 | M262: =MAX(MIN((Sheet6!F262 - Fuzzy_Parameters!$C$27)/(Fuzzy_Parameters!$C$28 - Fuzzy_Parameters!$C$27), 1, (Fuzzy_Parameters!$C$30 - Sheet6!F262)/(Fuzzy_Parameters!$C$30 - Fuzzy_Parameters!$C$29)), 0) -> 0.43686173 | N262: =MAX(MIN((Sheet6!F262 - Fuzzy_Parameters!$C$29)/(Fuzzy_Parameters!$C$30 - Fuzzy_Parameters!$C$29), 1), 0) -> 0

Sheet Sheet7
A1: Stock | B1: Year | C1: EPS | D1: Payout | E1: PS | F1: DE
A2: Adani Ports and Special Economic Zone Ltd | B2: 2025 | C2: 2.7395579 | D2: 1.3275594 | E2: 9.3916024 | F2: 1.9527646
B3: 2024 | C3: 2.0033184 | D3: 1.5128266 | E3: 10 | F3: 2.2299994
B4: 2023 | C4: 1.31136 | D4: 2.2595788 | E4: 7.4835761 | F4: 2.6262574
A5: Asian Paints Ltd | B5: 2025 | C5: 2.0406639 | D5: 9.631625 | E5: 7.552128 | F5: 0.13972966
B6: 2024 | C6: 3.0377883 | D6: 5.2704561 | E6: 8.7860611 | F6: 0.20759171
B7: 2023 | C7: 2.2844765 | D7: 5.2829588 | E7: 8.7746358 | F7: 0.20759171
A8: AXIS Bank Ltd | B8: 2025 | C8: 4.8111652 | D8: 0.13525648 | E8: 3.0619823 | F8: 7.7801201
B9: 2024 | C9: 4.5353422 | D9: 0.14207613 | E9: 3.2790631 | F9: 8.091114
B10: 2023 | C10: 1.8694082 | D10: 0.36939794 | E10: 3.4504427 | F10: 8.3396066
A11: Bajaj Finserv Ltd | B11: 2025 | C11: 0.51750169 | D11: 0.20345302 | E11: 2.7306484 | F11: 6.3174901
B12: 2024 | C12: 0.38946004 | D12: 0.17731101 | E12: 2.7077978 | F12: 6.2441568
B13: 2023 | C13: 0.24541317 | D13: 0.1125243 | E13: 2.8106255 | F13: 6.1120752
A14: Bajaj Finance Ltd | B14: 2025 | C14: 10 | D14: 1.5207829 | E14: 9.1059697 | F14: 5.5436153
B15: 2024 | C15: 10 | D15: 1.427581 | E15: 9.3001999 | F15: 5.6032427
B16: 2023 | C16: 10 | D16: 1.1923029 | E16: 9.3687518 | F16: 5.7267312
A17: Bharat Electronics Ltd | B17: 2025 | C17: 0.38839302 | D17: 3.590548 | E17: 10 | F17: 2.8089974
B18: 2024 | C18: 0.29076126 | D18: 4.1702186 | E18: 8.3061982 | F18: 2.6937978
B19: 2023 | C19: 0.21820432 | D19: 4.7317034 | E19: 4.5929734 | F19: 2.6432629
A20: Bharti Airtel Ltd | B20: 2025 | C20: 2.9897727 | D20: 1.5673839 | E20: 6.6266781 | F20: 2.6937978
B21: 2024 | C21: 0.68288883 | D21: 3.4632477 | E21: 5.3813196 | F21: 3.264423
B22: 2023 | C22: 0.77731955 | D22: 2.3118628 | E22: 3.4847187 | F22: 3.6935304
A23: HCL Technologies Ltd | B23: 2025 | C23: 3.4192457 | D23: 10 | E23: 4.2159383 | F23: 0.10530766
B24: 2024 | C24: 3.0868709 | D24: 10 | E24: 4.353042 | F24: 0.10530766
B25: 2023 | C25: 2.9230843 | D25: 9.9453291 | E25: 3.3247644 | F25: 0.10530766
A26: HDFC Bank Ltd | B26: 2025 | C26: 4.9290703 | D26: 2.8472056 | E26: 5.3241931 | F26: 7.0674289
B27: 2024 | C27: 4.8020956 | D27: 2.7710528 | E27: 4.8671808 | F27: 7.4613648
B28: 2023 | C28: 4.3891613 | D28: 2.735818 | E28: 6.3524707 | F28: 7.7478787
A29: Hindustan Unilever Ltd | B29: 2025 | C29: 2.4178533 | D29: 10 | E29: 9.6086832 | F29: 1.5842598
B30: 2024 | C30: 2.3335592 | D30: 10 | E30: 9.8371894 | F30: 1.6070245
B31: 2023 | C31: 2.2978142 | D31: 9.4997784 | E31: 10 | F31: 1.5382895
A32: ICICI Bank Ltd | B32: 2025 | C32: 3.7953681 | D32: 1.7503779 | E32: 5.8840331 | F32: 8.1566861
B33: 2024 | C33: 3.3056088 | D33: 1.8072084 | E33: 5.506998 | F33: 8.1746884
B34: 2023 | C34: 2.552297 | D34: 1.8640388 | E34: 5.7812054 | F34: 7.694856
A35: Infosys Ltd | B35: 2025 | C35: 3.4325834 | D35: 8.6348189 | E35: 4.5586975 | F35: 1.372555
B36: 2024 | C36: 3.3819002 | D36: 6.3650106 | E36: 4.6158241 | F36: 1.4206997
B37: 2023 | C37: 3.0697987 | D37: 6.4297973 | E37: 4.6043987 | F37: 1.6070245
A38: ITC Ltd | B38: 2025 | C38: 1.4804817 | D38: 2.6596652 | E38: 7.7806341 | F38: 0.43541862
B39: 2024 | C39: 0.8738843 | D39: 4.6600971 | E39: 8.6261068 | F39: 0.46680781
B40: 2023 | C40: 0.82480167 | D40: 4.4111797 | E40: 7.6778063 | F40: 0.73751898
A41: Kotak Mahindra Bank Ltd | B41: 2025 | C41: 5.9373983 | D41: 1.7776565 | E41: 7.5064267 | F41: 6.0146402
B42: 2024 | C42: 4.8789206 | D42: 1.9174595 | E42: 7.2093688 | F42: 6.3295669
B43: 2023 | C43: 3.9981007 | D43: 1.6276241 | E43: 9.3344759 | F43: 6.0992368
A44: Larsen & Toubro Ltd | B44: 2025 | C44: 5.8301634 | D44: 2.9097191 | E44: 2.1479577 | F44: 3.0135324
B45: 2024 | C45: 5.0085628 | D45: 3.6701106 | E45: 2.6849472 | F45: 2.9982091
B46: 2023 | C46: 3.9719589 | D46: 3.3552699 | E46: 1.896601 | F46: 3.0135324
A47: Mahindra & Mahindra Ltd | B47: 2025 | C47: 6.1385304 | D47: 2.0674918 | E47: 2.1365324 | F47: 3.3628061
B48: 2024 | C48: 5.3724145 | D48: 1.8253941 | E48: 1.7709226 | F48: 3.3489166
B49: 2023 | C49: 4.9061295 | D49: 1.4196247 | E49: 1.2110825 | F49: 3.3628061
A50: Maruti Suzuki India Ltd | B50: 2025 | C50: 10 | D50: 3.0802105 | E50: 2.7077978 | F50: 0.93471199
B51: 2024 | C51: 10 | D51: 2.2902672 | E51: 3.199086 | F51: 1.0954603
B52: 2023 | C52: 10 | D52: 2.5084962 | E52: 2.4335904 | F52: 1.0954603
A53: NTPC Ltd | B53: 2025 | C53: 1.085153 | D53: 3.8815199 | E53: 2.1022565 | F53: 2.7270938
B54: 2024 | C54: 1.1449058 | D54: 3.971312 | E54: 2.0794059 | F54: 2.8731911
B55: 2023 | C55: 0.95337683 | D55: 2.7687796 | E55: 1.0968295 | F55: 3.0135324
A56: Power Grid Corporation of India Ltd | B56: 2025 | C56: 0.89042302 | D56: 5.2772758 | E56: 6.7409312 | F56: 3.133802
B57: 2024 | C57: 0.92616798 | D57: 5.7694275 | E57: 6.4210226 | F57: 3.1485542
B58: 2023 | C58: 1.1790503 | D58: 5.1420193 | E58: 3.9417309 | F58: 3.2928108
A59: Reliance Industries Ltd | B59: 2025 | C59: 2.74596 | D59: 1.1036474 | E59: 2.04513 | F59: 1.2240898
B60: 2024 | C60: 5.489786 | D60: 0.9933963 | E60: 2.5592688 | F60: 1.2240898
B61: 2023 | C61: 5.2598445 | D61: 0.86609609 | E61: 2.0565553 | F61: 1.2990957
A62: State Bank of India | B62: 2025 | C62: 4.6367085 | D62: 2.2743547 | E62: 1.599543 | F62: 9.643081
B63: 2024 | C63: 4.0103714 | D63: 2.2754913 | E63: 1.748072 | F63: 9.9198198
B64: 2023 | C64: 3.3264155 | D64: 2.282311 | E64: 1.5195658 | F64: 9.9981708
A65: Sun Pharmaceutical Industries Ltd | B65: 2025 | C65: 2.4327915 | D65: 3.7576295 | E65: 9.0488432 | F65: 0.8515335
B66: 2024 | C66: 2.1286925 | D66: 3.439379 | E66: 9.1630963 | F66: 1.0426793
B67: 2023 | C67: 1.8832794 | D67: 3.3791387 | E67: 6.1353899 | F67: 1.1731939
A68: Tata Steel Ltd | B68: 2025 | C68: 0.14618089 | D68: 10 | E68: 1.005427 | F68: 2.4336348
B69: 2024 | C69: 0.11211648 | D69: 0 | E69: 0.9711511 | F69: 2.2679003
B70: 2023 | C70: 0.38252445 | D70: 8.0790171 | E70: 0.67809197 | F70: 2.0140151
A71: Tata Consultancy Services Ltd | B71: 2025 | C71: 7.1591291 | D71: 10 | E71: 5.8383319 | F71: 1.869424
B72: 2024 | C72: 6.7157849 | D72: 6.2229345 | E72: 6.6723793 | F72: 1.827011
B73: 2023 | C73: 6.145466 | D73: 10 | E73: 5.9411597 | F73: 1.6521219
A74: Tech Mahindra Ltd | B74: 2025 | C74: 2.5560316 | D74: 10 | E74: 2.7077978 | F74: 0.10530766
B75: 2024 | C75: 1.4180613 | D75: 10 | E75: 2.4221651 | F75: 0.20759171
B76: 2023 | C76: 2.9214838 | D76: 10 | E76: 2.0794059 | F76: 0.20759171
A77: Titan Company Ltd | B77: 2025 | C77: 2.0065195 | D77: 3.3234448 | E77: 5.1528135 | F77: 3.3489166
B78: 2024 | C78: 2.1009502 | D78: 2.886987 | E78: 7.5749786 | F78: 3.1189885
B79: 2023 | C79: 1.9531688 | D79: 2.3289119 | E79: 6.3067695 | F79: 1.7406395
A80: Trent Ltd | B80: 2025 | C80: 2.3212885 | D80: 0.83540764 | E80: 10 | F80: 0.30702095
B81: 2024 | C81: 2.2311259 | D81: 0.59785636 | E81: 10 | F81: 0.40375041
B82: 2023 | C82: 0.66741713 | D82: 0.99907935 | E82: 6.7752071 | F82: 0.61973471
A83: UltraTech Cement Ltd | B83: 2025 | C83: 10 | D83: 3.7962742 | E83: 5.0956869 | F83: 1.0159927
B84: 2024 | C84: 10 | D84: 1.7765199 | E84: 4.5358469 | F84: 0.55934937
B85: 2023 | C85: 9.3651801 | D85: 2.4516657 | E85: 3.9760069 | F85: 0.58966998

Sheet TESTING_MEMBERSHIP_GRADES
A1: Stock | B1: Year | C1: EPS_L | D1: EPS_S | E1: EPS_H | F1: PAYOUT_L | G1: PAYOUT_S | H1: PAYOUT_H | I1: PS_L | J1: PS_S | K1: PS_H | L1: DE_L | M1: DE_S | N1: DE_H
A2: Adani Ports and Special Economic Zone Ltd | B2: 2025 | C2: =MAX(MIN(1, (Fuzzy_Parameters!$C$4 - Sheet7!C2)/(Fuzzy_Parameters!$C$4 - Fuzzy_Parameters!$C$3)), 0) -> 0 | D2: =MAX(MIN((Sheet7!C2 - Fuzzy_Parameters!$C$3)/(Fuzzy_Parameters!$C$4 - Fuzzy_Parameters!$C$3), 1, (Fuzzy_Parameters!$C$6 - Sheet7!C2)/(Fuzzy_Parameters!$C$6 - Fuzzy_Parameters!$C$5)), 0) -> 0.67173423 | E2: =MAX(MIN((Sheet7!C2 - Fuzzy_Parameters!$C$5)/(Fuzzy_Parameters!$C$6 - Fuzzy_Parameters!$C$5), 1), 0) -> 0.32826577 | F2: =MAX(MIN(1, (Fuzzy_Parameters!$C$12 - Sheet7!D2)/(Fuzzy_Parameters!$C$12 - Fuzzy_Parameters!$C$11)), 0) -> 0.27870289 | G2: =MAX(MIN((Sheet7!D2 - Fuzzy_Parameters!$C$11)/(Fuzzy_Parameters!$C$12 - Fuzzy_Parameters!$C$11), 1, (Fuzzy_Parameters!$C$14 - Sheet7!D2)/(Fuzzy_Parameters!$C$14 - Fuzzy_Parameters!$C$13)), 0) -> 0.72129711 | H2: =MAX(MIN((Sheet7!D2 - Fuzzy_Parameters!$C$13)/(Fuzzy_Parameters!$C$14 - Fuzzy_Parameters!$C$13), 1), 0) -> 0 | I2: =MAX(MIN(1, (Fuzzy_Parameters!$C$20 - Sheet7!E2)/(Fuzzy_Parameters!$C$20 - Fuzzy_Parameters!$C$19)), 0) -> 0 | J2: =MAX(MIN((Sheet7!E2 - Fuzzy_Parameters!$C$19)/(Fuzzy_Parameters!$C$20 - Fuzzy_Parameters!$C$19), 1, (Fuzzy_Parameters!$C$22 - Sheet7!E2)/(Fuzzy_Parameters!$C$22 - Fuzzy_Parameters!$C$21)), 0) -> 0 | K2: =MAX(MIN((Sheet7!E2 - Fuzzy_Parameters!$C$21)/(Fuzzy_Parameters!$C$22 - Fuzzy_Parameters!$C$21), 1), 0) -> 1 | L2: =MAX(MIN(1, (Fuzzy_Parameters!$C$28 - Sheet7!F2)/(Fuzzy_Parameters!$C$28 - Fuzzy_Parameters!$C$27)), 0) -> 0 | M2: =MAX(MIN((Sheet7!F2 - Fuzzy_Parameters!$C$27)/(Fuzzy_Parameters!$C$28 - Fuzzy_Parameters!$C$27), 1, (Fuzzy_Parameters!$C$30 - Sheet7!F2)/(Fuzzy_Parameters!$C$30 - Fuzzy_Parameters!$C$29)), 0) -> 1 | N2: =MAX(MIN((Sheet7!F2 - Fuzzy_Parameters!$C$29)/(Fuzzy_Parameters!$C$30 - Fuzzy_Parameters!$C$29), 1), 0) -> 0
A3: Adani Ports and Special Economic Zone Ltd | B3: 2024 | C3: =MAX(MIN(1, (Fuzzy_Parameters!$C$4 - Sheet7!C3)/(Fuzzy_Parameters!$C$4 - Fuzzy_Parameters!$C$3)), 0) -> 0 | D3: =MAX(MIN((Sheet7!C3 - Fuzzy_Parameters!$C$3)/(Fuzzy_Parameters!$C$4 - Fuzzy_Parameters!$C$3), 1, (Fuzzy_Parameters!$C$6 - Sheet7!C3)/(Fuzzy_Parameters!$C$6 - Fuzzy_Parameters!$C$5)), 0) -> 1 | E3: =MAX(MIN((Sheet7!C3 - Fuzzy_Parameters!$C$5)/(Fuzzy_Parameters!$C$6 - Fuzzy_Parameters!$C$5), 1), 0) -> 0 | F3: =MAX(MIN(1, (Fuzzy_Parameters!$C$12 - Sheet7!D3)/(Fuzzy_Parameters!$C$12 - Fuzzy_Parameters!$C$11)), 0) -> 0.13584575 | G3: =MAX(MIN((Sheet7!D3 - Fuzzy_Parameters!$C$11)/(Fuzzy_Parameters!$C$12 - Fuzzy_Parameters!$C$11), 1, (Fuzzy_Parameters!$C$14 - Sheet7!D3)/(Fuzzy_Parameters!$C$14 - Fuzzy_Parameters!$C$13)), 0) -> 0.86415425 | H3: =MAX(MIN((Sheet7!D3 - Fuzzy_Parameters!$C$13)/(Fuzzy_Parameters!$C$14 - Fuzzy_Parameters!$C$13), 1), 0) -> 0 | I3: =MAX(MIN(1, (Fuzzy_Parameters!$C$20 - Sheet7!E3)/(Fuzzy_Parameters!$C$20 - Fuzzy_Parameters!$C$19)), 0) -> 0 | J3: =MAX(MIN((Sheet7!E3 - Fuzzy_Parameters!$C$19)/(Fuzzy_Parameters!$C$20 - Fuzzy_Parameters!$C$19), 1, (Fuzzy_Parameters!$C$22 - Sheet7!E3)/(Fuzzy_Parameters!$C$22 - Fuzzy_Parameters!$C$21)), 0) -> 0 | K3: =MAX(MIN((Sheet7!E3 - Fuzzy_Parameters!$C$21)/(Fuzzy_Parameters!$C$22 - Fuzzy_Parameters!$C$21), 1), 0) -> 1 | L3: =MAX(MIN(1, (Fuzzy_Parameters!$C$28 - Sheet7!F3)/(Fuzzy_Parameters!$C$28 - Fuzzy_Parameters!$C$27)), 0) -> 0 | M3: =MAX(MIN((Sheet7!F3 - Fuzzy_Parameters!$C$27)/(Fuzzy_Parameters!$C$28 - Fuzzy_Parameters!$C$27), 1, (Fuzzy_Parameters!$C$30 - Sheet7!F3)/(Fuzzy_Parameters!$C$30 - Fuzzy_Parameters!$C$29)), 0) -> 1 | N3: =MAX(MIN((Sheet7!F3 - Fuzzy_Parameters!$C$29)/(Fuzzy_Parameters!$C$30 - Fuzzy_Parameters!$C$29), 1), 0) -> 0
A4: Adani Ports and Special Economic Zone Ltd | B4: 2023 | C4: =MAX(MIN(1, (Fuzzy_Parameters!$C$4 - Sheet7!C4)/(Fuzzy_Parameters!$C$4 - Fuzzy_Parameters!$C$3)), 0) -> 0 | D4: =MAX(MIN((Sheet7!C4 - Fuzzy_Parameters!$C$3)/(Fuzzy_Parameters!$C$4 - Fuzzy_Parameters!$C$3), 1, (Fuzzy_Parameters!$C$6 - Sheet7!C4)/(Fuzzy_Parameters!$C$6 - Fuzzy_Parameters!$C$5)), 0) -> 1 | E4: =MAX(MIN((Sheet7!C4 - Fuzzy_Parameters!$C$5)/(Fuzzy_Parameters!$C$6 - Fuzzy_Parameters!$C$5), 1), 0) -> 0 | F4: =MAX(MIN(1, (Fuzzy_Parameters!$C$12 - Sheet7!D4)/(Fuzzy_Parameters!$C$12 - Fuzzy_Parameters!$C$11)), 0) -> 0 | G4: =MAX(MIN((Sheet7!D4 - Fuzzy_Parameters!$C$11)/(Fuzzy_Parameters!$C$12 - Fuzzy_Parameters!$C$11), 1, (Fuzzy_Parameters!$C$14 - Sheet7!D4)/(Fuzzy_Parameters!$C$14 - Fuzzy_Parameters!$C$13)), 0) -> 1 | H4: =MAX(MIN((Sheet7!D4 - Fuzzy_Parameters!$C$13)/(Fuzzy_Parameters!$C$14 - Fuzzy_Parameters!$C$13), 1), 0) -> 0 | I4: =MAX(MIN(1, (Fuzzy_Parameters!$C$20 - Sheet7!E4)/(Fuzzy_Parameters!$C$20 - Fuzzy_Parameters!$C$19)), 0) -> 0 | J4: =MAX(MIN((Sheet7!E4 - Fuzzy_Parameters!$C$19)/(Fuzzy_Parameters!$C$20 - Fuzzy_Parameters!$C$19), 1, (Fuzzy_Parameters!$C$22 - Sheet7!E4)/(Fuzzy_Parameters!$C$22 - Fuzzy_Parameters!$C$21)), 0) -> 0 | K4: =MAX(MIN((Sheet7!E4 - Fuzzy_Parameters!$C$21)/(Fuzzy_Parameters!$C$22 - Fuzzy_Parameters!$C$21), 1), 0) -> 1 | L4: =MAX(MIN(1, (Fuzzy_Parameters!$C$28 - Sheet7!F4)/(Fuzzy_Parameters!$C$28 - Fuzzy_Parameters!$C$27)), 0) -> 0 | M4: =MAX(MIN((Sheet7!F4 - Fuzzy_Parameters!$C$27)/(Fuzzy_Parameters!$C$28 - Fuzzy_Parameters!$C$27), 1, (Fuzzy_Parameters!$C$30 - Sheet7!F4)/(Fuzzy_Parameters!$C$30 - Fuzzy_Parameters!$C$29)), 0) -> 1 | N4: =MAX(MIN((Sheet7!F4 - Fuzzy_Parameters!$C$29)/(Fuzzy_Parameters!$C$30 - Fuzzy_Parameters!$C$29), 1), 0) -> 0
A5: Asian Paints Ltd | B5: 2025 | C5: =MAX(MIN(1, (Fuzzy_Parameters!$C$4 - Sheet7!C5)/(Fuzzy_Parameters!$C$4 - Fuzzy_Parameters!$C$3)), 0) -> 0 | D5: =MAX(MIN((Sheet7!C5 - Fuzzy_Parameters!$C$3)/(Fuzzy_Parameters!$C$4 - Fuzzy_Parameters!$C$3), 1, (Fuzzy_Parameters!$C$6 - Sheet7!C5)/(Fuzzy_Parameters!$C$6 - Fuzzy_Parameters!$C$5)), 0) -> 1 | E5: =MAX(MIN((Sheet7!C5 - Fuzzy_Parameters!$C$5)/(Fuzzy_Parameters!$C$6 - Fuzzy_Parameters!$C$5), 1), 0) -> 0 | F5: =MAX(MIN(1, (Fuzzy_Parameters!$C$12 - Sheet7!D5)/(Fuzzy_Parameters!$C$12 - Fuzzy_Parameters!$C$11)), 0) -> 0 | G5: =MAX(MIN((Sheet7!D5 - Fuzzy_Parameters!$C$11)/(Fuzzy_Parameters!$C$12 - Fuzzy_Parameters!$C$11), 1, (Fuzzy_Parameters!$C$14 - Sheet7!D5)/(Fuzzy_Parameters!$C$14 - Fuzzy_Parameters!$C$13)), 0) -> 0 | H5: =MAX(MIN((Sheet7!D5 - Fuzzy_Parameters!$C$13)/(Fuzzy_Parameters!$C$14 - Fuzzy_Parameters!$C$13), 1), 0) -> 1 | I5: =MAX(MIN(1, (Fuzzy_Parameters!$C$20 - Sheet7!E5)/(Fuzzy_Parameters!$C$20 - Fuzzy_Parameters!$C$19)), 0) -> 0 | J5: =MAX(MIN((Sheet7!E5 - Fuzzy_Parameters!$C$19)/(Fuzzy_Parameters!$C$20 - Fuzzy_Parameters!$C$19), 1, (Fuzzy_Parameters!$C$22 - Sheet7!E5)/(Fuzzy_Parameters!$C$22 - Fuzzy_Parameters!$C$21)), 0) -> 0 | K5: =MAX(MIN((Sheet7!E5 - Fuzzy_Parameters!$C$21)/(Fuzzy_Parameters!$C$22 - Fuzzy_Parameters!$C$21), 1), 0) -> 1 | L5: =MAX(MIN(1, (Fuzzy_Parameters!$C$28 - Sheet7!F5)/(Fuzzy_Parameters!$C$28 - Fuzzy_Parameters!$C$27)), 0) -> 1 | M5: =MAX(MIN((Sheet7!F5 - Fuzzy_Parameters!$C$27)/(Fuzzy_Parameters!$C$28 - Fuzzy_Parameters!$C$27), 1, (Fuzzy_Parameters!$C$30 - Sheet7!F5)/(Fuzzy_Parameters!$C$30 - Fuzzy_Parameters!$C$29)), 0) -> 0 | N5: =MAX(MIN((Sheet7!F5 - Fuzzy_Parameters!$C$29)/(Fuzzy_Parameters!$C$30 - Fuzzy_Parameters!$C$29), 1), 0) -> 0
A6: Asian Paints Ltd | B6: 2024 | C6: =MAX(MIN(1, (Fuzzy_Parameters!$C$4 - Sheet7!C6)/(Fuzzy_Parameters!$C$4 - Fuzzy_Parameters!$C$3)), 0) -> 0 | D6: =MAX(MIN((Sheet7!C6 - Fuzzy_Parameters!$C$3)/(Fuzzy_Parameters!$C$4 - Fuzzy_Parameters!$C$3), 1, (Fuzzy_Parameters!$C$6 - Sheet7!C6)/(Fuzzy_Parameters!$C$6 - Fuzzy_Parameters!$C$5)), 0) -> 0.51435811 | E6: =MAX(MIN((Sheet7!C6 - Fuzzy_Parameters!$C$5)/(Fuzzy_Parameters!$C$6 - Fuzzy_Parameters!$C$5), 1), 0) -> 0.48564189 | F6: =MAX(MIN(1, (Fuzzy_Parameters!$C$12 - Sheet7!D6)/(Fuzzy_Parameters!$C$12 - Fuzzy_Parameters!$C$11)), 0) -> 0 | G6: =MAX(MIN((Sheet7!D6 - Fuzzy_Parameters!$C$11)/(Fuzzy_Parameters!$C$12 - Fuzzy_Parameters!$C$11), 1, (Fuzzy_Parameters!$C$14 - Sheet7!D6)/(Fuzzy_Parameters!$C$14 - Fuzzy_Parameters!$C$13)), 0) -> 0 | H6: =MAX(MIN((Sheet7!D6 - Fuzzy_Parameters!$C$13)/(Fuzzy_Parameters!$C$14 - Fuzzy_Parameters!$C$13), 1), 0) -> 1 | I6: =MAX(MIN(1, (Fuzzy_Parameters!$C$20 - Sheet7!E6)/(Fuzzy_Parameters!$C$20 - Fuzzy_Parameters!$C$19)), 0) -> 0 | J6: =MAX(MIN((Sheet7!E6 - Fuzzy_Parameters!$C$19)/(Fuzzy_Parameters!$C$20 - Fuzzy_Parameters!$C$19), 1, (Fuzzy_Parameters!$C$22 - Sheet7!E6)/(Fuzzy_Parameters!$C$22 - Fuzzy_Parameters!$C$21)), 0) -> 0 | K6: =MAX(MIN((Sheet7!E6 - Fuzzy_Parameters!$C$21)/(Fuzzy_Parameters!$C$22 - Fuzzy_Parameters!$C$21), 1), 0) -> 1 | L6: =MAX(MIN(1, (Fuzzy_Parameters!$C$28 - Sheet7!F6)/(Fuzzy_Parameters!$C$28 - Fuzzy_Parameters!$C$27)), 0) -> 1 | M6: =MAX(MIN((Sheet7!F6 - Fuzzy_Parameters!$C$27)/(Fuzzy_Parameters!$C$28 - Fuzzy_Parameters!$C$27), 1, (Fuzzy_Parameters!$C$30 - Sheet7!F6)/(Fuzzy_Parameters!$C$30 - Fuzzy_Parameters!$C$29)), 0) -> 0 | N6: =MAX(MIN((Sheet7!F6 - Fuzzy_Parameters!$C$29)/(Fuzzy_Parameters!$C$30 - Fuzzy_Parameters!$C$29), 1), 0) -> 0
A7: Asian Paints Ltd | B7: 2023 | C7: =MAX(MIN(1, (Fuzzy_Parameters!$C$4 - Sheet7!C7)/(Fuzzy_Parameters!$C$4 - Fuzzy_Parameters!$C$3)), 0) -> 0 | D7: =MAX(MIN((Sheet7!C7 - Fuzzy_Parameters!$C$3)/(Fuzzy_Parameters!$C$4 - Fuzzy_Parameters!$C$3), 1, (Fuzzy_Parameters!$C$6 - Sheet7!C7)/(Fuzzy_Parameters!$C$6 - Fuzzy_Parameters!$C$5)), 0) -> 0.91188063 | E7: =MAX(MIN((Sheet7!C7 - Fuzzy_Parameters!$C$5)/(Fuzzy_Parameters!$C$6 - Fuzzy_Parameters!$C$5), 1), 0) -> 0.088119369 | F7: =MAX(MIN(1, (Fuzzy_Parameters!$C$12 - Sheet7!D7)/(Fuzzy_Parameters!$C$12 - Fuzzy_Parameters!$C$11)), 0) -> 0 | G7: =MAX(MIN((Sheet7!D7 - Fuzzy_Parameters!$C$11)/(Fuzzy_Parameters!$C$12 - Fuzzy_Parameters!$C$11), 1, (Fuzzy_Parameters!$C$14 - Sheet7!D7)/(Fuzzy_Parameters!$C$14 - Fuzzy_Parameters!$C$13)), 0) -> 0 | H7: =MAX(MIN((Sheet7!D7 - Fuzzy_Parameters!$C$13)/(Fuzzy_Parameters!$C$14 - Fuzzy_Parameters!$C$13), 1), 0) -> 1 | I7: =MAX(MIN(1, (Fuzzy_Parameters!$C$20 - Sheet7!E7)/(Fuzzy_Parameters!$C$20 - Fuzzy_Parameters!$C$19)), 0) -> 0 | J7: =MAX(MIN((Sheet7!E7 - Fuzzy_Parameters!$C$19)/(Fuzzy_Parameters!$C$20 - Fuzzy_Parameters!$C$19), 1, (Fuzzy_Parameters!$C$22 - Sheet7!E7)/(Fuzzy_Parameters!$C$22 - Fuzzy_Parameters!$C$21)), 0) -> 0 | K7: =MAX(MIN((Sheet7!E7 - Fuzzy_Parameters!$C$21)/(Fuzzy_Parameters!$C$22 - Fuzzy_Parameters!$C$21), 1), 0) -> 1 | L7: =MAX(MIN(1, (Fuzzy_Parameters!$C$28 - Sheet7!F7)/(Fuzzy_Parameters!$C$28 - Fuzzy_Parameters!$C$27)), 0) -> 1 | M7: =MAX(MIN((Sheet7!F7 - Fuzzy_Parameters!$C$27)/(Fuzzy_Parameters!$C$28 - Fuzzy_Parameters!$C$27), 1, (Fuzzy_Parameters!$C$30 - Sheet7!F7)/(Fuzzy_Parameters!$C$30 - Fuzzy_Parameters!$C$29)), 0) -> 0 | N7: =MAX(MIN((Sheet7!F7 - Fuzzy_Parameters!$C$29)/(Fuzzy_Parameters!$C$30 - Fuzzy_Parameters!$C$29), 1), 0) -> 0
A8: AXIS Bank Ltd | B8: 2025 | C8: =MAX(MIN(1, (Fuzzy_Parameters!$C$4 - Sheet7!C8)/(Fuzzy_Parameters!$C$4 - Fuzzy_Parameters!$C$3)), 0) -> 0 | D8: =MAX(MIN((Sheet7!C8 - Fuzzy_Parameters!$C$3)/(Fuzzy_Parameters!$C$4 - Fuzzy_Parameters!$C$3), 1, (Fuzzy_Parameters!$C$6 - Sheet7!C8)/(Fuzzy_Parameters!$C$6 - Fuzzy_Parameters!$C$5)), 0) -> 0 | E8: =MAX(MIN((Sheet7!C8 - Fuzzy_Parameters!$C$5)/(Fuzzy_Parameters!$C$6 - Fuzzy_Parameters!$C$5), 1), 0) -> 1 | F8: =MAX(MIN(1, (Fuzzy_Parameters!$C$12 - Sheet7!D8)/(Fuzzy_Parameters!$C$12 - Fuzzy_Parameters!$C$11)), 0) -> 1 | G8: =MAX(MIN((Sheet7!D8 - Fuzzy_Parameters!$C$11)/(Fuzzy_Parameters!$C$12 - Fuzzy_Parameters!$C$11), 1, (Fuzzy_Parameters!$C$14 - Sheet7!D8)/(Fuzzy_Parameters!$C$14 - Fuzzy_Parameters!$C$13)), 0) -> 0 | H8: =MAX(MIN((Sheet7!D8 - Fuzzy_Parameters!$C$13)/(Fuzzy_Parameters!$C$14 - Fuzzy_Parameters!$C$13), 1), 0) -> 0 | I8: =MAX(MIN(1, (Fuzzy_Parameters!$C$20 - Sheet7!E8)/(Fuzzy_Parameters!$C$20 - Fuzzy_Parameters!$C$19)), 0) -> 0 | J8: =MAX(MIN((Sheet7!E8 - Fuzzy_Parameters!$C$19)/(Fuzzy_Parameters!$C$20 - Fuzzy_Parameters!$C$19), 1, (Fuzzy_Parameters!$C$22 - Sheet7!E8)/(Fuzzy_Parameters!$C$22 - Fuzzy_Parameters!$C$21)), 0) -> 1 | K8: =MAX(MIN((Sheet7!E8 - Fuzzy_Parameters!$C$21)/(Fuzzy_Parameters!$C$22 - Fuzzy_Parameters!$C$21), 1), 0) -> 0 | L8: =MAX(MIN(1, (Fuzzy_Parameters!$C$28 - Sheet7!F8)/(Fuzzy_Parameters!$C$28 - Fuzzy_Parameters!$C$27)), 0) -> 0 | M8: =MAX(MIN((Sheet7!F8 - Fuzzy_Parameters!$C$27)/(Fuzzy_Parameters!$C$28 - Fuzzy_Parameters!$C$27), 1, (Fuzzy_Parameters!$C$30 - Sheet7!F8)/(Fuzzy_Parameters!$C$30 - Fuzzy_Parameters!$C$29)), 0) -> 0 | N8: =MAX(MIN((Sheet7!F8 - Fuzzy_Parameters!$C$29)/(Fuzzy_Parameters!$C$30 - Fuzzy_Parameters!$C$29), 1), 0) -> 1
A9: AXIS Bank Ltd | B9: 2024 | C9: =MAX(MIN(1, (Fuzzy_Parameters!$C$4 - Sheet7!C9)/(Fuzzy_Parameters!$C$4 - Fuzzy_Parameters!$C$3)), 0) -> 0 | D9: =MAX(MIN((Sheet7!C9 - Fuzzy_Parameters!$C$3)/(Fuzzy_Parameters!$C$4 - Fuzzy_Parameters!$C$3), 1, (Fuzzy_Parameters!$C$6 - Sheet7!C9)/(Fuzzy_Parameters!$C$6 - Fuzzy_Parameters!$C$5)), 0) -> 0 | E9: =MAX(MIN((Sheet7!C9 - Fuzzy_Parameters!$C$5)/(Fuzzy_Parameters!$C$6 - Fuzzy_Parameters!$C$5), 1), 0) -> 1 | F9: =MAX(MIN(1, (Fuzzy_Parameters!$C$12 - Sheet7!D9)/(Fuzzy_Parameters!$C$12 - Fuzzy_Parameters!$C$11)), 0) -> 1 | G9: =MAX(MIN((Sheet7!D9 - Fuzzy_Parameters!$C$11)/(Fuzzy_Parameters!$C$12 - Fuzzy_Parameters!$C$11), 1, (Fuzzy_Parameters!$C$14 - Sheet7!D9)/(Fuzzy_Parameters!$C$14 - Fuzzy_Parameters!$C$13)), 0) -> 0 | H9: =MAX(MIN((Sheet7!D9 - Fuzzy_Parameters!$C$13)/(Fuzzy_Parameters!$C$14 - Fuzzy_Parameters!$C$13), 1), 0) -> 0 | I9: =MAX(MIN(1, (Fuzzy_Parameters!$C$20 - Sheet7!E9)/(Fuzzy_Parameters!$C$20 - Fuzzy_Parameters!$C$19)), 0) -> 0 | J9: =MAX(MIN((Sheet7!E9 - Fuzzy_Parameters!$C$19)/(Fuzzy_Parameters!$C$20 - Fuzzy_Parameters!$C$19), 1, (Fuzzy_Parameters!$C$22 - Sheet7!E9)/(Fuzzy_Parameters!$C$22 - Fuzzy_Parameters!$C$21)), 0) -> 1 | K9: =MAX(MIN((Sheet7!E9 - Fuzzy_Parameters!$C$21)/(Fuzzy_Parameters!$C$22 - Fuzzy_Parameters!$C$21), 1), 0) -> 0 | L9: =MAX(MIN(1, (Fuzzy_Parameters!$C$28 - Sheet7!F9)/(Fuzzy_Parameters!$C$28 - Fuzzy_Parameters!$C$27)), 0) -> 0 | M9: =MAX(MIN((Sheet7!F9 - Fuzzy_Parameters!$C$27)/(Fuzzy_Parameters!$C$28 - Fuzzy_Parameters!$C$27), 1, (Fuzzy_Parameters!$C$30 - Sheet7!F9)/(Fuzzy_Parameters!$C$30 - Fuzzy_Parameters!$C$29)), 0) -> 0 | N9: =MAX(MIN((Sheet7!F9 - Fuzzy_Parameters!$C$29)/(Fuzzy_Parameters!$C$30 - Fuzzy_Parameters!$C$29), 1), 0) -> 1
A10: AXIS Bank Ltd | B10: 2023 | C10: =MAX(MIN(1, (Fuzzy_Parameters!$C$4 - Sheet7!C10)/(Fuzzy_Parameters!$C$4 - Fuzzy_Parameters!$C$3)), 0) -> 0 | D10: =MAX(MIN((Sheet7!C10 - Fuzzy_Parameters!$C$3)/(Fuzzy_Parameters!$C$4 - Fuzzy_Parameters!$C$3), 1, (Fuzzy_Parameters!$C$6 - Sheet7!C10)/(Fuzzy_Parameters!$C$6 - Fuzzy_Parameters!$C$5)), 0) -> 1 | E10: =MAX(MIN((Sheet7!C10 - Fuzzy_Parameters!$C$5)/(Fuzzy_Parameters!$C$6 - Fuzzy_Parameters!$C$5), 1), 0) -> 0 | F10: =MAX(MIN(1, (Fuzzy_Parameters!$C$12 - Sheet7!D10)/(Fuzzy_Parameters!$C$12 - Fuzzy_Parameters!$C$11)), 0) -> 1 | G10: =MAX(MIN((Sheet7!D10 - Fuzzy_Parameters!$C$11)/(Fuzzy_Parameters!$C$12 - Fuzzy_Parameters!$C$11), 1, (Fuzzy_Parameters!$C$14 - Sheet7!D10)/(Fuzzy_Parameters!$C$14 - Fuzzy_Parameters!$C$13)), 0) -> 0 | H10: =MAX(MIN((Sheet7!D10 - Fuzzy_Parameters!$C$13)/(Fuzzy_Parameters!$C$14 - Fuzzy_Parameters!$C$13), 1), 0) -> 0 | I10: =MAX(MIN(1, (Fuzzy_Parameters!$C$20 - Sheet7!E10)/(Fuzzy_Parameters!$C$20 - Fuzzy_Parameters!$C$19)), 0) -> 0 | J10: =MAX(MIN((Sheet7!E10 - Fuzzy_Parameters!$C$19)/(Fuzzy_Parameters!$C$20 - Fuzzy_Parameters!$C$19), 1, (Fuzzy_Parameters!$C$22 - Sheet7!E10)/(Fuzzy_Parameters!$C$22 - Fuzzy_Parameters!$C$21)), 0) -> 1 | K10: =MAX(MIN((Sheet7!E10 - Fuzzy_Parameters!$C$21)/(Fuzzy_Parameters!$C$22 - Fuzzy_Parameters!$C$21), 1), 0) -> 0 | L10: =MAX(MIN(1, (Fuzzy_Parameters!$C$28 - Sheet7!F10)/(Fuzzy_Parameters!$C$28 - Fuzzy_Parameters!$C$27)), 0) -> 0 | M10: =MAX(MIN((Sheet7!F10 - Fuzzy_Parameters!$C$27)/(Fuzzy_Parameters!$C$28 - Fuzzy_Parameters!$C$27), 1, (Fuzzy_Parameters!$C$30 - Sheet7!F10)/(Fuzzy_Parameters!$C$30 - Fuzzy_Parameters!$C$29)), 0) -> 0 | N10: =MAX(MIN((Sheet7!F10 - Fuzzy_Parameters!$C$29)/(Fuzzy_Parameters!$C$30 - Fuzzy_Parameters!$C$29), 1), 0) -> 1
A11: Bajaj Finserv Ltd | B11: 2025 | C11: =MAX(MIN(1, (Fuzzy_Parameters!$C$4 - Sheet7!C11)/(Fuzzy_Parameters!$C$4 - Fuzzy_Parameters!$C$3)), 0) -> 1 | D11: =MAX(MIN((Sheet7!C11 - Fuzzy_Parameters!$C$3)/(Fuzzy_Parameters!$C$4 - Fuzzy_Parameters!$C$3), 1, (Fuzzy_Parameters!$C$6 - Sheet7!C11)/(Fuzzy_Parameters!$C$6 - Fuzzy_Parameters!$C$5)), 0) -> 0 | E11: =MAX(MIN((Sheet7!C11 - Fuzzy_Parameters!$C$5)/(Fuzzy_Parameters!$C$6 - Fuzzy_Parameters!$C$5), 1), 0) -> 0 | F11: =MAX(MIN(1, (Fuzzy_Parameters!$C$12 - Sheet7!D11)/(Fuzzy_Parameters!$C$12 - Fuzzy_Parameters!$C$11)), 0) -> 1 | G11: =MAX(MIN((Sheet7!D11 - Fuzzy_Parameters!$C$11)/(Fuzzy_Parameters!$C$12 - Fuzzy_Parameters!$C$11), 1, (Fuzzy_Parameters!$C$14 - Sheet7!D11)/(Fuzzy_Parameters!$C$14 - Fuzzy_Parameters!$C$13)), 0) -> 0 | H11: =MAX(MIN((Sheet7!D11 - Fuzzy_Parameters!$C$13)/(Fuzzy_Parameters!$C$14 - Fuzzy_Parameters!$C$13), 1), 0) -> 0 | I11: =MAX(MIN(1, (Fuzzy_Parameters!$C$20 - Sheet7!E11)/(Fuzzy_Parameters!$C$20 - Fuzzy_Parameters!$C$19)), 0) -> 0.18548387 | J11: =MAX(MIN((Sheet7!E11 - Fuzzy_Parameters!$C$19)/(Fuzzy_Parameters!$C$20 - Fuzzy_Parameters!$C$19), 1, (Fuzzy_Parameters!$C$22 - Sheet7!E11)/(Fuzzy_Parameters!$C$22 - Fuzzy_Parameters!$C$21)), 0) -> 0.81451613 | K11: =MAX(MIN((Sheet7!E11 - Fuzzy_Parameters!$C$21)/(Fuzzy_Parameters!$C$22 - Fuzzy_Parameters!$C$21), 1), 0) -> 0 | L11: =MAX(MIN(1, (Fuzzy_Parameters!$C$28 - Sheet7!F11)/(Fuzzy_Parameters!$C$28 - Fuzzy_Parameters!$C$27)), 0) -> 0 | M11: =MAX(MIN((Sheet7!F11 - Fuzzy_Parameters!$C$27)/(Fuzzy_Parameters!$C$28 - Fuzzy_Parameters!$C$27), 1, (Fuzzy_Parameters!$C$30 - Sheet7!F11)/(Fuzzy_Parameters!$C$30 - Fuzzy_Parameters!$C$29)), 0) -> 0 | N11: =MAX(MIN((Sheet7!F11 - Fuzzy_Parameters!$C$29)/(Fuzzy_Parameters!$C$30 - Fuzzy_Parameters!$C$29), 1), 0) -> 1
A12: Bajaj Finserv Ltd | B12: 2024 | C12: =MAX(MIN(1, (Fuzzy_Parameters!$C$4 - Sheet7!C12)/(Fuzzy_Parameters!$C$4 - Fuzzy_Parameters!$C$3)), 0) -> 1 | D12: =MAX(MIN((Sheet7!C12 - Fuzzy_Parameters!$C$3)/(Fuzzy_Parameters!$C$4 - Fuzzy_Parameters!$C$3), 1, (Fuzzy_Parameters!$C$6 - Sheet7!C12)/(Fuzzy_Parameters!$C$6 - Fuzzy_Parameters!$C$5)), 0) -> 0 | E12: =MAX(MIN((Sheet7!C12 - Fuzzy_Parameters!$C$5)/(Fuzzy_Parameters!$C$6 - Fuzzy_Parameters!$C$5), 1), 0) -> 0 | F12: =MAX(MIN(1, (Fuzzy_Parameters!$C$12 - Sheet7!D12)/(Fuzzy_Parameters!$C$12 - Fuzzy_Parameters!$C$11)), 0) -> 1 | G12: =MAX(MIN((Sheet7!D12 - Fuzzy_Parameters!$C$11)/(Fuzzy_Parameters!$C$12 - Fuzzy_Parameters!$C$11), 1, (Fuzzy_Parameters!$C$14 - Sheet7!D12)/(Fuzzy_Parameters!$C$14 - Fuzzy_Parameters!$C$13)), 0) -> 0 | H12: =MAX(MIN((Sheet7!D12 - Fuzzy_Parameters!$C$13)/(Fuzzy_Parameters!$C$14 - Fuzzy_Parameters!$C$13), 1), 0) -> 0 | I12: =MAX(MIN(1, (Fuzzy_Parameters!$C$20 - Sheet7!E12)/(Fuzzy_Parameters!$C$20 - Fuzzy_Parameters!$C$19)), 0) -> 0.2016129 | J12: =MAX(MIN((Sheet7!E12 - Fuzzy_Parameters!$C$19)/(Fuzzy_Parameters!$C$20 - Fuzzy_Parameters!$C$19), 1, (Fuzzy_Parameters!$C$22 - Sheet7!E12)/(Fuzzy_Parameters!$C$22 - Fuzzy_Parameters!$C$21)), 0) -> 0.7983871 | K12: =MAX(MIN((Sheet7!E12 - Fuzzy_Parameters!$C$21)/(Fuzzy_Parameters!$C$22 - Fuzzy_Parameters!$C$21), 1), 0) -> 0 | L12: =MAX(MIN(1, (Fuzzy_Parameters!$C$28 - Sheet7!F12)/(Fuzzy_Parameters!$C$28 - Fuzzy_Parameters!$C$27)), 0) -> 0 | M12: =MAX(MIN((Sheet7!F12 - Fuzzy_Parameters!$C$27)/(Fuzzy_Parameters!$C$28 - Fuzzy_Parameters!$C$27), 1, (Fuzzy_Parameters!$C$30 - Sheet7!F12)/(Fuzzy_Parameters!$C$30 - Fuzzy_Parameters!$C$29)), 0) -> 0 | N12: =MAX(MIN((Sheet7!F12 - Fuzzy_Parameters!$C$29)/(Fuzzy_Parameters!$C$30 - Fuzzy_Parameters!$C$29), 1), 0) -> 1
A13: Bajaj Finserv Ltd | B13: 2023 | C13: =MAX(MIN(1, (Fuzzy_Parameters!$C$4 - Sheet7!C13)/(Fuzzy_Parameters!$C$4 - Fuzzy_Parameters!$C$3)), 0) -> 1 | D13: =MAX(MIN((Sheet7!C13 - Fuzzy_Parameters!$C$3)/(Fuzzy_Parameters!$C$4 - Fuzzy_Parameters!$C$3), 1, (Fuzzy_Parameters!$C$6 - Sheet7!C13)/(Fuzzy_Parameters!$C$6 - Fuzzy_Parameters!$C$5)), 0) -> 0 | E13: =MAX(MIN((Sheet7!C13 - Fuzzy_Parameters!$C$5)/(Fuzzy_Parameters!$C$6 - Fuzzy_Parameters!$C$5), 1), 0) -> 0 | F13: =MAX(MIN(1, (Fuzzy_Parameters!$C$12 - Sheet7!D13)/(Fuzzy_Parameters!$C$12 - Fuzzy_Parameters!$C$11)), 0) -> 1 | G13: =MAX(MIN((Sheet7!D13 - Fuzzy_Parameters!$C$11)/(Fuzzy_Parameters!$C$12 - Fuzzy_Parameters!$C$11), 1, (Fuzzy_Parameters!$C$14 - Sheet7!D13)/(Fuzzy_Parameters!$C$14 - Fuzzy_Parameters!$C$13)), 0) -> 0 | H13: =MAX(MIN((Sheet7!D13 - Fuzzy_Parameters!$C$13)/(Fuzzy_Parameters!$C$14 - Fuzzy_Parameters!$C$13), 1), 0) -> 0 | I13: =MAX(MIN(1, (Fuzzy_Parameters!$C$20 - Sheet7!E13)/(Fuzzy_Parameters!$C$20 - Fuzzy_Parameters!$C$19)), 0) -> 0.12903226 | J13: =MAX(MIN((Sheet7!E13 - Fuzzy_Parameters!$C$19)/(Fuzzy_Parameters!$C$20 - Fuzzy_Parameters!$C$19), 1, (Fuzzy_Parameters!$C$22 - Sheet7!E13)/(Fuzzy_Parameters!$C$22 - Fuzzy_Parameters!$C$21)), 0) -> 0.87096774 | K13: =MAX(MIN((Sheet7!E13 - Fuzzy_Parameters!$C$21)/(Fuzzy_Parameters!$C$22 - Fuzzy_Parameters!$C$21), 1), 0) -> 0 | L13: =MAX(MIN(1, (Fuzzy_Parameters!$C$28 - Sheet7!F13)/(Fuzzy_Parameters!$C$28 - Fuzzy_Parameters!$C$27)), 0) -> 0 | M13: =MAX(MIN((Sheet7!F13 - Fuzzy_Parameters!$C$27)/(Fuzzy_Parameters!$C$28 - Fuzzy_Parameters!$C$27), 1, (Fuzzy_Parameters!$C$30 - Sheet7!F13)/(Fuzzy_Parameters!$C$30 - Fuzzy_Parameters!$C$29)), 0) -> 0 | N13: =MAX(MIN((Sheet7!F13 - Fuzzy_Parameters!$C$29)/(Fuzzy_Parameters!$C$30 - Fuzzy_Parameters!$C$29), 1), 0) -> 1
... A85: UltraTech Cement Ltd | B85: 2023 | C85: =MAX(MIN(1, (Fuzzy_Parameters!$C$4 - Sheet7!C85)/(Fuzzy_Parameters!$C$4 - Fuzzy_Parameters!$C$3)), 0) -> 0 | D85: =MAX(MIN((Sheet7!C85 - Fuzzy_Parameters!$C$3)/(Fuzzy_Parameters!$C$4 - Fuzzy_Parameters!$C$3), 1, (Fuzzy_Parameters!$C$6 - Sheet7!C85)/(Fuzzy_Parameters!$C$6 - Fuzzy_Parameters!$C$5)), 0) -> 0 | E85: =MAX(MIN((Sheet7!C85 - Fuzzy_Parameters!$C$5)/(Fuzzy_Parameters!$C$6 - Fuzzy_Parameters!$C$5), 1), 0) -> 1 | F85: =MAX(MIN(1, (Fuzzy_Parameters!$C$12 - Sheet7!D85)/(Fuzzy_Parameters!$C$12 - Fuzzy_Parameters!$C$11)), 0) -> 0 | G85: =MAX(MIN((Sheet7!D85 - Fuzzy_Parameters!$C$11)/(Fuzzy_Parameters!$C$12 - Fuzzy_Parameters!$C$11), 1, (Fuzzy_Parameters!$C$14 - Sheet7!D85)/(Fuzzy_Parameters!$C$14 - Fuzzy_Parameters!$C$13)), 0) -> 1 | H85: =MAX(MIN((Sheet7!D85 - Fuzzy_Parameters!$C$13)/(Fuzzy_Parameters!$C$14 - Fuzzy_Parameters!$C$13), 1), 0) -> 0 | I85: =MAX(MIN(1, (Fuzzy_Parameters!$C$20 - Sheet7!E85)/(Fuzzy_Parameters!$C$20 - Fuzzy_Parameters!$C$19)), 0) -> 0 | J85: =MAX(MIN((Sheet7!E85 - Fuzzy_Parameters!$C$19)/(Fuzzy_Parameters!$C$20 - Fuzzy_Parameters!$C$19), 1, (Fuzzy_Parameters!$C$22 - Sheet7!E85)/(Fuzzy_Parameters!$C$22 - Fuzzy_Parameters!$C$21)), 0) -> 1 | K85: =MAX(MIN((Sheet7!E85 - Fuzzy_Parameters!$C$21)/(Fuzzy_Parameters!$C$22 - Fuzzy_Parameters!$C$21), 1), 0) -> 0 | L85: =MAX(MIN(1, (Fuzzy_Parameters!$C$28 - Sheet7!F85)/(Fuzzy_Parameters!$C$28 - Fuzzy_Parameters!$C$27)), 0) -> 1 | M85: =MAX(MIN((Sheet7!F85 - Fuzzy_Parameters!$C$27)/(Fuzzy_Parameters!$C$28 - Fuzzy_Parameters!$C$27), 1, (Fuzzy_Parameters!$C$30 - Sheet7!F85)/(Fuzzy_Parameters!$C$30 - Fuzzy_Parameters!$C$29)), 0) -> 0 | N85: =MAX(MIN((Sheet7!F85 - Fuzzy_Parameters!$C$29)/(Fuzzy_Parameters!$C$30 - Fuzzy_Parameters!$C$29), 1), 0) -> 0
