Workbook

Sheet Returns
A1: ANNUAL RETURN | B1: 2014 | C1: 2015 | D1: 2016 | E1: 2017 | F1: 2018 | G1: 2019 | H1: 2020 | I1: 2021 | J1: 2022 | K1: 2023 | L1: 2024 | M1: 2025
A2: Adani Ports and Special Economic Zone Ltd | B2: 0.35135135 | C2: 0.642933 | D2: -0.19591 | E2: 0.371821 | F2: 0.043702 | G2: 0.06584 | H2: -0.33519 | I2: 1.796458 | J2: 0.10153 | K2: -0.18383 | L2: 1.123615 | M2: -0.11899083
A3: Asian Paints Ltd | B3: -0.88879619 | C3: 0.479872 | D3: 0.074127 | E3: 0.233107 | F3: 0.04621 | G3: 0.331222 | H3: 0.117166 | I3: 0.52202 | J3: 0.214842 | K3: -0.10387 | L3: 0.030543 | M3: -0.52997189
A4: AXIS Bank Ltd | B4: 0.1223439 | C4: -0.61628 | D4: -0.20673 | E4: 0.104038 | F4: 0.037897 | G4: 0.523557 | H4: -0.51127 | I4: 0.838914 | J4: 0.090538 | K4: 0.128574 | L4: 0.221154 | M4: 0.051130402
A5: Bajaj Finserv Ltd | B5: 0.55069953 | C5: 1.288344 | D5: 0.691596 | E5: -0.83056 | F5: 0.507325 | G5: 0.709196 | H5: -0.26739 | I5: 1.323458 | J5: 0.409835 | K5: -0.22643 | L5: 0.289374 | M5: 0.23595544
A6: Bajaj Finance Ltd | B6: 0.02730109 | C6: 0.758352 | D6: 0.226205 | E6: 1.399296 | F6: 0.266831 | G6: 0.358575 | H6: -0.34763 | I6: 1.106389 | J6: 0.763809 | K6: -0.92574 | L6: 0.297943 | M6: 0.22042406
A7: Bharat Electronics Ltd | B7: -0.00391594 | C7: 1.924256 | D7: -0.63567 | E7: -0.87179 | F7: -0.09146 | G7: -0.34319 | H7: -0.20311 | I7: 0.682582 | J7: 0.685452 | K7: -0.53735 | L7: 1.065095 | M7: 0.49516009
A8: Bharti Airtel Ltd | B8: 0.09287183 | C8: 0.235183 | D8: -0.10916 | E8: -0.00271 | F8: 0.139877 | G8: -0.16546 | H8: 0.323521 | I8: 0.174081 | J8: 0.460275 | K8: -0.00847 | L8: 0.640921 | M8: 0.40836418
A9: HCL Technologies Ltd | B9: 0.74696903 | C9: -0.29547 | D9: -0.16894 | E9: 0.072345 | F9: 0.110475 | G9: 0.122228 | H9: -0.59858 | I9: 1.251746 | J9: 0.182927 | K9: -0.06632 | L9: 0.420825 | M9: 0.030875397
A10: HDFC Bank Ltd | B10: 0.19988784 | C10: 0.365894 | D10: 0.04727 | E10: 0.346434 | F10: 0.311412 | G10: 0.224722 | H10: -0.62789 | I10: 0.732657 | J10: -0.0158 | K10: 0.095105 | L10: -0.10036 | M10: 0.26260185
A11: Hindustan Unilever Ltd | B11: 0.29510835 | C11: 0.446037 | D11: -0.0039 | E11: 0.046291 | F11: 0.468425 | G11: 0.278389 | H11: 0.345679 | I11: 0.05772 | J11: -0.15713 | K11: 0.248871 | L11: -0.11353 | M11: -0.00392373
A12: ICICI Bank Ltd | B12: 0.19141914 | C12: -0.74684 | D12: -0.24976 | E12: 0.171423 | F12: 0.004691 | G12: 0.432651 | H12: -0.18641 | I12: 0.791217 | J12: 0.256344 | K12: 0.201232 | L12: 0.249259 | M12: 0.23046037
... A30: UltraTech Cement Ltd | B30: 0.17178801 | C30: 0.313445 | D30: 0.122435 | E30: 0.236427 | F30: -0.01055 | G30: 0.012969 | H30: -0.18624 | I30: 1.070308 | J30: -0.02006 | K30: 0.154169 | L30: 0.278878 | M30: 0.18054807

Sheet SR_Calculations
A1: Stock Name | B1: mean return | C1: semivariance | D1: S/R ratio
A2: Adani Ports and Special Economic Zone Ltd | B2: =AVERAGE(Returns!B2:M2) -> 0.30527746 | C2: {=AVERAGE(IF(Returns!B2:M2 < B2, ( Returns!B2:M2 - B2 )^2, 0))} -> 0.10399018 | D2: =C2 / B2 -> 0.34064153
A3: Asian Paints Ltd | B3: =AVERAGE(Returns!B3:M3) -> 0.043872577 | C3: {=AVERAGE(IF(Returns!B3:M3 < B3, ( Returns!B3:M3 - B3 )^2, 0))} -> 0.1017645 | D3: =C3 / B3 -> 2.319547
A4: AXIS Bank Ltd | B4: =AVERAGE(Returns!B4:M4) -> 0.065322192 | C4: {=AVERAGE(IF(Returns!B4:M4 < B4, ( Returns!B4:M4 - B4 )^2, 0))} -> 0.072667171 | D4: =C4 / B4 -> 1.1124423
A5: Bajaj Finserv Ltd | B5: =AVERAGE(Returns!B5:M5) -> 0.39011691 | C5: {=AVERAGE(IF(Returns!B5:M5 < B5, ( Returns!B5:M5 - B5 )^2, 0))} -> 0.19470104 | D5: =C5 / B5 -> 0.49908382
A6: Bajaj Finance Ltd | B6: =AVERAGE(Returns!B6:M6) -> 0.3459796 | C6: {=AVERAGE(IF(Returns!B6:M6 < B6, ( Returns!B6:M6 - B6 )^2, 0))} -> 0.18655026 | D6: =C6 / B6 -> 0.53919441
A7: Bharat Electronics Ltd | B7: =AVERAGE(Returns!B7:M7) -> 0.18050493 | C7: {=AVERAGE(IF(Returns!B7:M7 < B7, ( Returns!B7:M7 - B7 )^2, 0))} -> 0.23484788 | D7: =C7 / B7 -> 1.3010608
A8: Bharti Airtel Ltd | B8: =AVERAGE(Returns!B8:M8) -> 0.18244117 | C8: {=AVERAGE(IF(Returns!B8:M8 < B8, ( Returns!B8:M8 - B8 )^2, 0))} -> 0.023891563 | D8: =C8 / B8 -> 0.13095489
A9: HCL Technologies Ltd | B9: =AVERAGE(Returns!B9:M9) -> 0.1507567 | C9: {=AVERAGE(IF(Returns!B9:M9 < B9, ( Returns!B9:M9 - B9 )^2, 0))} -> 0.077742372 | D9: =C9 / B9 -> 0.51568103
A10: HDFC Bank Ltd | B10: =AVERAGE(Returns!B10:M10) -> 0.15349447 | C10: {=AVERAGE(IF(Returns!B10:M10 < B10, ( Returns!B10:M10 - B10 )^2, 0))} -> 0.059863115 | D10: =C10 / B10 -> 0.39000176
A11: Hindustan Unilever Ltd | B11: =AVERAGE(Returns!B11:M11) -> 0.15900305 | C11: {=AVERAGE(IF(Returns!B11:M11 < B11, ( Returns!B11:M11 - B11 )^2, 0))} -> 0.020854931 | D11: =C11 / B11 -> 0.13116057
A12: ICICI Bank Ltd | B12: =AVERAGE(Returns!B12:M12) -> 0.11214054 | C12: {=AVERAGE(IF(Returns!B12:M12 < B12, ( Returns!B12:M12 - B12 )^2, 0))} -> 0.080791451 | D12: =C12 / B12 -> 0.72044819
A13: Infosys Ltd | B13: =AVERAGE(Returns!B13:M13) -> 0.017923165 | C13: {=AVERAGE(IF(Returns!B13:M13 < B13, ( Returns!B13:M13 - B13 )^2, 0))} -> 0.051035417 | D13: =C13 / B13 -> 2.8474556
... A30: UltraTech Cement Ltd | B30: =AVERAGE(Returns!B30:M30) -> 0.19367642 | C30: {=AVERAGE(IF(Returns!B30:M30 < B30, ( Returns!B30:M30 - B30 )^2, 0))} -> 0.022639249 | D30: =C30 / B30 -> 0.11689213

Sheet Impact_Observations
A1: Stock Name | B1: Year | C1: EPS Impact | D1: Payout Impact | E1: PM Impact | F1: P/B Impact | G1: P/E Impact | H1: P/S Impact | I1: CR Impact | J1: D/E Impact
A2: Adani Ports and Special Economic Zone Ltd | B2: 2025 | C2: =Ratio_EPS!B2/SR_Calculations!D2 -> 150.74498 | D2: =Ratio_Payout!B2/SR_Calculations!D2 -> 34.288244 | E2: =Ratio_PM!B2/SR_Calculations!D2 -> 103.12894 | F2: =Ratio_PB!B2/SR_Calculations!D2 -> 12.036113 | G2: =Ratio_PE!B2/SR_Calculations!D2 -> 67.576904 | H2: =Ratio_PS!B2/SR_Calculations!D2 -> 24.130939 | I2: =Ratio_CR!B2/SR_Calculations!D2 -> 2.6420736 | J2: =Ratio_DE!B2/SR_Calculations!D2 -> 2.1430153
A3: Asian Paints Ltd | B3: 2025 | C3: =Ratio_EPS!B3/SR_Calculations!D3 -> 16.490289 | D3: =Ratio_Payout!B3/SR_Calculations!D3 -> 36.532995 | E3: =Ratio_PM!B3/SR_Calculations!D3 -> 4.5353683 | F3: =Ratio_PB!B3/SR_Calculations!D3 -> 4.9837317 | G3: =Ratio_PE!B3/SR_Calculations!D3 -> 15.077297 | H3: =Ratio_PS!B3/SR_Calculations!D3 -> 2.8496944 | I3: =Ratio_CR!B3/SR_Calculations!D3 -> 0.901038 | J3: =Ratio_DE!B3/SR_Calculations!D3 -> 0.017244746
A4: AXIS Bank Ltd | B4: 2025 | C4: =Ratio_EPS!B4/SR_Calculations!D4 -> 81.064877 | D4: =Ratio_Payout!B4/SR_Calculations!D4 -> 1.0697184 | E4: =Ratio_PM!B4/SR_Calculations!D4 -> 19.839231 | F4: =Ratio_PB!B4/SR_Calculations!D4 -> 1.6360399 | G4: =Ratio_PE!B4/SR_Calculations!D4 -> 10.918499 | H4: =Ratio_PS!B4/SR_Calculations!D4 -> 2.4091137 | I4: =Ratio_CR!B4/SR_Calculations!D4 -> 1.0103895 | J4: =Ratio_DE!B4/SR_Calculations!D4 -> 7.0835133
A5: Bajaj Finserv Ltd | B5: 2025 | C5: =Ratio_EPS!B5/SR_Calculations!D5 -> 19.435613 | D5: =Ratio_Payout!B5/SR_Calculations!D5 -> 3.5865719 | E5: =Ratio_PM!B5/SR_Calculations!D5 -> 26.248096 | F5: =Ratio_PB!B5/SR_Calculations!D5 -> 8.8562279 | G5: =Ratio_PE!B5/SR_Calculations!D5 -> 322.48832 | H5: =Ratio_PS!B5/SR_Calculations!D5 -> 4.7887748 | I5: =Ratio_CR!B5/SR_Calculations!D5 -> 2.4845526 | J5: =Ratio_DE!B5/SR_Calculations!D5 -> 9.7979534
A6: Bajaj Finance Ltd | B6: 2025 | C6: =Ratio_EPS!B6/SR_Calculations!D6 -> 498.78114 | D6: =Ratio_Payout!B6/SR_Calculations!D6 -> 24.814797 | E6: =Ratio_PM!B6/SR_Calculations!D6 -> 44.603578 | F6: =Ratio_PB!B6/SR_Calculations!D6 -> 10.664057 | G6: =Ratio_PE!B6/SR_Calculations!D6 -> 13.833044 | H6: =Ratio_PS!B6/SR_Calculations!D6 -> 14.781311 | I6: =Ratio_CR!B6/SR_Calculations!D6 -> 2.3368195 | J6: =Ratio_DE!B6/SR_Calculations!D6 -> 6.9362737
A7: Bharat Electronics Ltd | B7: 2025 | C7: =Ratio_EPS!B7/SR_Calculations!D7 -> 5.5954342 | D7: =Ratio_Payout!B7/SR_Calculations!D7 -> 24.280188 | E7: =Ratio_PM!B7/SR_Calculations!D7 -> 17.093744 | F7: =Ratio_PB!B7/SR_Calculations!D7 -> 8.4700117 | G7: =Ratio_PE!B7/SR_Calculations!D7 -> 31.799898 | H7: =Ratio_PS!B7/SR_Calculations!D7 -> 7.1172693 | I7: =Ratio_CR!B7/SR_Calculations!D7 -> 1.3527423 | J7: =Ratio_DE!B7/SR_Calculations!D7 -> 0.92232432
A8: Bharti Airtel Ltd | B8: 2025 | C8: =Ratio_EPS!B8/SR_Calculations!D8 -> 427.93361 | D8: =Ratio_Payout!B8/SR_Calculations!D8 -> 105.30344 | E8: =Ratio_PM!B8/SR_Calculations!D8 -> 149.05896 | F8: =Ratio_PB!B8/SR_Calculations!D8 -> 58.417062 | G8: =Ratio_PE!B8/SR_Calculations!D8 -> 227.89527 | H8: =Ratio_PS!B8/SR_Calculations!D8 -> 44.29006 | I8: =Ratio_CR!B8/SR_Calculations!D8 -> 2.8254004 | J8: =Ratio_DE!B8/SR_Calculations!D8 -> 8.6289255
A9: HCL Technologies Ltd | B9: 2025 | C9: =Ratio_EPS!B9/SR_Calculations!D9 -> 124.28225 | D9: =Ratio_Payout!B9/SR_Calculations!D9 -> 181.23606 | E9: =Ratio_PM!B9/SR_Calculations!D9 -> 28.816262 | F9: =Ratio_PB!B9/SR_Calculations!D9 -> 12.022936 | G9: =Ratio_PE!B9/SR_Calculations!D9 -> 48.08515 | H9: =Ratio_PS!B9/SR_Calculations!D9 -> 7.155586 | I9: =Ratio_CR!B9/SR_Calculations!D9 -> 4.3049867 | J9: =Ratio_DE!B9/SR_Calculations!D9 -> 0.058175496
A10: HDFC Bank Ltd | B10: 2025 | C10: =Ratio_EPS!B10/SR_Calculations!D10 -> 236.89637 | D10: =Ratio_Payout!B10/SR_Calculations!D10 -> 64.23048 | E10: =Ratio_PM!B10/SR_Calculations!D10 -> 57.461279 | F10: =Ratio_PB!B10/SR_Calculations!D10 -> 7.1538139 | G10: =Ratio_PE!B10/SR_Calculations!D10 -> 53.102837 | H10: =Ratio_PS!B10/SR_Calculations!D10 -> 11.948664 | I10: =Ratio_CR!B10/SR_Calculations!D10 -> 2.6666546 | J10: =Ratio_DE!B10/SR_Calculations!D10 -> 16.076851
A11: Hindustan Unilever Ltd | B11: 2025 | C11: =Ratio_EPS!B11/SR_Calculations!D11 -> 345.53067 | D11: =Ratio_Payout!B11/SR_Calculations!D11 -> 891.57891 | E11: =Ratio_PM!B11/SR_Calculations!D11 -> 128.92594 | F11: =Ratio_PB!B11/SR_Calculations!D11 -> 81.960606 | G11: =Ratio_PE!B11/SR_Calculations!D11 -> 380.09365 | H11: =Ratio_PS!B11/SR_Calculations!D11 -> 64.119879 | I11: =Ratio_CR!B11/SR_Calculations!D11 -> 10.140242 | J11: =Ratio_DE!B11/SR_Calculations!D11 -> 4.2695758
A12: ICICI Bank Ltd | B12: 2025 | C12: =Ratio_EPS!B12/SR_Calculations!D12 -> 98.744089 | D12: =Ratio_Payout!B12/SR_Calculations!D12 -> 21.375583 | E12: =Ratio_PM!B12/SR_Calculations!D12 -> 40.530326 | F12: =Ratio_PB!B12/SR_Calculations!D12 -> 4.3028771 | G12: =Ratio_PE!B12/SR_Calculations!D12 -> 25.847383 | H12: =Ratio_PS!B12/SR_Calculations!D12 -> 7.1483281 | I12: =Ratio_CR!B12/SR_Calculations!D12 -> 1.3880249 | J12: =Ratio_DE!B12/SR_Calculations!D12 -> 12.311781
A13: Infosys Ltd | B13: 2025 | C13: =Ratio_EPS!B13/SR_Calculations!D13 -> 22.595611 | D13: =Ratio_Payout!B13/SR_Calculations!D13 -> 26.679959 | E13: =Ratio_PM!B13/SR_Calculations!D13 -> 5.7630398 | F13: =Ratio_PB!B13/SR_Calculations!D13 -> 2.3880969 | G13: =Ratio_PE!B13/SR_Calculations!D13 -> 8.550546 | H13: =Ratio_PS!B13/SR_Calculations!D13 -> 1.401251 | I13: =Ratio_CR!B13/SR_Calculations!D13 -> 0.79720295 | J13: =Ratio_DE!B13/SR_Calculations!D13 -> 0.16505964
... A30: UltraTech Cement Ltd | B30: 2025 | C30: =Ratio_EPS!B30/SR_Calculations!D30 -> 1754.8659 | D30: =Ratio_Payout!B30/SR_Calculations!D30 -> 285.73353 | E30: =Ratio_PM!B30/SR_Calculations!D30 -> 68.096974 | F30: =Ratio_PB!B30/SR_Calculations!D30 -> 40.977953 | G30: =Ratio_PE!B30/SR_Calculations!D30 -> 479.395 | H30: =Ratio_PS!B30/SR_Calculations!D30 -> 38.154837 | I30: =Ratio_CR!B30/SR_Calculations!D30 -> 6.2450742 | J30: =Ratio_DE!B30/SR_Calculations!D30 -> 2.8231157
A32: Adani Ports and Special Economic Zone Ltd | B32: 2024 | C32: =Ratio_EPS!C2/SR_Calculations!D2 -> 110.23318 | D32: =Ratio_Payout!C2/SR_Calculations!D2 -> 39.073333 | E32: =Ratio_PM!C2/SR_Calculations!D2 -> 90.82862 | F32: =Ratio_PB!C2/SR_Calculations!D2 -> 16.116649 | G32: =Ratio_PE!C2/SR_Calculations!D2 -> 104.89326 | H32: =Ratio_PS!C2/SR_Calculations!D2 -> 31.851665 | I32: =Ratio_CR!C2/SR_Calculations!D2 -> 3.1117756 | J32: =Ratio_DE!C2/SR_Calculations!D2 -> 2.5540045
A33: Asian Paints Ltd | B33: 2024 | C33: =Ratio_EPS!C3/SR_Calculations!D3 -> 24.547897 | D33: =Ratio_Payout!C3/SR_Calculations!D3 -> 19.990972 | E33: =Ratio_PM!C3/SR_Calculations!D3 -> 6.5874931 | F33: =Ratio_PB!C3/SR_Calculations!D3 -> 6.2857101 | G33: =Ratio_PE!C3/SR_Calculations!D3 -> 21.544595 | H33: =Ratio_PS!C3/SR_Calculations!D3 -> 3.3153025 | I33: =Ratio_CR!C3/SR_Calculations!D3 -> 0.88810444 | J33: =Ratio_DE!C3/SR_Calculations!D3 -> 0.02586712
A34: AXIS Bank Ltd | B34: 2024 | C34: =Ratio_EPS!C4/SR_Calculations!D4 -> 76.417445 | D34: =Ratio_Payout!C4/SR_Calculations!D4 -> 1.1236538 | E34: =Ratio_PM!C4/SR_Calculations!D4 -> 21.061766 | F34: =Ratio_PB!C4/SR_Calculations!D4 -> 1.8517814 | G34: =Ratio_PE!C4/SR_Calculations!D4 -> 11.006054 | H34: =Ratio_PS!C4/SR_Calculations!D4 -> 2.579909 | I34: =Ratio_CR!C4/SR_Calculations!D4 -> 1.0005013 | J34: =Ratio_DE!C4/SR_Calculations!D4 -> 7.811641
A35: Bajaj Finserv Ltd | B35: 2024 | C35: =Ratio_EPS!C5/SR_Calculations!D5 -> 14.626802 | D35: =Ratio_Payout!C5/SR_Calculations!D5 -> 3.1257275 | E35: =Ratio_PM!C5/SR_Calculations!D5 -> 28.291841 | F35: =Ratio_PB!C5/SR_Calculations!D5 -> 8.6959341 | G35: =Ratio_PE!C5/SR_Calculations!D5 -> 283.34539 | H35: =Ratio_PS!C5/SR_Calculations!D5 -> 4.7487014 | I35: =Ratio_CR!C5/SR_Calculations!D5 -> 4.2077101 | J35: =Ratio_DE!C5/SR_Calculations!D5 -> 9.5575129
A36: Bajaj Finance Ltd | B36: 2024 | C36: =Ratio_EPS!C6/SR_Calculations!D6 -> 437.65291 | D36: =Ratio_Payout!C6/SR_Calculations!D6 -> 23.29401 | E36: =Ratio_PM!C6/SR_Calculations!D6 -> 48.720832 | F36: =Ratio_PB!C6/SR_Calculations!D6 -> 10.812427 | G36: =Ratio_PE!C6/SR_Calculations!D6 -> 12.868271 | H36: =Ratio_PS!C6/SR_Calculations!D6 -> 15.096596 | I36: =Ratio_CR!C6/SR_Calculations!D6 -> 2.2997271 | J36: =Ratio_DE!C6/SR_Calculations!D6 -> 7.0846432
A37: Bharat Electronics Ltd | B37: 2024 | C37: =Ratio_EPS!C7/SR_Calculations!D7 -> 4.1888896 | D37: =Ratio_Payout!C7/SR_Calculations!D7 -> 28.200066 | E37: =Ratio_PM!C7/SR_Calculations!D7 -> 14.94934 | F37: =Ratio_PB!C7/SR_Calculations!D7 -> 6.9328045 | G37: =Ratio_PE!C7/SR_Calculations!D7 -> 28.410125 | H37: =Ratio_PS!C7/SR_Calculations!D7 -> 5.5877482 | I37: =Ratio_CR!C7/SR_Calculations!D7 -> 1.1913356 | J37: =Ratio_DE!C7/SR_Calculations!D7 -> 0.86852207
A38: Bharti Airtel Ltd | B38: 2024 | C38: =Ratio_EPS!C8/SR_Calculations!D8 -> 97.743581 | D38: =Ratio_Payout!C8/SR_Calculations!D8 -> 232.67554 | E38: =Ratio_PM!C8/SR_Calculations!D8 -> 29.704885 | F38: =Ratio_PB!C8/SR_Calculations!D8 -> 53.453521 | G38: =Ratio_PE!C8/SR_Calculations!D8 -> 716.982 | H38: =Ratio_PS!C8/SR_Calculations!D8 -> 35.966583 | I38: =Ratio_CR!C8/SR_Calculations!D8 -> 3.2072112 | J38: =Ratio_DE!C8/SR_Calculations!D8 -> 11.454326
A39: HCL Technologies Ltd | B39: 2024 | C39: =Ratio_EPS!C9/SR_Calculations!D9 -> 112.20114 | D39: =Ratio_Payout!C9/SR_Calculations!D9 -> 173.88656 | E39: =Ratio_PM!C9/SR_Calculations!D9 -> 27.710928 | F39: =Ratio_PB!C9/SR_Calculations!D9 -> 11.906585 | G39: =Ratio_PE!C9/SR_Calculations!D9 -> 51.607871 | H39: =Ratio_PS!C9/SR_Calculations!D9 -> 7.388288 | I39: =Ratio_CR!C9/SR_Calculations!D9 -> 5.0612682 | J39: =Ratio_DE!C9/SR_Calculations!D9 -> 0.058175496
A40: HDFC Bank Ltd | B40: 2024 | C40: =Ratio_EPS!C10/SR_Calculations!D10 -> 230.79383 | D40: =Ratio_Payout!C10/SR_Calculations!D10 -> 62.512539 | E40: =Ratio_PM!C10/SR_Calculations!D10 -> 60.333061 | F40: =Ratio_PB!C10/SR_Calculations!D10 -> 6.4102275 | G40: =Ratio_PE!C10/SR_Calculations!D10 -> 43.263651 | H40: =Ratio_PS!C10/SR_Calculations!D10 -> 10.923028 | I40: =Ratio_CR!C10/SR_Calculations!D10 -> 2.7948592 | J40: =Ratio_DE!C10/SR_Calculations!D10 -> 18.256328
A41: Hindustan Unilever Ltd | B41: 2024 | C41: =Ratio_EPS!C11/SR_Calculations!D11 -> 333.48436 | D41: =Ratio_Payout!C11/SR_Calculations!D11 -> 697.16073 | E41: =Ratio_PM!C11/SR_Calculations!D11 -> 126.63867 | F41: =Ratio_PB!C11/SR_Calculations!D11 -> 79.368364 | G41: =Ratio_PE!C11/SR_Calculations!D11 -> 395.37492 | H41: =Ratio_PS!C11/SR_Calculations!D11 -> 65.644728 | I41: =Ratio_CR!C11/SR_Calculations!D11 -> 12.656242 | J41: =Ratio_DE!C11/SR_Calculations!D11 -> 4.3458182
A42: ICICI Bank Ltd | B42: 2024 | C42: =Ratio_EPS!C12/SR_Calculations!D12 -> 86.002021 | D42: =Ratio_Payout!C12/SR_Calculations!D12 -> 22.069595 | E42: =Ratio_PM!C12/SR_Calculations!D12 -> 39.156182 | F42: =Ratio_PB!C12/SR_Calculations!D12 -> 4.2195956 | G42: =Ratio_PE!C12/SR_Calculations!D12 -> 24.071266 | H42: =Ratio_PS!C12/SR_Calculations!D12 -> 6.6902799 | I42: =Ratio_CR!C12/SR_Calculations!D12 -> 1.3741446 | J42: =Ratio_DE!C12/SR_Calculations!D12 -> 12.381182
A43: Infosys Ltd | B43: 2024 | C43: =Ratio_EPS!C13/SR_Calculations!D13 -> 22.26198 | D43: =Ratio_Payout!C13/SR_Calculations!D13 -> 19.666681 | E43: =Ratio_PM!C13/SR_Calculations!D13 -> 5.9983376 | F43: =Ratio_PB!C13/SR_Calculations!D13 -> 2.4758946 | G43: =Ratio_PE!C13/SR_Calculations!D13 -> 8.3035887 | H43: =Ratio_PS!C13/SR_Calculations!D13 -> 1.4188105 | I43: =Ratio_CR!C13/SR_Calculations!D13 -> 0.81125058 | J43: =Ratio_DE!C13/SR_Calculations!D13 -> 0.17208346
... A60: UltraTech Cement Ltd | B60: 2024 | C60: =Ratio_EPS!C30/SR_Calculations!D30 -> 2077.7276 | D60: =Ratio_Payout!C30/SR_Calculations!D30 -> 133.71303 | E60: =Ratio_PM!C30/SR_Calculations!D30 -> 84.180179 | F60: =Ratio_PB!C30/SR_Calculations!D30 -> 39.951365 | G60: =Ratio_PE!C30/SR_Calculations!D30 -> 343.00685 | H60: =Ratio_PS!C30/SR_Calculations!D30 -> 33.962938 | I60: =Ratio_CR!C30/SR_Calculations!D30 -> 7.3572107 | J60: =Ratio_DE!C30/SR_Calculations!D30 -> 1.4543324
A62: Adani Ports and Special Economic Zone Ltd | B62: 2023 | C62: =Ratio_EPS!D2/SR_Calculations!D2 -> 72.157966 | D62: =Ratio_Payout!D2/SR_Calculations!D2 -> 58.36047 | E62: =Ratio_PM!D2/SR_Calculations!D2 -> 75.240385 | F62: =Ratio_PB!D2/SR_Calculations!D2 -> 8.8362684 | G62: =Ratio_PE!D2/SR_Calculations!D2 -> 75.457035 | H62: =Ratio_PS!D2/SR_Calculations!D2 -> 19.228425 | I62: =Ratio_CR!D2/SR_Calculations!D2 -> 3.9631104 | J62: =Ratio_DE!D2/SR_Calculations!D2 -> 3.1998447
A63: Asian Paints Ltd | B63: 2023 | C63: =Ratio_EPS!D3/SR_Calculations!D3 -> 18.460501 | D63: =Ratio_Payout!D3/SR_Calculations!D3 -> 20.038395 | E63: =Ratio_PM!D3/SR_Calculations!D3 -> 5.1260009 | F63: =Ratio_PB!D3/SR_Calculations!D3 -> 7.139325 | G63: =Ratio_PE!D3/SR_Calculations!D3 -> 27.798229 | H63: =Ratio_PS!D3/SR_Calculations!D3 -> 3.3109913 | I63: =Ratio_CR!D3/SR_Calculations!D3 -> 0.901038 | J63: =Ratio_DE!D3/SR_Calculations!D3 -> 0.02586712
A64: AXIS Bank Ltd | B64: 2023 | C64: =Ratio_EPS!D4/SR_Calculations!D4 -> 31.498262 | D64: =Ratio_Payout!D4/SR_Calculations!D4 -> 2.9214998 | E64: =Ratio_PM!D4/SR_Calculations!D4 -> 11.155635 | F64: =Ratio_PB!D4/SR_Calculations!D4 -> 1.8338029 | G64: =Ratio_PE!D4/SR_Calculations!D4 -> 21.922755 | H64: =Ratio_PS!D4/SR_Calculations!D4 -> 2.7147475 | I64: =Ratio_CR!D4/SR_Calculations!D4 -> 0.99061316 | J64: =Ratio_DE!D4/SR_Calculations!D4 -> 8.4408871
A65: Bajaj Finserv Ltd | B65: 2023 | C65: =Ratio_EPS!D5/SR_Calculations!D5 -> 9.2168887 | D65: =Ratio_Payout!D5/SR_Calculations!D5 -> 1.9836347 | E65: =Ratio_PM!D5/SR_Calculations!D5 -> 29.794595 | F65: =Ratio_PB!D5/SR_Calculations!D5 -> 8.7159709 | G65: =Ratio_PE!D5/SR_Calculations!D5 -> 279.19158 | H65: =Ratio_PS!D5/SR_Calculations!D5 -> 4.9290318 | I65: =Ratio_CR!D5/SR_Calculations!D5 -> 4.1275632 | J65: =Ratio_DE!D5/SR_Calculations!D5 -> 9.1367419
A66: Bajaj Finance Ltd | B66: 2023 | C66: =Ratio_EPS!D6/SR_Calculations!D6 -> 351.58006 | D66: =Ratio_Payout!D6/SR_Calculations!D6 -> 19.45495 | E66: =Ratio_PM!D6/SR_Calculations!D6 -> 51.539852 | F66: =Ratio_PB!D6/SR_Calculations!D6 -> 11.57282 | G66: =Ratio_PE!D6/SR_Calculations!D6 -> 12.326723 | H66: =Ratio_PS!D6/SR_Calculations!D6 -> 15.207873 | I66: =Ratio_CR!D6/SR_Calculations!D6 -> 2.2811809 | J66: =Ratio_DE!D6/SR_Calculations!D6 -> 7.3999284
A67: Bharat Electronics Ltd | B67: 2023 | C67: =Ratio_EPS!D7/SR_Calculations!D7 -> 3.1435887 | D67: =Ratio_Payout!D7/SR_Calculations!D7 -> 31.996968 | E67: =Ratio_PM!D7/SR_Calculations!D7 -> 12.735762 | F67: =Ratio_PB!D7/SR_Calculations!D7 -> 3.9506225 | G67: =Ratio_PE!D7/SR_Calculations!D7 -> 18.331888 | H67: =Ratio_PS!D7/SR_Calculations!D7 -> 3.0897865 | I67: =Ratio_CR!D7/SR_Calculations!D7 -> 1.1221613 | J67: =Ratio_DE!D7/SR_Calculations!D7 -> 0.84546396
A68: Bharti Airtel Ltd | B68: 2023 | C68: =Ratio_EPS!D8/SR_Calculations!D8 -> 111.25969 | D68: =Ratio_Payout!D8/SR_Calculations!D8 -> 155.32066 | E68: =Ratio_PM!D8/SR_Calculations!D8 -> 63.304241 | F68: =Ratio_PB!D8/SR_Calculations!D8 -> 35.737497 | G68: =Ratio_PE!D8/SR_Calculations!D8 -> 386.45445 | H68: =Ratio_PS!D8/SR_Calculations!D8 -> 23.290463 | I68: =Ratio_CR!D8/SR_Calculations!D8 -> 3.5890221 | J68: =Ratio_DE!D8/SR_Calculations!D8 -> 13.897915
A69: HCL Technologies Ltd | B69: 2023 | C69: =Ratio_EPS!D9/SR_Calculations!D9 -> 106.24785 | D69: =Ratio_Payout!D9/SR_Calculations!D9 -> 169.67853 | E69: =Ratio_PM!D9/SR_Calculations!D9 -> 28.37025 | F69: =Ratio_PB!D9/SR_Calculations!D9 -> 8.7457163 | G69: =Ratio_PE!D9/SR_Calculations!D9 -> 38.401839 | H69: =Ratio_PS!D9/SR_Calculations!D9 -> 5.6430231 | I69: =Ratio_CR!D9/SR_Calculations!D9 -> 4.847958 | J69: =Ratio_DE!D9/SR_Calculations!D9 -> 0.058175496
A70: HDFC Bank Ltd | B70: 2023 | C70: =Ratio_EPS!D10/SR_Calculations!D10 -> 210.94777 | D70: =Ratio_Payout!D10/SR_Calculations!D10 -> 61.71767 | E70: =Ratio_PM!D10/SR_Calculations!D10 -> 69.974043 | F70: =Ratio_PB!D10/SR_Calculations!D10 -> 8.2307321 | G70: =Ratio_PE!D10/SR_Calculations!D10 -> 52.082586 | H70: =Ratio_PS!D10/SR_Calculations!D10 -> 14.256346 | I70: =Ratio_CR!D10/SR_Calculations!D10 -> 2.3589637 | J70: =Ratio_DE!D10/SR_Calculations!D10 -> 19.99991
A71: Hindustan Unilever Ltd | B71: 2023 | C71: =Ratio_EPS!D11/SR_Calculations!D11 -> 328.37612 | D71: =Ratio_Payout!D11/SR_Calculations!D11 -> 637.23418 | E71: =Ratio_PM!D11/SR_Calculations!D11 -> 127.62982 | F71: =Ratio_PB!D11/SR_Calculations!D11 -> 91.109697 | G71: =Ratio_PE!D11/SR_Calculations!D11 -> 452.94938 | H71: =Ratio_PS!D11/SR_Calculations!D11 -> 75.708728 | I71: =Ratio_CR!D11/SR_Calculations!D11 -> 10.750182 | J71: =Ratio_DE!D11/SR_Calculations!D11 -> 4.1170909
A72: ICICI Bank Ltd | B72: 2023 | C72: =Ratio_EPS!D12/SR_Calculations!D12 -> 66.40311 | D72: =Ratio_Payout!D12/SR_Calculations!D12 -> 22.763608 | E72: =Ratio_PM!D12/SR_Calculations!D12 -> 39.503188 | F72: =Ratio_PB!D12/SR_Calculations!D12 -> 4.0252721 | G72: =Ratio_PE!D12/SR_Calculations!D12 -> 24.919627 | H72: =Ratio_PS!D12/SR_Calculations!D12 -> 7.0234058 | I72: =Ratio_CR!D12/SR_Calculations!D12 -> 1.4019051 | J72: =Ratio_DE!D12/SR_Calculations!D12 -> 10.646151
A73: Infosys Ltd | B73: 2023 | C73: =Ratio_EPS!D13/SR_Calculations!D13 -> 20.207514 | D73: =Ratio_Payout!D13/SR_Calculations!D13 -> 19.866859 | E73: =Ratio_PM!D13/SR_Calculations!D13 -> 5.7665517 | F73: =Ratio_PB!D13/SR_Calculations!D13 -> 2.7498234 | G73: =Ratio_PE!D13/SR_Calculations!D13 -> 8.3937042 | H73: =Ratio_PS!D13/SR_Calculations!D13 -> 1.4152986 | I73: =Ratio_CR!D13/SR_Calculations!D13 -> 0.63565521 | J73: =Ratio_DE!D13/SR_Calculations!D13 -> 0.20017871
... A90: UltraTech Cement Ltd | B90: 2023 | C90: =Ratio_EPS!D30/SR_Calculations!D30 -> 1501.7265 | D90: =Ratio_Payout!D30/SR_Calculations!D30 -> 184.52911 | E90: =Ratio_PM!D30/SR_Calculations!D30 -> 68.524719 | F90: =Ratio_PB!D30/SR_Calculations!D30 -> 34.64733 | G90: =Ratio_PE!D30/SR_Calculations!D30 -> 371.16871 | H90: =Ratio_PS!D30/SR_Calculations!D30 -> 29.771039 | I90: =Ratio_CR!D30/SR_Calculations!D30 -> 7.6138576 | J90: =Ratio_DE!D30/SR_Calculations!D30 -> 1.5398813

Sheet Correlation_Matrix
B1: EPS | C1: Payout | D1: PM | E1: P/B | F1: P/E | G1: P/S | H1: CR | I1: D/E
A2: EPS | B2: =CORREL(Impact_Observations!$C$2:$C$91, Impact_Observations!$C$2:$C$91) -> 1 | C2: =CORREL(Impact_Observations!$C$2:$C$91, Impact_Observations!$D$2:$D$91) -> 0.202742 | D2: =CORREL(Impact_Observations!$C$2:$C$91, Impact_Observations!$E$2:$E$91) -> 0.16772205 | E2: =CORREL(Impact_Observations!$C$2:$C$91, Impact_Observations!$F$2:$F$91) -> 0.18595417 | F2: =CORREL(Impact_Observations!$C$2:$C$91, Impact_Observations!$G$2:$G$91) -> 0.32222311 | G2: =CORREL(Impact_Observations!$C$2:$C$91, Impact_Observations!$H$2:$H$91) -> 0.30027002 | H2: =CORREL(Impact_Observations!$C$2:$C$91, Impact_Observations!$I$2:$I$91) -> 0.31193543 | I2: =CORREL(Impact_Observations!$C$2:$C$91, Impact_Observations!$J$2:$J$91) -> -0.072755173
A3: Payout | B3: =CORREL(Impact_Observations!$D$2:$D$91, Impact_Observations!$C$2:$C$91) -> 0.202742 | C3: =CORREL(Impact_Observations!$D$2:$D$91, Impact_Observations!$D$2:$D$91) -> 1 | D3: =CORREL(Impact_Observations!$D$2:$D$91, Impact_Observations!$E$2:$E$91) -> 0.57268887 | E3: =CORREL(Impact_Observations!$D$2:$D$91, Impact_Observations!$F$2:$F$91) -> 0.50383124 | F3: =CORREL(Impact_Observations!$D$2:$D$91, Impact_Observations!$G$2:$G$91) -> 0.49472098 | G3: =CORREL(Impact_Observations!$D$2:$D$91, Impact_Observations!$H$2:$H$91) -> 0.76815211 | H3: =CORREL(Impact_Observations!$D$2:$D$91, Impact_Observations!$I$2:$I$91) -> 0.75848509 | I3: =CORREL(Impact_Observations!$D$2:$D$91, Impact_Observations!$J$2:$J$91) -> -0.014788202
A4: PM | B4: =CORREL(Impact_Observations!$E$2:$E$91, Impact_Observations!$C$2:$C$91) -> 0.16772205 | C4: =CORREL(Impact_Observations!$E$2:$E$91, Impact_Observations!$D$2:$D$91) -> 0.57268887 | D4: =CORREL(Impact_Observations!$E$2:$E$91, Impact_Observations!$E$2:$E$91) -> 1 | E4: =CORREL(Impact_Observations!$E$2:$E$91, Impact_Observations!$F$2:$F$91) -> 0.23245976 | F4: =CORREL(Impact_Observations!$E$2:$E$91, Impact_Observations!$G$2:$G$91) -> 0.22703564 | G4: =CORREL(Impact_Observations!$E$2:$E$91, Impact_Observations!$H$2:$H$91) -> 0.72371135 | H4: =CORREL(Impact_Observations!$E$2:$E$91, Impact_Observations!$I$2:$I$91) -> 0.58702302 | I4: =CORREL(Impact_Observations!$E$2:$E$91, Impact_Observations!$J$2:$J$91) -> 0.34219714
A5: P/B | B5: =CORREL(Impact_Observations!$F$2:$F$91, Impact_Observations!$C$2:$C$91) -> 0.18595417 | C5: =CORREL(Impact_Observations!$F$2:$F$91, Impact_Observations!$D$2:$D$91) -> 0.50383124 | D5: =CORREL(Impact_Observations!$F$2:$F$91, Impact_Observations!$E$2:$E$91) -> 0.23245976 | E5: =CORREL(Impact_Observations!$F$2:$F$91, Impact_Observations!$F$2:$F$91) -> 1 | F5: =CORREL(Impact_Observations!$F$2:$F$91, Impact_Observations!$G$2:$G$91) -> 0.73831866 | G5: =CORREL(Impact_Observations!$F$2:$F$91, Impact_Observations!$H$2:$H$91) -> 0.68306745 | H5: =CORREL(Impact_Observations!$F$2:$F$91, Impact_Observations!$I$2:$I$91) -> 0.66578266 | I5: =CORREL(Impact_Observations!$F$2:$F$91, Impact_Observations!$J$2:$J$91) -> -0.067549425
A6: P/E | B6: =CORREL(Impact_Observations!$G$2:$G$91, Impact_Observations!$C$2:$C$91) -> 0.32222311 | C6: =CORREL(Impact_Observations!$G$2:$G$91, Impact_Observations!$D$2:$D$91) -> 0.49472098 | D6: =CORREL(Impact_Observations!$G$2:$G$91, Impact_Observations!$E$2:$E$91) -> 0.22703564 | E6: =CORREL(Impact_Observations!$G$2:$G$91, Impact_Observations!$F$2:$F$91) -> 0.73831866 | F6: =CORREL(Impact_Observations!$G$2:$G$91, Impact_Observations!$G$2:$G$91) -> 1 | G6: =CORREL(Impact_Observations!$G$2:$G$91, Impact_Observations!$H$2:$H$91) -> 0.67998039 | H6: =CORREL(Impact_Observations!$G$2:$G$91, Impact_Observations!$I$2:$I$91) -> 0.56386792 | I6: =CORREL(Impact_Observations!$G$2:$G$91, Impact_Observations!$J$2:$J$91) -> 0.058177151
A7: P/S | B7: =CORREL(Impact_Observations!$H$2:$H$91, Impact_Observations!$C$2:$C$91) -> 0.30027002 | C7: =CORREL(Impact_Observations!$H$2:$H$91, Impact_Observations!$D$2:$D$91) -> 0.76815211 | D7: =CORREL(Impact_Observations!$H$2:$H$91, Impact_Observations!$E$2:$E$91) -> 0.72371135 | E7: =CORREL(Impact_Observations!$H$2:$H$91, Impact_Observations!$F$2:$F$91) -> 0.68306745 | F7: =CORREL(Impact_Observations!$H$2:$H$91, Impact_Observations!$G$2:$G$91) -> 0.67998039 | G7: =CORREL(Impact_Observations!$H$2:$H$91, Impact_Observations!$H$2:$H$91) -> 1 | H7: =CORREL(Impact_Observations!$H$2:$H$91, Impact_Observations!$I$2:$I$91) -> 0.78120257 | I7: =CORREL(Impact_Observations!$H$2:$H$91, Impact_Observations!$J$2:$J$91) -> 0.12303779
A8: CR | B8: =CORREL(Impact_Observations!$I$2:$I$91, Impact_Observations!$C$2:$C$91) -> 0.31193543 | C8: =CORREL(Impact_Observations!$I$2:$I$91, Impact_Observations!$D$2:$D$91) -> 0.75848509 | D8: =CORREL(Impact_Observations!$I$2:$I$91, Impact_Observations!$E$2:$E$91) -> 0.58702302 | E8: =CORREL(Impact_Observations!$I$2:$I$91, Impact_Observations!$F$2:$F$91) -> 0.66578266 | F8: =CORREL(Impact_Observations!$I$2:$I$91, Impact_Observations!$G$2:$G$91) -> 0.56386792 | G8: =CORREL(Impact_Observations!$I$2:$I$91, Impact_Observations!$H$2:$H$91) -> 0.78120257 | H8: =CORREL(Impact_Observations!$I$2:$I$91, Impact_Observations!$I$2:$I$91) -> 1 | I8: =CORREL(Impact_Observations!$I$2:$I$91, Impact_Observations!$J$2:$J$91) -> -0.056030002
A9: D/E | B9: =CORREL(Impact_Observations!$J$2:$J$91, Impact_Observations!$C$2:$C$91) -> -0.072755173 | C9: =CORREL(Impact_Observations!$J$2:$J$91, Impact_Observations!$D$2:$D$91) -> -0.014788202 | D9: =CORREL(Impact_Observations!$J$2:$J$91, Impact_Observations!$E$2:$E$91) -> 0.34219714 | E9: =CORREL(Impact_Observations!$J$2:$J$91, Impact_Observations!$F$2:$F$91) -> -0.067549425 | F9: =CORREL(Impact_Observations!$J$2:$J$91, Impact_Observations!$G$2:$G$91) -> 0.058177151 | G9: =CORREL(Impact_Observations!$J$2:$J$91, Impact_Observations!$H$2:$H$91) -> 0.12303779 | H9: =CORREL(Impact_Observations!$J$2:$J$91, Impact_Observations!$I$2:$I$91) -> -0.056030002 | I9: =CORREL(Impact_Observations!$J$2:$J$91, Impact_Observations!$J$2:$J$91) -> 1
A15: Payout Ratio (Rank 1)
A17: Diluted EPS (Rank 2)
A19: Debt to Equity (Rank 3)
A21: Profit Margin (Rank 4)

Sheet Ratio_EPS
B1: 2025 | C1: 2024 | D1: 2023 | E1: 2022 | F1: 2021 | G1: 2020 | H1: 2019 | I1: 2018 | J1: 2017 | K1: 2016 | L1: 2015 | M1: 2014
A2: Adani Ports and Special Economic Zone Ltd | B2: 51.35 | C2: 37.55 | D2: 24.58 | E2: 22.39 | F2: 24.58 | G2: 18.35 | H2: 19.27 | I2: 17.74 | J2: 18.89 | K2: 13.99 | L2: 11.18 | M2: 8.45
A3: Asian Paints Ltd | B3: 38.25 | C3: 56.94 | D3: 42.82 | E3: 31.59 | F3: 32.73 | G3: 28.2 | H3: 22.48 | I3: 21.26 | J3: 20.22 | K3: 18.19 | L3: 14.54 | M3: 12.71
A4: AXIS Bank Ltd | B4: 90.18 | C4: 85.01 | D4: 35.04 | E4: 45.91 | F4: 24.19 | G4: 6.8 | H4: 19.49 | I4: 1.86 | J4: 16.48 | K4: 34.93 | L4: 31.23 | M4: 134.2
A5: Bajaj Finserv Ltd | B5: 9.7 | C5: 7.3 | D5: 4.6 | E5: 26.6 | F5: 11.2 | G5: 41.9 | H5: 19.3 | I5: 8.9 | J5: 4.4 | K5: 10.3 | L5: 7.9 | M5: 5.2
A6: Bajaj Finance Ltd | B6: 268.94 | C6: 235.98 | D6: 189.57 | E6: 115.79 | F6: 73 | G6: 89.07 | H6: 68.75 | I6: 47.05 | J6: 33.67 | K6: 238.85 | L6: 177.7 | M6: 143.65
A7: Bharat Electronics Ltd | B7: 7.28 | C7: 5.45 | D7: 4.09 | E7: 9.85 | F7: 8.62 | G7: 7.49 | H7: 7.74 | I7: 5.83 | J7: 5.94 | K7: 5.57 | L7: 149.65 | M7: 118.91
A8: Bharti Airtel Ltd | B8: 56.04 | C8: 12.8 | D8: 14.57 | E8: 7.63 | F8: -27.65 | G8: -63.41 | H8: 0.96 | I8: 2.75 | J8: 9.51 | K8: 15.2 | L8: 11.56 | M8: 7.01
A9: HCL Technologies Ltd | B9: 64.09 | C9: 57.86 | D9: 54.79 | E9: 49.77 | F9: 41.07 | G9: 40.75 | H9: 73.55 | I9: 62.19 | J9: 60.27 | K9: 39.69 | L9: 51.79 | M9: 91.93
A10: HDFC Bank Ltd | B10: 92.39 | C10: 90.01 | D10: 82.27 | E10: 68.31 | F10: 57.61 | G10: 49.46 | H10: 82.51 | I10: 70.76 | J10: 59.16 | K10: 50.24 | L10: 43.6 | M10: 36.31
A11: Hindustan Unilever Ltd | B11: 45.32 | C11: 43.74 | D11: 43.07 | E11: 37.79 | F11: 34.03 | G11: 31.17 | H11: 27.96 | I11: 24.08 | J11: 20.67 | K11: 19.09 | L11: 20.16 | M11: 18.23
A12: ICICI Bank Ltd | B12: 71.14 | C12: 61.96 | D12: 47.84 | E12: 35.44 | F12: 26.83 | G12: 14.55 | H12: 6.53 | I12: 11.89 | J12: 15.84 | K12: 17.41 | L12: 21.17 | M12: 95.65
A13: Infosys Ltd | B13: 64.34 | C13: 63.39 | D13: 57.54 | E13: 52.41 | F13: 45.52 | G13: 38.91 | H13: 35.38 | I13: 71 | J13: 62.77 | K13: 59.02 | L13: 108.26 | M13: 186.49
... A30: UltraTech Cement Ltd | B30: 205.13 | C30: 242.87 | D30: 175.54 | E30: 254.53 | F30: 189.33 | G30: 199.49 | H30: 84 | I30: 80.92 | J30: 98.88 | K30: 90.25 | L30: 76.44 | M30: 80.42

Sheet Ratio_Payout
B1: 2025 | C1: 2024 | D1: 2023 | E1: 2022 | F1: 2021 | G1: 2020 | H1: 2019 | I1: 2018 | J1: 2017 | K1: 2016 | L1: 2015 | M1: 2014
A2: Adani Ports and Special Economic Zone Ltd | B2: 11.68 | C2: 13.31 | D2: 19.88 | E2: 21.59 | F2: 0 | G2: 18.37 | H2: 10.38 | I2: 7.32 | J2: 0 | K2: 15.72 | L2: 9.83 | M2: 12.28
A3: Asian Paints Ltd | B3: 84.74 | C3: 46.37 | D3: 46.48 | E3: 57.44 | F3: 10.23 | G3: 64.35 | H3: 39.59 | I3: 48.45 | J3: 39.31 | K3: 35.72 | L3: 41.93 | M3: 41.71
A4: AXIS Bank Ltd | B4: 1.19 | C4: 1.25 | D4: 3.25 | E4: 1.24 | F4: 1.52 | G4: 1.25 | H4: 2.33 | I4: 1.39 | J4: 1.53 | K4: 1.09 | L4: 1.005 | M4: 1.32
A5: Bajaj Finserv Ltd | B5: 1.79 | C5: 1.56 | D5: 0.99 | E5: 1.04 | F5: 0 | G5: 3.54 | H5: 0.86 | I5: 1.05 | J5: 0 | K5: 1.49 | L5: 1.64 | M5: 1.8
A6: Bajaj Finance Ltd | B6: 13.38 | C6: 12.56 | D6: 10.49 | E6: 8.57 | F6: 0 | G6: 18.04 | H6: 5.78 | I6: 7.4 | J6: 0 | K6: 10.99 | L6: 10.05 | M6: 11.15
A7: Bharat Electronics Ltd | B7: 31.59 | C7: 36.69 | D7: 41.63 | E7: 42.65 | F7: 48.75 | G7: 41.41 | H7: 27.12 | I7: 43.83 | J7: 40.43 | K7: 18.36 | L7: 19.51 | M7: 19.59
A8: Bharti Airtel Ltd | B8: 13.79 | C8: 30.47 | D8: 20.34 | E8: 0 | F8: -8.23 | G8: 0 | H8: 588.42 | I8: 168.1 | J8: 17.21 | K8: 17.57 | L8: 33.3 | M8: 0
A9: HCL Technologies Ltd | B9: 93.46 | C9: 89.67 | D9: 87.5 | E9: 84.38 | F9: 29.22 | G9: 12.27 | H9: 10.85 | I9: 19.4 | J9: 39.34 | K9: 48.15 | L9: 32.6 | M9: 10.75
A10: HDFC Bank Ltd | B10: 25.05 | C10: 24.38 | D10: 24.07 | E10: 23.28 | F10: 11.54 | G10: 0 | H10: 18.63 | I10: 19.32 | J10: 20.84 | K10: 20.67 | L10: 0 | M10: 0
A11: Hindustan Unilever Ltd | B11: 116.94 | C11: 91.44 | D11: 83.58 | E11: 84.68 | F11: 110.2 | G11: 77 | H11: 75.09 | I11: 74.72 | J11: 79.78 | K11: 81.03 | L11: 74.38 | M11: 71.25
A12: ICICI Bank Ltd | B12: 15.4 | C12: 15.9 | D12: 16.4 | E12: 13.8 | F12: 7.5 | G12: 0 | H12: 15 | I12: 12 | J12: 14 | K12: 29 | L12: 24 | M12: 24
A13: Infosys Ltd | B13: 75.97 | C13: 56 | D13: 56.57 | E13: 57.23 | F13: 47.12 | G13: 57.35 | H13: 89.01 | I13: 46.59 | J13: 48.43 | K13: 50.51 | L13: 41.14 | M13: 33.83
... A30: UltraTech Cement Ltd | B30: 33.4 | C30: 15.63 | D30: 21.57 | E30: 14.52 | F30: 6.86 | G30: 6.61 | H30: 14.46 | I30: 14.86 | J30: 9.6 | K30: 11.83 | L30: 11.77 | M30: 11.18

Sheet Ratio_PM
B1: 2025 | C1: 2024 | D1: 2023 | E1: 2022 | F1: 2021 | G1: 2020 | H1: 2019 | I1: 2018 | J1: 2017 | K1: 2016 | L1: 2015 | M1: 2014
A2: Adani Ports and Special Economic Zone Ltd | B2: 35.13 | C2: 30.94 | D2: 25.63 | E2: 28.88 | F2: 40.34 | G2: 31.91 | H2: 37.02 | I2: 32.58 | J2: 46.12 | K2: 39.9 | L2: 37.78 | M2: 36.09
A3: Asian Paints Ltd | B3: 10.52 | C3: 15.28 | D3: 11.89 | E3: 10.49 | F3: 14.63 | G3: 13.47 | H3: 11.26 | I3: 12.19 | J3: 13.05 | K3: 12.39 | L3: 10.06 | M3: 9.93
A4: AXIS Bank Ltd | B4: 22.07 | C4: 23.43 | D4: 12.41 | E4: 20.57 | F4: 11.2 | G4: 2.94 | H4: 9 | I4: 0.99 | J4: 8.78 | K4: 20.18 | L4: 20.84 | M4: 20.52
A5: Bajaj Finserv Ltd | B5: 13.1 | C5: 14.12 | D5: 14.87 | E5: 12.15 | F5: 12.15 | G5: 11.02 | H5: 12.61 | I5: 12.7 | J5: 14.07 | K5: 29.37 | L5: 31.75 | M5: 36.38
A6: Bajaj Finance Ltd | B6: 24.05 | C6: 26.27 | D6: 27.79 | E6: 22.21 | F6: 16.57 | G6: 19.95 | H6: 21.6 | I6: 19.89 | J6: 18.42 | K6: 17.5 | L6: 16.68 | M6: 17.65
A7: Bharat Electronics Ltd | B7: 22.24 | C7: 19.45 | D7: 16.57 | E7: 15.32 | F7: 14.66 | G7: 13.82 | H7: 15.19 | I7: 13.53 | J7: 17.27 | K7: 17.72 | L7: 16.87 | M7: 14.6
A8: Bharti Airtel Ltd | B8: 19.52 | C8: 3.89 | D8: 8.29 | E8: 5.04 | F8: -12.19 | G8: -35.77 | H8: 1.64 | I8: 1.33 | J8: 3.34 | K8: 6.03 | L8: 5.25 | M8: 3.51
A9: HCL Technologies Ltd | B9: 14.86 | C9: 14.29 | D9: 14.63 | E9: 15.78 | F9: 14.81 | G9: 15.64 | H9: 16.74 | I9: 17.22 | J9: 18.08 | K9: 17.97 | L9: 19.89 | M9: 20.24
A10: HDFC Bank Ltd | B10: 22.41 | C10: 23.53 | D10: 27.29 | E10: 28.93 | F10: 25.74 | G10: 22.86 | H10: 21.29 | I10: 21.79 | J10: 20.99 | K10: 20.41 | L10: 21.07 | M10: 20.61
A11: Hindustan Unilever Ltd | B11: 16.91 | C11: 16.61 | D11: 16.74 | E11: 16.95 | F11: 17 | G11: 16.98 | H11: 15.41 | I11: 14.7 | J11: 13.53 | K11: 12.92 | L11: 13.68 | M11: 13.53
A12: ICICI Bank Ltd | B12: 29.2 | C12: 28.21 | D12: 28.46 | E12: 27.02 | F12: 22.67 | G12: 13.23 | H12: 7.9 | I12: 14.63 | J12: 18.6 | K12: 18.42 | L12: 23.54 | M12: 23.6
A13: Infosys Ltd | B13: 16.41 | C13: 17.08 | D13: 16.42 | E13: 18.2 | F13: 19.33 | G13: 18.32 | H13: 18.63 | I13: 22.82 | J13: 21 | K13: 21.6 | L13: 23.2 | M13: 21.25
... A30: UltraTech Cement Ltd | B30: 7.96 | C30: 9.84 | D30: 8.01 | E30: 13.94 | F30: 12.2 | G30: 13.55 | H30: 5.76 | I30: 7.18 | J30: 10.69 | K30: 9.85 | L30: 8.63 | M30: 10.21

Sheet Ratio_PB
B1: 2025 | C1: 2024 | D1: 2023 | E1: 2022 | F1: 2021 | G1: 2020 | H1: 2019 | I1: 2018 | J1: 2017 | K1: 2016 | L1: 2015 | M1: 2014
A2: Adani Ports and Special Economic Zone Ltd | B2: 4.1 | C2: 5.49 | D2: 3.01 | E2: 4.29 | F2: 4.69 | G2: 2.01 | H2: 3.19 | I2: 3.49 | J2: 4.02 | K2: 3.8 | L2: 5.92 | M2: 4.43
A3: Asian Paints Ltd | B3: 11.56 | C3: 14.58 | D3: 16.56 | E3: 21.4 | F3: 19 | G3: 15.78 | H3: 15.11 | I3: 12.78 | J3: 13.51 | K3: 12.77 | L3: 16.36 | M3: 12.98
A4: AXIS Bank Ltd | B4: 1.82 | C4: 2.06 | D4: 2.04 | E4: 1.97 | F4: 2.06 | G4: 1.24 | H4: 2.94 | I4: 2.04 | J4: 2.08 | K4: 1.98 | L4: 2.96 | M4: 1.79
A5: Bajaj Finserv Ltd | B5: 4.42 | C5: 4.34 | D5: 4.35 | E5: 6.74 | F5: 4.29 | G5: 2.33 | H5: 4.72 | I5: 4.02 | J5: 4.03 | K5: 1.99 | L5: 1.99 | M5: 1.32
A6: Bajaj Finance Ltd | B6: 5.75 | C6: 5.83 | D6: 6.24 | E6: 10.02 | F6: 8.39 | G6: 4.11 | H6: 8.86 | I6: 6.15 | J6: 6.69 | K6: 5 | L6: 4.27 | M6: 2.08
A7: Bharat Electronics Ltd | B7: 11.02 | C7: 9.02 | D7: 5.14 | E7: 4.18 | F7: 2.76 | G7: 1.8 | H7: 2.47 | I7: 4.32 | J7: 4.51 | K7: 3.17 | L7: 3.3 | M7: 1.27
A8: Bharti Airtel Ltd | B8: 7.65 | C8: 7 | D8: 4.68 | E8: 6.34 | F8: 4.82 | G8: 3.12 | H8: 1.86 | I8: 2.29 | J8: 2.07 | K8: 2.1 | L8: 3.96 | M8: 2.1
A9: HCL Technologies Ltd | B9: 6.2 | C9: 6.14 | D9: 4.51 | E9: 5.1 | F9: 4.46 | G9: 2.31 | H9: 3.56 | I9: 3.7 | J9: 3.78 | K9: 4.19 | L9: 5.35 | M9: 5.36
A10: HDFC Bank Ltd | B10: 2.79 | C10: 2.5 | D10: 3.21 | E10: 3.4 | F10: 4.04 | G10: 2.76 | H10: 4.23 | I10: 4.62 | J10: 4.13 | K10: 3.73 | L10: 4.13 | M10: 4.13
A11: Hindustan Unilever Ltd | B11: 10.75 | C11: 10.41 | D11: 11.95 | E11: 9.81 | F11: 11.98 | G11: 60.32 | H11: 46.89 | I11: 39.63 | J11: 29.14 | K11: 28.57 | L11: 46.97 | M11: 36.91
A12: ICICI Bank Ltd | B12: 3.1 | C12: 3.04 | D12: 2.9 | E12: 2.84 | F12: 2.6 | G12: 1.75 | H12: 2.31 | I12: 1.66 | J12: 1.59 | K12: 1.51 | L12: 2.16 | M12: 1.88
A13: Infosys Ltd | B13: 6.8 | C13: 7.05 | D13: 7.83 | E13: 10.62 | F13: 7.61 | G13: 4.15 | H13: 4.96 | I13: 3.8 | J13: 3.39 | K13: 4.51 | L13: 5 | M13: 4.21
... A30: UltraTech Cement Ltd | B30: 4.79 | C30: 4.67 | D30: 4.05 | E30: 3.78 | F30: 4.4 | G30: 2.41 | H30: 3.87 | I30: 4.11 | J30: 4.49 | K30: 4.04 | L30: 4.14 | M30: 3.49

Sheet Ratio_PE
B1: 2025 | C1: 2024 | D1: 2023 | E1: 2022 | F1: 2021 | G1: 2020 | H1: 2019 | I1: 2018 | J1: 2017 | K1: 2016 | L1: 2015 | M1: 2014
A2: Adani Ports and Special Economic Zone Ltd | B2: 23.0195 | C2: 35.731 | D2: 25.7038 | E2: 34.5735 | F2: 28.5903 | G2: 13.6948 | H2: 19.616 | I2: 19.9915 | J2: 17.9884 | K2: 17.7055 | L2: 27.5537 | M2: 22.1893
A3: Asian Paints Ltd | B3: 34.9725 | C3: 49.9737 | D3: 64.4793 | E3: 97.5546 | F3: 77.5053 | G3: 59.1028 | H3: 66.3657 | I3: 52.714 | J3: 52.9773 | K3: 47.757 | L3: 55.6224 | M3: 42.9976
A4: AXIS Bank Ltd | B4: 12.1462 | C4: 12.2436 | D4: 24.3878 | E4: 16.5215 | F4: 28.8342 | G4: 55.5344 | H4: 39.5767 | I4: 273.871 | J4: 29.6735 | K4: 12.658 | L4: 17.7567 | M4: 10.8559
A5: Bajaj Finserv Ltd | B5: 160.9487 | C5: 141.4131 | D5: 139.34 | E5: 25.3549 | F5: 18.33 | G5: 10.4679 | H5: 14.9523 | I5: 10.6291 | J5: 8.2625 | K5: 59.1734 | L5: 38.5711 | M5: 18.4541
A6: Bajaj Finance Ltd | B6: 7.4587 | C6: 6.9385 | D6: 6.6465 | E6: 146.1947 | F6: 131.3917 | G6: 51.1279 | H6: 101.4777 | I6: 108.9304 | J6: 120.1941 | K6: 7.031 | L6: 7.7217 | M6: 5.4576
A7: Bharat Electronics Ltd | B7: 41.3736 | C7: 36.9633 | D7: 23.8509 | E7: 21.4061 | F7: 14.5128 | G7: 9.9266 | H7: 12.0543 | I7: 24.3654 | J7: 26.3215 | K7: 218.9408 | L7: 22.3672 | M7: 9.6262
A8: Bharti Airtel Ltd | B8: 29.844 | C8: 93.8923 | D8: 50.6081 | E8: 98.4876 | F8: -18.7089 | G8: -6.9484 | H8: 346.7708 | I8: 145.0545 | J8: 36.7981 | K8: 23.0703 | L8: 34.0744 | M8: 45.4274
A9: HCL Technologies Ltd | B9: 24.7966 | C9: 26.6132 | D9: 19.8031 | E9: 23.3745 | F9: 23.9457 | G9: 10.7178 | H9: 14.7866 | I9: 15.5793 | J9: 14.4712 | K9: 20.4612 | L9: 18.8069 | M9: 14.9227
A10: HDFC Bank Ltd | B10: 20.7102 | C10: 16.8729 | D10: 20.3123 | E10: 22.0052 | F10: 26.3971 | G10: 17.9546 | H10: 29.4533 | I10: 27.914 | J10: 25.2239 | K10: 21.9328 | L10: 24.2669 | M10: 21.1122
A11: Hindustan Unilever Ltd | B11: 49.8533 | C11: 51.8576 | D11: 59.4091 | E11: 54.2167 | F11: 71.4311 | G11: 73.7295 | H11: 61.0583 | I11: 55.4545 | J11: 43.9918 | K11: 45.5236 | L11: 43.2771 | M11: 33.0948
A12: ICICI Bank Ltd | B12: 18.6217 | C12: 17.3421 | D12: 17.9533 | E12: 20.1671 | F12: 21.3225 | G12: 21.9109 | H12: 60.3404 | I12: 23.1614 | J12: 17.4167 | K12: 13.494 | L12: 14.8937 | M12: 13.0209
A13: Infosys Ltd | B13: 24.3473 | C13: 23.6441 | D13: 23.9007 | E13: 36.3138 | F13: 29.9879 | G13: 16.4306 | H13: 20.9453 | I13: 15.9617 | J13: 16.2548 | K13: 20.6362 | L13: 20.4748 | M13: 17.5819
... A30: UltraTech Cement Ltd | B30: 56.0375 | C30: 40.0948 | D30: 43.3867 | E30: 25.9274 | F30: 35.5718 | G30: 16.3079 | H30: 47.5964 | I30: 48.775 | J30: 40.3351 | K30: 35.7364 | L30: 37.5915 | M30: 27.2082

Sheet Ratio_PS
B1: 2025 | C1: 2024 | D1: 2023 | E1: 2022 | F1: 2021 | G1: 2020 | H1: 2019 | I1: 2018 | J1: 2017 | K1: 2016 | L1: 2015 | M1: 2014
A2: Adani Ports and Special Economic Zone Ltd | B2: 8.22 | C2: 10.85 | D2: 6.55 | E2: 10.26 | F2: 11.38 | G2: 4.3 | H2: 7.17 | I2: 6.49 | J2: 8.34 | K2: 7.22 | L2: 10.37 | M2: 8.05
A3: Asian Paints Ltd | B3: 6.61 | C3: 7.69 | D3: 7.68 | E3: 10.16 | F3: 11.21 | G3: 7.91 | H3: 7.44 | I3: 6.39 | J3: 6.82 | K3: 5.84 | L3: 5.47 | M3: 4.12
A4: AXIS Bank Ltd | B4: 2.68 | C4: 2.87 | D4: 3.02 | E4: 3.39 | F4: 3.3 | G4: 1.68 | H4: 3.56 | I4: 2.8 | J4: 2.6 | K4: 2.56 | L4: 3.72 | M4: 2.23
A5: Bajaj Finserv Ltd | B5: 2.39 | C5: 2.37 | D5: 2.46 | E5: 3.97 | F5: 2.54 | G5: 1.34 | H5: 2.63 | I5: 2.51 | J5: 2.65 | K5: 2.87 | L5: 2.91 | M5: 2.09
A6: Bajaj Finance Ltd | B6: 7.97 | C6: 8.14 | D6: 8.2 | E6: 13.84 | F6: 11.62 | G6: 5.04 | H6: 9.44 | I6: 7.57 | J6: 6.44 | K6: 5.08 | L6: 3.81 | M6: 2.05
A7: Bharat Electronics Ltd | B7: 9.26 | C7: 7.27 | D7: 4.02 | E7: 3.34 | F7: 2.16 | G7: 1.4 | H7: 1.87 | I7: 3.33 | J7: 4.03 | K7: 3.98 | L7: 3.78 | M7: 1.4
A8: Bharti Airtel Ltd | B8: 5.8 | C8: 4.71 | D8: 3.05 | E8: 3.62 | F8: 2.82 | G8: 2.75 | H8: 1.65 | I8: 1.9 | J8: 1.46 | K8: 1.45 | L8: 1.64 | M8: 1.46
A9: HCL Technologies Ltd | B9: 3.69 | C9: 3.81 | D9: 2.91 | E9: 3.69 | F9: 3.54 | G9: 1.68 | H9: 2.44 | I9: 2.66 | J9: 2.62 | K9: 3.69 | L9: 3.53 | M9: 3.26
A10: HDFC Bank Ltd | B10: 4.66 | C10: 4.26 | D10: 5.56 | E10: 6.38 | F10: 6.81 | G10: 4.12 | H10: 6.37 | I10: 6.12 | J10: 5.33 | K10: 4.5 | L10: 5.29 | M10: 4.37
A11: Hindustan Unilever Ltd | B11: 8.41 | C11: 8.61 | D11: 9.93 | E11: 9.18 | F11: 12.15 | G11: 12.48 | H11: 9.38 | I11: 8.12 | J11: 5.93 | K11: 5.84 | L11: 5.91 | M11: 4.47
A12: ICICI Bank Ltd | B12: 5.15 | C12: 4.82 | D12: 5.06 | E12: 5.32 | F12: 4.51 | G12: 2.48 | H12: 3.57 | I12: 2.88 | J12: 2.65 | K12: 2.32 | L12: 3.33 | M12: 2.91
A13: Infosys Ltd | B13: 3.99 | C13: 4.04 | D13: 4.03 | E13: 6.58 | F13: 5.78 | G13: 2.99 | H13: 3.9 | I13: 3.5 | J13: 3.41 | K13: 4.46 | L13: 4.76 | M13: 3.74
... A30: UltraTech Cement Ltd | B30: 4.46 | C30: 3.97 | D30: 3.48 | E30: 3.62 | F30: 4.35 | G30: 2.21 | H30: 2.64 | I30: 3.5 | J30: 4.32 | K30: 3.52 | L30: 3.24 | M30: 2.77

Sheet Ratio_CR
B1: 2025 | C1: 2024 | D1: 2023 | E1: 2022 | F1: 2021 | G1: 2020 | H1: 2019 | I1: 2018 | J1: 2017 | K1: 2016 | L1: 2015 | M1: 2014
A2: Adani Ports and Special Economic Zone Ltd | B2: 0.9 | C2: 1.06 | D2: 1.35 | E2: 1.6 | F2: 1.78 | G2: 1.93 | H2: 1.41 | I2: 3.56 | J2: 1.82 | K2: 0.89 | L2: 1.25 | M2: 2.2
A3: Asian Paints Ltd | B3: 2.09 | C3: 2.06 | D3: 2.09 | E3: 2 | F3: 2.03 | G3: 1.73 | H3: 1.47 | I3: 1.55 | J3: 1.79 | K3: 1.82 | L3: 1.52 | M3: 1.48
A4: AXIS Bank Ltd | B4: 1.124 | C4: 1.113 | D4: 1.102 | E4: 1.105 | F4: 1.109 | G4: 1.097 | H4: 1.085 | I4: 1.094 | J4: 1.095 | K4: 1.104 | L4: 1.101 | M4: 1.103
A5: Bajaj Finserv Ltd | B5: 1.24 | C5: 2.1 | D5: 2.06 | E5: 2.04 | F5: 1.95 | G5: 1.92 | H5: 1.87 | I5: 2.46 | J5: 1.16 | K5: 1.36 | L5: 1.02 | M5: 0.87
A6: Bajaj Finance Ltd | B6: 1.26 | C6: 1.24 | D6: 1.23 | E6: 1.25 | F6: 1.26 | G6: 1.23 | H6: 1.18 | I6: 1.66 | J6: 1.55 | K6: 1.57 | L6: 1.48 | M6: 1.03
A7: Bharat Electronics Ltd | B7: 1.76 | C7: 1.55 | D7: 1.46 | E7: 1.39 | F7: 1.41 | G7: 1.46 | H7: 1.52 | I7: 1.45 | J7: 1.61 | K7: 1.87 | L7: 2.01 | M7: 1.86
A8: Bharti Airtel Ltd | B8: 0.37 | C8: 0.42 | D8: 0.47 | E8: 0.46 | F8: 0.49 | G8: 0.58 | H8: 0.35 | I8: 0.43 | J8: 0.29 | K8: 0.39 | L8: 0.33 | M8: 0.39
A9: HCL Technologies Ltd | B9: 2.22 | C9: 2.61 | D9: 2.5 | E9: 2.56 | F9: 2.48 | G9: 1.62 | H9: 2.42 | I9: 2.43 | J9: 2.33 | K9: 2.54 | L9: 2.32 | M9: 2.09
A10: HDFC Bank Ltd | B10: 1.04 | C10: 1.09 | D10: 0.92 | E10: 0.92 | F10: 0.9 | G10: 0.9 | H10: 0.96 | I10: 0.96 | J10: 0.91 | K10: 0.88 | L10: 0.89 | M10: 0.93
A11: Hindustan Unilever Ltd | B11: 1.33 | C11: 1.66 | D11: 1.41 | E11: 1.38 | F11: 1.28 | G11: 1.32 | H11: 1.37 | I11: 1.31 | J11: 1.32 | K11: 1.46 | L11: 1.08 | M11: 1.05
A12: ICICI Bank Ltd | B12: 1 | C12: 0.99 | D12: 1.01 | E12: 1.01 | F12: 0.98 | G12: 1.04 | H12: 1.08 | I12: 1.12 | J12: 1.16 | K12: 1.24 | L12: 1.26 | M12: 1.21
A13: Infosys Ltd | B13: 2.27 | C13: 2.31 | D13: 1.81 | E13: 2 | F13: 2.54 | G13: 2.62 | H13: 2.84 | I13: 3.55 | J13: 3.83 | K13: 3.91 | L13: 3.05 | M13: 3.58
... A30: UltraTech Cement Ltd | B30: 0.73 | C30: 0.86 | D30: 0.89 | E30: 0.87 | F30: 1.17 | G30: 0.89 | H30: 0.83 | I30: 1 | J30: 1.6 | K30: 0.91 | L30: 0.8 | M30: 1.45

Sheet Ratio_DE
B1: 2025 | C1: 2024 | D1: 2023 | E1: 2022 | F1: 2021 | G1: 2020 | H1: 2019 | I1: 2018 | J1: 2017 | K1: 2016 | L1: 2015 | M1: 2014
A2: Adani Ports and Special Economic Zone Ltd | B2: 0.73 | C2: 0.87 | D2: 1.09 | E2: 1.19 | F2: 1.13 | G2: 1.09 | H2: 1.07 | I2: 1.01 | J2: 1.2 | K2: 1.4 | L2: 1.41 | M2: 1.33
A3: Asian Paints Ltd | B3: 0.04 | C3: 0.06 | D3: 0.06 | E3: 0.06 | F3: 0.03 | G3: 0.03 | H3: 0.07 | I3: 0.06 | J3: 0.07 | K3: 0.05 | L3: 0.09 | M3: 0.06
A4: AXIS Bank Ltd | B4: 7.88 | C4: 8.69 | D4: 9.39 | E4: 9.12 | F4: 8.66 | G4: 8 | H4: 10.99 | I4: 9.72 | J4: 9.79 | K4: 8.88 | L4: 9.33 | M4: 9.06
A5: Bajaj Finserv Ltd | B5: 4.89 | C5: 4.77 | D5: 4.56 | E5: 3.99 | F5: 3.57 | G5: 4.04 | H5: 4.2 | I5: 3.21 | J5: 2.99 | K5: 2.65 | L5: 2.01 | M5: 1.66
A6: Bajaj Finance Ltd | B6: 3.74 | C6: 3.82 | D6: 3.99 | E6: 3.78 | F6: 3.57 | G6: 4.02 | H6: 5.16 | I6: 3.42 | J6: 4.38 | K6: 4.99 | L6: 4.71 | M6: 5.17
A7: Bharat Electronics Ltd | B7: 1.2 | C7: 1.13 | D7: 1.1 | E7: 0.93 | F7: 0.82 | G7: 1.41 | H7: 1.26 | I7: 0.63 | J7: 0.73 | K7: 0.56 | L7: 0.7 | M7: 0.78
A8: Bharti Airtel Ltd | B8: 1.13 | C8: 1.5 | D8: 1.82 | E8: 2 | F8: 2.2 | G8: 1.52 | H8: 1.69 | I8: 1.41 | J8: 1.52 | K8: 1.5 | L8: 1.76 | M8: 1.27
A9: HCL Technologies Ltd | B9: 0.03 | C9: 0.03 | D9: 0.03 | E9: 0.06 | F9: 0.06 | G9: 0.09 | H9: 0.09 | I9: 0.01 | J9: 0.01 | K9: 0.03 | L9: 0.02 | M9: 0.02
A10: HDFC Bank Ltd | B10: 6.27 | C10: 7.12 | D10: 7.8 | E10: 7.58 | F10: 7.58 | G10: 7.92 | H10: 7.43 | I10: 9.17 | J10: 8.02 | K10: 7.89 | L10: 8.61 | M10: 10.36
A11: Hindustan Unilever Ltd | B11: 0.56 | C11: 0.57 | D11: 0.54 | E11: 0.52 | F11: 0.49 | G11: 1.64 | H11: 1.38 | I11: 1.41 | J11: 1.57 | K11: 1.34 | L11: 1.94 | M11: 2.36
A12: ICICI Bank Ltd | B12: 8.87 | C12: 8.92 | D12: 7.67 | E12: 8.13 | F12: 8.31 | G12: 9.38 | H12: 9.13 | I12: 8.63 | J12: 8.2 | K12: 8.19 | L12: 8.35 | M12: 8.29
A13: Infosys Ltd | B13: 0.47 | C13: 0.49 | D13: 0.57 | E13: 0.56 | F13: 0.43 | G13: 0.42 | H13: 0.28 | I13: 0.23 | J13: 0.19 | K13: 0.2 | L13: 0.2 | M13: 0.26
... A30: UltraTech Cement Ltd | B30: 0.33 | C30: 0.17 | D30: 0.18 | E30: 0.2 | F30: 0.4 | G30: 0.55 | H30: 0.86 | I30: 0.71 | J30: 0.31 | K30: 0.34 | L30: 0.4 | M30: 0.41
