Workbook

Sheet Annual_return_and_ratios
A1: Annual Return | B1: 2025 | C1: 2024 | D1: 2023 | E1: 2022 | F1: 2021 | G1: 2020 | H1: 2019 | I1: 2018 | J1: 2017 | K1: 2016 | L1: 2015 | M1: 2014 | O1: Annual Return | P1: Diluted EPS | Q1: Current Ratio
A2: Adani Ports and Special Economic Zone Ltd | B2: -0.018388853 | C2: 0.064866104 | D2: -0.013411015 | E2: 0.004794169 | F2: 0.097112015 | G2: -0.02803944 | H2: 0.0081405251 | I2: 0.0034890724 | J2: 0.028748929 | K2: -0.013624531 | L2: 0.045516874 | M2: 0.027678695 | O2: =IFERROR(__xludf.DUMMYFUNCTION("Flatten(B2:M30)"),-0.01838885255621591) -> -0.018388853 | P2: =IFERROR(__xludf.DUMMYFUNCTION("Flatten(B35:M63)"),0.2657233426) -> 0.26572334 | Q2: =IFERROR(__xludf.DUMMYFUNCTION("Flatten(B233:M261)"),0.6883852691) -> 0.68838527
A3: Asian Paints Ltd | B3: -0.015508059 | C3: 0.0034231375 | D3: -0.0044897477 | E3: 0.017684069 | F3: 0.03472095 | G3: 0.009850388 | H3: 0.02510981 | I3: 0.0024750057 | J3: 0.018412948 | K3: 0.0057830479 | L3: 0.035916925 | M3: 0.014119278 | O3: =IFERROR(__xludf.DUMMYFUNCTION("""COMPUTED_VALUE"""),0.06486610376095205) -> 0.064866104 | P3: =IFERROR(__xludf.DUMMYFUNCTION("""COMPUTED_VALUE"""),0.1912645849) -> 0.19126458 | Q3: =IFERROR(__xludf.DUMMYFUNCTION("""COMPUTED_VALUE"""),0.7337110482) -> 0.73371105
A4: AXIS Bank Ltd | B4: 0.0031449812 | C4: 0.015642564 | D4: 0.016450513 | E4: 0.005847556 | F4: 0.054840008 | G4: -0.043748563 | H4: 0.037541142 | I4: 0.0035987805 | J4: 0.0072456263 | K4: -0.018288142 | L4: 0.050253859 | M4: 0.020824255 | O4: =IFERROR(__xludf.DUMMYFUNCTION("""COMPUTED_VALUE"""),-0.01341101462370109) -> -0.013411015 | P4: =IFERROR(__xludf.DUMMYFUNCTION("""COMPUTED_VALUE"""),0.1212841438) -> 0.12128414 | Q4: =IFERROR(__xludf.DUMMYFUNCTION("""COMPUTED_VALUE"""),0.8158640227) -> 0.81586402
A5: Bajaj Finserv Ltd | B5: 0.013268901 | C5: 0.021027313 | D5: -0.01579449 | E5: 0.049937612 | F5: 0.074710705 | G5: -0.013627338 | H5: 0.026467161 | I5: 0.021593213 | J5: 0.074197429 | K5: 0.016304197 | L5: 0.054265082 | M5: 0.0057696166 | O5: =IFERROR(__xludf.DUMMYFUNCTION("""COMPUTED_VALUE"""),0.004794169009003115) -> 0.004794169 | P5: =IFERROR(__xludf.DUMMYFUNCTION("""COMPUTED_VALUE"""),0.1094678627) -> 0.10946786 | Q5: =IFERROR(__xludf.DUMMYFUNCTION("""COMPUTED_VALUE"""),0.8866855524) -> 0.88668555
A6: Bajaj Finance Ltd | B6: 0.016012116 | C6: 0.021363854 | D6: -0.013425761 | E6: 0.030882716 | F6: 0.085722308 | G6: -0.0044409445 | H6: 0.047675208 | I6: 0.033765903 | J6: 0.044848665 | K6: 0.043550629 | L6: 0.061872866 | M6: 0.043106995 | O6: =IFERROR(__xludf.DUMMYFUNCTION("""COMPUTED_VALUE"""),0.09711201496689581) -> 0.097112015 | P6: =IFERROR(__xludf.DUMMYFUNCTION("""COMPUTED_VALUE"""),0.1212841438) -> 0.12128414 | Q6: =IFERROR(__xludf.DUMMYFUNCTION("""COMPUTED_VALUE"""),0.9376770538) -> 0.93767705
A7: Bharat Electronics Ltd | B7: 0.027854067 | C7: 0.060032519 | D7: 0.028760919 | E7: 0.043856665 | F7: 0.051465264 | G7: -0.0065329825 | H7: -0.03212618 | I7: -0.0033593882 | J7: 0.021688596 | K7: 0.013684397 | L7: 0.10420563 | M7: 0.0061107392 | O7: =IFERROR(__xludf.DUMMYFUNCTION("""COMPUTED_VALUE"""),-0.02803943999678881) -> -0.02803944 | P7: =IFERROR(__xludf.DUMMYFUNCTION("""COMPUTED_VALUE"""),0.0876697916) -> 0.087669792 | Q7: =IFERROR(__xludf.DUMMYFUNCTION("""COMPUTED_VALUE"""),0.9801699717) -> 0.98016997
A8: Bharti Airtel Ltd | B8: 0.026702653 | C8: 0.046051621 | D8: -0.00065184027 | E8: 0.032532989 | F8: 0.012751318 | G8: 0.028987966 | H8: -0.015063661 | I8: 0.012324354 | J8: 0.0028883304 | K8: -0.0028876544 | L8: 0.019992274 | M8: 0.013501463 | O8: =IFERROR(__xludf.DUMMYFUNCTION("""COMPUTED_VALUE"""),0.008140525116234972) -> 0.0081405251 | P8: =IFERROR(__xludf.DUMMYFUNCTION("""COMPUTED_VALUE"""),0.09263370877) -> 0.092633709 | Q8: =IFERROR(__xludf.DUMMYFUNCTION("""COMPUTED_VALUE"""),0.8328611898) -> 0.83286119
A9: HCL Technologies Ltd | B9: 0.0059402318 | C9: 0.033035712 | D9: 0.00050588316 | E9: 0.017730025 | F9: 0.075759107 | G9: -0.016076783 | H9: 0.010918662 | I9: 0.010621993 | J9: 0.0062164689 | K9: 0.0049023095 | L9: 0.028270595 | M9: 0.051797648 | O9: =IFERROR(__xludf.DUMMYFUNCTION("""COMPUTED_VALUE"""),0.003489072436931193) -> 0.0034890724 | P9: =IFERROR(__xludf.DUMMYFUNCTION("""COMPUTED_VALUE"""),0.08437849868) -> 0.084378499 | Q9: =IFERROR(__xludf.DUMMYFUNCTION("""COMPUTED_VALUE"""),0.5580736544) -> 0.55807365
A10: HDFC Bank Ltd | B10: 0.016101132 | C10: -0.0058276044 | D10: 0.010052314 | E10: 0.0018512656 | F10: 0.046435038 | G10: -0.019558332 | H10: 0.017925707 | I10: 0.02310927 | J10: 0.025591428 | K10: 0.0051465079 | L10: 0.02696064 | M10: 0.016349853 | O10: =IFERROR(__xludf.DUMMYFUNCTION("""COMPUTED_VALUE"""),0.0287489292939952) -> 0.028748929 | P10: =IFERROR(__xludf.DUMMYFUNCTION("""COMPUTED_VALUE"""),0.09058339516) -> 0.090583395 | Q10: =IFERROR(__xludf.DUMMYFUNCTION("""COMPUTED_VALUE"""),0.9490084986) -> 0.9490085
A11: Hindustan Unilever Ltd | B11: 0.0021438945 | C11: -0.010169015 | D11: 0.019518438 | E11: -0.013631594 | F11: 0.0064105839 | G11: 0.025133487 | H11: 0.021783993 | I11: 0.033005659 | J11: 0.0033624168 | K11: 0.0020781671 | L11: 0.033479572 | M11: 0.027625274 | O11: =IFERROR(__xludf.DUMMYFUNCTION("""COMPUTED_VALUE"""),-0.01362453114351661) -> -0.013624531 | P11: =IFERROR(__xludf.DUMMYFUNCTION("""COMPUTED_VALUE"""),0.06414514062) -> 0.064145141 | Q11: =IFERROR(__xludf.DUMMYFUNCTION("""COMPUTED_VALUE"""),0.6855524079) -> 0.68555241
A12: ICICI Bank Ltd | B12: 0.015304241 | C12: 0.017928119 | D12: 0.019352031 | E12: 0.022089283 | F12: 0.04656278 | G12: -0.0081086488 | H12: 0.031910416 | I12: 0.0093822508 | J12: 0.021300104 | K12: -0.020895898 | L12: 0.020279245 | M12: 0.02113549 | O12: =IFERROR(__xludf.DUMMYFUNCTION("""COMPUTED_VALUE"""),0.04551687424786283) -> 0.045516874 | P12: =IFERROR(__xludf.DUMMYFUNCTION("""COMPUTED_VALUE"""),0.04898361098) -> 0.048983611 | Q12: =IFERROR(__xludf.DUMMYFUNCTION("""COMPUTED_VALUE"""),0.7875354108) -> 0.78753541
A13: Infosys Ltd | B13: 0.0071915879 | C13: 0.0075726879 | D13: -0.019672524 | E13: 0.02912291 | F13: 0.071033761 | G13: -0.0089107377 | H13: 0.023217617 | I13: 0.010325168 | J13: -0.011950934 | K13: 0.010477373 | L13: 0.02741054 | M13: 0.015127996 | O13: =IFERROR(__xludf.DUMMYFUNCTION("""COMPUTED_VALUE"""),0.02767869517985113) -> 0.027678695 | P13: =IFERROR(__xludf.DUMMYFUNCTION("""COMPUTED_VALUE"""),0.03425372631) -> 0.034253726 | Q13: =IFERROR(__xludf.DUMMYFUNCTION("""COMPUTED_VALUE"""),0.9433427762) -> 0.94334278
A14: ITC Ltd | B14: 0.00080016843 | C14: 0.01218268 | D14: 0.040903903 | E14: 0.016986342 | F14: 0.023694266 | G14: -0.03640857 | H14: 0.013125397 | I14: -0.012879023 | J14: 0.023501273 | K14: 0.0028203458 | L14: 0.0028571705 | M14: 0.013988984 | O14: =IFERROR(__xludf.DUMMYFUNCTION("""COMPUTED_VALUE"""),-0.01550805906788396) -> -0.015508059 | P14: =IFERROR(__xludf.DUMMYFUNCTION("""COMPUTED_VALUE"""),0.1950414784) -> 0.19504148 | Q14: =IFERROR(__xludf.DUMMYFUNCTION("""COMPUTED_VALUE"""),0.9745042493) -> 0.97450425
A15: Kotak Mahindra Bank Ltd | B15: 0.017714023 | C15: 0.0065065588 | D15: 0.0038693461 | E15: -0.00041895223 | F15: 0.030733862 | G15: 0.0035122161 | H15: 0.024913189 | I15: 0.015169472 | J15: 0.019291035 | K15: 0.0080234666 | L15: 0.041615059 | M15: 0.019368773 | O15: =IFERROR(__xludf.DUMMYFUNCTION("""COMPUTED_VALUE"""),0.003423137479009528) -> 0.0034231375 | P15: =IFERROR(__xludf.DUMMYFUNCTION("""COMPUTED_VALUE"""),0.295884535) -> 0.29588454 | Q15: =IFERROR(__xludf.DUMMYFUNCTION("""COMPUTED_VALUE"""),0.9830028329) -> 0.98300283
A16: Larsen & Toubro Ltd | B16: -0.0074579983 | C16: 0.045849857 | D16: 0.020977232 | E16: 0.020735118 | F16: 0.048978805 | G16: -0.032551731 | H16: 0.0012700295 | I16: 0.018037568 | J16: 0.024065207 | K16: -0.025941129 | L16: 0.025079873 | M16: 0.036673697 | O16: =IFERROR(__xludf.DUMMYFUNCTION("""COMPUTED_VALUE"""),-0.004489747690076594) -> -0.0044897477 | P16: =IFERROR(__xludf.DUMMYFUNCTION("""COMPUTED_VALUE"""),0.2196991974) -> 0.2196992 | Q16: =IFERROR(__xludf.DUMMYFUNCTION("""COMPUTED_VALUE"""),0.9745042493) -> 0.97450425
A17: Mahindra & Mahindra Ltd | B17: 0.024294356 | C17: 0.041173611 | D17: 0.032385582 | E17: 0.0034884913 | F17: 0.093507229 | G17: -0.05388821 | H17: -0.01230839 | I17: 0.0092316108 | J17: 0.0056745011 | K17: 0.0049285533 | L17: 0.020900993 | M17: 0.017918085 | O17: =IFERROR(__xludf.DUMMYFUNCTION("""COMPUTED_VALUE"""),0.01768406932126746) -> 0.017684069 | P17: =IFERROR(__xludf.DUMMYFUNCTION("""COMPUTED_VALUE"""),0.1591070345) -> 0.15910703 | Q17: =IFERROR(__xludf.DUMMYFUNCTION("""COMPUTED_VALUE"""),1.0) -> 1
A18: Maruti Suzuki India Ltd | B18: -0.0085739182 | C18: 0.035676248 | D18: 0.0078403336 | E18: 0.010815818 | F18: 0.039310232 | G18: -0.024544869 | H18: -0.024855082 | I18: 0.02802177 | J18: 0.038272362 | K18: 0.0018332969 | L18: 0.056533506 | M18: 0.047620216 | O18: =IFERROR(__xludf.DUMMYFUNCTION("""COMPUTED_VALUE"""),0.03472094963678952) -> 0.03472095 | P18: =IFERROR(__xludf.DUMMYFUNCTION("""COMPUTED_VALUE"""),0.1652579753) -> 0.16525798 | Q18: =IFERROR(__xludf.DUMMYFUNCTION("""COMPUTED_VALUE"""),0.9915014164) -> 0.99150142
A19: NTPC Ltd | B19: -0.0002763521 | C19: 0.059375032 | D19: 0.025799576 | E19: 0.024615434 | F19: 0.029208582 | G19: -0.03518133 | H19: 0.0013279555 | I19: 0.0044575562 | J19: 0.024293236 | K19: -0.0060716406 | L19: 0.02320403 | M19: -0.0077007392 | O19: =IFERROR(__xludf.DUMMYFUNCTION("""COMPUTED_VALUE"""),0.009850388008809675) -> 0.009850388 | P19: =IFERROR(__xludf.DUMMYFUNCTION("""COMPUTED_VALUE"""),0.1408160788) -> 0.14081608 | Q19: =IFERROR(__xludf.DUMMYFUNCTION("""COMPUTED_VALUE"""),0.9235127479) -> 0.92351275
A20: Power Grid Corporation of India Ltd | B20: 0.00083146406 | C20: 0.046396075 | D20: 0.0076339248 | E20: 0.030461605 | F20: 0.029017078 | G20: -0.014306376 | H20: 0.0076670342 | I20: -0.00046367097 | J20: 0.0300338 | K20: -0.0025886874 | L20: 0.030680866 | M20: 0.0083611295 | O20: =IFERROR(__xludf.DUMMYFUNCTION("""COMPUTED_VALUE"""),0.0251098098275308) -> 0.02510981 | P20: =IFERROR(__xludf.DUMMYFUNCTION("""COMPUTED_VALUE"""),0.1099534633) -> 0.10995346 | Q20: =IFERROR(__xludf.DUMMYFUNCTION("""COMPUTED_VALUE"""),0.8498583569) -> 0.84985836
A21: Reliance Industries Ltd | B21: -0.015457557 | C21: 0.026691237 | D21: -0.0098398948 | E21: 0.023888633 | F21: 0.054133944 | G21: -0.015057342 | H21: 0.037318771 | I21: 0.02311088 | J21: 0.021421743 | K21: 0.023274431 | L21: -0.0092202545 | M21: 0.018471682 | O21: =IFERROR(__xludf.DUMMYFUNCTION("""COMPUTED_VALUE"""),0.002475005739429222) -> 0.0024750057 | P21: =IFERROR(__xludf.DUMMYFUNCTION("""COMPUTED_VALUE"""),0.1033708775) -> 0.10337088 | Q21: =IFERROR(__xludf.DUMMYFUNCTION("""COMPUTED_VALUE"""),0.8725212465) -> 0.87252125
A22: State Bank of India | B22: -9.1539287e-06 | C22: 0.0327997 | D22: 0.0088733531 | E22: 0.028159527 | F22: 0.059749205 | G22: -0.027804186 | H22: 0.020200127 | I22: -0.011748359 | J22: 0.034051401 | K22: -0.025147216 | L22: 0.029377404 | M22: -0.00056298714 | O22: =IFERROR(__xludf.DUMMYFUNCTION("""COMPUTED_VALUE"""),0.01841294789589839) -> 0.018412948 | P22: =IFERROR(__xludf.DUMMYFUNCTION("""COMPUTED_VALUE"""),0.09775949282) -> 0.097759493 | Q22: =IFERROR(__xludf.DUMMYFUNCTION("""COMPUTED_VALUE"""),0.940509915) -> 0.94050992
A23: Sun Pharmaceutical Industries Ltd | B23: 0.0045864804 | C23: 0.043070164 | D23: 0.0072399436 | E23: 0.035430654 | F23: 0.043769361 | G23: -0.020543748 | H23: 0.0044766526 | I23: -0.024611496 | J23: -0.017114299 | K23: -0.010636672 | L23: 0.046259989 | M23: 0.032498627 | O23: =IFERROR(__xludf.DUMMYFUNCTION("""COMPUTED_VALUE"""),0.005783047936699363) -> 0.0057830479 | P23: =IFERROR(__xludf.DUMMYFUNCTION("""COMPUTED_VALUE"""),0.08680650165) -> 0.086806502 | Q23: =IFERROR(__xludf.DUMMYFUNCTION("""COMPUTED_VALUE"""),0.9490084986) -> 0.9490085
A24: Tata Motors Ltd | B24: 0.079588178 | C24: 0.30103891 | D24: 0.11795617 | E24: 0.17929265 | F24: 0.54952967 | G24: 0.043888312 | H24: 0.060301175 | I24: 0.082742311 | J24: 0.1490187 | K24: 0.082698866 | L24: 0.17197631 | M24: 0.18496169 | O24: =IFERROR(__xludf.DUMMYFUNCTION("""COMPUTED_VALUE"""),0.03591692511264611) -> 0.035916925 | P24: =IFERROR(__xludf.DUMMYFUNCTION("""COMPUTED_VALUE"""),0.0671126998) -> 0.0671127 | Q24: =IFERROR(__xludf.DUMMYFUNCTION("""COMPUTED_VALUE"""),0.8640226629) -> 0.86402266
A25: Tata Steel Ltd | B25: -0.0034763223 | C25: 0.033861143 | D25: -0.010399398 | E25: 0.044060292 | F25: 0.10341164 | G25: -0.040818871 | H25: -0.01175668 | I25: 0.019238304 | J25: 0.035967264 | K25: 0.0098082016 | L25: -0.013443551 | M25: 0.029121528 | O25: =IFERROR(__xludf.DUMMYFUNCTION("""COMPUTED_VALUE"""),0.01411927848446944) -> 0.014119278 | P25: =IFERROR(__xludf.DUMMYFUNCTION("""COMPUTED_VALUE"""),0.05723882107) -> 0.057238821 | Q25: =IFERROR(__xludf.DUMMYFUNCTION("""COMPUTED_VALUE"""),0.8526912181) -> 0.85269122
A26: Tata Consultancy Services Ltd | B26: -0.0022352864 | C26: 0.016157167 | D26: -0.010560826 | E26: 0.013763541 | F26: 0.048628352 | G26: -0.0068496008 | H26: 0.030186658 | I26: 0.017171977 | J26: -0.0017700173 | K26: 9.5428579e-05 | L26: 0.016667754 | M26: 0.033187095 | O26: =IFERROR(__xludf.DUMMYFUNCTION("""COMPUTED_VALUE"""),0.003144981180246767) -> 0.0031449812 | P26: =IFERROR(__xludf.DUMMYFUNCTION("""COMPUTED_VALUE"""),0.4752330208) -> 0.47523302 | Q26: =IFERROR(__xludf.DUMMYFUNCTION("""COMPUTED_VALUE"""),0.7518413598) -> 0.75184136
A27: Tech Mahindra Ltd | B27: 0.012174951 | C27: 0.012972896 | D27: -0.018545439 | E27: 0.040224667 | F27: 0.053068331 | G27: -0.02242105 | H27: 0.018453096 | I27: 0.02798524 | J27: 0.0033047456 | K27: -0.019150687 | L27: 0.032876523 | M27: 0.047723765 | O27: =IFERROR(__xludf.DUMMYFUNCTION("""COMPUTED_VALUE"""),0.0156425637222698) -> 0.015642564 | P27: =IFERROR(__xludf.DUMMYFUNCTION("""COMPUTED_VALUE"""),0.4473379645) -> 0.44733796 | Q27: =IFERROR(__xludf.DUMMYFUNCTION("""COMPUTED_VALUE"""),0.7487252125) -> 0.74872521
A28: Titan Company Ltd | B28: -0.018857025 | C28: 0.032481438 | D28: 0.0029580187 | E28: 0.039459912 | F28: 0.045578973 | G28: -0.0083747091 | H28: 0.014850575 | I28: 0.061094544 | J28: 0.025111101 | K28: -0.00054904764 | L28: 0.032579019 | M28: 0.012014397 | O28: =IFERROR(__xludf.DUMMYFUNCTION("""COMPUTED_VALUE"""),0.01645051331551754) -> 0.016450513 | P28: =IFERROR(__xludf.DUMMYFUNCTION("""COMPUTED_VALUE"""),0.1777217239) -> 0.17772172 | Q28: =IFERROR(__xludf.DUMMYFUNCTION("""COMPUTED_VALUE"""),0.7456090652) -> 0.74560907
A29: Trent Ltd | B29: 0.025242339 | C29: 0.092310144 | D29: 0.0080962239 | E29: 0.045613628 | F29: 0.042659575 | G29: 0.033918567 | H29: 0.005211067 | I29: 0.014549981 | J29: 0.040263331 | K29: 0.0089241564 | L29: 0.035042438 | M29: 0.0057484694 | O29: =IFERROR(__xludf.DUMMYFUNCTION("""COMPUTED_VALUE"""),0.005847555985461925) -> 0.005847556 | P29: =IFERROR(__xludf.DUMMYFUNCTION("""COMPUTED_VALUE"""),0.2363714845) -> 0.23637148 | Q29: =IFERROR(__xludf.DUMMYFUNCTION("""COMPUTED_VALUE"""),0.7464589235) -> 0.74645892
A30: UltraTech Cement Ltd | B30: 0.011267776 | C30: 0.019115597 | D30: 0.014258521 | E30: -0.0027189614 | F30: 0.062923229 | G30: -0.010341532 | H30: -0.0021300429 | I30: -0.0032286041 | J30: 0.017915268 | K30: 0.011674742 | L30: 0.021949111 | M30: 0.017814461 | O30: =IFERROR(__xludf.DUMMYFUNCTION("""COMPUTED_VALUE"""),0.05484000762334306) -> 0.054840008 | P30: =IFERROR(__xludf.DUMMYFUNCTION("""COMPUTED_VALUE"""),0.1191798746) -> 0.11917987 | Q30: =IFERROR(__xludf.DUMMYFUNCTION("""COMPUTED_VALUE"""),0.747592068) -> 0.74759207
O31: =IFERROR(__xludf.DUMMYFUNCTION("""COMPUTED_VALUE"""),-0.04374856333401774) -> -0.043748563 | P31: =IFERROR(__xludf.DUMMYFUNCTION("""COMPUTED_VALUE"""),0.02535104876) -> 0.025351049 | Q31: =IFERROR(__xludf.DUMMYFUNCTION("""COMPUTED_VALUE"""),0.7441926346) -> 0.74419263
O32: =IFERROR(__xludf.DUMMYFUNCTION("""COMPUTED_VALUE"""),0.0375411415132909) -> 0.037541142 | P32: =IFERROR(__xludf.DUMMYFUNCTION("""COMPUTED_VALUE"""),0.09382073245) -> 0.093820732 | Q32: =IFERROR(__xludf.DUMMYFUNCTION("""COMPUTED_VALUE"""),0.7407932011) -> 0.7407932
O33: =IFERROR(__xludf.DUMMYFUNCTION("""COMPUTED_VALUE"""),0.003598780509103944) -> 0.0035987805 | P33: =IFERROR(__xludf.DUMMYFUNCTION("""COMPUTED_VALUE"""),0.0) -> 0 | Q33: =IFERROR(__xludf.DUMMYFUNCTION("""COMPUTED_VALUE"""),0.7433427762) -> 0.74334278
A34: Diluted EPS | B34: 2025 | C34: 2024 | D34: 2023 | E34: 2022 | F34: 2021 | G34: 2020 | H34: 2019 | I34: 2018 | J34: 2017 | K34: 2016 | L34: 2015 | M34: 2014 | O34: =IFERROR(__xludf.DUMMYFUNCTION("""COMPUTED_VALUE"""),0.007245626328476344) -> 0.0072456263 | P34: =IFERROR(__xludf.DUMMYFUNCTION("""COMPUTED_VALUE"""),0.07758009038) -> 0.07758009 | Q34: =IFERROR(__xludf.DUMMYFUNCTION("""COMPUTED_VALUE"""),0.7436260623) -> 0.74362606
A35: Adani Ports and Special Economic Zone Ltd | B35: 0.26572334 | C35: 0.19126458 | D35: 0.12128414 | E35: 0.10946786 | F35: 0.12128414 | G35: 0.087669792 | H35: 0.092633709 | I35: 0.084378499 | J35: 0.090583395 | K35: 0.064145141 | L35: 0.048983611 | M35: 0.034253726 | O35: =IFERROR(__xludf.DUMMYFUNCTION("""COMPUTED_VALUE"""),-0.01828814174192833) -> -0.018288142 | P35: =IFERROR(__xludf.DUMMYFUNCTION("""COMPUTED_VALUE"""),0.177128212) -> 0.17712821 | Q35: =IFERROR(__xludf.DUMMYFUNCTION("""COMPUTED_VALUE"""),0.7461756374) -> 0.74617564
A36: Asian Paints Ltd | B36: 0.19504148 | C36: 0.29588454 | D36: 0.2196992 | E36: 0.15910703 | F36: 0.16525798 | G36: 0.14081608 | H36: 0.10995346 | I36: 0.10337088 | J36: 0.097759493 | K36: 0.086806502 | L36: 0.0671127 | M36: 0.057238821 | O36: =IFERROR(__xludf.DUMMYFUNCTION("""COMPUTED_VALUE"""),0.05025385912291375) -> 0.050253859 | P36: =IFERROR(__xludf.DUMMYFUNCTION("""COMPUTED_VALUE"""),0.1571646321) -> 0.15716463 | Q36: =IFERROR(__xludf.DUMMYFUNCTION("""COMPUTED_VALUE"""),0.745325779) -> 0.74532578
A37: AXIS Bank Ltd | B37: 0.47523302 | C37: 0.44733796 | D37: 0.17772172 | E37: 0.23637148 | F37: 0.11917987 | G37: 0.025351049 | H37: 0.093820732 | I37: 0 | J37: 0.07758009 | K37: 0.17712821 | L37: 0.15716463 | M37: 0.71274567 | O37: =IFERROR(__xludf.DUMMYFUNCTION("""COMPUTED_VALUE"""),0.02082425450500124) -> 0.020824255 | P37: =IFERROR(__xludf.DUMMYFUNCTION("""COMPUTED_VALUE"""),0.7127456667) -> 0.71274567 | Q37: =IFERROR(__xludf.DUMMYFUNCTION("""COMPUTED_VALUE"""),0.7458923513) -> 0.74589235
A38: Bajaj Finserv Ltd | B38: 0.040998179 | C38: 0.02804883 | D38: 0.013480812 | E38: 0.13218318 | F38: 0.049091522 | G38: 0.21473528 | H38: 0.092795576 | I38: 0.036681729 | J38: 0.0124017 | K38: 0.044235516 | L38: 0.031286167 | M38: 0.016718149 | O38: =IFERROR(__xludf.DUMMYFUNCTION("""COMPUTED_VALUE"""),0.01326890111153658) -> 0.013268901 | P38: =IFERROR(__xludf.DUMMYFUNCTION("""COMPUTED_VALUE"""),0.040998179) -> 0.040998179 | Q38: =IFERROR(__xludf.DUMMYFUNCTION("""COMPUTED_VALUE"""),0.7847025496) -> 0.78470255
A39: Bajaj Finance Ltd | B39: 1 | C39: 1 | D39: 1 | E39: 0.61341337 | F39: 0.38253726 | G39: 0.46924395 | H39: 0.35960612 | I39: 0.24252243 | J39: 0.1703298 | K39: 1 | L39: 0.94745262 | M39: 0.76373373 | O39: =IFERROR(__xludf.DUMMYFUNCTION("""COMPUTED_VALUE"""),0.02102731258654204) -> 0.021027313 | P39: =IFERROR(__xludf.DUMMYFUNCTION("""COMPUTED_VALUE"""),0.02804882984) -> 0.02804883 | Q39: =IFERROR(__xludf.DUMMYFUNCTION("""COMPUTED_VALUE"""),0.9716713881) -> 0.97167139
A40: Bharat Electronics Ltd | B40: 0.027940919 | C40: 0.01806704 | D40: 0.010729075 | E40: 0.041807513 | F40: 0.035170972 | G40: 0.029073987 | H40: 0.030422877 | I40: 0.020117353 | J40: 0.020710865 | K40: 0.018714507 | L40: 0.7961071 | M40: 0.63024752 | O40: =IFERROR(__xludf.DUMMYFUNCTION("""COMPUTED_VALUE"""),-0.0157944904480797) -> -0.01579449 | P40: =IFERROR(__xludf.DUMMYFUNCTION("""COMPUTED_VALUE"""),0.01348081203) -> 0.013480812 | Q40: =IFERROR(__xludf.DUMMYFUNCTION("""COMPUTED_VALUE"""),0.9830028329) -> 0.98300283
A41: Bharti Airtel Ltd | B41: 0.29102853 | C41: 0.057724422 | D41: 0.067274567 | E41: 0.029829365 | F41: 0 | G41: 0 | H41: 0 | I41: 0.0034990221 | J41: 0.039973022 | K41: 0.070673771 | L41: 0.051033925 | M41: 0.026484117 | O41: =IFERROR(__xludf.DUMMYFUNCTION("""COMPUTED_VALUE"""),0.04993761237661055) -> 0.049937612 | P41: =IFERROR(__xludf.DUMMYFUNCTION("""COMPUTED_VALUE"""),0.1321831793) -> 0.13218318 | Q41: =IFERROR(__xludf.DUMMYFUNCTION("""COMPUTED_VALUE"""),0.9886685552) -> 0.98866856
A42: HCL Technologies Ltd | B42: 0.3344628 | C42: 0.30084845 | D42: 0.28428408 | E42: 0.25719835 | F42: 0.21025696 | G42: 0.20853038 | H42: 0.38550482 | I42: 0.32421124 | J42: 0.31385176 | K42: 0.20281109 | L42: 0.26809739 | M42: 0.48467525 | O42: =IFERROR(__xludf.DUMMYFUNCTION("""COMPUTED_VALUE"""),0.07471070482948455) -> 0.074710705 | P42: =IFERROR(__xludf.DUMMYFUNCTION("""COMPUTED_VALUE"""),0.04909152222) -> 0.049091522 | Q42: =IFERROR(__xludf.DUMMYFUNCTION("""COMPUTED_VALUE"""),0.9858356941) -> 0.98583569
A43: HDFC Bank Ltd | B43: 0.48715721 | C43: 0.47431578 | D43: 0.43255412 | E43: 0.35723208 | F43: 0.29949956 | G43: 0.25552573 | H43: 0.43384906 | I43: 0.3704512 | J43: 0.30786268 | K43: 0.25973427 | L43: 0.22390774 | M43: 0.18457409 | O43: =IFERROR(__xludf.DUMMYFUNCTION("""COMPUTED_VALUE"""),-0.01362733828095101) -> -0.013627338 | P43: =IFERROR(__xludf.DUMMYFUNCTION("""COMPUTED_VALUE"""),0.2147352802) -> 0.21473528 | Q43: =IFERROR(__xludf.DUMMYFUNCTION("""COMPUTED_VALUE"""),0.9773371105) -> 0.97733711
A44: Hindustan Unilever Ltd | B44: 0.2331881 | C44: 0.22466311 | D44: 0.22104809 | E44: 0.19255952 | F44: 0.17227221 | G44: 0.1568409 | H44: 0.13952114 | I44: 0.11858636 | J44: 0.1001875 | K44: 0.091662508 | L44: 0.097435759 | M44: 0.087022324 | O44: =IFERROR(__xludf.DUMMYFUNCTION("""COMPUTED_VALUE"""),0.02646716128931413) -> 0.026467161 | P44: =IFERROR(__xludf.DUMMYFUNCTION("""COMPUTED_VALUE"""),0.09279557564) -> 0.092795576 | Q44: =IFERROR(__xludf.DUMMYFUNCTION("""COMPUTED_VALUE"""),0.9631728045) -> 0.9631728
A45: ICICI Bank Ltd | B45: 0.37250152 | C45: 0.32297026 | D45: 0.24678492 | E45: 0.17987995 | F45: 0.13342416 | G45: 0.067166655 | H45: 0.023894247 | I45: 0.05281446 | J45: 0.074126931 | K45: 0.082597963 | L45: 0.10288528 | M45: 0.50474675 | O45: =IFERROR(__xludf.DUMMYFUNCTION("""COMPUTED_VALUE"""),0.0215932128507568) -> 0.021593213 | P45: =IFERROR(__xludf.DUMMYFUNCTION("""COMPUTED_VALUE"""),0.03668172928) -> 0.036681729 | Q45: =IFERROR(__xludf.DUMMYFUNCTION("""COMPUTED_VALUE"""),0.8696883853) -> 0.86968839
A46: Infosys Ltd | B46: 0.33581169 | C46: 0.33068591 | D46: 0.29912187 | E46: 0.27144264 | F46: 0.23426722 | G46: 0.19860255 | H46: 0.17955621 | I46: 0.37174614 | J46: 0.32734066 | K46: 0.3071073 | L46: 0.57278478 | M46: 0.99487961 | O46: =IFERROR(__xludf.DUMMYFUNCTION("""COMPUTED_VALUE"""),0.07419742882408908) -> 0.074197429 | P46: =IFERROR(__xludf.DUMMYFUNCTION("""COMPUTED_VALUE"""),0.0124016996) -> 0.0124017 | Q46: =IFERROR(__xludf.DUMMYFUNCTION("""COMPUTED_VALUE"""),0.7620396601) -> 0.76203966
A47: ITC Ltd | B47: 0.13838808 | C47: 0.077040534 | D47: 0.072076617 | E47: 0.05540433 | F47: 0.046393741 | G47: 0.055835975 | H47: 0.043911783 | I47: 0.038300398 | J47: 0.034253726 | K47: 0.03026101 | L47: 0.053407972 | M47: 0.04849801 | O47: =IFERROR(__xludf.DUMMYFUNCTION("""COMPUTED_VALUE"""),0.01630419717550051) -> 0.016304197 | P47: =IFERROR(__xludf.DUMMYFUNCTION("""COMPUTED_VALUE"""),0.04423551629) -> 0.044235516 | Q47: =IFERROR(__xludf.DUMMYFUNCTION("""COMPUTED_VALUE"""),0.8186968839) -> 0.81869688
A48: Kotak Mahindra Bank Ltd | B48: 0.58913334 | C48: 0.48208538 | D48: 0.39300465 | E48: 0.31633372 | F48: 0.26108316 | G48: 0.22973494 | H48: 0.19228974 | I48: 0.16488029 | J48: 0.13358603 | K48: 0.090475484 | L48: 0.20124637 | M48: 0.16207459 | O48: =IFERROR(__xludf.DUMMYFUNCTION("""COMPUTED_VALUE"""),0.05426508242025393) -> 0.054265082 | P48: =IFERROR(__xludf.DUMMYFUNCTION("""COMPUTED_VALUE"""),0.03128616713) -> 0.031286167 | Q48: =IFERROR(__xludf.DUMMYFUNCTION("""COMPUTED_VALUE"""),0.7223796034) -> 0.7223796
A49: Larsen & Toubro Ltd | B49: 0.57828826 | C49: 0.4951966 | D49: 0.39036083 | E49: 0.32129763 | F49: 0.4333095 | G49: 0.35528967 | H49: 0.33073987 | I49: 0.27187428 | J49: 0.22094018 | K49: 0.23291832 | L49: 0.26372698 | M49: 0.27273757 | O49: =IFERROR(__xludf.DUMMYFUNCTION("""COMPUTED_VALUE"""),0.005769616615423394) -> 0.0057696166 | P49: =IFERROR(__xludf.DUMMYFUNCTION("""COMPUTED_VALUE"""),0.01671814932) -> 0.016718149 | Q49: =IFERROR(__xludf.DUMMYFUNCTION("""COMPUTED_VALUE"""),0.6798866856) -> 0.67988669
A50: Mahindra & Mahindra Ltd | B50: 0.60947461 | C50: 0.53199433 | D50: 0.48483712 | E50: 0.30608215 | F50: 0.075799555 | G50: 0 | H50: 0.2514251 | I50: 0.36019964 | J50: 0.17200243 | K50: 0.29345653 | L50: 0.26216227 | M50: 0.3978067 | O50: =IFERROR(__xludf.DUMMYFUNCTION("""COMPUTED_VALUE"""),0.01601211644650248) -> 0.016012116 | P50: =IFERROR(__xludf.DUMMYFUNCTION("""COMPUTED_VALUE"""),1.0) -> 1 | Q50: =IFERROR(__xludf.DUMMYFUNCTION("""COMPUTED_VALUE"""),0.790368272) -> 0.79036827
A51: Maruti Suzuki India Ltd | B51: 1 | C51: 1 | D51: 1 | E51: 0.68161327 | F51: 0.77263641 | G51: 1 | H51: 1 | I51: 1 | J51: 1 | K51: 0.97054563 | L51: 0.66871788 | M51: 0.49821812 | O51: =IFERROR(__xludf.DUMMYFUNCTION("""COMPUTED_VALUE"""),0.02136385420964921) -> 0.021363854 | P51: =IFERROR(__xludf.DUMMYFUNCTION("""COMPUTED_VALUE"""),1.0) -> 1 | Q51: =IFERROR(__xludf.DUMMYFUNCTION("""COMPUTED_VALUE"""),0.7847025496) -> 0.78470255
A52: NTPC Ltd | B52: 0.09840696 | C52: 0.10444999 | D52: 0.085079922 | E52: 0.073155729 | F52: 0.068893235 | G52: 0.051897215 | H52: 0.063551629 | I52: 0.046177919 | J52: 0.058803534 | K52: 0.05934309 | L52: 0.054001484 | M52: 0.063281851 | O52: =IFERROR(__xludf.DUMMYFUNCTION("""COMPUTED_VALUE"""),-0.01342576101066626) -> -0.013425761 | P52: =IFERROR(__xludf.DUMMYFUNCTION("""COMPUTED_VALUE"""),1.0) -> 1 | Q52: =IFERROR(__xludf.DUMMYFUNCTION("""COMPUTED_VALUE"""),0.7818696884) -> 0.78186969
A53: Power Grid Corporation of India Ltd | B53: 0.078713158 | C53: 0.082328185 | D53: 0.10790315 | E53: 0.11880219 | F53: 0.11281311 | G53: 0.10272341 | H53: 0.092148108 | I53: 0.073263641 | J53: 0.065494031 | K53: 0.050116679 | L53: 0.040728401 | M53: 0.0397572 | O53: =IFERROR(__xludf.DUMMYFUNCTION("""COMPUTED_VALUE"""),0.03088271557038757) -> 0.030882716 | P53: =IFERROR(__xludf.DUMMYFUNCTION("""COMPUTED_VALUE"""),0.6134133675) -> 0.61341337 | Q53: =IFERROR(__xludf.DUMMYFUNCTION("""COMPUTED_VALUE"""),0.7875354108) -> 0.78753541
A54: Reliance Industries Ltd | B54: 0.26637081 | C54: 0.54386457 | D54: 0.5206097 | E54: 0.47884805 | F54: 0.39446146 | G54: 0.32890538 | H54: 0.34908478 | I54: 0.31719701 | J54: 0.53436838 | K54: 0.53226411 | L54: 0.42089971 | M54: 0.40169151 | O54: =IFERROR(__xludf.DUMMYFUNCTION("""COMPUTED_VALUE"""),0.0857223075714149) -> 0.085722308 | P54: =IFERROR(__xludf.DUMMYFUNCTION("""COMPUTED_VALUE"""),0.3825372631) -> 0.38253726 | Q54: =IFERROR(__xludf.DUMMYFUNCTION("""COMPUTED_VALUE"""),0.790368272) -> 0.79036827
A55: State Bank of India | B55: 0.45758953 | C55: 0.39424563 | D55: 0.32507453 | E55: 0.20254131 | F55: 0.12414379 | G55: 0.10817293 | H55: 0.0025817765 | I55: 0 | J55: 0 | K55: 0.074720442 | L55: 0.11146422 | M55: 1 | O55: =IFERROR(__xludf.DUMMYFUNCTION("""COMPUTED_VALUE"""),-0.004440944515757203) -> -0.0044409445 | P55: =IFERROR(__xludf.DUMMYFUNCTION("""COMPUTED_VALUE"""),0.4692439469) -> 0.46924395 | Q55: =IFERROR(__xludf.DUMMYFUNCTION("""COMPUTED_VALUE"""),0.7818696884) -> 0.78186969
A56: Sun Pharmaceutical Industries Ltd | B56: 0.23469886 | C56: 0.20394416 | D56: 0.17912457 | E56: 0.062040871 | F56: 0.053947528 | G56: 0.073371552 | H56: 0.048551966 | I56: 0.037221285 | J56: 0.14513253 | K56: 0.090637351 | L56: 0.090637351 | M56: 0.070673771 | O56: =IFERROR(__xludf.DUMMYFUNCTION("""COMPUTED_VALUE"""),0.04767520760201058) -> 0.047675208 | P56: =IFERROR(__xludf.DUMMYFUNCTION("""COMPUTED_VALUE"""),0.359606124) -> 0.35960612 | Q56: =IFERROR(__xludf.DUMMYFUNCTION("""COMPUTED_VALUE"""),0.7677053824) -> 0.76770538
A57: Tata Motors Ltd | B57: 0.41356175 | C57: 0.43044985 | D57: 0.022599312 | E57: 0 | F57: 0 | G57: 0 | H57: 0 | I57: 0.13137384 | J57: 0.1069859 | K57: 0.17340527 | L57: 0.22299049 | M57: 0.22336818 | O57: =IFERROR(__xludf.DUMMYFUNCTION("""COMPUTED_VALUE"""),0.03376590325780882) -> 0.033765903 | P57: =IFERROR(__xludf.DUMMYFUNCTION("""COMPUTED_VALUE"""),0.2425224253) -> 0.24252243 | Q57: =IFERROR(__xludf.DUMMYFUNCTION("""COMPUTED_VALUE"""),0.9036827195) -> 0.90368272
A58: Tata Steel Ltd | B58: 0.0034450664 | C58: 0 | D58: 0.027347407 | E58: 1 | F58: 0.33279018 | G58: 0.052652593 | H58: 0.46206785 | I58: 0.67983274 | J58: 0 | K58: 0 | L58: 0 | M58: 0.17853106 | O58: =IFERROR(__xludf.DUMMYFUNCTION("""COMPUTED_VALUE"""),0.04484866529795104) -> 0.044848665 | P58: =IFERROR(__xludf.DUMMYFUNCTION("""COMPUTED_VALUE"""),0.1703298037) -> 0.1703298 | Q58: =IFERROR(__xludf.DUMMYFUNCTION("""COMPUTED_VALUE"""),0.8725212465) -> 0.87252125
A59: Tata Consultancy Services Ltd | B59: 0.71269171 | C59: 0.66785459 | D59: 0.61017603 | E59: 0.54774938 | F59: 0.45651042 | G59: 0.45370473 | H59: 0.43676266 | I59: 0.71269171 | J59: 0.70848317 | K59: 0.65328657 | L59: 0.53550145 | M59: 0.51564578 | O59: =IFERROR(__xludf.DUMMYFUNCTION("""COMPUTED_VALUE"""),0.04355062928916748) -> 0.043550629 | P59: =IFERROR(__xludf.DUMMYFUNCTION("""COMPUTED_VALUE"""),1.0) -> 1 | Q59: =IFERROR(__xludf.DUMMYFUNCTION("""COMPUTED_VALUE"""),0.8781869688) -> 0.87818697
A60: Tech Mahindra Ltd | B60: 0.24716261 | C60: 0.13207527 | D60: 0.28412221 | E60: 0.32755648 | F60: 0.25946449 | G60: 0.23604775 | H60: 0.24613745 | I60: 0.21883591 | J60: 0.15937681 | K60: 0.17054563 | L60: 0.13293856 | M60: 0.6727106 | O60: =IFERROR(__xludf.DUMMYFUNCTION("""COMPUTED_VALUE"""),0.06187286633370392) -> 0.061872866 | P60: =IFERROR(__xludf.DUMMYFUNCTION("""COMPUTED_VALUE"""),0.9474526202) -> 0.94745262 | Q60: =IFERROR(__xludf.DUMMYFUNCTION("""COMPUTED_VALUE"""),0.8526912181) -> 0.85269122
A61: Titan Company Ltd | B61: 0.19158832 | C61: 0.20113846 | D61: 0.18619276 | E61: 0.12079854 | F61: 0.047796587 | G61: 0.079900182 | H61: 0.074019019 | I61: 0.057454644 | J61: 0.032742969 | K61: 0.029667498 | L61: 0.038246442 | M61: 0.033336481 | O61: =IFERROR(__xludf.DUMMYFUNCTION("""COMPUTED_VALUE"""),0.04310699519610491) -> 0.043106995 | P61: =IFERROR(__xludf.DUMMYFUNCTION("""COMPUTED_VALUE"""),0.763733729) -> 0.76373373 | Q61: =IFERROR(__xludf.DUMMYFUNCTION("""COMPUTED_VALUE"""),0.7252124646) -> 0.72521246
A62: Trent Ltd | B62: 0.22342214 | C62: 0.21430364 | D62: 0.056159709 | E62: 0.0047400013 | F62: 0 | G62: 0.0077075605 | H62: 0.0044162676 | I62: 0.002797599 | J62: 0.0024199096 | K62: 0 | L62: 0.19865651 | M62: 0 | O62: =IFERROR(__xludf.DUMMYFUNCTION("""COMPUTED_VALUE"""),0.02785406711317295) -> 0.027854067 | P62: =IFERROR(__xludf.DUMMYFUNCTION("""COMPUTED_VALUE"""),0.02794091859) -> 0.027940919 | Q62: =IFERROR(__xludf.DUMMYFUNCTION("""COMPUTED_VALUE"""),0.9320113314) -> 0.93201133
A63: UltraTech Cement Ltd | B63: 1 | C63: 1 | D63: 0.93579821 | E63: 1 | F63: 1 | G63: 1 | H63: 0.44188845 | I63: 0.42527012 | J63: 0.52217441 | K63: 0.47561071 | L63: 0.401098 | M63: 0.42257233 | O63: =IFERROR(__xludf.DUMMYFUNCTION("""COMPUTED_VALUE"""),0.06003251854615443) -> 0.060032519 | P63: =IFERROR(__xludf.DUMMYFUNCTION("""COMPUTED_VALUE"""),0.01806703986) -> 0.01806704 | Q63: =IFERROR(__xludf.DUMMYFUNCTION("""COMPUTED_VALUE"""),0.8725212465) -> 0.87252125
O64: =IFERROR(__xludf.DUMMYFUNCTION("""COMPUTED_VALUE"""),0.02876091907921292) -> 0.028760919 | P64: =IFERROR(__xludf.DUMMYFUNCTION("""COMPUTED_VALUE"""),0.01072907534) -> 0.010729075 | Q64: =IFERROR(__xludf.DUMMYFUNCTION("""COMPUTED_VALUE"""),0.8470254958) -> 0.8470255
O65: =IFERROR(__xludf.DUMMYFUNCTION("""COMPUTED_VALUE"""),0.04385666457728446) -> 0.043856665 | P65: =IFERROR(__xludf.DUMMYFUNCTION("""COMPUTED_VALUE"""),0.04180751332) -> 0.041807513 | Q65: =IFERROR(__xludf.DUMMYFUNCTION("""COMPUTED_VALUE"""),0.8271954674) -> 0.82719547
O66: =IFERROR(__xludf.DUMMYFUNCTION("""COMPUTED_VALUE"""),0.05146526373579547) -> 0.051465264 | P66: =IFERROR(__xludf.DUMMYFUNCTION("""COMPUTED_VALUE"""),0.03517097188) -> 0.035170972 | Q66: =IFERROR(__xludf.DUMMYFUNCTION("""COMPUTED_VALUE"""),0.8328611898) -> 0.83286119
A67: payout ratio | B67: (PR)2025 | C67: (PR)2024 | D67: (PR)2023 | E67: (PR)2022 | F67: (PR)2021 | G67: (PR)2020 | H67: (PR)2019 | I67: (PR)2018 | J67: (PR)2017 | K67: (PR)2016 | L67: (PR)2015 | M67: (PR)2014 | O67: =IFERROR(__xludf.DUMMYFUNCTION("""COMPUTED_VALUE"""),-0.006532982534919865) -> -0.0065329825 | P67: =IFERROR(__xludf.DUMMYFUNCTION("""COMPUTED_VALUE"""),0.02907398665) -> 0.029073987 | Q67: =IFERROR(__xludf.DUMMYFUNCTION("""COMPUTED_VALUE"""),0.8470254958) -> 0.8470255
A68: Adani Ports and Special Economic Zone Ltd | B68: 0.13275594 | C68: 0.15128266 | D68: 0.22595788 | E68: 0.24539389 | F68: 0 | G68: 0.20879508 | H68: 0.11798002 | I68: 0.083199782 | J68: 0 | K68: 0.17867494 | L68: 0.11172867 | M68: 0.13957559 | O68: =IFERROR(__xludf.DUMMYFUNCTION("""COMPUTED_VALUE"""),-0.03212617967245016) -> -0.03212618 | P68: =IFERROR(__xludf.DUMMYFUNCTION("""COMPUTED_VALUE"""),0.03042287718) -> 0.030422877 | Q68: =IFERROR(__xludf.DUMMYFUNCTION("""COMPUTED_VALUE"""),0.8640226629) -> 0.86402266
A69: Asian Paints Ltd | B69: 0.9631625 | C69: 0.52704561 | D69: 0.52829588 | E69: 0.65286823 | F69: 0.1162751 | G69: 0.73140792 | H69: 0.44998352 | I69: 0.55068708 | J69: 0.44680101 | K69: 0.40599675 | L69: 0.47658017 | M69: 0.47407963 | O69: =IFERROR(__xludf.DUMMYFUNCTION("""COMPUTED_VALUE"""),-0.003359388218960351) -> -0.0033593882 | P69: =IFERROR(__xludf.DUMMYFUNCTION("""COMPUTED_VALUE"""),0.02011735348) -> 0.020117353 | Q69: =IFERROR(__xludf.DUMMYFUNCTION("""COMPUTED_VALUE"""),0.8441926346) -> 0.84419263
A70: AXIS Bank Ltd | B70: 0.013525648 | C70: 0.014207613 | D70: 0.036939794 | E70: 0.014093952 | F70: 0.017276457 | G70: 0.014207613 | H70: 0.026482991 | I70: 0.015798866 | J70: 0.017390118 | K70: 0.012389039 | L70: 0.011422921 | M70: 0.015003239 | O70: =IFERROR(__xludf.DUMMYFUNCTION("""COMPUTED_VALUE"""),0.02168859577219879) -> 0.021688596 | P70: =IFERROR(__xludf.DUMMYFUNCTION("""COMPUTED_VALUE"""),0.02071086531) -> 0.020710865 | Q70: =IFERROR(__xludf.DUMMYFUNCTION("""COMPUTED_VALUE"""),0.8895184136) -> 0.88951841
A71: Bajaj Finserv Ltd | B71: 0.020345302 | C71: 0.017731101 | D71: 0.011252429 | E71: 0.011820734 | F71: 0 | G71: 0.04023596 | H71: 0.0097748377 | I71: 0.011934395 | J71: 0 | K71: 0.016935475 | L71: 0.018640388 | M71: 0.020458963 | O71: =IFERROR(__xludf.DUMMYFUNCTION("""COMPUTED_VALUE"""),0.01368439652022365) -> 0.013684397 | P71: =IFERROR(__xludf.DUMMYFUNCTION("""COMPUTED_VALUE"""),0.01871450732) -> 0.018714507 | Q71: =IFERROR(__xludf.DUMMYFUNCTION("""COMPUTED_VALUE"""),0.9631728045) -> 0.9631728
A72: Bajaj Finance Ltd | B72: 0.15207829 | C72: 0.1427581 | D72: 0.11923029 | E72: 0.097407395 | F72: 0 | G72: 0.20504427 | H72: 0.065696003 | I72: 0.084109069 | J72: 0 | K72: 0.12491333 | L72: 0.11422921 | M72: 0.12673191 | O72: =IFERROR(__xludf.DUMMYFUNCTION("""COMPUTED_VALUE"""),0.1042056304774356) -> 0.10420563 | P72: =IFERROR(__xludf.DUMMYFUNCTION("""COMPUTED_VALUE"""),0.7961071019) -> 0.7961071 | Q72: =IFERROR(__xludf.DUMMYFUNCTION("""COMPUTED_VALUE"""),0.9971671388) -> 0.99716714
A73: Bharat Electronics Ltd | B73: 0.3590548 | C73: 0.41702186 | D73: 0.47317034 | E73: 0.48476376 | F73: 0.55409691 | G73: 0.4706698 | H73: 0.30824837 | I73: 0.49817574 | J73: 0.45953104 | K73: 0.20868142 | L73: 0.22175242 | M73: 0.22266171 | O73: =IFERROR(__xludf.DUMMYFUNCTION("""COMPUTED_VALUE"""),0.006110739245778565) -> 0.0061107392 | P73: =IFERROR(__xludf.DUMMYFUNCTION("""COMPUTED_VALUE"""),0.6302475214) -> 0.63024752 | Q73: =IFERROR(__xludf.DUMMYFUNCTION("""COMPUTED_VALUE"""),0.9603399433) -> 0.96033994
A74: Bharti Airtel Ltd | B74: 0.15673839 | C74: 0.34632477 | D74: 0.23118628 | E74: 0 | F74: 0 | G74: 0 | H74: 1 | I74: 1 | J74: 0.19561042 | K74: 0.19970221 | L74: 0.37849081 | M74: 0 | O74: =IFERROR(__xludf.DUMMYFUNCTION("""COMPUTED_VALUE"""),0.02670265310725271) -> 0.026702653 | P74: =IFERROR(__xludf.DUMMYFUNCTION("""COMPUTED_VALUE"""),0.291028529) -> 0.29102853 | Q74: =IFERROR(__xludf.DUMMYFUNCTION("""COMPUTED_VALUE"""),0.5382436261) -> 0.53824363
A75: HCL Technologies Ltd | B75: 1 | C75: 1 | D75: 0.99453291 | E75: 0.95907071 | F75: 0.33211716 | G75: 0.13946193 | H75: 0.12332208 | I75: 0.22050215 | J75: 0.447142 | K75: 0.54727725 | L75: 0.37053455 | M75: 0.12218547 | O75: =IFERROR(__xludf.DUMMYFUNCTION("""COMPUTED_VALUE"""),0.04605162117843559) -> 0.046051621 | P75: =IFERROR(__xludf.DUMMYFUNCTION("""COMPUTED_VALUE"""),0.05772442166) -> 0.057724422 | Q75: =IFERROR(__xludf.DUMMYFUNCTION("""COMPUTED_VALUE"""),0.552407932) -> 0.55240793
A76: HDFC Bank Ltd | B76: 0.28472056 | C76: 0.27710528 | D76: 0.2735818 | E76: 0.26460258 | F76: 0.13116468 | G76: 0 | H76: 0.21175026 | I76: 0.21959287 | J76: 0.23686932 | K76: 0.23493709 | L76: 0 | M76: 0 | O76: =IFERROR(__xludf.DUMMYFUNCTION("""COMPUTED_VALUE"""),-6.518402651160745E-4) -> -0.00065184027 | P76: =IFERROR(__xludf.DUMMYFUNCTION("""COMPUTED_VALUE"""),0.06727456667) -> 0.067274567 | Q76: =IFERROR(__xludf.DUMMYFUNCTION("""COMPUTED_VALUE"""),0.566572238) -> 0.56657224
A77: Hindustan Unilever Ltd | B77: 1 | C77: 1 | D77: 0.94997784 | E77: 0.96248054 | F77: 1 | G77: 0.87518896 | H77: 0.85347973 | I77: 0.84927428 | J77: 0.90678669 | K77: 0.92099431 | L77: 0.8454098 | M77: 0.80983394 | O77: =IFERROR(__xludf.DUMMYFUNCTION("""COMPUTED_VALUE"""),0.03253298914980095) -> 0.032532989 | P77: =IFERROR(__xludf.DUMMYFUNCTION("""COMPUTED_VALUE"""),0.02982936535) -> 0.029829365 | Q77: =IFERROR(__xludf.DUMMYFUNCTION("""COMPUTED_VALUE"""),0.5637393768) -> 0.56373938
A78: ICICI Bank Ltd | B78: 0.17503779 | C78: 0.18072084 | D78: 0.18640388 | E78: 0.15685205 | F78: 0.085245678 | G78: 0 | H78: 0.17049136 | I78: 0.13639308 | J78: 0.15912527 | K78: 0.32961662 | L78: 0.27278617 | M78: 0.27278617 | O78: =IFERROR(__xludf.DUMMYFUNCTION("""COMPUTED_VALUE"""),0.01275131806608723) -> 0.012751318 | P78: =IFERROR(__xludf.DUMMYFUNCTION("""COMPUTED_VALUE"""),0.0) -> 0 | Q78: =IFERROR(__xludf.DUMMYFUNCTION("""COMPUTED_VALUE"""),0.5722379603) -> 0.57223796
A79: Infosys Ltd | B79: 0.86348189 | C79: 0.63650106 | D79: 0.64297973 | E79: 0.65048135 | F79: 0.53557018 | G79: 0.65184528 | H79: 1 | I79: 0.52954615 | J79: 0.55045976 | K79: 0.57410123 | L79: 0.46760096 | M79: 0.38451484 | O79: =IFERROR(__xludf.DUMMYFUNCTION("""COMPUTED_VALUE"""),0.02898796598277473) -> 0.028987966 | P79: =IFERROR(__xludf.DUMMYFUNCTION("""COMPUTED_VALUE"""),0.0) -> 0 | Q79: =IFERROR(__xludf.DUMMYFUNCTION("""COMPUTED_VALUE"""),0.597733711) -> 0.59773371
A80: ITC Ltd | B80: 0.26596652 | C80: 0.46600971 | D80: 0.44111797 | E80: 0.48237688 | F80: 0.53125107 | G80: 0.52340846 | H80: 0.56728157 | I80: 0.58183017 | J80: 0.75550403 | K80: 0.60933611 | L80: 0.58921813 | M80: 0.60990441 | O80: =IFERROR(__xludf.DUMMYFUNCTION("""COMPUTED_VALUE"""),-0.01506366077335594) -> -0.015063661 | P80: =IFERROR(__xludf.DUMMYFUNCTION("""COMPUTED_VALUE"""),0.0) -> 0 | Q80: =IFERROR(__xludf.DUMMYFUNCTION("""COMPUTED_VALUE"""),0.5325779037) -> 0.5325779
A81: Kotak Mahindra Bank Ltd | B81: 0.17776565 | C81: 0.19174595 | D81: 0.16276241 | E81: 0.1782203 | F81: 0.1741285 | G81: 0.16162581 | H81: 0.19140496 | I81: 0.16151214 | J81: 0.16708153 | K81: 0.16549028 | L81: 0.17446949 | M81: 0.17026403 | O81: =IFERROR(__xludf.DUMMYFUNCTION("""COMPUTED_VALUE"""),0.01232435382021643) -> 0.012324354 | P81: =IFERROR(__xludf.DUMMYFUNCTION("""COMPUTED_VALUE"""),0.003499022054) -> 0.0034990221 | Q81: =IFERROR(__xludf.DUMMYFUNCTION("""COMPUTED_VALUE"""),0.5552407932) -> 0.55524079
A82: Larsen & Toubro Ltd | B82: 0.29097191 | C82: 0.36701106 | D82: 0.33552699 | E82: 0.3314352 | F82: 0.35814551 | G82: 0.46771462 | H82: 0 | I82: 0 | J82: 0 | K82: 0 | L82: 0.36030507 | M82: 0.30620248 | O82: =IFERROR(__xludf.DUMMYFUNCTION("""COMPUTED_VALUE"""),0.00288833041413772) -> 0.0028883304 | P82: =IFERROR(__xludf.DUMMYFUNCTION("""COMPUTED_VALUE"""),0.03997302219) -> 0.039973022 | Q82: =IFERROR(__xludf.DUMMYFUNCTION("""COMPUTED_VALUE"""),0.5155807365) -> 0.51558074
A83: Mahindra & Mahindra Ltd | B83: 0.20674918 | C83: 0.18253941 | D83: 0.14196247 | E83: 0.16912743 | F83: 0.16435367 | G83: 1 | H83: 0.20038417 | I83: 0.12832316 | J83: 0.23777861 | K83: 0.27960582 | L83: 0.26994465 | M83: 0.20993169 | O83: =IFERROR(__xludf.DUMMYFUNCTION("""COMPUTED_VALUE"""),-0.002887654425389955) -> -0.0028876544 | P83: =IFERROR(__xludf.DUMMYFUNCTION("""COMPUTED_VALUE"""),0.07067377082) -> 0.070673771 | Q83: =IFERROR(__xludf.DUMMYFUNCTION("""COMPUTED_VALUE"""),0.5439093484) -> 0.54390935
A84: Maruti Suzuki India Ltd | B84: 0.30802105 | C84: 0.22902672 | D84: 0.25084962 | E84: 0.39826781 | F84: 0.46930587 | G84: 0.48385447 | H84: 0.3590548 | I84: 0.3267751 | J84: 0.15992089 | K84: 0.15617008 | L84: 0.22538957 | M84: 0.14434935 | O84: =IFERROR(__xludf.DUMMYFUNCTION("""COMPUTED_VALUE"""),0.01999227389611892) -> 0.019992274 | P84: =IFERROR(__xludf.DUMMYFUNCTION("""COMPUTED_VALUE"""),0.0510339246) -> 0.051033925 | Q84: =IFERROR(__xludf.DUMMYFUNCTION("""COMPUTED_VALUE"""),0.5269121813) -> 0.52691218
A85: NTPC Ltd | B85: 0.38815199 | C85: 0.3971312 | D85: 0.27687796 | E85: 0.2642616 | F85: 0.42952456 | G85: 0.048419545 | H85: 0.24982667 | I85: 0.43543492 | J85: 0.38110501 | K85: 0.29063093 | L85: 0.23459611 | M85: 0.47748946 | O85: =IFERROR(__xludf.DUMMYFUNCTION("""COMPUTED_VALUE"""),0.01350146304322639) -> 0.013501463 | P85: =IFERROR(__xludf.DUMMYFUNCTION("""COMPUTED_VALUE"""),0.02648411681) -> 0.026484117 | Q85: =IFERROR(__xludf.DUMMYFUNCTION("""COMPUTED_VALUE"""),0.5439093484) -> 0.54390935
A86: Power Grid Corporation of India Ltd | B86: 0.52772758 | C86: 0.57694275 | D86: 0.51420193 | E86: 0.5889908 | F86: 0.64411634 | G86: 0.32041009 | H86: 0.51136041 | I86: 0.42031802 | J86: 0.079789955 | K86: 0.21049999 | L86: 0.25187256 | M86: 0.35121219 | O86: =IFERROR(__xludf.DUMMYFUNCTION("""COMPUTED_VALUE"""),0.005940231823942157) -> 0.0059402318 | P86: =IFERROR(__xludf.DUMMYFUNCTION("""COMPUTED_VALUE"""),0.3344628043) -> 0.3344628 | Q86: =IFERROR(__xludf.DUMMYFUNCTION("""COMPUTED_VALUE"""),0.9376770538) -> 0.93767705
A87: Reliance Industries Ltd | B87: 0.11036474 | C87: 0.09933963 | D87: 0.086609609 | E87: 0.080358259 | F87: 0.090701401 | G87: 0.11116036 | H87: 0.10195383 | I87: 0.10252214 | J87: 0 | K87: 0.23073164 | L87: 0.14196247 | M87: 0.14105318 | O87: =IFERROR(__xludf.DUMMYFUNCTION("""COMPUTED_VALUE"""),0.03303571244379668) -> 0.033035712 | P87: =IFERROR(__xludf.DUMMYFUNCTION("""COMPUTED_VALUE"""),0.3008484521) -> 0.30084845 | Q87: =IFERROR(__xludf.DUMMYFUNCTION("""COMPUTED_VALUE"""),0.8271954674) -> 0.82719547
A88: State Bank of India | B88: 0.22743547 | C88: 0.22754913 | D88: 0.2282311 | E88: 0.22732181 | F88: 0.19879292 | G88: 0 | H88: 0 | I88: 0 | J88: 0.22857208 | K88: 0.23050431 | L88: 0.22970869 | M88: 0.23368682 | O88: =IFERROR(__xludf.DUMMYFUNCTION("""COMPUTED_VALUE"""),5.058831587710402E-4) -> 0.00050588316 | P88: =IFERROR(__xludf.DUMMYFUNCTION("""COMPUTED_VALUE"""),0.2842840763) -> 0.28428408 | Q88: =IFERROR(__xludf.DUMMYFUNCTION("""COMPUTED_VALUE"""),0.8583569405) -> 0.85835694
A89: Sun Pharmaceutical Industries Ltd | B89: 0.37576295 | C89: 0.3439379 | D89: 0.33791387 | E89: 0.74970732 | F89: 0.61013173 | G89: 0.41622623 | H89: 0.20424864 | I89: 0.41940874 | J89: 0.039213012 | K89: 0.18049352 | L89: 0.18072084 | M89: 0.11229697 | O89: =IFERROR(__xludf.DUMMYFUNCTION("""COMPUTED_VALUE"""),0.01773002475456282) -> 0.017730025 | P89: =IFERROR(__xludf.DUMMYFUNCTION("""COMPUTED_VALUE"""),0.2571983544) -> 0.25719835 | Q89: =IFERROR(__xludf.DUMMYFUNCTION("""COMPUTED_VALUE"""),0.8413597734) -> 0.84135977
A90: Tata Motors Ltd | B90: 0.09433855 | C90: 0.027846921 | D90: 0 | E90: 0 | F90: 0 | G90: 0 | H90: 0 | I90: 0 | J90: 0 | K90: 0 | L90: 0 | M90: 0.052624999 | O90: =IFERROR(__xludf.DUMMYFUNCTION("""COMPUTED_VALUE"""),0.07575910669939087) -> 0.075759107 | P90: =IFERROR(__xludf.DUMMYFUNCTION("""COMPUTED_VALUE"""),0.2102569636) -> 0.21025696 | Q90: =IFERROR(__xludf.DUMMYFUNCTION("""COMPUTED_VALUE"""),0.8640226629) -> 0.86402266
A91: Tata Steel Ltd | B91: 1 | C91: 0 | D91: 0.80790171 | E91: 0.085018356 | F91: 0.17367386 | G91: 1 | H91: 0.12730021 | I91: 0.10456803 | J91: 0 | K91: 0 | L91: 0 | M91: 0.3069981 | O91: =IFERROR(__xludf.DUMMYFUNCTION("""COMPUTED_VALUE"""),-0.01607678257973191) -> -0.016076783 | P91: =IFERROR(__xludf.DUMMYFUNCTION("""COMPUTED_VALUE"""),0.2085303838) -> 0.20853038 | Q91: =IFERROR(__xludf.DUMMYFUNCTION("""COMPUTED_VALUE"""),0.8923512748) -> 0.89235127
A92: Tata Consultancy Services Ltd | B92: 1 | C92: 0.62229345 | D92: 1 | E92: 0.39485798 | F92: 0.38019572 | G92: 1 | H92: 0.36405588 | I92: 0.40849729 | J92: 0.39610825 | K92: 0.37428536 | L92: 0.88587309 | M92: 0.37167116 | O92: =IFERROR(__xludf.DUMMYFUNCTION("""COMPUTED_VALUE"""),0.01091866195308789) -> 0.010918662 | P92: =IFERROR(__xludf.DUMMYFUNCTION("""COMPUTED_VALUE"""),0.3855048223) -> 0.38550482 | Q92: =IFERROR(__xludf.DUMMYFUNCTION("""COMPUTED_VALUE"""),0.88101983) -> 0.88101983
A93: Tech Mahindra Ltd | B93: 1 | C93: 1 | D93: 1 | E93: 0.81290279 | F93: 0.45146111 | G93: 0.70219707 | H93: 0.39417602 | I93: 0.28222002 | J93: 0.50067628 | K93: 0.21061366 | L93: 0.25050863 | M93: 0.17515145 | O93: =IFERROR(__xludf.DUMMYFUNCTION("""COMPUTED_VALUE"""),0.01062199346479478) -> 0.010621993 | P93: =IFERROR(__xludf.DUMMYFUNCTION("""COMPUTED_VALUE"""),0.3242112363) -> 0.32421124 | Q93: =IFERROR(__xludf.DUMMYFUNCTION("""COMPUTED_VALUE"""),0.8781869688) -> 0.87818697
A94: Titan Company Ltd | B94: 0.33234448 | C94: 0.2886987 | D94: 0.23289119 | E94: 0.18560826 | F94: 0.41463498 | G94: 0.33598163 | H94: 0.26937634 | I94: 0.23209557 | J94: 0 | K94: 0.67309987 | L94: 0.28426592 | M94: 0.28824405 | O94: =IFERROR(__xludf.DUMMYFUNCTION("""COMPUTED_VALUE"""),0.006216468858179857) -> 0.0062164689 | P94: =IFERROR(__xludf.DUMMYFUNCTION("""COMPUTED_VALUE"""),0.3138517569) -> 0.31385176 | Q94: =IFERROR(__xludf.DUMMYFUNCTION("""COMPUTED_VALUE"""),0.9065155807) -> 0.90651558
A95: Trent Ltd | B95: 0.083540764 | C95: 0.059785636 | D95: 0.099907935 | E95: 0.45805344 | F95: 0 | G95: 0.48203589 | H95: 0.54000296 | I95: 0.5227265 | J95: 0 | K95: 1 | L95: 0.29199486 | M95: 0 | O95: =IFERROR(__xludf.DUMMYFUNCTION("""COMPUTED_VALUE"""),0.004902309532710447) -> 0.0049023095 | P95: =IFERROR(__xludf.DUMMYFUNCTION("""COMPUTED_VALUE"""),0.2028110879) -> 0.20281109 | Q95: =IFERROR(__xludf.DUMMYFUNCTION("""COMPUTED_VALUE"""),0.8470254958) -> 0.8470255
A96: UltraTech Cement Ltd | B96: 0.37962742 | C96: 0.17765199 | D96: 0.24516657 | E96: 0.16503563 | F96: 0.07797138 | G96: 0.075129858 | H96: 0.16435367 | I96: 0.1689001 | J96: 0.10911447 | K96: 0.13446085 | L96: 0.13377888 | M96: 0.12707289 | O96: =IFERROR(__xludf.DUMMYFUNCTION("""COMPUTED_VALUE"""),0.02827059478120083) -> 0.028270595 | P96: =IFERROR(__xludf.DUMMYFUNCTION("""COMPUTED_VALUE"""),0.2680973899) -> 0.26809739 | Q96: =IFERROR(__xludf.DUMMYFUNCTION("""COMPUTED_VALUE"""),0.9093484419) -> 0.90934844
O97: =IFERROR(__xludf.DUMMYFUNCTION("""COMPUTED_VALUE"""),0.05179764772161512) -> 0.051797648 | P97: =IFERROR(__xludf.DUMMYFUNCTION("""COMPUTED_VALUE"""),0.4846752546) -> 0.48467525 | Q97: =IFERROR(__xludf.DUMMYFUNCTION("""COMPUTED_VALUE"""),0.9745042493) -> 0.97450425
O98: =IFERROR(__xludf.DUMMYFUNCTION("""COMPUTED_VALUE"""),0.01610113229278614) -> 0.016101132 | P98: =IFERROR(__xludf.DUMMYFUNCTION("""COMPUTED_VALUE"""),0.4871572132) -> 0.48715721 | Q98: =IFERROR(__xludf.DUMMYFUNCTION("""COMPUTED_VALUE"""),0.7280453258) -> 0.72804533
O99: =IFERROR(__xludf.DUMMYFUNCTION("""COMPUTED_VALUE"""),-0.005827604352744331) -> -0.0058276044 | P99: =IFERROR(__xludf.DUMMYFUNCTION("""COMPUTED_VALUE"""),0.4743157753) -> 0.47431578 | Q99: =IFERROR(__xludf.DUMMYFUNCTION("""COMPUTED_VALUE"""),0.7422096317) -> 0.74220963
A100: Profit margin | B100: (PM)2025 | C100: (PM)2024 | D100: (PM)2023 | E100: (PM)2022 | F100: (PM)2021 | G100: (PM)2020 | H100: (PM)2019 | I100: (PM)2018 | J100: (PM)2017 | K100: (PM)2016 | L100: (PM)2015 | M100: (PM)2014 | O100: =IFERROR(__xludf.DUMMYFUNCTION("""COMPUTED_VALUE"""),0.01005231398367576) -> 0.010052314 | P100: =IFERROR(__xludf.DUMMYFUNCTION("""COMPUTED_VALUE"""),0.4325541242) -> 0.43255412 | Q100: =IFERROR(__xludf.DUMMYFUNCTION("""COMPUTED_VALUE"""),0.6940509915) -> 0.69405099
...

Sheet Deviation_sequence
A1: Diluted EPS | B1: 2025 | C1: 2024 | D1: 2023 | E1: 2022 | F1: 2021 | G1: 2020 | H1: 2019 | I1: 2018 | J1: 2017 | K1: 2016 | L1: 2015 | M1: 2014
A2: Adani Ports and Special Economic Zone Ltd | B2: =ABS(Annual_return_and_ratios!B2 - Annual_return_and_ratios!B35) -> 0.2841122 | C2: =ABS(Annual_return_and_ratios!C2 - Annual_return_and_ratios!C35) -> 0.12639848 | D2: =ABS(Annual_return_and_ratios!D2 - Annual_return_and_ratios!D35) -> 0.13469516 | E2: =ABS(Annual_return_and_ratios!E2 - Annual_return_and_ratios!E35) -> 0.10467369 | F2: =ABS(Annual_return_and_ratios!F2 - Annual_return_and_ratios!F35) -> 0.024172129 | G2: =ABS(Annual_return_and_ratios!G2 - Annual_return_and_ratios!G35) -> 0.11570923 | H2: =ABS(Annual_return_and_ratios!H2 - Annual_return_and_ratios!H35) -> 0.084493184 | I2: =ABS(Annual_return_and_ratios!I2 - Annual_return_and_ratios!I35) -> 0.080889426 | ... M2: =ABS(Annual_return_and_ratios!M2 - Annual_return_and_ratios!M35) -> 0.0065750311
A3: Asian Paints Ltd | B3: =ABS(Annual_return_and_ratios!B3 - Annual_return_and_ratios!B36) -> 0.21054954 | C3: =ABS(Annual_return_and_ratios!C3 - Annual_return_and_ratios!C36) -> 0.2924614 | D3: =ABS(Annual_return_and_ratios!D3 - Annual_return_and_ratios!D36) -> 0.22418895 | E3: =ABS(Annual_return_and_ratios!E3 - Annual_return_and_ratios!E36) -> 0.14142297 | F3: =ABS(Annual_return_and_ratios!F3 - Annual_return_and_ratios!F36) -> 0.13053703 | G3: =ABS(Annual_return_and_ratios!G3 - Annual_return_and_ratios!G36) -> 0.13096569 | H3: =ABS(Annual_return_and_ratios!H3 - Annual_return_and_ratios!H36) -> 0.084843653 | I3: =ABS(Annual_return_and_ratios!I3 - Annual_return_and_ratios!I36) -> 0.10089587 | ... M3: =ABS(Annual_return_and_ratios!M3 - Annual_return_and_ratios!M36) -> 0.043119543
A4: AXIS Bank Ltd | B4: =ABS(Annual_return_and_ratios!B4 - Annual_return_and_ratios!B37) -> 0.47208804 | C4: =ABS(Annual_return_and_ratios!C4 - Annual_return_and_ratios!C37) -> 0.4316954 | D4: =ABS(Annual_return_and_ratios!D4 - Annual_return_and_ratios!D37) -> 0.16127121 | E4: =ABS(Annual_return_and_ratios!E4 - Annual_return_and_ratios!E37) -> 0.23052393 | F4: =ABS(Annual_return_and_ratios!F4 - Annual_return_and_ratios!F37) -> 0.064339867 | G4: =ABS(Annual_return_and_ratios!G4 - Annual_return_and_ratios!G37) -> 0.069099612 | H4: =ABS(Annual_return_and_ratios!H4 - Annual_return_and_ratios!H37) -> 0.056279591 | I4: =ABS(Annual_return_and_ratios!I4 - Annual_return_and_ratios!I37) -> 0.0035987805 | ... M4: =ABS(Annual_return_and_ratios!M4 - Annual_return_and_ratios!M37) -> 0.69192141
A5: Bajaj Finserv Ltd | B5: =ABS(Annual_return_and_ratios!B5 - Annual_return_and_ratios!B38) -> 0.027729278 | C5: =ABS(Annual_return_and_ratios!C5 - Annual_return_and_ratios!C38) -> 0.0070215173 | D5: =ABS(Annual_return_and_ratios!D5 - Annual_return_and_ratios!D38) -> 0.029275302 | E5: =ABS(Annual_return_and_ratios!E5 - Annual_return_and_ratios!E38) -> 0.082245567 | F5: =ABS(Annual_return_and_ratios!F5 - Annual_return_and_ratios!F38) -> 0.025619183 | G5: =ABS(Annual_return_and_ratios!G5 - Annual_return_and_ratios!G38) -> 0.22836262 | H5: =ABS(Annual_return_and_ratios!H5 - Annual_return_and_ratios!H38) -> 0.066328414 | I5: =ABS(Annual_return_and_ratios!I5 - Annual_return_and_ratios!I38) -> 0.015088516 | ... M5: =ABS(Annual_return_and_ratios!M5 - Annual_return_and_ratios!M38) -> 0.010948533
A6: Bajaj Finance Ltd | B6: =ABS(Annual_return_and_ratios!B6 - Annual_return_and_ratios!B39) -> 0.98398788 | C6: =ABS(Annual_return_and_ratios!C6 - Annual_return_and_ratios!C39) -> 0.97863615 | D6: =ABS(Annual_return_and_ratios!D6 - Annual_return_and_ratios!D39) -> 1.0134258 | E6: =ABS(Annual_return_and_ratios!E6 - Annual_return_and_ratios!E39) -> 0.58253065 | F6: =ABS(Annual_return_and_ratios!F6 - Annual_return_and_ratios!F39) -> 0.29681496 | G6: =ABS(Annual_return_and_ratios!G6 - Annual_return_and_ratios!G39) -> 0.47368489 | H6: =ABS(Annual_return_and_ratios!H6 - Annual_return_and_ratios!H39) -> 0.31193092 | I6: =ABS(Annual_return_and_ratios!I6 - Annual_return_and_ratios!I39) -> 0.20875652 | ... M6: =ABS(Annual_return_and_ratios!M6 - Annual_return_and_ratios!M39) -> 0.72062673
A7: Bharat Electronics Ltd | B7: =ABS(Annual_return_and_ratios!B7 - Annual_return_and_ratios!B40) -> 8.6851477e-05 | C7: =ABS(Annual_return_and_ratios!C7 - Annual_return_and_ratios!C40) -> 0.041965479 | D7: =ABS(Annual_return_and_ratios!D7 - Annual_return_and_ratios!D40) -> 0.018031844 | E7: =ABS(Annual_return_and_ratios!E7 - Annual_return_and_ratios!E40) -> 0.0020491513 | F7: =ABS(Annual_return_and_ratios!F7 - Annual_return_and_ratios!F40) -> 0.016294292 | G7: =ABS(Annual_return_and_ratios!G7 - Annual_return_and_ratios!G40) -> 0.035606969 | H7: =ABS(Annual_return_and_ratios!H7 - Annual_return_and_ratios!H40) -> 0.062549057 | I7: =ABS(Annual_return_and_ratios!I7 - Annual_return_and_ratios!I40) -> 0.023476742 | ... M7: =ABS(Annual_return_and_ratios!M7 - Annual_return_and_ratios!M40) -> 0.62413678
A8: Bharti Airtel Ltd | B8: =ABS(Annual_return_and_ratios!B8 - Annual_return_and_ratios!B41) -> 0.26432588 | C8: =ABS(Annual_return_and_ratios!C8 - Annual_return_and_ratios!C41) -> 0.0116728 | D8: =ABS(Annual_return_and_ratios!D8 - Annual_return_and_ratios!D41) -> 0.067926407 | E8: =ABS(Annual_return_and_ratios!E8 - Annual_return_and_ratios!E41) -> 0.0027036238 | F8: =ABS(Annual_return_and_ratios!F8 - Annual_return_and_ratios!F41) -> 0.012751318 | G8: =ABS(Annual_return_and_ratios!G8 - Annual_return_and_ratios!G41) -> 0.028987966 | H8: =ABS(Annual_return_and_ratios!H8 - Annual_return_and_ratios!H41) -> 0.015063661 | I8: =ABS(Annual_return_and_ratios!I8 - Annual_return_and_ratios!I41) -> 0.0088253318 | ... M8: =ABS(Annual_return_and_ratios!M8 - Annual_return_and_ratios!M41) -> 0.012982654
A9: HCL Technologies Ltd | B9: =ABS(Annual_return_and_ratios!B9 - Annual_return_and_ratios!B42) -> 0.32852257 | C9: =ABS(Annual_return_and_ratios!C9 - Annual_return_and_ratios!C42) -> 0.26781274 | D9: =ABS(Annual_return_and_ratios!D9 - Annual_return_and_ratios!D42) -> 0.28377819 | E9: =ABS(Annual_return_and_ratios!E9 - Annual_return_and_ratios!E42) -> 0.23946833 | F9: =ABS(Annual_return_and_ratios!F9 - Annual_return_and_ratios!F42) -> 0.13449786 | G9: =ABS(Annual_return_and_ratios!G9 - Annual_return_and_ratios!G42) -> 0.22460717 | H9: =ABS(Annual_return_and_ratios!H9 - Annual_return_and_ratios!H42) -> 0.37458616 | I9: =ABS(Annual_return_and_ratios!I9 - Annual_return_and_ratios!I42) -> 0.31358924 | ... M9: =ABS(Annual_return_and_ratios!M9 - Annual_return_and_ratios!M42) -> 0.43287761
A10: HDFC Bank Ltd | B10: =ABS(Annual_return_and_ratios!B10 - Annual_return_and_ratios!B43) -> 0.47105608 | C10: =ABS(Annual_return_and_ratios!C10 - Annual_return_and_ratios!C43) -> 0.48014338 | D10: =ABS(Annual_return_and_ratios!D10 - Annual_return_and_ratios!D43) -> 0.42250181 | E10: =ABS(Annual_return_and_ratios!E10 - Annual_return_and_ratios!E43) -> 0.35538081 | F10: =ABS(Annual_return_and_ratios!F10 - Annual_return_and_ratios!F43) -> 0.25306452 | G10: =ABS(Annual_return_and_ratios!G10 - Annual_return_and_ratios!G43) -> 0.27508406 | H10: =ABS(Annual_return_and_ratios!H10 - Annual_return_and_ratios!H43) -> 0.41592335 | I10: =ABS(Annual_return_and_ratios!I10 - Annual_return_and_ratios!I43) -> 0.34734193 | ... M10: =ABS(Annual_return_and_ratios!M10 - Annual_return_and_ratios!M43) -> 0.16822423
A11: Hindustan Unilever Ltd | B11: =ABS(Annual_return_and_ratios!B11 - Annual_return_and_ratios!B44) -> 0.23104421 | C11: =ABS(Annual_return_and_ratios!C11 - Annual_return_and_ratios!C44) -> 0.23483213 | D11: =ABS(Annual_return_and_ratios!D11 - Annual_return_and_ratios!D44) -> 0.20152965 | E11: =ABS(Annual_return_and_ratios!E11 - Annual_return_and_ratios!E44) -> 0.20619111 | F11: =ABS(Annual_return_and_ratios!F11 - Annual_return_and_ratios!F44) -> 0.16586162 | G11: =ABS(Annual_return_and_ratios!G11 - Annual_return_and_ratios!G44) -> 0.13170741 | H11: =ABS(Annual_return_and_ratios!H11 - Annual_return_and_ratios!H44) -> 0.11773715 | I11: =ABS(Annual_return_and_ratios!I11 - Annual_return_and_ratios!I44) -> 0.085580704 | ... M11: =ABS(Annual_return_and_ratios!M11 - Annual_return_and_ratios!M44) -> 0.05939705
A12: ICICI Bank Ltd | B12: =ABS(Annual_return_and_ratios!B12 - Annual_return_and_ratios!B45) -> 0.35719728 | C12: =ABS(Annual_return_and_ratios!C12 - Annual_return_and_ratios!C45) -> 0.30504214 | D12: =ABS(Annual_return_and_ratios!D12 - Annual_return_and_ratios!D45) -> 0.22743289 | E12: =ABS(Annual_return_and_ratios!E12 - Annual_return_and_ratios!E45) -> 0.15779067 | F12: =ABS(Annual_return_and_ratios!F12 - Annual_return_and_ratios!F45) -> 0.086861379 | G12: =ABS(Annual_return_and_ratios!G12 - Annual_return_and_ratios!G45) -> 0.075275304 | H12: =ABS(Annual_return_and_ratios!H12 - Annual_return_and_ratios!H45) -> 0.0080161693 | I12: =ABS(Annual_return_and_ratios!I12 - Annual_return_and_ratios!I45) -> 0.043432209 | ... M12: =ABS(Annual_return_and_ratios!M12 - Annual_return_and_ratios!M45) -> 0.48361126
A13: Infosys Ltd | B13: =ABS(Annual_return_and_ratios!B13 - Annual_return_and_ratios!B46) -> 0.32862011 | C13: =ABS(Annual_return_and_ratios!C13 - Annual_return_and_ratios!C46) -> 0.32311322 | D13: =ABS(Annual_return_and_ratios!D13 - Annual_return_and_ratios!D46) -> 0.3187944 | E13: =ABS(Annual_return_and_ratios!E13 - Annual_return_and_ratios!E46) -> 0.24231973 | F13: =ABS(Annual_return_and_ratios!F13 - Annual_return_and_ratios!F46) -> 0.16323345 | G13: =ABS(Annual_return_and_ratios!G13 - Annual_return_and_ratios!G46) -> 0.20751329 | H13: =ABS(Annual_return_and_ratios!H13 - Annual_return_and_ratios!H46) -> 0.1563386 | I13: =ABS(Annual_return_and_ratios!I13 - Annual_return_and_ratios!I46) -> 0.36142097 | ... M13: =ABS(Annual_return_and_ratios!M13 - Annual_return_and_ratios!M46) -> 0.97975162
... A30: UltraTech Cement Ltd | B30: =ABS(Annual_return_and_ratios!B30 - Annual_return_and_ratios!B63) -> 0.98873222 | C30: =ABS(Annual_return_and_ratios!C30 - Annual_return_and_ratios!C63) -> 0.9808844 | D30: =ABS(Annual_return_and_ratios!D30 - Annual_return_and_ratios!D63) -> 0.92153968 | E30: =ABS(Annual_return_and_ratios!E30 - Annual_return_and_ratios!E63) -> 1.002719 | F30: =ABS(Annual_return_and_ratios!F30 - Annual_return_and_ratios!F63) -> 0.93707677 | G30: =ABS(Annual_return_and_ratios!G30 - Annual_return_and_ratios!G63) -> 1.0103415 | H30: =ABS(Annual_return_and_ratios!H30 - Annual_return_and_ratios!H63) -> 0.44401849 | I30: =ABS(Annual_return_and_ratios!I30 - Annual_return_and_ratios!I63) -> 0.42849872 | ... M30: =ABS(Annual_return_and_ratios!M30 - Annual_return_and_ratios!M63) -> 0.40475787
A34: payout ratio | B34: (PR)2025 | C34: (PR)2024 | D34: (PR)2023 | E34: (PR)2022 | F34: (PR)2021 | G34: (PR)2020 | H34: (PR)2019 | I34: (PR)2018 | J34: (PR)2017 | K34: (PR)2016 | L34: (PR)2015 | M34: (PR)2014
A35: Adani Ports and Special Economic Zone Ltd | B35: =ABS(Annual_return_and_ratios!B2 - Annual_return_and_ratios!B68) -> 0.15114479 | C35: =ABS(Annual_return_and_ratios!C2 - Annual_return_and_ratios!C68) -> 0.08641656 | D35: =ABS(Annual_return_and_ratios!D2 - Annual_return_and_ratios!D68) -> 0.23936889 | E35: =ABS(Annual_return_and_ratios!E2 - Annual_return_and_ratios!E68) -> 0.24059972 | F35: =ABS(Annual_return_and_ratios!F2 - Annual_return_and_ratios!F68) -> 0.097112015 | G35: =ABS(Annual_return_and_ratios!G2 - Annual_return_and_ratios!G68) -> 0.23683452 | H35: =ABS(Annual_return_and_ratios!H2 - Annual_return_and_ratios!H68) -> 0.10983949 | I35: =ABS(Annual_return_and_ratios!I2 - Annual_return_and_ratios!I68) -> 0.079710709 | ... M35: =ABS(Annual_return_and_ratios!M2 - Annual_return_and_ratios!M68) -> 0.11189689
A36: Asian Paints Ltd | B36: =ABS(Annual_return_and_ratios!B3 - Annual_return_and_ratios!B69) -> 0.97867056 | C36: =ABS(Annual_return_and_ratios!C3 - Annual_return_and_ratios!C69) -> 0.52362247 | D36: =ABS(Annual_return_and_ratios!D3 - Annual_return_and_ratios!D69) -> 0.53278563 | E36: =ABS(Annual_return_and_ratios!E3 - Annual_return_and_ratios!E69) -> 0.63518416 | F36: =ABS(Annual_return_and_ratios!F3 - Annual_return_and_ratios!F69) -> 0.081554155 | G36: =ABS(Annual_return_and_ratios!G3 - Annual_return_and_ratios!G69) -> 0.72155753 | H36: =ABS(Annual_return_and_ratios!H3 - Annual_return_and_ratios!H69) -> 0.42487371 | I36: =ABS(Annual_return_and_ratios!I3 - Annual_return_and_ratios!I69) -> 0.54821207 | ... M36: =ABS(Annual_return_and_ratios!M3 - Annual_return_and_ratios!M69) -> 0.45996035
A37: AXIS Bank Ltd | B37: =ABS(Annual_return_and_ratios!B4 - Annual_return_and_ratios!B70) -> 0.010380666 | C37: =ABS(Annual_return_and_ratios!C4 - Annual_return_and_ratios!C70) -> 0.0014349507 | D37: =ABS(Annual_return_and_ratios!D4 - Annual_return_and_ratios!D70) -> 0.02048928 | E37: =ABS(Annual_return_and_ratios!E4 - Annual_return_and_ratios!E70) -> 0.0082463961 | F37: =ABS(Annual_return_and_ratios!F4 - Annual_return_and_ratios!F70) -> 0.03756355 | G37: =ABS(Annual_return_and_ratios!G4 - Annual_return_and_ratios!G70) -> 0.057956176 | H37: =ABS(Annual_return_and_ratios!H4 - Annual_return_and_ratios!H70) -> 0.011058151 | I37: =ABS(Annual_return_and_ratios!I4 - Annual_return_and_ratios!I70) -> 0.012200085 | ... M37: =ABS(Annual_return_and_ratios!M4 - Annual_return_and_ratios!M70) -> 0.0058210152
A38: Bajaj Finserv Ltd | B38: =ABS(Annual_return_and_ratios!B5 - Annual_return_and_ratios!B71) -> 0.0070764007 | C38: =ABS(Annual_return_and_ratios!C5 - Annual_return_and_ratios!C71) -> 0.0032962116 | D38: =ABS(Annual_return_and_ratios!D5 - Annual_return_and_ratios!D71) -> 0.02704692 | E38: =ABS(Annual_return_and_ratios!E5 - Annual_return_and_ratios!E71) -> 0.038116878 | F38: =ABS(Annual_return_and_ratios!F5 - Annual_return_and_ratios!F71) -> 0.074710705 | G38: =ABS(Annual_return_and_ratios!G5 - Annual_return_and_ratios!G71) -> 0.053863298 | H38: =ABS(Annual_return_and_ratios!H5 - Annual_return_and_ratios!H71) -> 0.016692324 | I38: =ABS(Annual_return_and_ratios!I5 - Annual_return_and_ratios!I71) -> 0.0096588179 | ... M38: =ABS(Annual_return_and_ratios!M5 - Annual_return_and_ratios!M71) -> 0.014689346
A39: Bajaj Finance Ltd | B39: =ABS(Annual_return_and_ratios!B6 - Annual_return_and_ratios!B72) -> 0.13606617 | C39: =ABS(Annual_return_and_ratios!C6 - Annual_return_and_ratios!C72) -> 0.12139424 | D39: =ABS(Annual_return_and_ratios!D6 - Annual_return_and_ratios!D72) -> 0.13265605 | E39: =ABS(Annual_return_and_ratios!E6 - Annual_return_and_ratios!E72) -> 0.066524679 | F39: =ABS(Annual_return_and_ratios!F6 - Annual_return_and_ratios!F72) -> 0.085722308 | G39: =ABS(Annual_return_and_ratios!G6 - Annual_return_and_ratios!G72) -> 0.20948522 | H39: =ABS(Annual_return_and_ratios!H6 - Annual_return_and_ratios!H72) -> 0.018020795 | I39: =ABS(Annual_return_and_ratios!I6 - Annual_return_and_ratios!I72) -> 0.050343166 | ... M39: =ABS(Annual_return_and_ratios!M6 - Annual_return_and_ratios!M72) -> 0.083624913
A40: Bharat Electronics Ltd | B40: =ABS(Annual_return_and_ratios!B7 - Annual_return_and_ratios!B73) -> 0.33120073 | C40: =ABS(Annual_return_and_ratios!C7 - Annual_return_and_ratios!C73) -> 0.35698934 | D40: =ABS(Annual_return_and_ratios!D7 - Annual_return_and_ratios!D73) -> 0.44440942 | E40: =ABS(Annual_return_and_ratios!E7 - Annual_return_and_ratios!E73) -> 0.44090709 | F40: =ABS(Annual_return_and_ratios!F7 - Annual_return_and_ratios!F73) -> 0.50263164 | G40: =ABS(Annual_return_and_ratios!G7 - Annual_return_and_ratios!G73) -> 0.47720279 | H40: =ABS(Annual_return_and_ratios!H7 - Annual_return_and_ratios!H73) -> 0.34037455 | I40: =ABS(Annual_return_and_ratios!I7 - Annual_return_and_ratios!I73) -> 0.50153513 | ... M40: =ABS(Annual_return_and_ratios!M7 - Annual_return_and_ratios!M73) -> 0.21655097
A41: Bharti Airtel Ltd | B41: =ABS(Annual_return_and_ratios!B8 - Annual_return_and_ratios!B74) -> 0.13003573 | C41: =ABS(Annual_return_and_ratios!C8 - Annual_return_and_ratios!C74) -> 0.30027315 | D41: =ABS(Annual_return_and_ratios!D8 - Annual_return_and_ratios!D74) -> 0.23183812 | E41: =ABS(Annual_return_and_ratios!E8 - Annual_return_and_ratios!E74) -> 0.032532989 | F41: =ABS(Annual_return_and_ratios!F8 - Annual_return_and_ratios!F74) -> 0.012751318 | G41: =ABS(Annual_return_and_ratios!G8 - Annual_return_and_ratios!G74) -> 0.028987966 | H41: =ABS(Annual_return_and_ratios!H8 - Annual_return_and_ratios!H74) -> 1.0150637 | I41: =ABS(Annual_return_and_ratios!I8 - Annual_return_and_ratios!I74) -> 0.98767565 | ... M41: =ABS(Annual_return_and_ratios!M8 - Annual_return_and_ratios!M74) -> 0.013501463
A42: HCL Technologies Ltd | B42: =ABS(Annual_return_and_ratios!B9 - Annual_return_and_ratios!B75) -> 0.99405977 | C42: =ABS(Annual_return_and_ratios!C9 - Annual_return_and_ratios!C75) -> 0.96696429 | D42: =ABS(Annual_return_and_ratios!D9 - Annual_return_and_ratios!D75) -> 0.99402703 | E42: =ABS(Annual_return_and_ratios!E9 - Annual_return_and_ratios!E75) -> 0.94134068 | F42: =ABS(Annual_return_and_ratios!F9 - Annual_return_and_ratios!F75) -> 0.25635805 | G42: =ABS(Annual_return_and_ratios!G9 - Annual_return_and_ratios!G75) -> 0.15553871 | H42: =ABS(Annual_return_and_ratios!H9 - Annual_return_and_ratios!H75) -> 0.11240342 | I42: =ABS(Annual_return_and_ratios!I9 - Annual_return_and_ratios!I75) -> 0.20988016 | ... M42: =ABS(Annual_return_and_ratios!M9 - Annual_return_and_ratios!M75) -> 0.070387824
A43: HDFC Bank Ltd | B43: =ABS(Annual_return_and_ratios!B10 - Annual_return_and_ratios!B76) -> 0.26861943 | C43: =ABS(Annual_return_and_ratios!C10 - Annual_return_and_ratios!C76) -> 0.28293289 | D43: =ABS(Annual_return_and_ratios!D10 - Annual_return_and_ratios!D76) -> 0.26352948 | E43: =ABS(Annual_return_and_ratios!E10 - Annual_return_and_ratios!E76) -> 0.26275132 | F43: =ABS(Annual_return_and_ratios!F10 - Annual_return_and_ratios!F76) -> 0.084729645 | G43: =ABS(Annual_return_and_ratios!G10 - Annual_return_and_ratios!G76) -> 0.019558332 | H43: =ABS(Annual_return_and_ratios!H10 - Annual_return_and_ratios!H76) -> 0.19382456 | I43: =ABS(Annual_return_and_ratios!I10 - Annual_return_and_ratios!I76) -> 0.1964836 | ... M43: =ABS(Annual_return_and_ratios!M10 - Annual_return_and_ratios!M76) -> 0.016349853
A44: Hindustan Unilever Ltd | B44: =ABS(Annual_return_and_ratios!B11 - Annual_return_and_ratios!B77) -> 0.99785611 | C44: =ABS(Annual_return_and_ratios!C11 - Annual_return_and_ratios!C77) -> 1.010169 | D44: =ABS(Annual_return_and_ratios!D11 - Annual_return_and_ratios!D77) -> 0.9304594 | E44: =ABS(Annual_return_and_ratios!E11 - Annual_return_and_ratios!E77) -> 0.97611213 | F44: =ABS(Annual_return_and_ratios!F11 - Annual_return_and_ratios!F77) -> 0.99358942 | G44: =ABS(Annual_return_and_ratios!G11 - Annual_return_and_ratios!G77) -> 0.85005547 | H44: =ABS(Annual_return_and_ratios!H11 - Annual_return_and_ratios!H77) -> 0.83169574 | I44: =ABS(Annual_return_and_ratios!I11 - Annual_return_and_ratios!I77) -> 0.81626862 | ... M44: =ABS(Annual_return_and_ratios!M11 - Annual_return_and_ratios!M77) -> 0.78220867
A45: ICICI Bank Ltd | B45: =ABS(Annual_return_and_ratios!B12 - Annual_return_and_ratios!B78) -> 0.15973355 | C45: =ABS(Annual_return_and_ratios!C12 - Annual_return_and_ratios!C78) -> 0.16279272 | D45: =ABS(Annual_return_and_ratios!D12 - Annual_return_and_ratios!D78) -> 0.16705185 | E45: =ABS(Annual_return_and_ratios!E12 - Annual_return_and_ratios!E78) -> 0.13476276 | F45: =ABS(Annual_return_and_ratios!F12 - Annual_return_and_ratios!F78) -> 0.038682898 | G45: =ABS(Annual_return_and_ratios!G12 - Annual_return_and_ratios!G78) -> 0.0081086488 | H45: =ABS(Annual_return_and_ratios!H12 - Annual_return_and_ratios!H78) -> 0.13858094 | I45: =ABS(Annual_return_and_ratios!I12 - Annual_return_and_ratios!I78) -> 0.12701083 | ... M45: =ABS(Annual_return_and_ratios!M12 - Annual_return_and_ratios!M78) -> 0.25165068
A46: Infosys Ltd | B46: =ABS(Annual_return_and_ratios!B13 - Annual_return_and_ratios!B79) -> 0.8562903 | C46: =ABS(Annual_return_and_ratios!C13 - Annual_return_and_ratios!C79) -> 0.62892837 | D46: =ABS(Annual_return_and_ratios!D13 - Annual_return_and_ratios!D79) -> 0.66265226 | E46: =ABS(Annual_return_and_ratios!E13 - Annual_return_and_ratios!E79) -> 0.62135844 | F46: =ABS(Annual_return_and_ratios!F13 - Annual_return_and_ratios!F79) -> 0.46453642 | G46: =ABS(Annual_return_and_ratios!G13 - Annual_return_and_ratios!G79) -> 0.66075602 | H46: =ABS(Annual_return_and_ratios!H13 - Annual_return_and_ratios!H79) -> 0.97678238 | I46: =ABS(Annual_return_and_ratios!I13 - Annual_return_and_ratios!I79) -> 0.51922098 | ... M46: =ABS(Annual_return_and_ratios!M13 - Annual_return_and_ratios!M79) -> 0.36938684
... A63: UltraTech Cement Ltd | B63: =ABS(Annual_return_and_ratios!B30 - Annual_return_and_ratios!B96) -> 0.36835964 | C63: =ABS(Annual_return_and_ratios!C30 - Annual_return_and_ratios!C96) -> 0.1585364 | D63: =ABS(Annual_return_and_ratios!D30 - Annual_return_and_ratios!D96) -> 0.23090805 | E63: =ABS(Annual_return_and_ratios!E30 - Annual_return_and_ratios!E96) -> 0.16775459 | F63: =ABS(Annual_return_and_ratios!F30 - Annual_return_and_ratios!F96) -> 0.015048151 | G63: =ABS(Annual_return_and_ratios!G30 - Annual_return_and_ratios!G96) -> 0.08547139 | H63: =ABS(Annual_return_and_ratios!H30 - Annual_return_and_ratios!H96) -> 0.16648371 | I63: =ABS(Annual_return_and_ratios!I30 - Annual_return_and_ratios!I96) -> 0.17212871 | ... M63: =ABS(Annual_return_and_ratios!M30 - Annual_return_and_ratios!M96) -> 0.10925843
A67: Profit margin | B67: (PM)2025 | C67: (PM)2024 | D67: (PM)2023 | E67: (PM)2022 | F67: (PM)2021 | G67: (PM)2020 | H67: (PM)2019 | I67: (PM)2018 | J67: (PM)2017 | K67: (PM)2016 | L67: (PM)2015 | M67: (PM)2014
A68: Adani Ports and Special Economic Zone Ltd | B68: =ABS(Annual_return_and_ratios!B2 - Annual_return_and_ratios!B101) -> 1.0183889 | C68: =ABS(Annual_return_and_ratios!C2 - Annual_return_and_ratios!C101) -> 0.90308005 | D68: =ABS(Annual_return_and_ratios!D2 - Annual_return_and_ratios!D101) -> 0.81157571 | E68: =ABS(Annual_return_and_ratios!E2 - Annual_return_and_ratios!E101) -> 0.89728573 | F68: =ABS(Annual_return_and_ratios!F2 - Annual_return_and_ratios!F101) -> 0.90288799 | G68: =ABS(Annual_return_and_ratios!G2 - Annual_return_and_ratios!G101) -> 1.0270003 | H68: =ABS(Annual_return_and_ratios!H2 - Annual_return_and_ratios!H101) -> 0.99185947 | I68: =ABS(Annual_return_and_ratios!I2 - Annual_return_and_ratios!I101) -> 0.99651093 | ... M68: =ABS(Annual_return_and_ratios!M2 - Annual_return_and_ratios!M101) -> 0.9723213
A69: Asian Paints Ltd | B69: =ABS(Annual_return_and_ratios!B3 - Annual_return_and_ratios!B102) -> 0.33054699 | C69: =ABS(Annual_return_and_ratios!C3 - Annual_return_and_ratios!C102) -> 0.4638116 | D69: =ABS(Annual_return_and_ratios!D3 - Annual_return_and_ratios!D102) -> 0.36333293 | E69: =ABS(Annual_return_and_ratios!E3 - Annual_return_and_ratios!E102) -> 0.29639564 | F69: =ABS(Annual_return_and_ratios!F3 - Annual_return_and_ratios!F102) -> 0.41173075 | G69: =ABS(Annual_return_and_ratios!G3 - Annual_return_and_ratios!G102) -> 0.39951157 | H69: =ABS(Annual_return_and_ratios!H3 - Annual_return_and_ratios!H102) -> 0.31358981 | I69: =ABS(Annual_return_and_ratios!I3 - Annual_return_and_ratios!I102) -> 0.36596035 | ... M69: =ABS(Annual_return_and_ratios!M3 - Annual_return_and_ratios!M102) -> 0.28205504
A70: AXIS Bank Ltd | B70: =ABS(Annual_return_and_ratios!B4 - Annual_return_and_ratios!B103) -> 0.6811926 | C70: =ABS(Annual_return_and_ratios!C4 - Annual_return_and_ratios!C103) -> 0.71217953 | D70: =ABS(Annual_return_and_ratios!D4 - Annual_return_and_ratios!D103) -> 0.3590191 | E70: =ABS(Annual_return_and_ratios!E4 - Annual_return_and_ratios!E103) -> 0.63052916 | F70: =ABS(Annual_return_and_ratios!F4 - Annual_return_and_ratios!F103) -> 0.28194118 | G70: =ABS(Annual_return_and_ratios!G4 - Annual_return_and_ratios!G103) -> 0.11642526 | H70: =ABS(Annual_return_and_ratios!H4 - Annual_return_and_ratios!H103) -> 0.22889744 | I70: =ABS(Annual_return_and_ratios!I4 - Annual_return_and_ratios!I103) -> 0.0067287922 | ... M70: =ABS(Annual_return_and_ratios!M4 - Annual_return_and_ratios!M103) -> 0.61395377
A71: Bajaj Finserv Ltd | B71: =ABS(Annual_return_and_ratios!B5 - Annual_return_and_ratios!B104) -> 0.38426271 | C71: =ABS(Annual_return_and_ratios!C5 - Annual_return_and_ratios!C104) -> 0.40911769 | D71: =ABS(Annual_return_and_ratios!D5 - Annual_return_and_ratios!D104) -> 0.46991992 | E71: =ABS(Annual_return_and_ratios!E5 - Annual_return_and_ratios!E104) -> 0.31721879 | F71: =ABS(Annual_return_and_ratios!F5 - Annual_return_and_ratios!F104) -> 0.2924457 | G71: =ABS(Annual_return_and_ratios!G5 - Annual_return_and_ratios!G104) -> 0.34465322 | H71: =ABS(Annual_return_and_ratios!H5 - Annual_return_and_ratios!H104) -> 0.35539724 | I71: =ABS(Annual_return_and_ratios!I5 - Annual_return_and_ratios!I104) -> 0.36314884 | ... M71: =ABS(Annual_return_and_ratios!M5 - Annual_return_and_ratios!M104) -> 0.99423038
A72: Bajaj Finance Ltd | B72: =ABS(Annual_return_and_ratios!B6 - Annual_return_and_ratios!B105) -> 0.7316338 | C72: =ABS(Annual_return_and_ratios!C6 - Annual_return_and_ratios!C105) -> 0.79726415 | D72: =ABS(Annual_return_and_ratios!D6 - Annual_return_and_ratios!D105) -> 0.8806541 | E72: =ABS(Annual_return_and_ratios!E6 - Annual_return_and_ratios!E105) -> 0.65793121 | F72: =ABS(Annual_return_and_ratios!F6 - Annual_return_and_ratios!F105) -> 0.42275877 | G72: =ABS(Annual_return_and_ratios!G6 - Annual_return_and_ratios!G105) -> 0.62099384 | H72: =ABS(Annual_return_and_ratios!H6 - Annual_return_and_ratios!H105) -> 0.62163464 | I72: =ABS(Annual_return_and_ratios!I6 - Annual_return_and_ratios!I105) -> 0.58086856 | ... M72: =ABS(Annual_return_and_ratios!M6 - Annual_return_and_ratios!M105) -> 0.49990591
A73: Bharat Electronics Ltd | B73: =ABS(Annual_return_and_ratios!B7 - Annual_return_and_ratios!B106) -> 0.66191908 | C73: =ABS(Annual_return_and_ratios!C7 - Annual_return_and_ratios!C106) -> 0.54053342 | D73: =ABS(Annual_return_and_ratios!D7 - Annual_return_and_ratios!D106) -> 0.47972016 | E73: =ABS(Annual_return_and_ratios!E7 - Annual_return_and_ratios!E106) -> 0.42465703 | F73: =ABS(Annual_return_and_ratios!F7 - Annual_return_and_ratios!F106) -> 0.39594565 | G73: =ABS(Annual_return_and_ratios!G7 - Annual_return_and_ratios!G106) -> 0.42708581 | H73: =ABS(Annual_return_and_ratios!H7 - Annual_return_and_ratios!H106) -> 0.49648326 | I73: =ABS(Annual_return_and_ratios!I7 - Annual_return_and_ratios!I106) -> 0.41463978 | ... M73: =ABS(Annual_return_and_ratios!M7 - Annual_return_and_ratios!M106) -> 0.43938174
A74: Bharti Airtel Ltd | B74: =ABS(Annual_return_and_ratios!B8 - Annual_return_and_ratios!B107) -> 0.57610146 | C74: =ABS(Annual_return_and_ratios!C8 - Annual_return_and_ratios!C107) -> 0.057000288 | D74: =ABS(Annual_return_and_ratios!D8 - Annual_return_and_ratios!D107) -> 0.24438895 | E74: =ABS(Annual_return_and_ratios!E8 - Annual_return_and_ratios!E107) -> 0.10728892 | F74: =ABS(Annual_return_and_ratios!F8 - Annual_return_and_ratios!F107) -> 0.012751318 | G74: =ABS(Annual_return_and_ratios!G8 - Annual_return_and_ratios!G107) -> 0.028987966 | H74: =ABS(Annual_return_and_ratios!H8 - Annual_return_and_ratios!H107) -> 0.046174275 | I74: =ABS(Annual_return_and_ratios!I8 - Annual_return_and_ratios!I107) -> 0.008874348 | ... M74: =ABS(Annual_return_and_ratios!M8 - Annual_return_and_ratios!M107) -> 0.077400361
A75: HCL Technologies Ltd | B75: =ABS(Annual_return_and_ratios!B9 - Annual_return_and_ratios!B108) -> 0.44786546 | C75: =ABS(Annual_return_and_ratios!C9 - Annual_return_and_ratios!C108) -> 0.40254485 | D75: =ABS(Annual_return_and_ratios!D9 - Annual_return_and_ratios!D108) -> 0.44594581 | E75: =ABS(Annual_return_and_ratios!E9 - Annual_return_and_ratios!E108) -> 0.46549167 | F75: =ABS(Annual_return_and_ratios!F9 - Annual_return_and_ratios!F108) -> 0.37644789 | G75: =ABS(Annual_return_and_ratios!G9 - Annual_return_and_ratios!G108) -> 0.49482213 | H75: =ABS(Annual_return_and_ratios!H9 - Annual_return_and_ratios!H108) -> 0.50299798 | I75: =ABS(Annual_return_and_ratios!I9 - Annual_return_and_ratios!I108) -> 0.51864213 | ... M75: =ABS(Annual_return_and_ratios!M9 - Annual_return_and_ratios!M108) -> 0.57402768
A76: HDFC Bank Ltd | B76: =ABS(Annual_return_and_ratios!B10 - Annual_return_and_ratios!B109) -> 0.67910758 | C76: =ABS(Annual_return_and_ratios!C10 - Annual_return_and_ratios!C109) -> 0.73684709 | D76: =ABS(Annual_return_and_ratios!D10 - Annual_return_and_ratios!D109) -> 0.84118907 | E76: =ABS(Annual_return_and_ratios!E10 - Annual_return_and_ratios!E109) -> 0.90182733 | F76: =ABS(Annual_return_and_ratios!F10 - Annual_return_and_ratios!F109) -> 0.75524679 | G76: =ABS(Annual_return_and_ratios!G10 - Annual_return_and_ratios!G109) -> 0.7291553 | H76: =ABS(Annual_return_and_ratios!H10 - Annual_return_and_ratios!H109) -> 0.64147222 | I76: =ABS(Annual_return_and_ratios!I10 - Annual_return_and_ratios!I109) -> 0.65227562 | ... M76: =ABS(Annual_return_and_ratios!M10 - Annual_return_and_ratios!M109) -> 0.62130582
A77: Hindustan Unilever Ltd | B77: =ABS(Annual_return_and_ratios!B11 - Annual_return_and_ratios!B110) -> 0.51720831 | C77: =ABS(Annual_return_and_ratios!C11 - Annual_return_and_ratios!C110) -> 0.51992905 | D77: =ABS(Annual_return_and_ratios!D11 - Annual_return_and_ratios!D110) -> 0.49439821 | E77: =ABS(Annual_return_and_ratios!E11 - Annual_return_and_ratios!E110) -> 0.53426276 | F77: =ABS(Annual_return_and_ratios!F11 - Annual_return_and_ratios!F110) -> 0.51581928 | G77: =ABS(Annual_return_and_ratios!G11 - Annual_return_and_ratios!G110) -> 0.49645689 | H77: =ABS(Annual_return_and_ratios!H11 - Annual_return_and_ratios!H110) -> 0.44960735 | I77: =ABS(Annual_return_and_ratios!I11 - Annual_return_and_ratios!I110) -> 0.41568421 | ... M77: =ABS(Annual_return_and_ratios!M11 - Annual_return_and_ratios!M110) -> 0.38365512
A78: ICICI Bank Ltd | B78: =ABS(Annual_return_and_ratios!B12 - Annual_return_and_ratios!B111) -> 0.89700731 | C78: =ABS(Annual_return_and_ratios!C12 - Annual_return_and_ratios!C111) -> 0.86272926 | D78: =ABS(Annual_return_and_ratios!D12 - Annual_return_and_ratios!D111) -> 0.86929883 | E78: =ABS(Annual_return_and_ratios!E12 - Annual_return_and_ratios!E111) -> 0.82051915 | F78: =ABS(Annual_return_and_ratios!F12 - Annual_return_and_ratios!F111) -> 0.65695915 | G78: =ABS(Annual_return_and_ratios!G12 - Annual_return_and_ratios!G111) -> 0.40979687 | H78: =ABS(Annual_return_and_ratios!H12 - Annual_return_and_ratios!H111) -> 0.19935687 | I78: =ABS(Annual_return_and_ratios!I12 - Annual_return_and_ratios!I111) -> 0.43706944 | ... M78: =ABS(Annual_return_and_ratios!M12 - Annual_return_and_ratios!M111) -> 0.71212217
A79: Infosys Ltd | B79: =ABS(Annual_return_and_ratios!B13 - Annual_return_and_ratios!B112) -> 0.49617367 | C79: =ABS(Annual_return_and_ratios!C13 - Annual_return_and_ratios!C112) -> 0.51721509 | D79: =ABS(Annual_return_and_ratios!D13 - Annual_return_and_ratios!D112) -> 0.52335752 | E79: =ABS(Annual_return_and_ratios!E13 - Annual_return_and_ratios!E112) -> 0.53147564 | F79: =ABS(Annual_return_and_ratios!F13 - Annual_return_and_ratios!F112) -> 0.52569531 | G79: =ABS(Annual_return_and_ratios!G13 - Annual_return_and_ratios!G112) -> 0.57334616 | H79: =ABS(Annual_return_and_ratios!H13 - Annual_return_and_ratios!H112) -> 0.55112972 | I79: =ABS(Annual_return_and_ratios!I13 - Annual_return_and_ratios!I112) -> 0.69799284 | ... M79: =ABS(Annual_return_and_ratios!M13 - Annual_return_and_ratios!M112) -> 0.64299098
... A96: UltraTech Cement Ltd | B96: =ABS(Annual_return_and_ratios!B30 - Annual_return_and_ratios!B129) -> 0.22191794 | C96: =ABS(Annual_return_and_ratios!C30 - Annual_return_and_ratios!C129) -> 0.27418107 | D96: =ABS(Annual_return_and_ratios!D30 - Annual_return_and_ratios!D129) -> 0.22052589 | E96: =ABS(Annual_return_and_ratios!E30 - Annual_return_and_ratios!E129) -> 0.42710866 | F96: =ABS(Annual_return_and_ratios!F30 - Annual_return_and_ratios!F129) -> 0.30583187 | G96: =ABS(Annual_return_and_ratios!G30 - Annual_return_and_ratios!G129) -> 0.42226141 | H96: =ABS(Annual_return_and_ratios!H30 - Annual_return_and_ratios!H129) -> 0.16497316 | I96: =ABS(Annual_return_and_ratios!I30 - Annual_return_and_ratios!I129) -> 0.21147468 | ... M96: =ABS(Annual_return_and_ratios!M30 - Annual_return_and_ratios!M129) -> 0.28731256
A100: Price to BV | B100: (P/B)2025 | C100: (P/B)2024 | D100: (P/B)2023 | E100: (P/B)2022 | F100: (P/B)2021 | G100: (P/B)2020 | H100: (P/B)2019 | I100: (P/B)2018 | J100: (P/B)2017 | K100: (P/B)2016 | L100: (P/B)2015 | M100: (P/B)2014
A101: Adani Ports and Special Economic Zone Ltd | B101: =ABS(Annual_return_and_ratios!B2 - Annual_return_and_ratios!B134) -> 0.8411945 | C101: =ABS(Annual_return_and_ratios!C2 - Annual_return_and_ratios!C134) -> 0.67471598 | D101: =ABS(Annual_return_and_ratios!D2 - Annual_return_and_ratios!D134) -> 0.90147831 | E101: =ABS(Annual_return_and_ratios!E2 - Annual_return_and_ratios!E134) -> 0.8066356 | F101: =ABS(Annual_return_and_ratios!F2 - Annual_return_and_ratios!F134) -> 0.69036853 | G101: =ABS(Annual_return_and_ratios!G2 - Annual_return_and_ratios!G134) -> 0.97597981 | H101: =ABS(Annual_return_and_ratios!H2 - Annual_return_and_ratios!H134) -> 0.86914962 | I101: =ABS(Annual_return_and_ratios!I2 - Annual_return_and_ratios!I134) -> 0.85583915 | ... M101: =ABS(Annual_return_and_ratios!M2 - Annual_return_and_ratios!M134) -> 0.77536884
A102: Asian Paints Ltd | B102: =ABS(Annual_return_and_ratios!B3 - Annual_return_and_ratios!B135) -> 0.39166062 | C102: =ABS(Annual_return_and_ratios!C3 - Annual_return_and_ratios!C135) -> 0.19191275 | D102: =ABS(Annual_return_and_ratios!D3 - Annual_return_and_ratios!D135) -> 0.081276959 | E102: =ABS(Annual_return_and_ratios!E3 - Annual_return_and_ratios!E135) -> 0.017684069 | F102: =ABS(Annual_return_and_ratios!F3 - Annual_return_and_ratios!F135) -> 0.03472095 | G102: =ABS(Annual_return_and_ratios!G3 - Annual_return_and_ratios!G135) -> 0.11363782 | H102: =ABS(Annual_return_and_ratios!H3 - Annual_return_and_ratios!H135) -> 0.13849335 | I102: =ABS(Annual_return_and_ratios!I3 - Annual_return_and_ratios!I135) -> 0.30063241 | ... M102: =ABS(Annual_return_and_ratios!M3 - Annual_return_and_ratios!M135) -> 0.27701352
A103: AXIS Bank Ltd | B103: =ABS(Annual_return_and_ratios!B4 - Annual_return_and_ratios!B136) -> 0.95617127 | C103: =ABS(Annual_return_and_ratios!C4 - Annual_return_and_ratios!C136) -> 0.92930415 | D103: =ABS(Annual_return_and_ratios!D4 - Annual_return_and_ratios!D136) -> 0.92969366 | E103: =ABS(Annual_return_and_ratios!E4 - Annual_return_and_ratios!E136) -> 0.94448773 | F103: =ABS(Annual_return_and_ratios!F4 - Annual_return_and_ratios!F136) -> 0.89010671 | G103: =ABS(Annual_return_and_ratios!G4 - Annual_return_and_ratios!G136) -> 1.0377912 | H103: =ABS(Annual_return_and_ratios!H4 - Annual_return_and_ratios!H136) -> 0.85471727 | I103: =ABS(Annual_return_and_ratios!I4 - Annual_return_and_ratios!I136) -> 0.94254539 | ... M103: =ABS(Annual_return_and_ratios!M4 - Annual_return_and_ratios!M136) -> 0.94028819
A104: Bajaj Finserv Ltd | B104: =ABS(Annual_return_and_ratios!B5 - Annual_return_and_ratios!B137) -> 0.79037737 | C104: =ABS(Annual_return_and_ratios!C5 - Annual_return_and_ratios!C137) -> 0.7874088 | D104: =ABS(Annual_return_and_ratios!D5 - Annual_return_and_ratios!D137) -> 0.82363188 | E104: =ABS(Annual_return_and_ratios!E5 - Annual_return_and_ratios!E137) -> 0.61480314 | F104: =ABS(Annual_return_and_ratios!F5 - Annual_return_and_ratios!F137) -> 0.73671906 | G104: =ABS(Annual_return_and_ratios!G5 - Annual_return_and_ratios!G137) -> 0.94240832 | H104: =ABS(Annual_return_and_ratios!H5 - Annual_return_and_ratios!H137) -> 0.75921719 | I104: =ABS(Annual_return_and_ratios!I5 - Annual_return_and_ratios!I137) -> 0.80600228 | ... M104: =ABS(Annual_return_and_ratios!M5 - Annual_return_and_ratios!M137) -> 0.98348317
A105: Bajaj Finance Ltd | B105: =ABS(Annual_return_and_ratios!B6 - Annual_return_and_ratios!B138) -> 0.70800297 | C105: =ABS(Annual_return_and_ratios!C6 - Annual_return_and_ratios!C138) -> 0.69786139 | D105: =ABS(Annual_return_and_ratios!D6 - Annual_return_and_ratios!D138) -> 0.70810305 | E105: =ABS(Annual_return_and_ratios!E6 - Annual_return_and_ratios!E138) -> 0.43747437 | F105: =ABS(Annual_return_and_ratios!F6 - Annual_return_and_ratios!F138) -> 0.48022788 | G105: =ABS(Annual_return_and_ratios!G6 - Annual_return_and_ratios!G138) -> 0.82664787 | H105: =ABS(Annual_return_and_ratios!H6 - Annual_return_and_ratios!H138) -> 0.49013464 | I105: =ABS(Annual_return_and_ratios!I6 - Annual_return_and_ratios!I138) -> 0.66629996 | ... M105: =ABS(Annual_return_and_ratios!M6 - Annual_return_and_ratios!M138) -> 0.90064226
A106: Bharat Electronics Ltd | B106: =ABS(Annual_return_and_ratios!B7 - Annual_return_and_ratios!B139) -> 0.38062995 | C106: =ABS(Annual_return_and_ratios!C7 - Annual_return_and_ratios!C139) -> 0.46819763 | D106: =ABS(Annual_return_and_ratios!D7 - Annual_return_and_ratios!D139) -> 0.73177674 | E106: =ABS(Annual_return_and_ratios!E7 - Annual_return_and_ratios!E139) -> 0.77415914 | F106: =ABS(Annual_return_and_ratios!F7 - Annual_return_and_ratios!F139) -> 0.8515703 | G106: =ABS(Annual_return_and_ratios!G7 - Annual_return_and_ratios!G139) -> 0.96704669 | H106: =ABS(Annual_return_and_ratios!H7 - Annual_return_and_ratios!H139) -> 0.95252493 | I106: =ABS(Annual_return_and_ratios!I7 - Annual_return_and_ratios!I139) -> 0.81299296 | ... M106: =ABS(Annual_return_and_ratios!M7 - Annual_return_and_ratios!M139) -> 0.9861357
A107: Bharti Airtel Ltd | B107: =ABS(Annual_return_and_ratios!B8 - Annual_return_and_ratios!B140) -> 0.5835536 | C107: =ABS(Annual_return_and_ratios!C8 - Annual_return_and_ratios!C140) -> 0.60312213 | D107: =ABS(Annual_return_and_ratios!D8 - Annual_return_and_ratios!D140) -> 0.78873111 | E107: =ABS(Annual_return_and_ratios!E8 - Annual_return_and_ratios!E140) -> 0.65615699 | F107: =ABS(Annual_return_and_ratios!F8 - Annual_return_and_ratios!F140) -> 0.76694572 | G107: =ABS(Annual_return_and_ratios!G8 - Annual_return_and_ratios!G140) -> 0.85249329 | H107: =ABS(Annual_return_and_ratios!H8 - Annual_return_and_ratios!H140) -> 0.97198499 | I107: =ABS(Annual_return_and_ratios!I8 - Annual_return_and_ratios!I140) -> 0.91885155 | ... M107: =ABS(Annual_return_and_ratios!M8 - Annual_return_and_ratios!M140) -> 0.92905033
A108: HCL Technologies Ltd | B108: =ABS(Annual_return_and_ratios!B9 - Annual_return_and_ratios!B141) -> 0.69113198 | C108: =ABS(Annual_return_and_ratios!C9 - Annual_return_and_ratios!C141) -> 0.66762888 | D108: =ABS(Annual_return_and_ratios!D9 - Annual_return_and_ratios!D141) -> 0.79775181 | E108: =ABS(Annual_return_and_ratios!E9 - Annual_return_and_ratios!E141) -> 0.74520256 | F108: =ABS(Annual_return_and_ratios!F9 - Annual_return_and_ratios!F141) -> 0.72549224 | G108: =ABS(Annual_return_and_ratios!G9 - Annual_return_and_ratios!G141) -> 0.94605523 | H108: =ABS(Annual_return_and_ratios!H9 - Annual_return_and_ratios!H141) -> 0.84421845 | I108: =ABS(Annual_return_and_ratios!I9 - Annual_return_and_ratios!I141) -> 0.83613289 | ... M108: =ABS(Annual_return_and_ratios!M9 - Annual_return_and_ratios!M141) -> 0.69556794
A109: HDFC Bank Ltd | B109: =ABS(Annual_return_and_ratios!B10 - Annual_return_and_ratios!B142) -> 0.88513824 | C109: =ABS(Annual_return_and_ratios!C10 - Annual_return_and_ratios!C142) -> 0.92443017 | D109: =ABS(Annual_return_and_ratios!D10 - Annual_return_and_ratios!D142) -> 0.86604037 | E109: =ABS(Annual_return_and_ratios!E10 - Annual_return_and_ratios!E142) -> 0.86286553 | F109: =ABS(Annual_return_and_ratios!F10 - Annual_return_and_ratios!F142) -> 0.779963 | G109: =ABS(Annual_return_and_ratios!G10 - Annual_return_and_ratios!G142) -> 0.9225939 | H109: =ABS(Annual_return_and_ratios!H10 - Annual_return_and_ratios!H142) -> 0.79709645 | I109: =ABS(Annual_return_and_ratios!I10 - Annual_return_and_ratios!I142) -> 0.76856239 | ... M109: =ABS(Annual_return_and_ratios!M10 - Annual_return_and_ratios!M142) -> 0.80465961
A110: Hindustan Unilever Ltd | B110: =ABS(Annual_return_and_ratios!B11 - Annual_return_and_ratios!B143) -> 0.42250585 | C110: =ABS(Annual_return_and_ratios!C11 - Annual_return_and_ratios!C143) -> 0.4551756 | D110: =ABS(Annual_return_and_ratios!D11 - Annual_return_and_ratios!D143) -> 0.33328362 | E110: =ABS(Annual_return_and_ratios!E11 - Annual_return_and_ratios!E143) -> 0.49456202 | F110: =ABS(Annual_return_and_ratios!F11 - Annual_return_and_ratios!F143) -> 0.34459528 | G110: =ABS(Annual_return_and_ratios!G11 - Annual_return_and_ratios!G143) -> 0.025133487 | H110: =ABS(Annual_return_and_ratios!H11 - Annual_return_and_ratios!H143) -> 0.021783993 | I110: =ABS(Annual_return_and_ratios!I11 - Annual_return_and_ratios!I143) -> 0.033005659 | ... M110: =ABS(Annual_return_and_ratios!M11 - Annual_return_and_ratios!M143) -> 0.027625274
A111: ICICI Bank Ltd | B111: =ABS(Annual_return_and_ratios!B12 - Annual_return_and_ratios!B144) -> 0.86737448 | C111: =ABS(Annual_return_and_ratios!C12 - Annual_return_and_ratios!C144) -> 0.86834299 | D111: =ABS(Annual_return_and_ratios!D12 - Annual_return_and_ratios!D144) -> 0.8753013 | E111: =ABS(Annual_return_and_ratios!E12 - Annual_return_and_ratios!E144) -> 0.87615644 | F111: =ABS(Annual_return_and_ratios!F12 - Annual_return_and_ratios!F144) -> 0.86605248 | G111: =ABS(Annual_return_and_ratios!G12 - Annual_return_and_ratios!G144) -> 0.97161601 | H111: =ABS(Annual_return_and_ratios!H12 - Annual_return_and_ratios!H144) -> 0.89806803 | I111: =ABS(Annual_return_and_ratios!I12 - Annual_return_and_ratios!I144) -> 0.95951369 | ... M111: =ABS(Annual_return_and_ratios!M12 - Annual_return_and_ratios!M144) -> 0.93458838
A112: Infosys Ltd | B112: =ABS(Annual_return_and_ratios!B13 - Annual_return_and_ratios!B145) -> 0.65395678 | C112: =ABS(Annual_return_and_ratios!C13 - Annual_return_and_ratios!C145) -> 0.63860741 | D112: =ABS(Annual_return_and_ratios!D13 - Annual_return_and_ratios!D145) -> 0.61915163 | E112: =ABS(Annual_return_and_ratios!E13 - Annual_return_and_ratios!E145) -> 0.40331033 | F112: =ABS(Annual_return_and_ratios!F13 - Annual_return_and_ratios!F145) -> 0.54161742 | G112: =ABS(Annual_return_and_ratios!G13 - Annual_return_and_ratios!G145) -> 0.82872274 | H112: =ABS(Annual_return_and_ratios!H13 - Annual_return_and_ratios!H145) -> 0.7480972 | I112: =ABS(Annual_return_and_ratios!I13 - Annual_return_and_ratios!I145) -> 0.8304424 | ... M112: =ABS(Annual_return_and_ratios!M13 - Annual_return_and_ratios!M145) -> 0.80109162
... A129: UltraTech Cement Ltd | B129: =ABS(Annual_return_and_ratios!B30 - Annual_return_and_ratios!B162) -> 0.77022546 | C129: =ABS(Annual_return_and_ratios!C30 - Annual_return_and_ratios!C162) -> 0.76956241 | D129: =ABS(Annual_return_and_ratios!D30 - Annual_return_and_ratios!D162) -> 0.81154078 | E129: =ABS(Annual_return_and_ratios!E30 - Annual_return_and_ratios!E162) -> 0.844684 | F129: =ABS(Annual_return_and_ratios!F30 - Annual_return_and_ratios!F162) -> 0.7419205 | G129: =ABS(Annual_return_and_ratios!G30 - Annual_return_and_ratios!G162) -> 0.93433267 | H129: =ABS(Annual_return_and_ratios!H30 - Annual_return_and_ratios!H162) -> 0.8387065 | I129: =ABS(Annual_return_and_ratios!I30 - Annual_return_and_ratios!I162) -> 0.82543553 | ... M129: =ABS(Annual_return_and_ratios!M30 - Annual_return_and_ratios!M162) -> 0.84151376
A133: Price to Earng | B133: (P/E)2025 | C133: (P/E)2024 | D133: (P/E)2023 | E133: (P/E)2022 | F133: (P/E)2021 | G133: (P/E)2020 | H133: (P/E)2019 | I133: (P/E)2018 | J133: (P/E)2017 | K133: (P/E)2016 | L133: (P/E)2015 | M133: (P/E)2014
A134: Adani Ports and Special Economic Zone Ltd | B134: =ABS(Annual_return_and_ratios!B2 - Annual_return_and_ratios!B167) -> 0.87228365 | C134: =ABS(Annual_return_and_ratios!C2 - Annual_return_and_ratios!C167) -> 0.67871048 | D134: =ABS(Annual_return_and_ratios!D2 - Annual_return_and_ratios!D167) -> 0.8440098 | E134: =ABS(Annual_return_and_ratios!E2 - Annual_return_and_ratios!E167) -> 0.74882792 | F134: =ABS(Annual_return_and_ratios!F2 - Annual_return_and_ratios!F167) -> 0.70843595 | G134: =ABS(Annual_return_and_ratios!G2 - Annual_return_and_ratios!G167) -> 0.96285971 | H134: =ABS(Annual_return_and_ratios!H2 - Annual_return_and_ratios!H167) -> 0.87529193 | I134: =ABS(Annual_return_and_ratios!I2 - Annual_return_and_ratios!I167) -> 0.87668456 | ... M134: =ABS(Annual_return_and_ratios!M2 - Annual_return_and_ratios!M167) -> 0.83342108
A135: Asian Paints Ltd | B135: =ABS(Annual_return_and_ratios!B3 - Annual_return_and_ratios!B168) -> 0.76566738 | C135: =ABS(Annual_return_and_ratios!C3 - Annual_return_and_ratios!C168) -> 0.61654655 | D135: =ABS(Annual_return_and_ratios!D3 - Annual_return_and_ratios!D168) -> 0.49857093 | E135: =ABS(Annual_return_and_ratios!E3 - Annual_return_and_ratios!E168) -> 0.18934935 | F135: =ABS(Annual_return_and_ratios!F3 - Annual_return_and_ratios!F168) -> 0.34631261 | G135: =ABS(Annual_return_and_ratios!G3 - Annual_return_and_ratios!G168) -> 0.53089137 | H135: =ABS(Annual_return_and_ratios!H3 - Annual_return_and_ratios!H168) -> 0.45260004 | I135: =ABS(Annual_return_and_ratios!I3 - Annual_return_and_ratios!I168) -> 0.59371268 | ... M135: =ABS(Annual_return_and_ratios!M3 - Annual_return_and_ratios!M168) -> 0.66639329
A136: AXIS Bank Ltd | B136: =ABS(Annual_return_and_ratios!B4 - Annual_return_and_ratios!B169) -> 0.94511499 | C136: =ABS(Annual_return_and_ratios!C4 - Annual_return_and_ratios!C169) -> 0.93177211 | D136: =ABS(Annual_return_and_ratios!D4 - Annual_return_and_ratios!D169) -> 0.82556933 | E136: =ABS(Annual_return_and_ratios!E4 - Annual_return_and_ratios!E169) -> 0.90444087 | F136: =ABS(Annual_return_and_ratios!F4 - Annual_return_and_ratios!F169) -> 0.74859125 | G136: =ABS(Annual_return_and_ratios!G4 - Annual_return_and_ratios!G169) -> 0.61545908 | H136: =ABS(Annual_return_and_ratios!H4 - Annual_return_and_ratios!H169) -> 0.6726601 | I136: =ABS(Annual_return_and_ratios!I4 - Annual_return_and_ratios!I169) -> 0.0035987805 | ... M136: =ABS(Annual_return_and_ratios!M4 - Annual_return_and_ratios!M169) -> 0.93863373
A137: Bajaj Finserv Ltd | B137: =ABS(Annual_return_and_ratios!B5 - Annual_return_and_ratios!B170) -> 0.013268901 | C137: =ABS(Annual_return_and_ratios!C5 - Annual_return_and_ratios!C170) -> 0.021027313 | D137: =ABS(Annual_return_and_ratios!D5 - Annual_return_and_ratios!D170) -> 0.01579449 | E137: =ABS(Annual_return_and_ratios!E5 - Annual_return_and_ratios!E170) -> 0.78368914 | F137: =ABS(Annual_return_and_ratios!F5 - Annual_return_and_ratios!F170) -> 0.81988245 | G137: =ABS(Annual_return_and_ratios!G5 - Annual_return_and_ratios!G170) -> 0.97645262 | H137: =ABS(Annual_return_and_ratios!H5 - Annual_return_and_ratios!H170) -> 0.89743975 | I137: =ABS(Annual_return_and_ratios!I5 - Annual_return_and_ratios!I170) -> 0.93983308 | ... M137: =ABS(Annual_return_and_ratios!M5 - Annual_return_and_ratios!M170) -> 0.88774652
A138: Bajaj Finance Ltd | B138: =ABS(Annual_return_and_ratios!B6 - Annual_return_and_ratios!B171) -> 0.97292886 | C138: =ABS(Annual_return_and_ratios!C6 - Annual_return_and_ratios!C171) -> 0.97209173 | D138: =ABS(Annual_return_and_ratios!D6 - Annual_return_and_ratios!D171) -> 1.0094155 | E138: =ABS(Annual_return_and_ratios!E6 - Annual_return_and_ratios!E171) -> 0.030882716 | F138: =ABS(Annual_return_and_ratios!F6 - Annual_return_and_ratios!F171) -> 0.085722308 | G138: =ABS(Annual_return_and_ratios!G6 - Annual_return_and_ratios!G171) -> 0.61439378 | H138: =ABS(Annual_return_and_ratios!H6 - Annual_return_and_ratios!H171) -> 0.12531114 | I138: =ABS(Annual_return_and_ratios!I6 - Annual_return_and_ratios!I171) -> 0.074541336 | ... M138: =ABS(Annual_return_and_ratios!M6 - Annual_return_and_ratios!M171) -> 0.956893
A139: Bharat Electronics Ltd | B139: =ABS(Annual_return_and_ratios!B7 - Annual_return_and_ratios!B172) -> 0.66675257 | C139: =ABS(Annual_return_and_ratios!C7 - Annual_return_and_ratios!C172) -> 0.67284941 | D139: =ABS(Annual_return_and_ratios!D7 - Annual_return_and_ratios!D172) -> 0.81791847 | E139: =ABS(Annual_return_and_ratios!E7 - Annual_return_and_ratios!E172) -> 0.8240402 | F139: =ABS(Annual_return_and_ratios!F7 - Annual_return_and_ratios!F172) -> 0.8762559 | G139: =ABS(Annual_return_and_ratios!G7 - Annual_return_and_ratios!G172) -> 0.974056 | H139: =ABS(Annual_return_and_ratios!H7 - Annual_return_and_ratios!H172) -> 0.98118371 | I139: =ABS(Annual_return_and_ratios!I7 - Annual_return_and_ratios!I172) -> 0.84557363 | ... M139: =ABS(Annual_return_and_ratios!M7 - Annual_return_and_ratios!M172) -> 0.96401934
A140: Bharti Airtel Ltd | B140: =ABS(Annual_return_and_ratios!B8 - Annual_return_and_ratios!B173) -> 0.76796494 | C140: =ABS(Annual_return_and_ratios!C8 - Annual_return_and_ratios!C173) -> 0.19276549 | D140: =ABS(Annual_return_and_ratios!D8 - Annual_return_and_ratios!D173) -> 0.61511582 | E140: =ABS(Annual_return_and_ratios!E8 - Annual_return_and_ratios!E173) -> 0.16640328 | F140: =ABS(Annual_return_and_ratios!F8 - Annual_return_and_ratios!F173) -> 0.98724868 | G140: =ABS(Annual_return_and_ratios!G8 - Annual_return_and_ratios!G173) -> 0.97101203 | H140: =ABS(Annual_return_and_ratios!H8 - Annual_return_and_ratios!H173) -> 0.015063661 | I140: =ABS(Annual_return_and_ratios!I8 - Annual_return_and_ratios!I173) -> 0.012324354 | ... M140: =ABS(Annual_return_and_ratios!M8 - Annual_return_and_ratios!M173) -> 0.64592381
A141: HCL Technologies Ltd | B141: =ABS(Annual_return_and_ratios!B9 - Annual_return_and_ratios!B174) -> 0.8325318 | C141: =ABS(Annual_return_and_ratios!C9 - Annual_return_and_ratios!C174) -> 0.78967074 | D141: =ABS(Annual_return_and_ratios!D9 - Annual_return_and_ratios!D174) -> 0.8813028 | E141: =ABS(Annual_return_and_ratios!E9 - Annual_return_and_ratios!E174) -> 0.83308386 | F141: =ABS(Annual_return_and_ratios!F9 - Annual_return_and_ratios!F174) -> 0.77009755 | G141: =ABS(Annual_return_and_ratios!G9 - Annual_return_and_ratios!G174) -> 0.97673328 | H141: =ABS(Annual_return_and_ratios!H9 - Annual_return_and_ratios!H174) -> 0.91442629 | I141: =ABS(Annual_return_and_ratios!I9 - Annual_return_and_ratios!I174) -> 0.90784342 | ... M141: =ABS(Annual_return_and_ratios!M9 - Annual_return_and_ratios!M174) -> 0.87236615
A142: HDFC Bank Ltd | B142: =ABS(Annual_return_and_ratios!B10 - Annual_return_and_ratios!B175) -> 0.85783518 | C142: =ABS(Annual_return_and_ratios!C10 - Annual_return_and_ratios!C175) -> 0.91306637 | D142: =ABS(Annual_return_and_ratios!D10 - Annual_return_and_ratios!D175) -> 0.86733722 | E142: =ABS(Annual_return_and_ratios!E10 - Annual_return_and_ratios!E175) -> 0.86084625 | F142: =ABS(Annual_return_and_ratios!F10 - Annual_return_and_ratios!F175) -> 0.77814687 | G142: =ABS(Annual_return_and_ratios!G10 - Annual_return_and_ratios!G175) -> 0.91740944 | H142: =ABS(Annual_return_and_ratios!H10 - Annual_return_and_ratios!H175) -> 0.78013262 | I142: =ABS(Annual_return_and_ratios!I10 - Annual_return_and_ratios!I175) -> 0.78830805 | ... M142: =ABS(Annual_return_and_ratios!M10 - Annual_return_and_ratios!M175) -> 0.85409766
A143: Hindustan Unilever Ltd | B143: =ABS(Annual_return_and_ratios!B11 - Annual_return_and_ratios!B176) -> 0.6188707 | C143: =ABS(Annual_return_and_ratios!C11 - Annual_return_and_ratios!C176) -> 0.61378906 | D143: =ABS(Annual_return_and_ratios!D11 - Annual_return_and_ratios!D176) -> 0.51856506 | E143: =ABS(Annual_return_and_ratios!E11 - Annual_return_and_ratios!E176) -> 0.59677793 | F143: =ABS(Annual_return_and_ratios!F11 - Annual_return_and_ratios!F176) -> 0.42733861 | G143: =ABS(Annual_return_and_ratios!G11 - Annual_return_and_ratios!G176) -> 0.38866878 | H143: =ABS(Annual_return_and_ratios!H11 - Annual_return_and_ratios!H176) -> 0.50198673 | I143: =ABS(Annual_return_and_ratios!I11 - Annual_return_and_ratios!I176) -> 0.53939828 | ... M143: =ABS(Annual_return_and_ratios!M11 - Annual_return_and_ratios!M176) -> 0.73882988
A144: ICICI Bank Ltd | B144: =ABS(Annual_return_and_ratios!B12 - Annual_return_and_ratios!B177) -> 0.87675736 | C144: =ABS(Annual_return_and_ratios!C12 - Annual_return_and_ratios!C177) -> 0.88523864 | D144: =ABS(Annual_return_and_ratios!D12 - Annual_return_and_ratios!D177) -> 0.87851036 | E144: =ABS(Annual_return_and_ratios!E12 - Annual_return_and_ratios!E177) -> 0.85656039 | F144: =ABS(Annual_return_and_ratios!F12 - Annual_return_and_ratios!F177) -> 0.82205962 | G144: =ABS(Annual_return_and_ratios!G12 - Annual_return_and_ratios!G177) -> 0.87162455 | H144: =ABS(Annual_return_and_ratios!H12 - Annual_return_and_ratios!H177) -> 0.49809069 | I144: =ABS(Annual_return_and_ratios!I12 - Annual_return_and_ratios!I177) -> 0.84328105 | ... M144: =ABS(Annual_return_and_ratios!M12 - Annual_return_and_ratios!M177) -> 0.91953329
A145: Infosys Ltd | B145: =ABS(Annual_return_and_ratios!B13 - Annual_return_and_ratios!B178) -> 0.83517974 | C145: =ABS(Annual_return_and_ratios!C13 - Annual_return_and_ratios!C178) -> 0.84090144 | D145: =ABS(Annual_return_and_ratios!D13 - Annual_return_and_ratios!D178) -> 0.86591972 | E145: =ABS(Annual_return_and_ratios!E13 - Annual_return_and_ratios!E178) -> 0.70939578 | F145: =ABS(Annual_return_and_ratios!F13 - Annual_return_and_ratios!F178) -> 0.72238498 | G145: =ABS(Annual_return_and_ratios!G13 - Annual_return_and_ratios!G178) -> 0.91998805 | H145: =ABS(Annual_return_and_ratios!H13 - Annual_return_and_ratios!H178) -> 0.84867836 | I145: =ABS(Annual_return_and_ratios!I13 - Annual_return_and_ratios!I178) -> 0.90482155 | ... M145: =ABS(Annual_return_and_ratios!M13 - Annual_return_and_ratios!M178) -> 0.88595763
... A162: UltraTech Cement Ltd | B162: =ABS(Annual_return_and_ratios!B30 - Annual_return_and_ratios!B195) -> 0.55607653 | C162: =ABS(Annual_return_and_ratios!C30 - Annual_return_and_ratios!C195) -> 0.68658926 | D162: =ABS(Annual_return_and_ratios!D30 - Annual_return_and_ratios!D195) -> 0.6628772 | E162: =ABS(Annual_return_and_ratios!E30 - Annual_return_and_ratios!E195) -> 0.83137721 | F162: =ABS(Annual_return_and_ratios!F30 - Annual_return_and_ratios!F195) -> 0.68203499 | G162: =ABS(Annual_return_and_ratios!G30 - Annual_return_and_ratios!G195) -> 0.92248371 | H162: =ABS(Annual_return_and_ratios!H30 - Annual_return_and_ratios!H195) -> 0.6427314 | I162: =ABS(Annual_return_and_ratios!I30 - Annual_return_and_ratios!I195) -> 0.63360135 | ... M162: =ABS(Annual_return_and_ratios!M30 - Annual_return_and_ratios!M195) -> 0.79972822
A166: Price to sales | B166: (P/S)2025 | C166: (P/S)2024 | D166: (P/S)2023 | E166: (P/S)2022 | F166: (P/S)2021 | G166: (P/S)2020 | H166: (P/S)2019 | I166: (P/S)2018 | J166: (P/S)2017 | K166: (P/S)2016 | L166: (P/S)2015 | M166: (P/S)2014
A167: Adani Ports and Special Economic Zone Ltd | B167: =ABS(Annual_return_and_ratios!B2 - Annual_return_and_ratios!B200) -> 0.083654204 | C167: =ABS(Annual_return_and_ratios!C2 - Annual_return_and_ratios!C200) -> 0.064866104 | D167: =ABS(Annual_return_and_ratios!D2 - Annual_return_and_ratios!D200) -> 0.28335831 | E167: =ABS(Annual_return_and_ratios!E2 - Annual_return_and_ratios!E200) -> 0.004794169 | F167: =ABS(Annual_return_and_ratios!F2 - Annual_return_and_ratios!F200) -> 0.097112015 | G167: =ABS(Annual_return_and_ratios!G2 - Annual_return_and_ratios!G200) -> 0.57375583 | H167: =ABS(Annual_return_and_ratios!H2 - Annual_return_and_ratios!H200) -> 0.18581707 | I167: =ABS(Annual_return_and_ratios!I2 - Annual_return_and_ratios!I200) -> 0.27381207 | ... M167: =ABS(Annual_return_and_ratios!M2 - Annual_return_and_ratios!M200) -> 0.058422543
A168: Asian Paints Ltd | B168: =ABS(Annual_return_and_ratios!B3 - Annual_return_and_ratios!B201) -> 0.27810151 | C168: =ABS(Annual_return_and_ratios!C3 - Annual_return_and_ratios!C201) -> 0.12680115 | D168: =ABS(Annual_return_and_ratios!D3 - Annual_return_and_ratios!D201) -> 0.13593968 | E168: =ABS(Annual_return_and_ratios!E3 - Annual_return_and_ratios!E201) -> 0.017684069 | F168: =ABS(Annual_return_and_ratios!F3 - Annual_return_and_ratios!F201) -> 0.03472095 | G168: =ABS(Annual_return_and_ratios!G3 - Annual_return_and_ratios!G201) -> 0.093409815 | H168: =ABS(Annual_return_and_ratios!H3 - Annual_return_and_ratios!H201) -> 0.13575549 | I168: =ABS(Annual_return_and_ratios!I3 - Annual_return_and_ratios!I201) -> 0.28708254 | ... M168: =ABS(Annual_return_and_ratios!M3 - Annual_return_and_ratios!M201) -> 0.55365864
A169: AXIS Bank Ltd | B169: =ABS(Annual_return_and_ratios!B4 - Annual_return_and_ratios!B202) -> 0.74112515 | C169: =ABS(Annual_return_and_ratios!C4 - Annual_return_and_ratios!C202) -> 0.7053404 | D169: =ABS(Annual_return_and_ratios!D4 - Annual_return_and_ratios!D202) -> 0.68614784 | E169: =ABS(Annual_return_and_ratios!E4 - Annual_return_and_ratios!E202) -> 0.65140211 | F169: =ABS(Annual_return_and_ratios!F4 - Annual_return_and_ratios!F202) -> 0.61344042 | G169: =ABS(Annual_return_and_ratios!G4 - Annual_return_and_ratios!G202) -> 0.91058273 | H169: =ABS(Annual_return_and_ratios!H4 - Annual_return_and_ratios!H202) -> 0.59887263 | I169: =ABS(Annual_return_and_ratios!I4 - Annual_return_and_ratios!I202) -> 0.72596367 | ... M169: =ABS(Annual_return_and_ratios!M4 - Annual_return_and_ratios!M202) -> 0.77859969
A170: Bajaj Finserv Ltd | B170: =ABS(Annual_return_and_ratios!B5 - Annual_return_and_ratios!B203) -> 0.7665448 | C170: =ABS(Annual_return_and_ratios!C5 - Annual_return_and_ratios!C203) -> 0.76123767 | D170: =ABS(Annual_return_and_ratios!D5 - Annual_return_and_ratios!D203) -> 0.78702871 | E170: =ABS(Annual_return_and_ratios!E5 - Annual_return_and_ratios!E203) -> 0.53622491 | F170: =ABS(Annual_return_and_ratios!F5 - Annual_return_and_ratios!F203) -> 0.68671839 | G170: =ABS(Annual_return_and_ratios!G5 - Annual_return_and_ratios!G203) -> 0.92213328 | H170: =ABS(Annual_return_and_ratios!H5 - Annual_return_and_ratios!H203) -> 0.72393117 | I170: =ABS(Annual_return_and_ratios!I5 - Annual_return_and_ratios!I203) -> 0.74351281 | ... M170: =ABS(Annual_return_and_ratios!M5 - Annual_return_and_ratios!M203) -> 0.8108133
A171: Bajaj Finance Ltd | B171: =ABS(Annual_return_and_ratios!B6 - Annual_return_and_ratios!B204) -> 0.079894245 | C171: =ABS(Annual_return_and_ratios!C6 - Annual_return_and_ratios!C204) -> 0.05370662 | D171: =ABS(Annual_return_and_ratios!D6 - Annual_return_and_ratios!D204) -> 0.081142393 | E171: =ABS(Annual_return_and_ratios!E6 - Annual_return_and_ratios!E204) -> 0.030882716 | F171: =ABS(Annual_return_and_ratios!F6 - Annual_return_and_ratios!F204) -> 0.085722308 | G171: =ABS(Annual_return_and_ratios!G6 - Annual_return_and_ratios!G204) -> 0.45945994 | H171: =ABS(Annual_return_and_ratios!H6 - Annual_return_and_ratios!H204) -> 0.047675208 | I171: =ABS(Annual_return_and_ratios!I6 - Annual_return_and_ratios!I204) -> 0.11116607 | ... M171: =ABS(Annual_return_and_ratios!M6 - Annual_return_and_ratios!M204) -> 0.77837848
A172: Bharat Electronics Ltd | B172: =ABS(Annual_return_and_ratios!B7 - Annual_return_and_ratios!B205) -> 0.027854067 | C172: =ABS(Annual_return_and_ratios!C7 - Annual_return_and_ratios!C205) -> 0.12166867 | D172: =ABS(Annual_return_and_ratios!D7 - Annual_return_and_ratios!D205) -> 0.5512734 | E172: =ABS(Annual_return_and_ratios!E7 - Annual_return_and_ratios!E205) -> 0.6195212 | F172: =ABS(Annual_return_and_ratios!F7 - Annual_return_and_ratios!F205) -> 0.75653817 | G172: =ABS(Annual_return_and_ratios!G7 - Annual_return_and_ratios!G205) -> 0.90768508 | H172: =ABS(Annual_return_and_ratios!H7 - Annual_return_and_ratios!H205) -> 0.87567318 | I172: =ABS(Annual_return_and_ratios!I7 - Annual_return_and_ratios!I205) -> 0.66796289 | ... M172: =ABS(Annual_return_and_ratios!M7 - Annual_return_and_ratios!M205) -> 0.89504136
A173: Bharti Airtel Ltd | B173: =ABS(Annual_return_and_ratios!B8 - Annual_return_and_ratios!B206) -> 0.33516767 | C173: =ABS(Annual_return_and_ratios!C8 - Annual_return_and_ratios!C206) -> 0.44941351 | D173: =ABS(Annual_return_and_ratios!D8 - Annual_return_and_ratios!D206) -> 0.69957328 | E173: =ABS(Annual_return_and_ratios!E8 - Annual_return_and_ratios!E206) -> 0.59652694 | F173: =ABS(Annual_return_and_ratios!F8 - Annual_return_and_ratios!F206) -> 0.71435985 | G173: =ABS(Annual_return_and_ratios!G8 - Annual_return_and_ratios!G206) -> 0.70670268 | H173: =ABS(Annual_return_and_ratios!H8 - Annual_return_and_ratios!H206) -> 0.88557475 | I173: =ABS(Annual_return_and_ratios!I8 - Annual_return_and_ratios!I206) -> 0.82754573 | ... M173: =ABS(Annual_return_and_ratios!M8 - Annual_return_and_ratios!M206) -> 0.8802968
A174: HCL Technologies Ltd | B174: =ABS(Annual_return_and_ratios!B9 - Annual_return_and_ratios!B207) -> 0.61454022 | C174: =ABS(Annual_return_and_ratios!C9 - Annual_return_and_ratios!C207) -> 0.57273705 | D174: =ABS(Annual_return_and_ratios!D9 - Annual_return_and_ratios!D207) -> 0.71557452 | E174: =ABS(Annual_return_and_ratios!E9 - Annual_return_and_ratios!E207) -> 0.60275043 | F174: =ABS(Annual_return_and_ratios!F9 - Annual_return_and_ratios!F207) -> 0.56310595 | G174: =ABS(Annual_return_and_ratios!G9 - Annual_return_and_ratios!G207) -> 0.88291095 | H174: =ABS(Annual_return_and_ratios!H9 - Annual_return_and_ratios!H207) -> 0.76276684 | I174: =ABS(Annual_return_and_ratios!I9 - Annual_return_and_ratios!I207) -> 0.73609942 | ... M174: =ABS(Annual_return_and_ratios!M9 - Annual_return_and_ratios!M207) -> 0.62138534
A175: HDFC Bank Ltd | B175: =ABS(Annual_return_and_ratios!B10 - Annual_return_and_ratios!B208) -> 0.4854922 | C175: =ABS(Annual_return_and_ratios!C10 - Annual_return_and_ratios!C208) -> 0.55644655 | D175: =ABS(Annual_return_and_ratios!D10 - Annual_return_and_ratios!D208) -> 0.38123338 | E175: =ABS(Annual_return_and_ratios!E10 - Annual_return_and_ratios!E208) -> 0.28893192 | F175: =ABS(Annual_return_and_ratios!F10 - Annual_return_and_ratios!F208) -> 0.19164561 | G175: =ABS(Annual_return_and_ratios!G10 - Annual_return_and_ratios!G208) -> 0.58733625 | H175: =ABS(Annual_return_and_ratios!H10 - Annual_return_and_ratios!H208) -> 0.27408312 | I175: =ABS(Annual_return_and_ratios!I10 - Annual_return_and_ratios!I208) -> 0.29954056 | ... M175: =ABS(Annual_return_and_ratios!M10 - Annual_return_and_ratios!M208) -> 0.52078705
A176: Hindustan Unilever Ltd | B176: =ABS(Annual_return_and_ratios!B11 - Annual_return_and_ratios!B209) -> 0.039834289 | C176: =ABS(Annual_return_and_ratios!C11 - Annual_return_and_ratios!C209) -> 0.027634391 | D176: =ABS(Annual_return_and_ratios!D11 - Annual_return_and_ratios!D209) -> 0.019518438 | E176: =ABS(Annual_return_and_ratios!E11 - Annual_return_and_ratios!E209) -> 0.013631595 | F176: =ABS(Annual_return_and_ratios!F11 - Annual_return_and_ratios!F209) -> 0.0064105839 | G176: =ABS(Annual_return_and_ratios!G11 - Annual_return_and_ratios!G209) -> 0.025133487 | H176: =ABS(Annual_return_and_ratios!H11 - Annual_return_and_ratios!H209) -> 0.021783993 | I176: =ABS(Annual_return_and_ratios!I11 - Annual_return_and_ratios!I209) -> 0.044516097 | ... M176: =ABS(Annual_return_and_ratios!M11 - Annual_return_and_ratios!M209) -> 0.49725523
A177: ICICI Bank Ltd | B177: =ABS(Annual_return_and_ratios!B12 - Annual_return_and_ratios!B210) -> 0.42623271 | C177: =ABS(Annual_return_and_ratios!C12 - Annual_return_and_ratios!C210) -> 0.46405497 | D177: =ABS(Annual_return_and_ratios!D12 - Annual_return_and_ratios!D210) -> 0.43321569 | E177: =ABS(Annual_return_and_ratios!E12 - Annual_return_and_ratios!E210) -> 0.39861178 | F177: =ABS(Annual_return_and_ratios!F12 - Annual_return_and_ratios!F210) -> 0.47341516 | G177: =ABS(Annual_return_and_ratios!G12 - Annual_return_and_ratios!G210) -> 0.77689159 | H177: =ABS(Annual_return_and_ratios!H12 - Annual_return_and_ratios!H210) -> 0.60327772 | I177: =ABS(Annual_return_and_ratios!I12 - Annual_return_and_ratios!I210) -> 0.71037507 | ... M177: =ABS(Annual_return_and_ratios!M12 - Annual_return_and_ratios!M210) -> 0.69494491
A178: Infosys Ltd | B178: =ABS(Annual_return_and_ratios!B13 - Annual_return_and_ratios!B211) -> 0.57651965 | C178: =ABS(Annual_return_and_ratios!C13 - Annual_return_and_ratios!C211) -> 0.57001035 | D178: =ABS(Annual_return_and_ratios!D13 - Annual_return_and_ratios!D211) -> 0.5984812 | E178: =ABS(Annual_return_and_ratios!E13 - Annual_return_and_ratios!E211) -> 0.23714747 | F178: =ABS(Annual_return_and_ratios!F13 - Annual_return_and_ratios!F211) -> 0.29328785 | G178: =ABS(Annual_return_and_ratios!G13 - Annual_return_and_ratios!G211) -> 0.71518602 | H178: =ABS(Annual_return_and_ratios!H13 - Annual_return_and_ratios!H211) -> 0.57152439 | I178: =ABS(Annual_return_and_ratios!I13 - Annual_return_and_ratios!I211) -> 0.63344245 | ... M178: =ABS(Annual_return_and_ratios!M13 - Annual_return_and_ratios!M211) -> 0.59922425
... A195: UltraTech Cement Ltd | B195: =ABS(Annual_return_and_ratios!B30 - Annual_return_and_ratios!B228) -> 0.51483836 | C195: =ABS(Annual_return_and_ratios!C30 - Annual_return_and_ratios!C228) -> 0.56704692 | D195: =ABS(Annual_return_and_ratios!D30 - Annual_return_and_ratios!D228) -> 0.63196038 | E195: =ABS(Annual_return_and_ratios!E30 - Annual_return_and_ratios!E228) -> 0.6317789 | F195: =ABS(Annual_return_and_ratios!F30 - Annual_return_and_ratios!F228) -> 0.47666496 | G195: =ABS(Annual_return_and_ratios!G30 - Annual_return_and_ratios!G228) -> 0.81221676 | H195: =ABS(Annual_return_and_ratios!H30 - Annual_return_and_ratios!H228) -> 0.75130274 | I195: =ABS(Annual_return_and_ratios!I30 - Annual_return_and_ratios!I228) -> 0.64699622 | ... M195: =ABS(Annual_return_and_ratios!M30 - Annual_return_and_ratios!M228) -> 0.71542491
A199: Current ratio | B199: (CR)2025 | C199: (CR)2024 | D199: (CR)2023 | E199: (CR)2022 | F199: (CR)2021 | G199: (CR)2020 | H199: (CR)2019 | I199: (CR)2018 | J199: (CR)2017 | K199: (CR)2016 | L199: (CR)2015 | M199: (CR)2014
A200: Adani Ports and Special Economic Zone Ltd | B200: =ABS(Annual_return_and_ratios!B2 - Annual_return_and_ratios!B233) -> 0.70677412 | C200: =ABS(Annual_return_and_ratios!C2 - Annual_return_and_ratios!C233) -> 0.66884494 | D200: =ABS(Annual_return_and_ratios!D2 - Annual_return_and_ratios!D233) -> 0.82927504 | E200: =ABS(Annual_return_and_ratios!E2 - Annual_return_and_ratios!E233) -> 0.88189138 | F200: =ABS(Annual_return_and_ratios!F2 - Annual_return_and_ratios!F233) -> 0.84056504 | G200: =ABS(Annual_return_and_ratios!G2 - Annual_return_and_ratios!G233) -> 1.0082094 | H200: =ABS(Annual_return_and_ratios!H2 - Annual_return_and_ratios!H233) -> 0.82472066 | I200: =ABS(Annual_return_and_ratios!I2 - Annual_return_and_ratios!I233) -> 0.55458458 | ... M200: =ABS(Annual_return_and_ratios!M2 - Annual_return_and_ratios!M233) -> 0.91566408
A201: Asian Paints Ltd | B201: =ABS(Annual_return_and_ratios!B3 - Annual_return_and_ratios!B234) -> 0.99001231 | C201: =ABS(Annual_return_and_ratios!C3 - Annual_return_and_ratios!C234) -> 0.9795797 | D201: =ABS(Annual_return_and_ratios!D3 - Annual_return_and_ratios!D234) -> 0.978994 | E201: =ABS(Annual_return_and_ratios!E3 - Annual_return_and_ratios!E234) -> 0.98231593 | F201: =ABS(Annual_return_and_ratios!F3 - Annual_return_and_ratios!F234) -> 0.95678047 | G201: =ABS(Annual_return_and_ratios!G3 - Annual_return_and_ratios!G234) -> 0.91366236 | H201: =ABS(Annual_return_and_ratios!H3 - Annual_return_and_ratios!H234) -> 0.82474855 | I201: =ABS(Annual_return_and_ratios!I3 - Annual_return_and_ratios!I234) -> 0.87004624 | ... M201: =ABS(Annual_return_and_ratios!M3 - Annual_return_and_ratios!M234) -> 0.83857194
A202: AXIS Bank Ltd | B202: =ABS(Annual_return_and_ratios!B4 - Annual_return_and_ratios!B235) -> 0.74869638 | C202: =ABS(Annual_return_and_ratios!C4 - Annual_return_and_ratios!C235) -> 0.73308265 | D202: =ABS(Annual_return_and_ratios!D4 - Annual_return_and_ratios!D235) -> 0.72915855 | E202: =ABS(Annual_return_and_ratios!E4 - Annual_return_and_ratios!E235) -> 0.74061137 | F202: =ABS(Annual_return_and_ratios!F4 - Annual_return_and_ratios!F235) -> 0.69275206 | G202: =ABS(Annual_return_and_ratios!G4 - Annual_return_and_ratios!G235) -> 0.7879412 | H202: =ABS(Annual_return_and_ratios!H4 - Annual_return_and_ratios!H235) -> 0.70325206 | I202: =ABS(Annual_return_and_ratios!I4 - Annual_return_and_ratios!I235) -> 0.739744 | ... M202: =ABS(Annual_return_and_ratios!M4 - Annual_return_and_ratios!M235) -> 0.7250681
A203: Bajaj Finserv Ltd | B203: =ABS(Annual_return_and_ratios!B5 - Annual_return_and_ratios!B236) -> 0.77143365 | C203: =ABS(Annual_return_and_ratios!C5 - Annual_return_and_ratios!C236) -> 0.95064408 | D203: =ABS(Annual_return_and_ratios!D5 - Annual_return_and_ratios!D236) -> 0.99879732 | E203: =ABS(Annual_return_and_ratios!E5 - Annual_return_and_ratios!E236) -> 0.93873094 | F203: =ABS(Annual_return_and_ratios!F5 - Annual_return_and_ratios!F236) -> 0.91112499 | G203: =ABS(Annual_return_and_ratios!G5 - Annual_return_and_ratios!G236) -> 0.99096445 | H203: =ABS(Annual_return_and_ratios!H5 - Annual_return_and_ratios!H236) -> 0.93670564 | I203: =ABS(Annual_return_and_ratios!I5 - Annual_return_and_ratios!I236) -> 0.84809517 | ... M203: =ABS(Annual_return_and_ratios!M5 - Annual_return_and_ratios!M236) -> 0.67411707
A204: Bajaj Finance Ltd | B204: =ABS(Annual_return_and_ratios!B6 - Annual_return_and_ratios!B237) -> 0.77435616 | C204: =ABS(Annual_return_and_ratios!C6 - Annual_return_and_ratios!C237) -> 0.7633387 | D204: =ABS(Annual_return_and_ratios!D6 - Annual_return_and_ratios!D237) -> 0.79529545 | E204: =ABS(Annual_return_and_ratios!E6 - Annual_return_and_ratios!E237) -> 0.7566527 | F204: =ABS(Annual_return_and_ratios!F6 - Annual_return_and_ratios!F237) -> 0.70464596 | G204: =ABS(Annual_return_and_ratios!G6 - Annual_return_and_ratios!G237) -> 0.78631063 | H204: =ABS(Annual_return_and_ratios!H6 - Annual_return_and_ratios!H237) -> 0.72003017 | I204: =ABS(Annual_return_and_ratios!I6 - Annual_return_and_ratios!I237) -> 0.86991682 | ... M204: =ABS(Annual_return_and_ratios!M6 - Annual_return_and_ratios!M237) -> 0.68210547
A205: Bharat Electronics Ltd | B205: =ABS(Annual_return_and_ratios!B7 - Annual_return_and_ratios!B238) -> 0.90415726 | C205: =ABS(Annual_return_and_ratios!C7 - Annual_return_and_ratios!C238) -> 0.81248873 | D205: =ABS(Annual_return_and_ratios!D7 - Annual_return_and_ratios!D238) -> 0.81826458 | E205: =ABS(Annual_return_and_ratios!E7 - Annual_return_and_ratios!E238) -> 0.7833388 | F205: =ABS(Annual_return_and_ratios!F7 - Annual_return_and_ratios!F238) -> 0.78139593 | G205: =ABS(Annual_return_and_ratios!G7 - Annual_return_and_ratios!G238) -> 0.85355848 | H205: =ABS(Annual_return_and_ratios!H7 - Annual_return_and_ratios!H238) -> 0.89614884 | I205: =ABS(Annual_return_and_ratios!I7 - Annual_return_and_ratios!I238) -> 0.84755202 | ... M205: =ABS(Annual_return_and_ratios!M7 - Annual_return_and_ratios!M238) -> 0.9542292
A206: Bharti Airtel Ltd | B206: =ABS(Annual_return_and_ratios!B8 - Annual_return_and_ratios!B239) -> 0.51154097 | C206: =ABS(Annual_return_and_ratios!C8 - Annual_return_and_ratios!C239) -> 0.50635631 | D206: =ABS(Annual_return_and_ratios!D8 - Annual_return_and_ratios!D239) -> 0.56722408 | E206: =ABS(Annual_return_and_ratios!E8 - Annual_return_and_ratios!E239) -> 0.53120639 | F206: =ABS(Annual_return_and_ratios!F8 - Annual_return_and_ratios!F239) -> 0.55948664 | G206: =ABS(Annual_return_and_ratios!G8 - Annual_return_and_ratios!G239) -> 0.56874574 | H206: =ABS(Annual_return_and_ratios!H8 - Annual_return_and_ratios!H239) -> 0.54764156 | I206: =ABS(Annual_return_and_ratios!I8 - Annual_return_and_ratios!I239) -> 0.54291644 | ... M206: =ABS(Annual_return_and_ratios!M8 - Annual_return_and_ratios!M239) -> 0.53040789
A207: HCL Technologies Ltd | B207: =ABS(Annual_return_and_ratios!B9 - Annual_return_and_ratios!B240) -> 0.93173682 | C207: =ABS(Annual_return_and_ratios!C9 - Annual_return_and_ratios!C240) -> 0.79415976 | D207: =ABS(Annual_return_and_ratios!D9 - Annual_return_and_ratios!D240) -> 0.85785106 | E207: =ABS(Annual_return_and_ratios!E9 - Annual_return_and_ratios!E240) -> 0.82362975 | F207: =ABS(Annual_return_and_ratios!F9 - Annual_return_and_ratios!F240) -> 0.78826356 | G207: =ABS(Annual_return_and_ratios!G9 - Annual_return_and_ratios!G240) -> 0.90842806 | H207: =ABS(Annual_return_and_ratios!H9 - Annual_return_and_ratios!H240) -> 0.87010117 | I207: =ABS(Annual_return_and_ratios!I9 - Annual_return_and_ratios!I240) -> 0.86756498 | ... M207: =ABS(Annual_return_and_ratios!M9 - Annual_return_and_ratios!M240) -> 0.9227066
A208: HDFC Bank Ltd | B208: =ABS(Annual_return_and_ratios!B10 - Annual_return_and_ratios!B241) -> 0.71194419 | C208: =ABS(Annual_return_and_ratios!C10 - Annual_return_and_ratios!C241) -> 0.74803724 | D208: =ABS(Annual_return_and_ratios!D10 - Annual_return_and_ratios!D241) -> 0.68399868 | E208: =ABS(Annual_return_and_ratios!E10 - Annual_return_and_ratios!E241) -> 0.69219973 | F208: =ABS(Annual_return_and_ratios!F10 - Annual_return_and_ratios!F241) -> 0.64195023 | G208: =ABS(Annual_return_and_ratios!G10 - Annual_return_and_ratios!G241) -> 0.7079436 | H208: =ABS(Annual_return_and_ratios!H10 - Annual_return_and_ratios!H241) -> 0.68745673 | I208: =ABS(Annual_return_and_ratios!I10 - Annual_return_and_ratios!I241) -> 0.68227317 | ... M208: =ABS(Annual_return_and_ratios!M10 - Annual_return_and_ratios!M241) -> 0.680534
A209: Hindustan Unilever Ltd | B209: =ABS(Annual_return_and_ratios!B11 - Annual_return_and_ratios!B242) -> 0.80805441 | C209: =ABS(Annual_return_and_ratios!C11 - Annual_return_and_ratios!C242) -> 0.91385173 | D209: =ABS(Annual_return_and_ratios!D11 - Annual_return_and_ratios!D242) -> 0.81334275 | E209: =ABS(Annual_return_and_ratios!E11 - Annual_return_and_ratios!E242) -> 0.8379942 | F209: =ABS(Annual_return_and_ratios!F11 - Annual_return_and_ratios!F242) -> 0.78962341 | G209: =ABS(Annual_return_and_ratios!G11 - Annual_return_and_ratios!G242) -> 0.78223195 | H209: =ABS(Annual_return_and_ratios!H11 - Annual_return_and_ratios!H242) -> 0.79974575 | I209: =ABS(Annual_return_and_ratios!I11 - Annual_return_and_ratios!I242) -> 0.77152692 | ... M209: =ABS(Annual_return_and_ratios!M11 - Annual_return_and_ratios!M242) -> 0.70325291
A210: ICICI Bank Ltd | B210: =ABS(Annual_return_and_ratios!B12 - Annual_return_and_ratios!B243) -> 0.70140964 | C210: =ABS(Annual_return_and_ratios!C12 - Annual_return_and_ratios!C243) -> 0.6959529 | D210: =ABS(Annual_return_and_ratios!D12 - Annual_return_and_ratios!D243) -> 0.70019471 | E210: =ABS(Annual_return_and_ratios!E12 - Annual_return_and_ratios!E243) -> 0.69745746 | F210: =ABS(Annual_return_and_ratios!F12 - Annual_return_and_ratios!F243) -> 0.66448538 | G210: =ABS(Annual_return_and_ratios!G12 - Annual_return_and_ratios!G243) -> 0.73615397 | H210: =ABS(Annual_return_and_ratios!H12 - Annual_return_and_ratios!H243) -> 0.70746635 | I210: =ABS(Annual_return_and_ratios!I12 - Annual_return_and_ratios!I243) -> 0.74132596 | ... M210: =ABS(Annual_return_and_ratios!M12 - Annual_return_and_ratios!M243) -> 0.75506848
A211: Infosys Ltd | B211: =ABS(Annual_return_and_ratios!B13 - Annual_return_and_ratios!B244) -> 0.91632116 | C211: =ABS(Annual_return_and_ratios!C13 - Annual_return_and_ratios!C244) -> 0.90460862 | D211: =ABS(Annual_return_and_ratios!D13 - Annual_return_and_ratios!D244) -> 0.96584816 | E211: =ABS(Annual_return_and_ratios!E13 - Annual_return_and_ratios!E244) -> 0.97087709 | F211: =ABS(Annual_return_and_ratios!F13 - Annual_return_and_ratios!F244) -> 0.77599173 | G211: =ABS(Annual_return_and_ratios!G13 - Annual_return_and_ratios!G244) -> 0.83327334 | H211: =ABS(Annual_return_and_ratios!H13 - Annual_return_and_ratios!H244) -> 0.73882204 | I211: =ABS(Annual_return_and_ratios!I13 - Annual_return_and_ratios!I244) -> 0.55058135 | ... M211: =ABS(Annual_return_and_ratios!M13 - Annual_return_and_ratios!M244) -> 0.53727994
... A228: UltraTech Cement Ltd | B228: =ABS(Annual_return_and_ratios!B30 - Annual_return_and_ratios!B261) -> 0.62895885 | C228: =ABS(Annual_return_and_ratios!C30 - Annual_return_and_ratios!C261) -> 0.65793823 | D228: =ABS(Annual_return_and_ratios!D30 - Annual_return_and_ratios!D261) -> 0.67129389 | E228: =ABS(Annual_return_and_ratios!E30 - Annual_return_and_ratios!E261) -> 0.68260565 | F228: =ABS(Annual_return_and_ratios!F30 - Annual_return_and_ratios!F261) -> 0.70194929 | G228: =ABS(Annual_return_and_ratios!G30 - Annual_return_and_ratios!G261) -> 0.69589394 | H228: =ABS(Annual_return_and_ratios!H30 - Annual_return_and_ratios!H261) -> 0.67068528 | I228: =ABS(Annual_return_and_ratios!I30 - Annual_return_and_ratios!I261) -> 0.71994249 | ... M228: =ABS(Annual_return_and_ratios!M30 - Annual_return_and_ratios!M261) -> 0.82637817
A232: Global max | B232: =MAX(B2:M30,B35:M63,B68:M96,B101:M129,B134:M162,B167:M195,B200:M228,B238:M266) -> 1.0538882
A233: global min | B233: =MIN(B2:M30,B35:M63,B68:M96,B101:M129,B134:M162,B167:M195,B200:M228,B238:M266) -> 8.6851477e-05
...

Sheet GRC
A1: Diluted EPS | B1: 2025 | C1: 2024 | D1: 2023 | E1: 2022 | F1: 2021 | G1: 2020 | H1: 2019 | I1: 2018 | J1: 2017 | K1: 2016 | L1: 2015 | M1: 2014 | O1: Company mean
A2: Adani Ports and Special Economic Zone Ltd | B2: =(Deviation_sequence!$B$233 + 0.5 *Deviation_sequence!$B$232) / (Deviation_sequence!B2 + 0.5 * Deviation_sequence!$B$232) -> 0.6498081 | C2: =(Deviation_sequence!$B$233 + 0.5 *Deviation_sequence!$B$232) / (Deviation_sequence!C2 + 0.5 * Deviation_sequence!$B$232) -> 0.80666861 | D2: =(Deviation_sequence!$B$233 + 0.5 *Deviation_sequence!$B$232) / (Deviation_sequence!D2 + 0.5 * Deviation_sequence!$B$232) -> 0.79655333 | E2: =(Deviation_sequence!$B$233 + 0.5 *Deviation_sequence!$B$232) / (Deviation_sequence!E2 + 0.5 * Deviation_sequence!$B$232) -> 0.83441435 | F2: =(Deviation_sequence!$B$233 + 0.5 *Deviation_sequence!$B$232) / (Deviation_sequence!F2 + 0.5 * Deviation_sequence!$B$232) -> 0.95629728 | G2: =(Deviation_sequence!$B$233 + 0.5 *Deviation_sequence!$B$232) / (Deviation_sequence!G2 + 0.5 * Deviation_sequence!$B$232) -> 0.82008593 | H2: =(Deviation_sequence!$B$233 + 0.5 *Deviation_sequence!$B$232) / (Deviation_sequence!H2 + 0.5 * Deviation_sequence!$B$232) -> 0.86195423 | I2: =(Deviation_sequence!$B$233 + 0.5 *Deviation_sequence!$B$232) / (Deviation_sequence!I2 + 0.5 * Deviation_sequence!$B$232) -> 0.86706463 | ... M2: =(Deviation_sequence!$B$233 + 0.5 *Deviation_sequence!$B$232) / (Deviation_sequence!M2 + 0.5 * Deviation_sequence!$B$232) -> 0.9878389 | O2: =AVERAGE(B2:M2) -> 0.86174808
A3: Asian Paints Ltd | B3: =(Deviation_sequence!$B$233 + 0.5 *Deviation_sequence!$B$232) / (Deviation_sequence!B3 + 0.5 * Deviation_sequence!$B$232) -> 0.71462441 | C3: =(Deviation_sequence!$B$233 + 0.5 *Deviation_sequence!$B$232) / (Deviation_sequence!C3 + 0.5 * Deviation_sequence!$B$232) -> 0.64318699 | D3: =(Deviation_sequence!$B$233 + 0.5 *Deviation_sequence!$B$232) / (Deviation_sequence!D3 + 0.5 * Deviation_sequence!$B$232) -> 0.70164794 | E3: =(Deviation_sequence!$B$233 + 0.5 *Deviation_sequence!$B$232) / (Deviation_sequence!E3 + 0.5 * Deviation_sequence!$B$232) -> 0.78853519 | F3: =(Deviation_sequence!$B$233 + 0.5 *Deviation_sequence!$B$232) / (Deviation_sequence!F3 + 0.5 * Deviation_sequence!$B$232) -> 0.801591 | G3: =(Deviation_sequence!$B$233 + 0.5 *Deviation_sequence!$B$232) / (Deviation_sequence!G3 + 0.5 * Deviation_sequence!$B$232) -> 0.80106872 | H3: =(Deviation_sequence!$B$233 + 0.5 *Deviation_sequence!$B$232) / (Deviation_sequence!H3 + 0.5 * Deviation_sequence!$B$232) -> 0.86146045 | I3: =(Deviation_sequence!$B$233 + 0.5 *Deviation_sequence!$B$232) / (Deviation_sequence!I3 + 0.5 * Deviation_sequence!$B$232) -> 0.83943517 | ... M3: =(Deviation_sequence!$B$233 + 0.5 *Deviation_sequence!$B$232) / (Deviation_sequence!M3 + 0.5 * Deviation_sequence!$B$232) -> 0.92451248 | O3: =AVERAGE(B3:M3) -> 0.81303918
A4: AXIS Bank Ltd | B4: =(Deviation_sequence!$B$233 + 0.5 *Deviation_sequence!$B$232) / (Deviation_sequence!B4 + 0.5 * Deviation_sequence!$B$232) -> 0.52754154 | C4: =(Deviation_sequence!$B$233 + 0.5 *Deviation_sequence!$B$232) / (Deviation_sequence!C4 + 0.5 * Deviation_sequence!$B$232) -> 0.5497697 | D4: =(Deviation_sequence!$B$233 + 0.5 *Deviation_sequence!$B$232) / (Deviation_sequence!D4 + 0.5 * Deviation_sequence!$B$232) -> 0.76579371 | E4: =(Deviation_sequence!$B$233 + 0.5 *Deviation_sequence!$B$232) / (Deviation_sequence!E4 + 0.5 * Deviation_sequence!$B$232) -> 0.6957798 | F4: =(Deviation_sequence!$B$233 + 0.5 *Deviation_sequence!$B$232) / (Deviation_sequence!F4 + 0.5 * Deviation_sequence!$B$232) -> 0.89133307 | G4: =(Deviation_sequence!$B$233 + 0.5 *Deviation_sequence!$B$232) / (Deviation_sequence!G4 + 0.5 * Deviation_sequence!$B$232) -> 0.88421527 | H4: =(Deviation_sequence!$B$233 + 0.5 *Deviation_sequence!$B$232) / (Deviation_sequence!H4 + 0.5 * Deviation_sequence!$B$232) -> 0.90365148 | I4: =(Deviation_sequence!$B$233 + 0.5 *Deviation_sequence!$B$232) / (Deviation_sequence!I4 + 0.5 * Deviation_sequence!$B$232) -> 0.9933805 | ... M4: =(Deviation_sequence!$B$233 + 0.5 *Deviation_sequence!$B$232) / (Deviation_sequence!M4 + 0.5 * Deviation_sequence!$B$232) -> 0.43239467 | O4: =AVERAGE(B4:M4) -> 0.75727599
A5: Bajaj Finserv Ltd | B5: =(Deviation_sequence!$B$233 + 0.5 *Deviation_sequence!$B$232) / (Deviation_sequence!B5 + 0.5 * Deviation_sequence!$B$232) -> 0.9501645 | C5: =(Deviation_sequence!$B$233 + 0.5 *Deviation_sequence!$B$232) / (Deviation_sequence!C5 + 0.5 * Deviation_sequence!$B$232) -> 0.9870129 | D5: =(Deviation_sequence!$B$233 + 0.5 *Deviation_sequence!$B$232) / (Deviation_sequence!D5 + 0.5 * Deviation_sequence!$B$232) -> 0.94752349 | E5: =(Deviation_sequence!$B$233 + 0.5 *Deviation_sequence!$B$232) / (Deviation_sequence!E5 + 0.5 * Deviation_sequence!$B$232) -> 0.86513442 | F5: =(Deviation_sequence!$B$233 + 0.5 *Deviation_sequence!$B$232) / (Deviation_sequence!F5 + 0.5 * Deviation_sequence!$B$232) -> 0.95379293 | G5: =(Deviation_sequence!$B$233 + 0.5 *Deviation_sequence!$B$232) / (Deviation_sequence!G5 + 0.5 * Deviation_sequence!$B$232) -> 0.69777077 | H5: =(Deviation_sequence!$B$233 + 0.5 *Deviation_sequence!$B$232) / (Deviation_sequence!H5 + 0.5 * Deviation_sequence!$B$232) -> 0.88834547 | I5: =(Deviation_sequence!$B$233 + 0.5 *Deviation_sequence!$B$232) / (Deviation_sequence!I5 + 0.5 * Deviation_sequence!$B$232) -> 0.97232332 | ... M5: =(Deviation_sequence!$B$233 + 0.5 *Deviation_sequence!$B$232) / (Deviation_sequence!M5 + 0.5 * Deviation_sequence!$B$232) -> 0.97980697 | O5: =AVERAGE(B5:M5) -> 0.92043753
A6: Bajaj Finance Ltd | B6: =(Deviation_sequence!$B$233 + 0.5 *Deviation_sequence!$B$232) / (Deviation_sequence!B6 + 0.5 * Deviation_sequence!$B$232) -> 0.34881183 | C6: =(Deviation_sequence!$B$233 + 0.5 *Deviation_sequence!$B$232) / (Deviation_sequence!C6 + 0.5 * Deviation_sequence!$B$232) -> 0.35005172 | D6: =(Deviation_sequence!$B$233 + 0.5 *Deviation_sequence!$B$232) / (Deviation_sequence!D6 + 0.5 * Deviation_sequence!$B$232) -> 0.34214572 | E6: =(Deviation_sequence!$B$233 + 0.5 *Deviation_sequence!$B$232) / (Deviation_sequence!E6 + 0.5 * Deviation_sequence!$B$232) -> 0.47502744 | F6: =(Deviation_sequence!$B$233 + 0.5 *Deviation_sequence!$B$232) / (Deviation_sequence!F6 + 0.5 * Deviation_sequence!$B$232) -> 0.63978775 | G6: =(Deviation_sequence!$B$233 + 0.5 *Deviation_sequence!$B$232) / (Deviation_sequence!G6 + 0.5 * Deviation_sequence!$B$232) -> 0.52669966 | H6: =(Deviation_sequence!$B$233 + 0.5 *Deviation_sequence!$B$232) / (Deviation_sequence!H6 + 0.5 * Deviation_sequence!$B$232) -> 0.62825921 | I6: =(Deviation_sequence!$B$233 + 0.5 *Deviation_sequence!$B$232) / (Deviation_sequence!I6 + 0.5 * Deviation_sequence!$B$232) -> 0.71636606 | ... M6: =(Deviation_sequence!$B$233 + 0.5 *Deviation_sequence!$B$232) / (Deviation_sequence!M6 + 0.5 * Deviation_sequence!$B$232) -> 0.42244572 | O6: =AVERAGE(B6:M6) -> 0.49881652
A7: Bharat Electronics Ltd | B7: =(Deviation_sequence!$B$233 + 0.5 *Deviation_sequence!$B$232) / (Deviation_sequence!B7 + 0.5 * Deviation_sequence!$B$232) -> 1 | C7: =(Deviation_sequence!$B$233 + 0.5 *Deviation_sequence!$B$232) / (Deviation_sequence!C7 + 0.5 * Deviation_sequence!$B$232) -> 0.9263879 | D7: =(Deviation_sequence!$B$233 + 0.5 *Deviation_sequence!$B$232) / (Deviation_sequence!D7 + 0.5 * Deviation_sequence!$B$232) -> 0.96707196 | E7: =(Deviation_sequence!$B$233 + 0.5 *Deviation_sequence!$B$232) / (Deviation_sequence!E7 + 0.5 * Deviation_sequence!$B$232) -> 0.9962905 | F7: =(Deviation_sequence!$B$233 + 0.5 *Deviation_sequence!$B$232) / (Deviation_sequence!F7 + 0.5 * Deviation_sequence!$B$232) -> 0.97016514 | G7: =(Deviation_sequence!$B$233 + 0.5 *Deviation_sequence!$B$232) / (Deviation_sequence!G7 + 0.5 * Deviation_sequence!$B$232) -> 0.93685886 | H7: =(Deviation_sequence!$B$233 + 0.5 *Deviation_sequence!$B$232) / (Deviation_sequence!H7 + 0.5 * Deviation_sequence!$B$232) -> 0.89404083 | I7: =(Deviation_sequence!$B$233 + 0.5 *Deviation_sequence!$B$232) / (Deviation_sequence!I7 + 0.5 * Deviation_sequence!$B$232) -> 0.95750544 | ... M7: =(Deviation_sequence!$B$233 + 0.5 *Deviation_sequence!$B$232) / (Deviation_sequence!M7 + 0.5 * Deviation_sequence!$B$232) -> 0.45785745 | O7: =AVERAGE(B7:M7) -> 0.8773
A8: Bharti Airtel Ltd | B8: =(Deviation_sequence!$B$233 + 0.5 *Deviation_sequence!$B$232) / (Deviation_sequence!B8 + 0.5 * Deviation_sequence!$B$232) -> 0.66605706 | C8: =(Deviation_sequence!$B$233 + 0.5 *Deviation_sequence!$B$232) / (Deviation_sequence!C8 + 0.5 * Deviation_sequence!$B$232) -> 0.97848944 | D8: =(Deviation_sequence!$B$233 + 0.5 *Deviation_sequence!$B$232) / (Deviation_sequence!D8 + 0.5 * Deviation_sequence!$B$232) -> 0.88595912 | E8: =(Deviation_sequence!$B$233 + 0.5 *Deviation_sequence!$B$232) / (Deviation_sequence!E8 + 0.5 * Deviation_sequence!$B$232) -> 0.99505941 | F8: =(Deviation_sequence!$B$233 + 0.5 *Deviation_sequence!$B$232) / (Deviation_sequence!F8 + 0.5 * Deviation_sequence!$B$232) -> 0.97653405 | G8: =(Deviation_sequence!$B$233 + 0.5 *Deviation_sequence!$B$232) / (Deviation_sequence!G8 + 0.5 * Deviation_sequence!$B$232) -> 0.94801323 | H8: =(Deviation_sequence!$B$233 + 0.5 *Deviation_sequence!$B$232) / (Deviation_sequence!H8 + 0.5 * Deviation_sequence!$B$232) -> 0.97236791 | I8: =(Deviation_sequence!$B$233 + 0.5 *Deviation_sequence!$B$232) / (Deviation_sequence!I8 + 0.5 * Deviation_sequence!$B$232) -> 0.98368985 | ... M8: =(Deviation_sequence!$B$233 + 0.5 *Deviation_sequence!$B$232) / (Deviation_sequence!M8 + 0.5 * Deviation_sequence!$B$232) -> 0.97611565 | O8: =AVERAGE(B8:M8) -> 0.9282383
A9: HCL Technologies Ltd | B9: =(Deviation_sequence!$B$233 + 0.5 *Deviation_sequence!$B$232) / (Deviation_sequence!B9 + 0.5 * Deviation_sequence!$B$232) -> 0.61607421 | C9: =(Deviation_sequence!$B$233 + 0.5 *Deviation_sequence!$B$232) / (Deviation_sequence!C9 + 0.5 * Deviation_sequence!$B$232) -> 0.66313484 | D9: =(Deviation_sequence!$B$233 + 0.5 *Deviation_sequence!$B$232) / (Deviation_sequence!D9 + 0.5 * Deviation_sequence!$B$232) -> 0.65007581 | E9: =(Deviation_sequence!$B$233 + 0.5 *Deviation_sequence!$B$232) / (Deviation_sequence!E9 + 0.5 * Deviation_sequence!$B$232) -> 0.68765972 | F9: =(Deviation_sequence!$B$233 + 0.5 *Deviation_sequence!$B$232) / (Deviation_sequence!F9 + 0.5 * Deviation_sequence!$B$232) -> 0.79679093 | G9: =(Deviation_sequence!$B$233 + 0.5 *Deviation_sequence!$B$232) / (Deviation_sequence!G9 + 0.5 * Deviation_sequence!$B$232) -> 0.70125749 | H9: =(Deviation_sequence!$B$233 + 0.5 *Deviation_sequence!$B$232) / (Deviation_sequence!H9 + 0.5 * Deviation_sequence!$B$232) -> 0.58459597 | I9: =(Deviation_sequence!$B$233 + 0.5 *Deviation_sequence!$B$232) / (Deviation_sequence!I9 + 0.5 * Deviation_sequence!$B$232) -> 0.62701969 | ... M9: =(Deviation_sequence!$B$233 + 0.5 *Deviation_sequence!$B$232) / (Deviation_sequence!M9 + 0.5 * Deviation_sequence!$B$232) -> 0.54909256 | O9: =AVERAGE(B9:M9) -> 0.66013493
A10: HDFC Bank Ltd | B10: =(Deviation_sequence!$B$233 + 0.5 *Deviation_sequence!$B$232) / (Deviation_sequence!B10 + 0.5 * Deviation_sequence!$B$232) -> 0.52808703 | C10: =(Deviation_sequence!$B$233 + 0.5 *Deviation_sequence!$B$232) / (Deviation_sequence!C10 + 0.5 * Deviation_sequence!$B$232) -> 0.52332192 | D10: =(Deviation_sequence!$B$233 + 0.5 *Deviation_sequence!$B$232) / (Deviation_sequence!D10 + 0.5 * Deviation_sequence!$B$232) -> 0.55509318 | E10: =(Deviation_sequence!$B$233 + 0.5 *Deviation_sequence!$B$232) / (Deviation_sequence!E10 + 0.5 * Deviation_sequence!$B$232) -> 0.59732072 | F10: =(Deviation_sequence!$B$233 + 0.5 *Deviation_sequence!$B$232) / (Deviation_sequence!F10 + 0.5 * Deviation_sequence!$B$232) -> 0.67567324 | G10: =(Deviation_sequence!$B$233 + 0.5 *Deviation_sequence!$B$232) / (Deviation_sequence!G10 + 0.5 * Deviation_sequence!$B$232) -> 0.65712275 | H10: =(Deviation_sequence!$B$233 + 0.5 *Deviation_sequence!$B$232) / (Deviation_sequence!H10 + 0.5 * Deviation_sequence!$B$232) -> 0.55896611 | I10: =(Deviation_sequence!$B$233 + 0.5 *Deviation_sequence!$B$232) / (Deviation_sequence!I10 + 0.5 * Deviation_sequence!$B$232) -> 0.60281296 | ... M10: =(Deviation_sequence!$B$233 + 0.5 *Deviation_sequence!$B$232) / (Deviation_sequence!M10 + 0.5 * Deviation_sequence!$B$232) -> 0.75813429 | O10: =AVERAGE(B10:M10) -> 0.6258523
A11: Hindustan Unilever Ltd | B11: =(Deviation_sequence!$B$233 + 0.5 *Deviation_sequence!$B$232) / (Deviation_sequence!B11 + 0.5 * Deviation_sequence!$B$232) -> 0.69530222 | C11: =(Deviation_sequence!$B$233 + 0.5 *Deviation_sequence!$B$232) / (Deviation_sequence!C11 + 0.5 * Deviation_sequence!$B$232) -> 0.69184484 | D11: =(Deviation_sequence!$B$233 + 0.5 *Deviation_sequence!$B$232) / (Deviation_sequence!D11 + 0.5 * Deviation_sequence!$B$232) -> 0.72347281 | E11: =(Deviation_sequence!$B$233 + 0.5 *Deviation_sequence!$B$232) / (Deviation_sequence!E11 + 0.5 * Deviation_sequence!$B$232) -> 0.71887278 | F11: =(Deviation_sequence!$B$233 + 0.5 *Deviation_sequence!$B$232) / (Deviation_sequence!F11 + 0.5 * Deviation_sequence!$B$232) -> 0.76071969 | G11: =(Deviation_sequence!$B$233 + 0.5 *Deviation_sequence!$B$232) / (Deviation_sequence!G11 + 0.5 * Deviation_sequence!$B$232) -> 0.80016662 | H11: =(Deviation_sequence!$B$233 + 0.5 *Deviation_sequence!$B$232) / (Deviation_sequence!H11 + 0.5 * Deviation_sequence!$B$232) -> 0.81750625 | I11: =(Deviation_sequence!$B$233 + 0.5 *Deviation_sequence!$B$232) / (Deviation_sequence!I11 + 0.5 * Deviation_sequence!$B$232) -> 0.86042385 | ... M11: =(Deviation_sequence!$B$233 + 0.5 *Deviation_sequence!$B$232) / (Deviation_sequence!M11 + 0.5 * Deviation_sequence!$B$232) -> 0.89884695 | O11: =AVERAGE(B11:M11) -> 0.79656814
A12: ICICI Bank Ltd | B12: =(Deviation_sequence!$B$233 + 0.5 *Deviation_sequence!$B$232) / (Deviation_sequence!B12 + 0.5 * Deviation_sequence!$B$232) -> 0.59609353 | C12: =(Deviation_sequence!$B$233 + 0.5 *Deviation_sequence!$B$232) / (Deviation_sequence!C12 + 0.5 * Deviation_sequence!$B$232) -> 0.63346114 | D12: =(Deviation_sequence!$B$233 + 0.5 *Deviation_sequence!$B$232) / (Deviation_sequence!D12 + 0.5 * Deviation_sequence!$B$232) -> 0.69863074 | E12: =(Deviation_sequence!$B$233 + 0.5 *Deviation_sequence!$B$232) / (Deviation_sequence!E12 + 0.5 * Deviation_sequence!$B$232) -> 0.76968628 | F12: =(Deviation_sequence!$B$233 + 0.5 *Deviation_sequence!$B$232) / (Deviation_sequence!F12 + 0.5 * Deviation_sequence!$B$232) -> 0.85862862 | G12: =(Deviation_sequence!$B$233 + 0.5 *Deviation_sequence!$B$232) / (Deviation_sequence!G12 + 0.5 * Deviation_sequence!$B$232) -> 0.87514774 | H12: =(Deviation_sequence!$B$233 + 0.5 *Deviation_sequence!$B$232) / (Deviation_sequence!H12 + 0.5 * Deviation_sequence!$B$232) -> 0.98517774 | I12: =(Deviation_sequence!$B$233 + 0.5 *Deviation_sequence!$B$232) / (Deviation_sequence!I12 + 0.5 * Deviation_sequence!$B$232) -> 0.92400568 | ... M12: =(Deviation_sequence!$B$233 + 0.5 *Deviation_sequence!$B$232) / (Deviation_sequence!M12 + 0.5 * Deviation_sequence!$B$232) -> 0.52152606 | O12: =AVERAGE(B12:M12) -> 0.78933245
A13: Infosys Ltd | B13: =(Deviation_sequence!$B$233 + 0.5 *Deviation_sequence!$B$232) / (Deviation_sequence!B13 + 0.5 * Deviation_sequence!$B$232) -> 0.61600398 | C13: =(Deviation_sequence!$B$233 + 0.5 *Deviation_sequence!$B$232) / (Deviation_sequence!C13 + 0.5 * Deviation_sequence!$B$232) -> 0.6199946 | D13: =(Deviation_sequence!$B$233 + 0.5 *Deviation_sequence!$B$232) / (Deviation_sequence!D13 + 0.5 * Deviation_sequence!$B$232) -> 0.62316065 | E13: =(Deviation_sequence!$B$233 + 0.5 *Deviation_sequence!$B$232) / (Deviation_sequence!E13 + 0.5 * Deviation_sequence!$B$232) -> 0.68511079 | F13: =(Deviation_sequence!$B$233 + 0.5 *Deviation_sequence!$B$232) / (Deviation_sequence!F13 + 0.5 * Deviation_sequence!$B$232) -> 0.76361648 | G13: =(Deviation_sequence!$B$233 + 0.5 *Deviation_sequence!$B$232) / (Deviation_sequence!G13 + 0.5 * Deviation_sequence!$B$232) -> 0.71757867 | H13: =(Deviation_sequence!$B$233 + 0.5 *Deviation_sequence!$B$232) / (Deviation_sequence!H13 + 0.5 * Deviation_sequence!$B$232) -> 0.77132196 | I13: =(Deviation_sequence!$B$233 + 0.5 *Deviation_sequence!$B$232) / (Deviation_sequence!I13 + 0.5 * Deviation_sequence!$B$232) -> 0.59325943 | ... M13: =(Deviation_sequence!$B$233 + 0.5 *Deviation_sequence!$B$232) / (Deviation_sequence!M13 + 0.5 * Deviation_sequence!$B$232) -> 0.34979256 | O13: =AVERAGE(B13:M13) -> 0.6233061
... A30: UltraTech Cement Ltd | B30: =(Deviation_sequence!$B$233 + 0.5 *Deviation_sequence!$B$232) / (Deviation_sequence!B30 + 0.5 * Deviation_sequence!$B$232) -> 0.34771999 | C30: =(Deviation_sequence!$B$233 + 0.5 *Deviation_sequence!$B$232) / (Deviation_sequence!C30 + 0.5 * Deviation_sequence!$B$232) -> 0.34952977 | D30: =(Deviation_sequence!$B$233 + 0.5 *Deviation_sequence!$B$232) / (Deviation_sequence!D30 + 0.5 * Deviation_sequence!$B$232) -> 0.36385009 | E30: =(Deviation_sequence!$B$233 + 0.5 *Deviation_sequence!$B$232) / (Deviation_sequence!E30 + 0.5 * Deviation_sequence!$B$232) -> 0.34454055 | F30: =(Deviation_sequence!$B$233 + 0.5 *Deviation_sequence!$B$232) / (Deviation_sequence!F30 + 0.5 * Deviation_sequence!$B$232) -> 0.35998869 | G30: =(Deviation_sequence!$B$233 + 0.5 *Deviation_sequence!$B$232) / (Deviation_sequence!G30 + 0.5 * Deviation_sequence!$B$232) -> 0.34283216 | H30: =(Deviation_sequence!$B$233 + 0.5 *Deviation_sequence!$B$232) / (Deviation_sequence!H30 + 0.5 * Deviation_sequence!$B$232) -> 0.54279223 | I30: =(Deviation_sequence!$B$233 + 0.5 *Deviation_sequence!$B$232) / (Deviation_sequence!I30 + 0.5 * Deviation_sequence!$B$232) -> 0.5516091 | ... M30: =(Deviation_sequence!$B$233 + 0.5 *Deviation_sequence!$B$232) / (Deviation_sequence!M30 + 0.5 * Deviation_sequence!$B$232) -> 0.56566474 | O30: =AVERAGE(B30:M30) -> 0.44942872
N31: ratioscore= | O31: =AVERAGE(O2:O30) -> 0.74014435
A34: payout ratio | B34: (PR)2025 | C34: (PR)2024 | D34: (PR)2023 | E34: (PR)2022 | F34: (PR)2021 | G34: (PR)2020 | H34: (PR)2019 | I34: (PR)2018 | J34: (PR)2017 | K34: (PR)2016 | L34: (PR)2015 | M34: (PR)2014
A35: Adani Ports and Special Economic Zone Ltd | B35: =(Deviation_sequence!$B$233 + 0.5 *Deviation_sequence!$B$232) / (Deviation_sequence!B35 + 0.5 * Deviation_sequence!$B$232) -> 0.77722989 | C35: =(Deviation_sequence!$B$233 + 0.5 *Deviation_sequence!$B$232) / (Deviation_sequence!C35 + 0.5 * Deviation_sequence!$B$232) -> 0.85925131 | D35: =(Deviation_sequence!$B$233 + 0.5 *Deviation_sequence!$B$232) / (Deviation_sequence!D35 + 0.5 * Deviation_sequence!$B$232) -> 0.68774895 | E35: =(Deviation_sequence!$B$233 + 0.5 *Deviation_sequence!$B$232) / (Deviation_sequence!E35 + 0.5 * Deviation_sequence!$B$232) -> 0.68664607 | F35: =(Deviation_sequence!$B$233 + 0.5 *Deviation_sequence!$B$232) / (Deviation_sequence!F35 + 0.5 * Deviation_sequence!$B$232) -> 0.84452494 | G35: =(Deviation_sequence!$B$233 + 0.5 *Deviation_sequence!$B$232) / (Deviation_sequence!G35 + 0.5 * Deviation_sequence!$B$232) -> 0.69003104 | H35: =(Deviation_sequence!$B$233 + 0.5 *Deviation_sequence!$B$232) / (Deviation_sequence!H35 + 0.5 * Deviation_sequence!$B$232) -> 0.82764531 | I35: =(Deviation_sequence!$B$233 + 0.5 *Deviation_sequence!$B$232) / (Deviation_sequence!I35 + 0.5 * Deviation_sequence!$B$232) -> 0.86874932 | ... M35: =(Deviation_sequence!$B$233 + 0.5 *Deviation_sequence!$B$232) / (Deviation_sequence!M35 + 0.5 * Deviation_sequence!$B$232) -> 0.82497986 | O35: =AVERAGE(B35:M35) -> 0.80304209
A36: Asian Paints Ltd | B36: =(Deviation_sequence!$B$233 + 0.5 *Deviation_sequence!$B$232) / (Deviation_sequence!B36 + 0.5 * Deviation_sequence!$B$232) -> 0.35004372 | C36: =(Deviation_sequence!$B$233 + 0.5 *Deviation_sequence!$B$232) / (Deviation_sequence!C36 + 0.5 * Deviation_sequence!$B$232) -> 0.50166355 | D36: =(Deviation_sequence!$B$233 + 0.5 *Deviation_sequence!$B$232) / (Deviation_sequence!D36 + 0.5 * Deviation_sequence!$B$232) -> 0.49732582 | E36: =(Deviation_sequence!$B$233 + 0.5 *Deviation_sequence!$B$232) / (Deviation_sequence!E36 + 0.5 * Deviation_sequence!$B$232) -> 0.45350498 | F36: =(Deviation_sequence!$B$233 + 0.5 *Deviation_sequence!$B$232) / (Deviation_sequence!F36 + 0.5 * Deviation_sequence!$B$232) -> 0.86611744 | G36: =(Deviation_sequence!$B$233 + 0.5 *Deviation_sequence!$B$232) / (Deviation_sequence!G36 + 0.5 * Deviation_sequence!$B$232) -> 0.42213077 | H36: =(Deviation_sequence!$B$233 + 0.5 *Deviation_sequence!$B$232) / (Deviation_sequence!H36 + 0.5 * Deviation_sequence!$B$232) -> 0.55370991 | I36: =(Deviation_sequence!$B$233 + 0.5 *Deviation_sequence!$B$232) / (Deviation_sequence!I36 + 0.5 * Deviation_sequence!$B$232) -> 0.49019014 | ... M36: =(Deviation_sequence!$B$233 + 0.5 *Deviation_sequence!$B$232) / (Deviation_sequence!M36 + 0.5 * Deviation_sequence!$B$232) -> 0.53402429 | O36: =AVERAGE(B36:M36) -> 0.52779126
A37: AXIS Bank Ltd | B37: =(Deviation_sequence!$B$233 + 0.5 *Deviation_sequence!$B$232) / (Deviation_sequence!B37 + 0.5 * Deviation_sequence!$B$232) -> 0.98084247 | C37: =(Deviation_sequence!$B$233 + 0.5 *Deviation_sequence!$B$232) / (Deviation_sequence!C37 + 0.5 * Deviation_sequence!$B$232) -> 0.99744861 | D37: =(Deviation_sequence!$B$233 + 0.5 *Deviation_sequence!$B$232) / (Deviation_sequence!D37 + 0.5 * Deviation_sequence!$B$232) -> 0.96273075 | E37: =(Deviation_sequence!$B$233 + 0.5 *Deviation_sequence!$B$232) / (Deviation_sequence!E37 + 0.5 * Deviation_sequence!$B$232) -> 0.98475394 | F37: =(Deviation_sequence!$B$233 + 0.5 *Deviation_sequence!$B$232) / (Deviation_sequence!F37 + 0.5 * Deviation_sequence!$B$232) -> 0.93361171 | G37: =(Deviation_sequence!$B$233 + 0.5 *Deviation_sequence!$B$232) / (Deviation_sequence!G37 + 0.5 * Deviation_sequence!$B$232) -> 0.90106121 | H37: =(Deviation_sequence!$B$233 + 0.5 *Deviation_sequence!$B$232) / (Deviation_sequence!H37 + 0.5 * Deviation_sequence!$B$232) -> 0.97960734 | I37: =(Deviation_sequence!$B$233 + 0.5 *Deviation_sequence!$B$232) / (Deviation_sequence!I37 + 0.5 * Deviation_sequence!$B$232) -> 0.97753248 | ... M37: =(Deviation_sequence!$B$233 + 0.5 *Deviation_sequence!$B$232) / (Deviation_sequence!M37 + 0.5 * Deviation_sequence!$B$232) -> 0.98923698 | O37: =AVERAGE(B37:M37) -> 0.96373008
A38: Bajaj Finserv Ltd | B38: =(Deviation_sequence!$B$233 + 0.5 *Deviation_sequence!$B$232) / (Deviation_sequence!B38 + 0.5 * Deviation_sequence!$B$232) -> 0.98691146 | C38: =(Deviation_sequence!$B$233 + 0.5 *Deviation_sequence!$B$232) / (Deviation_sequence!C38 + 0.5 * Deviation_sequence!$B$232) -> 0.99394735 | D38: =(Deviation_sequence!$B$233 + 0.5 *Deviation_sequence!$B$232) / (Deviation_sequence!D38 + 0.5 * Deviation_sequence!$B$232) -> 0.95133483 | E38: =(Deviation_sequence!$B$233 + 0.5 *Deviation_sequence!$B$232) / (Deviation_sequence!E38 + 0.5 * Deviation_sequence!$B$232) -> 0.93269748 | F38: =(Deviation_sequence!$B$233 + 0.5 *Deviation_sequence!$B$232) / (Deviation_sequence!F38 + 0.5 * Deviation_sequence!$B$232) -> 0.87596899 | G38: =(Deviation_sequence!$B$233 + 0.5 *Deviation_sequence!$B$232) / (Deviation_sequence!G38 + 0.5 * Deviation_sequence!$B$232) -> 0.90741088 | H38: =(Deviation_sequence!$B$233 + 0.5 *Deviation_sequence!$B$232) / (Deviation_sequence!H38 + 0.5 * Deviation_sequence!$B$232) -> 0.96945482 | I38: =(Deviation_sequence!$B$233 + 0.5 *Deviation_sequence!$B$232) / (Deviation_sequence!I38 + 0.5 * Deviation_sequence!$B$232) -> 0.98216192 | ... M38: =(Deviation_sequence!$B$233 + 0.5 *Deviation_sequence!$B$232) / (Deviation_sequence!M38 + 0.5 * Deviation_sequence!$B$232) -> 0.9730399 | O38: =AVERAGE(B38:M38) -> 0.94878683
A39: Bajaj Finance Ltd | B39: =(Deviation_sequence!$B$233 + 0.5 *Deviation_sequence!$B$232) / (Deviation_sequence!B39 + 0.5 * Deviation_sequence!$B$232) -> 0.79490616 | C39: =(Deviation_sequence!$B$233 + 0.5 *Deviation_sequence!$B$232) / (Deviation_sequence!C39 + 0.5 * Deviation_sequence!$B$232) -> 0.81289493 | D39: =(Deviation_sequence!$B$233 + 0.5 *Deviation_sequence!$B$232) / (Deviation_sequence!D39 + 0.5 * Deviation_sequence!$B$232) -> 0.79901582 | E39: =(Deviation_sequence!$B$233 + 0.5 *Deviation_sequence!$B$232) / (Deviation_sequence!E39 + 0.5 * Deviation_sequence!$B$232) -> 0.88805169 | F39: =(Deviation_sequence!$B$233 + 0.5 *Deviation_sequence!$B$232) / (Deviation_sequence!F39 + 0.5 * Deviation_sequence!$B$232) -> 0.86022499 | G39: =(Deviation_sequence!$B$233 + 0.5 *Deviation_sequence!$B$232) / (Deviation_sequence!G39 + 0.5 * Deviation_sequence!$B$232) -> 0.71565722 | H39: =(Deviation_sequence!$B$233 + 0.5 *Deviation_sequence!$B$232) / (Deviation_sequence!H39 + 0.5 * Deviation_sequence!$B$232) -> 0.96709156 | I39: =(Deviation_sequence!$B$233 + 0.5 *Deviation_sequence!$B$232) / (Deviation_sequence!I39 + 0.5 * Deviation_sequence!$B$232) -> 0.91294401 | ... M39: =(Deviation_sequence!$B$233 + 0.5 *Deviation_sequence!$B$232) / (Deviation_sequence!M39 + 0.5 * Deviation_sequence!$B$232) -> 0.86317999 | O39: =AVERAGE(B39:M39) -> 0.85932037
A40: Bharat Electronics Ltd | B40: =(Deviation_sequence!$B$233 + 0.5 *Deviation_sequence!$B$232) / (Deviation_sequence!B40 + 0.5 * Deviation_sequence!$B$232) -> 0.61415152 | C40: =(Deviation_sequence!$B$233 + 0.5 *Deviation_sequence!$B$232) / (Deviation_sequence!C40 + 0.5 * Deviation_sequence!$B$232) -> 0.59623376 | D40: =(Deviation_sequence!$B$233 + 0.5 *Deviation_sequence!$B$232) / (Deviation_sequence!D40 + 0.5 * Deviation_sequence!$B$232) -> 0.54257378 | E40: =(Deviation_sequence!$B$233 + 0.5 *Deviation_sequence!$B$232) / (Deviation_sequence!E40 + 0.5 * Deviation_sequence!$B$232) -> 0.54453718 | F40: =(Deviation_sequence!$B$233 + 0.5 *Deviation_sequence!$B$232) / (Deviation_sequence!F40 + 0.5 * Deviation_sequence!$B$232) -> 0.51189139 | G40: =(Deviation_sequence!$B$233 + 0.5 *Deviation_sequence!$B$232) / (Deviation_sequence!G40 + 0.5 * Deviation_sequence!$B$232) -> 0.52485444 | H40: =(Deviation_sequence!$B$233 + 0.5 *Deviation_sequence!$B$232) / (Deviation_sequence!H40 + 0.5 * Deviation_sequence!$B$232) -> 0.60765551 | I40: =(Deviation_sequence!$B$233 + 0.5 *Deviation_sequence!$B$232) / (Deviation_sequence!I40 + 0.5 * Deviation_sequence!$B$232) -> 0.51243714 | ... M40: =(Deviation_sequence!$B$233 + 0.5 *Deviation_sequence!$B$232) / (Deviation_sequence!M40 + 0.5 * Deviation_sequence!$B$232) -> 0.70885601 | O40: =AVERAGE(B40:M40) -> 0.60476872
A41: Bharti Airtel Ltd | B41: =(Deviation_sequence!$B$233 + 0.5 *Deviation_sequence!$B$232) / (Deviation_sequence!B41 + 0.5 * Deviation_sequence!$B$232) -> 0.80220263 | C41: =(Deviation_sequence!$B$233 + 0.5 *Deviation_sequence!$B$232) / (Deviation_sequence!C41 + 0.5 * Deviation_sequence!$B$232) -> 0.63711311 | D41: =(Deviation_sequence!$B$233 + 0.5 *Deviation_sequence!$B$232) / (Deviation_sequence!D41 + 0.5 * Deviation_sequence!$B$232) -> 0.69457473 | E41: =(Deviation_sequence!$B$233 + 0.5 *Deviation_sequence!$B$232) / (Deviation_sequence!E41 + 0.5 * Deviation_sequence!$B$232) -> 0.94200632 | F41: =(Deviation_sequence!$B$233 + 0.5 *Deviation_sequence!$B$232) / (Deviation_sequence!F41 + 0.5 * Deviation_sequence!$B$232) -> 0.97653405 | G41: =(Deviation_sequence!$B$233 + 0.5 *Deviation_sequence!$B$232) / (Deviation_sequence!G41 + 0.5 * Deviation_sequence!$B$232) -> 0.94801323 | H41: =(Deviation_sequence!$B$233 + 0.5 *Deviation_sequence!$B$232) / (Deviation_sequence!H41 + 0.5 * Deviation_sequence!$B$232) -> 0.3417823 | I41: =(Deviation_sequence!$B$233 + 0.5 *Deviation_sequence!$B$232) / (Deviation_sequence!I41 + 0.5 * Deviation_sequence!$B$232) -> 0.34796255 | ... M41: =(Deviation_sequence!$B$233 + 0.5 *Deviation_sequence!$B$232) / (Deviation_sequence!M41 + 0.5 * Deviation_sequence!$B$232) -> 0.97517861 | O41: =AVERAGE(B41:M41) -> 0.72627778
A42: HCL Technologies Ltd | B42: =(Deviation_sequence!$B$233 + 0.5 *Deviation_sequence!$B$232) / (Deviation_sequence!B42 + 0.5 * Deviation_sequence!$B$232) -> 0.34650205 | C42: =(Deviation_sequence!$B$233 + 0.5 *Deviation_sequence!$B$232) / (Deviation_sequence!C42 + 0.5 * Deviation_sequence!$B$232) -> 0.35278666 | D42: =(Deviation_sequence!$B$233 + 0.5 *Deviation_sequence!$B$232) / (Deviation_sequence!D42 + 0.5 * Deviation_sequence!$B$232) -> 0.34650951 | E42: =(Deviation_sequence!$B$233 + 0.5 *Deviation_sequence!$B$232) / (Deviation_sequence!E42 + 0.5 * Deviation_sequence!$B$232) -> 0.35894328 | F42: =(Deviation_sequence!$B$233 + 0.5 *Deviation_sequence!$B$232) / (Deviation_sequence!F42 + 0.5 * Deviation_sequence!$B$232) -> 0.67283225 | G42: =(Deviation_sequence!$B$233 + 0.5 *Deviation_sequence!$B$232) / (Deviation_sequence!G42 + 0.5 * Deviation_sequence!$B$232) -> 0.77222597 | H42: =(Deviation_sequence!$B$233 + 0.5 *Deviation_sequence!$B$232) / (Deviation_sequence!H42 + 0.5 * Deviation_sequence!$B$232) -> 0.82432626 | I42: =(Deviation_sequence!$B$233 + 0.5 *Deviation_sequence!$B$232) / (Deviation_sequence!I42 + 0.5 * Deviation_sequence!$B$232) -> 0.71527362 | ... M42: =(Deviation_sequence!$B$233 + 0.5 *Deviation_sequence!$B$232) / (Deviation_sequence!M42 + 0.5 * Deviation_sequence!$B$232) -> 0.88230836 | O42: =AVERAGE(B42:M42) -> 0.57628628
A43: HDFC Bank Ltd | B43: =(Deviation_sequence!$B$233 + 0.5 *Deviation_sequence!$B$232) / (Deviation_sequence!B43 + 0.5 * Deviation_sequence!$B$232) -> 0.66246243 | C43: =(Deviation_sequence!$B$233 + 0.5 *Deviation_sequence!$B$232) / (Deviation_sequence!C43 + 0.5 * Deviation_sequence!$B$232) -> 0.65075433 | D43: =(Deviation_sequence!$B$233 + 0.5 *Deviation_sequence!$B$232) / (Deviation_sequence!D43 + 0.5 * Deviation_sequence!$B$232) -> 0.6667281 | E43: =(Deviation_sequence!$B$233 + 0.5 *Deviation_sequence!$B$232) / (Deviation_sequence!E43 + 0.5 * Deviation_sequence!$B$232) -> 0.6673851 | F43: =(Deviation_sequence!$B$233 + 0.5 *Deviation_sequence!$B$232) / (Deviation_sequence!F43 + 0.5 * Deviation_sequence!$B$232) -> 0.86162101 | G43: =(Deviation_sequence!$B$233 + 0.5 *Deviation_sequence!$B$232) / (Deviation_sequence!G43 + 0.5 * Deviation_sequence!$B$232) -> 0.96437073 | H43: =(Deviation_sequence!$B$233 + 0.5 *Deviation_sequence!$B$232) / (Deviation_sequence!H43 + 0.5 * Deviation_sequence!$B$232) -> 0.73120681 | I43: =(Deviation_sequence!$B$233 + 0.5 *Deviation_sequence!$B$232) / (Deviation_sequence!I43 + 0.5 * Deviation_sequence!$B$232) -> 0.72851918 | ... M43: =(Deviation_sequence!$B$233 + 0.5 *Deviation_sequence!$B$232) / (Deviation_sequence!M43 + 0.5 * Deviation_sequence!$B$232) -> 0.97006593 | O43: =AVERAGE(B43:M43) -> 0.77208084
A44: Hindustan Unilever Ltd | B44: =(Deviation_sequence!$B$233 + 0.5 *Deviation_sequence!$B$232) / (Deviation_sequence!B44 + 0.5 * Deviation_sequence!$B$232) -> 0.34563935 | C44: =(Deviation_sequence!$B$233 + 0.5 *Deviation_sequence!$B$232) / (Deviation_sequence!C44 + 0.5 * Deviation_sequence!$B$232) -> 0.34287064 | D44: =(Deviation_sequence!$B$233 + 0.5 *Deviation_sequence!$B$232) / (Deviation_sequence!D44 + 0.5 * Deviation_sequence!$B$232) -> 0.36162323 | E44: =(Deviation_sequence!$B$233 + 0.5 *Deviation_sequence!$B$232) / (Deviation_sequence!E44 + 0.5 * Deviation_sequence!$B$232) -> 0.35063955 | F44: =(Deviation_sequence!$B$233 + 0.5 *Deviation_sequence!$B$232) / (Deviation_sequence!F44 + 0.5 * Deviation_sequence!$B$232) -> 0.34660923 | G44: =(Deviation_sequence!$B$233 + 0.5 *Deviation_sequence!$B$232) / (Deviation_sequence!G44 + 0.5 * Deviation_sequence!$B$232) -> 0.38273865 | H44: =(Deviation_sequence!$B$233 + 0.5 *Deviation_sequence!$B$232) / (Deviation_sequence!H44 + 0.5 * Deviation_sequence!$B$232) -> 0.38791072 | I44: =(Deviation_sequence!$B$233 + 0.5 *Deviation_sequence!$B$232) / (Deviation_sequence!I44 + 0.5 * Deviation_sequence!$B$232) -> 0.39236597 | ... M44: =(Deviation_sequence!$B$233 + 0.5 *Deviation_sequence!$B$232) / (Deviation_sequence!M44 + 0.5 * Deviation_sequence!$B$232) -> 0.40257407 | O44: =AVERAGE(B44:M44) -> 0.36996477
A45: ICICI Bank Ltd | B45: =(Deviation_sequence!$B$233 + 0.5 *Deviation_sequence!$B$232) / (Deviation_sequence!B45 + 0.5 * Deviation_sequence!$B$232) -> 0.76750853 | C45: =(Deviation_sequence!$B$233 + 0.5 *Deviation_sequence!$B$232) / (Deviation_sequence!C45 + 0.5 * Deviation_sequence!$B$232) -> 0.76410442 | D45: =(Deviation_sequence!$B$233 + 0.5 *Deviation_sequence!$B$232) / (Deviation_sequence!D45 + 0.5 * Deviation_sequence!$B$232) -> 0.75941502 | E45: =(Deviation_sequence!$B$233 + 0.5 *Deviation_sequence!$B$232) / (Deviation_sequence!E45 + 0.5 * Deviation_sequence!$B$232) -> 0.79647194 | F45: =(Deviation_sequence!$B$233 + 0.5 *Deviation_sequence!$B$232) / (Deviation_sequence!F45 + 0.5 * Deviation_sequence!$B$232) -> 0.93176414 | G45: =(Deviation_sequence!$B$233 + 0.5 *Deviation_sequence!$B$232) / (Deviation_sequence!G45 + 0.5 * Deviation_sequence!$B$232) -> 0.98500746 | H45: =(Deviation_sequence!$B$233 + 0.5 *Deviation_sequence!$B$232) / (Deviation_sequence!H45 + 0.5 * Deviation_sequence!$B$232) -> 0.79190251 | I45: =(Deviation_sequence!$B$233 + 0.5 *Deviation_sequence!$B$232) / (Deviation_sequence!I45 + 0.5 * Deviation_sequence!$B$232) -> 0.80591326 | ... M45: =(Deviation_sequence!$B$233 + 0.5 *Deviation_sequence!$B$232) / (Deviation_sequence!M45 + 0.5 * Deviation_sequence!$B$232) -> 0.67690019 | O45: =AVERAGE(B45:M45) -> 0.77904847
A46: Infosys Ltd | B46: =(Deviation_sequence!$B$233 + 0.5 *Deviation_sequence!$B$232) / (Deviation_sequence!B46 + 0.5 * Deviation_sequence!$B$232) -> 0.38101348 | C46: =(Deviation_sequence!$B$233 + 0.5 *Deviation_sequence!$B$232) / (Deviation_sequence!C46 + 0.5 * Deviation_sequence!$B$232) -> 0.45595943 | D46: =(Deviation_sequence!$B$233 + 0.5 *Deviation_sequence!$B$232) / (Deviation_sequence!D46 + 0.5 * Deviation_sequence!$B$232) -> 0.44303343 | E46: =(Deviation_sequence!$B$233 + 0.5 *Deviation_sequence!$B$232) / (Deviation_sequence!E46 + 0.5 * Deviation_sequence!$B$232) -> 0.45896524 | F46: =(Deviation_sequence!$B$233 + 0.5 *Deviation_sequence!$B$232) / (Deviation_sequence!F46 + 0.5 * Deviation_sequence!$B$232) -> 0.53155957 | G46: =(Deviation_sequence!$B$233 + 0.5 *Deviation_sequence!$B$232) / (Deviation_sequence!G46 + 0.5 * Deviation_sequence!$B$232) -> 0.44374076 | H46: =(Deviation_sequence!$B$233 + 0.5 *Deviation_sequence!$B$232) / (Deviation_sequence!H46 + 0.5 * Deviation_sequence!$B$232) -> 0.35048326 | I46: =(Deviation_sequence!$B$233 + 0.5 *Deviation_sequence!$B$232) / (Deviation_sequence!I46 + 0.5 * Deviation_sequence!$B$232) -> 0.50377418 | ... M46: =(Deviation_sequence!$B$233 + 0.5 *Deviation_sequence!$B$232) / (Deviation_sequence!M46 + 0.5 * Deviation_sequence!$B$232) -> 0.58798701 | O46: =AVERAGE(B46:M46) -> 0.47237674
... A63: UltraTech Cement Ltd | B63: =(Deviation_sequence!$B$233 + 0.5 *Deviation_sequence!$B$232) / (Deviation_sequence!B63 + 0.5 * Deviation_sequence!$B$232) -> 0.58866162 | C63: =(Deviation_sequence!$B$233 + 0.5 *Deviation_sequence!$B$232) / (Deviation_sequence!C63 + 0.5 * Deviation_sequence!$B$232) -> 0.76884894 | D63: =(Deviation_sequence!$B$233 + 0.5 *Deviation_sequence!$B$232) / (Deviation_sequence!D63 + 0.5 * Deviation_sequence!$B$232) -> 0.69542714 | E63: =(Deviation_sequence!$B$233 + 0.5 *Deviation_sequence!$B$232) / (Deviation_sequence!E63 + 0.5 * Deviation_sequence!$B$232) -> 0.75864682 | F63: =(Deviation_sequence!$B$233 + 0.5 *Deviation_sequence!$B$232) / (Deviation_sequence!F63 + 0.5 * Deviation_sequence!$B$232) -> 0.97239573 | G63: =(Deviation_sequence!$B$233 + 0.5 *Deviation_sequence!$B$232) / (Deviation_sequence!G63 + 0.5 * Deviation_sequence!$B$232) -> 0.86057744 | H63: =(Deviation_sequence!$B$233 + 0.5 *Deviation_sequence!$B$232) / (Deviation_sequence!H63 + 0.5 * Deviation_sequence!$B$232) -> 0.76003723 | I63: =(Deviation_sequence!$B$233 + 0.5 *Deviation_sequence!$B$232) / (Deviation_sequence!I63 + 0.5 * Deviation_sequence!$B$232) -> 0.75389995 | ... M63: =(Deviation_sequence!$B$233 + 0.5 *Deviation_sequence!$B$232) / (Deviation_sequence!M63 + 0.5 * Deviation_sequence!$B$232) -> 0.82840122 | O63: =AVERAGE(B63:M63) -> 0.78964328
N64: ratioscore= | O64: =AVERAGE(O35:O63) -> 0.69292876
A67: Profit margin | B67: (PM)2025 | C67: (PM)2024 | D67: (PM)2023 | E67: (PM)2022 | F67: (PM)2021 | G67: (PM)2020 | H67: (PM)2019 | I67: (PM)2018 | J67: (PM)2017 | K67: (PM)2016 | L67: (PM)2015 | M67: (PM)2014
A68: Adani Ports and Special Economic Zone Ltd | B68: =(Deviation_sequence!$B$233 + 0.5 *Deviation_sequence!$B$232) / (Deviation_sequence!B68 + 0.5 * Deviation_sequence!$B$232) -> 0.34104686 | C68: =(Deviation_sequence!$B$233 + 0.5 *Deviation_sequence!$B$232) / (Deviation_sequence!C68 + 0.5 * Deviation_sequence!$B$232) -> 0.36854689 | D68: =(Deviation_sequence!$B$233 + 0.5 *Deviation_sequence!$B$232) / (Deviation_sequence!D68 + 0.5 * Deviation_sequence!$B$232) -> 0.39374162 | E68: =(Deviation_sequence!$B$233 + 0.5 *Deviation_sequence!$B$232) / (Deviation_sequence!E68 + 0.5 * Deviation_sequence!$B$232) -> 0.37004628 | F68: =(Deviation_sequence!$B$233 + 0.5 *Deviation_sequence!$B$232) / (Deviation_sequence!F68 + 0.5 * Deviation_sequence!$B$232) -> 0.3685964 | G68: =(Deviation_sequence!$B$233 + 0.5 *Deviation_sequence!$B$232) / (Deviation_sequence!G68 + 0.5 * Deviation_sequence!$B$232) -> 0.3391569 | H68: =(Deviation_sequence!$B$233 + 0.5 *Deviation_sequence!$B$232) / (Deviation_sequence!H68 + 0.5 * Deviation_sequence!$B$232) -> 0.34700403 | I68: =(Deviation_sequence!$B$233 + 0.5 *Deviation_sequence!$B$232) / (Deviation_sequence!I68 + 0.5 * Deviation_sequence!$B$232) -> 0.34594454 | ... M68: =(Deviation_sequence!$B$233 + 0.5 *Deviation_sequence!$B$232) / (Deviation_sequence!M68 + 0.5 * Deviation_sequence!$B$232) -> 0.35152612 | O68: =AVERAGE(B68:M68) -> 0.35627061
A69: Asian Paints Ltd | B69: =(Deviation_sequence!$B$233 + 0.5 *Deviation_sequence!$B$232) / (Deviation_sequence!B69 + 0.5 * Deviation_sequence!$B$232) -> 0.61461975 | C69: =(Deviation_sequence!$B$233 + 0.5 *Deviation_sequence!$B$232) / (Deviation_sequence!C69 + 0.5 * Deviation_sequence!$B$232) -> 0.53194845 | D69: =(Deviation_sequence!$B$233 + 0.5 *Deviation_sequence!$B$232) / (Deviation_sequence!D69 + 0.5 * Deviation_sequence!$B$232) -> 0.59198534 | E69: =(Deviation_sequence!$B$233 + 0.5 *Deviation_sequence!$B$232) / (Deviation_sequence!E69 + 0.5 * Deviation_sequence!$B$232) -> 0.64011358 | F69: =(Deviation_sequence!$B$233 + 0.5 *Deviation_sequence!$B$232) / (Deviation_sequence!F69 + 0.5 * Deviation_sequence!$B$232) -> 0.56146274 | G69: =(Deviation_sequence!$B$233 + 0.5 *Deviation_sequence!$B$232) / (Deviation_sequence!G69 + 0.5 * Deviation_sequence!$B$232) -> 0.56886797 | H69: =(Deviation_sequence!$B$233 + 0.5 *Deviation_sequence!$B$232) / (Deviation_sequence!H69 + 0.5 * Deviation_sequence!$B$232) -> 0.62701926 | I69: =(Deviation_sequence!$B$233 + 0.5 *Deviation_sequence!$B$232) / (Deviation_sequence!I69 + 0.5 * Deviation_sequence!$B$232) -> 0.59024339 | ... M69: =(Deviation_sequence!$B$233 + 0.5 *Deviation_sequence!$B$232) / (Deviation_sequence!M69 + 0.5 * Deviation_sequence!$B$232) -> 0.65146046 | O69: =AVERAGE(B69:M69) -> 0.60121779
A70: AXIS Bank Ltd | B70: =(Deviation_sequence!$B$233 + 0.5 *Deviation_sequence!$B$232) / (Deviation_sequence!B70 + 0.5 * Deviation_sequence!$B$232) -> 0.43623454 | C70: =(Deviation_sequence!$B$233 + 0.5 *Deviation_sequence!$B$232) / (Deviation_sequence!C70 + 0.5 * Deviation_sequence!$B$232) -> 0.42532556 | D70: =(Deviation_sequence!$B$233 + 0.5 *Deviation_sequence!$B$232) / (Deviation_sequence!D70 + 0.5 * Deviation_sequence!$B$232) -> 0.59486777 | E70: =(Deviation_sequence!$B$233 + 0.5 *Deviation_sequence!$B$232) / (Deviation_sequence!E70 + 0.5 * Deviation_sequence!$B$232) -> 0.45532884 | F70: =(Deviation_sequence!$B$233 + 0.5 *Deviation_sequence!$B$232) / (Deviation_sequence!F70 + 0.5 * Deviation_sequence!$B$232) -> 0.65155216 | G70: =(Deviation_sequence!$B$233 + 0.5 *Deviation_sequence!$B$232) / (Deviation_sequence!G70 + 0.5 * Deviation_sequence!$B$232) -> 0.81917322 | H70: =(Deviation_sequence!$B$233 + 0.5 *Deviation_sequence!$B$232) / (Deviation_sequence!H70 + 0.5 * Deviation_sequence!$B$232) -> 0.69727704 | I70: =(Deviation_sequence!$B$233 + 0.5 *Deviation_sequence!$B$232) / (Deviation_sequence!I70 + 0.5 * Deviation_sequence!$B$232) -> 0.98755429 | ... M70: =(Deviation_sequence!$B$233 + 0.5 *Deviation_sequence!$B$232) / (Deviation_sequence!M70 + 0.5 * Deviation_sequence!$B$232) -> 0.46194403 | O70: =AVERAGE(B70:M70) -> 0.59386266
A71: Bajaj Finserv Ltd | B71: =(Deviation_sequence!$B$233 + 0.5 *Deviation_sequence!$B$232) / (Deviation_sequence!B71 + 0.5 * Deviation_sequence!$B$232) -> 0.57838785 | C71: =(Deviation_sequence!$B$233 + 0.5 *Deviation_sequence!$B$232) / (Deviation_sequence!C71 + 0.5 * Deviation_sequence!$B$232) -> 0.56303009 | D71: =(Deviation_sequence!$B$233 + 0.5 *Deviation_sequence!$B$232) / (Deviation_sequence!D71 + 0.5 * Deviation_sequence!$B$232) -> 0.52868891 | E71: =(Deviation_sequence!$B$233 + 0.5 *Deviation_sequence!$B$232) / (Deviation_sequence!E71 + 0.5 * Deviation_sequence!$B$232) -> 0.62432377 | F71: =(Deviation_sequence!$B$233 + 0.5 *Deviation_sequence!$B$232) / (Deviation_sequence!F71 + 0.5 * Deviation_sequence!$B$232) -> 0.64319931 | G71: =(Deviation_sequence!$B$233 + 0.5 *Deviation_sequence!$B$232) / (Deviation_sequence!G71 + 0.5 * Deviation_sequence!$B$232) -> 0.60467253 | H71: =(Deviation_sequence!$B$233 + 0.5 *Deviation_sequence!$B$232) / (Deviation_sequence!H71 + 0.5 * Deviation_sequence!$B$232) -> 0.5973096 | I71: =(Deviation_sequence!$B$233 + 0.5 *Deviation_sequence!$B$232) / (Deviation_sequence!I71 + 0.5 * Deviation_sequence!$B$232) -> 0.59210778 | ... M71: =(Deviation_sequence!$B$233 + 0.5 *Deviation_sequence!$B$232) / (Deviation_sequence!M71 + 0.5 * Deviation_sequence!$B$232) -> 0.34646318 | O71: =AVERAGE(B71:M71) -> 0.53371223
A72: Bajaj Finance Ltd | B72: =(Deviation_sequence!$B$233 + 0.5 *Deviation_sequence!$B$232) / (Deviation_sequence!B72 + 0.5 * Deviation_sequence!$B$232) -> 0.41875116 | C72: =(Deviation_sequence!$B$233 + 0.5 *Deviation_sequence!$B$232) / (Deviation_sequence!C72 + 0.5 * Deviation_sequence!$B$232) -> 0.39799703 | D72: =(Deviation_sequence!$B$233 + 0.5 *Deviation_sequence!$B$232) / (Deviation_sequence!D72 + 0.5 * Deviation_sequence!$B$232) -> 0.3744186 | E72: =(Deviation_sequence!$B$233 + 0.5 *Deviation_sequence!$B$232) / (Deviation_sequence!E72 + 0.5 * Deviation_sequence!$B$232) -> 0.44479866 | F72: =(Deviation_sequence!$B$233 + 0.5 *Deviation_sequence!$B$232) / (Deviation_sequence!F72 + 0.5 * Deviation_sequence!$B$232) -> 0.55494299 | G72: =(Deviation_sequence!$B$233 + 0.5 *Deviation_sequence!$B$232) / (Deviation_sequence!G72 + 0.5 * Deviation_sequence!$B$232) -> 0.45911102 | H72: =(Deviation_sequence!$B$233 + 0.5 *Deviation_sequence!$B$232) / (Deviation_sequence!H72 + 0.5 * Deviation_sequence!$B$232) -> 0.45885488 | I72: =(Deviation_sequence!$B$233 + 0.5 *Deviation_sequence!$B$232) / (Deviation_sequence!I72 + 0.5 * Deviation_sequence!$B$232) -> 0.47574015 | ... M72: =(Deviation_sequence!$B$233 + 0.5 *Deviation_sequence!$B$232) / (Deviation_sequence!M72 + 0.5 * Deviation_sequence!$B$232) -> 0.51325018 | O72: =AVERAGE(B72:M72) -> 0.47126759
A73: Bharat Electronics Ltd | B73: =(Deviation_sequence!$B$233 + 0.5 *Deviation_sequence!$B$232) / (Deviation_sequence!B73 + 0.5 * Deviation_sequence!$B$232) -> 0.44330665 | C73: =(Deviation_sequence!$B$233 + 0.5 *Deviation_sequence!$B$232) / (Deviation_sequence!C73 + 0.5 * Deviation_sequence!$B$232) -> 0.49371621 | D73: =(Deviation_sequence!$B$233 + 0.5 *Deviation_sequence!$B$232) / (Deviation_sequence!D73 + 0.5 * Deviation_sequence!$B$232) -> 0.52354193 | E73: =(Deviation_sequence!$B$233 + 0.5 *Deviation_sequence!$B$232) / (Deviation_sequence!E73 + 0.5 * Deviation_sequence!$B$232) -> 0.55383599 | F73: =(Deviation_sequence!$B$233 + 0.5 *Deviation_sequence!$B$232) / (Deviation_sequence!F73 + 0.5 * Deviation_sequence!$B$232) -> 0.571066 | G73: =(Deviation_sequence!$B$233 + 0.5 *Deviation_sequence!$B$232) / (Deviation_sequence!G73 + 0.5 * Deviation_sequence!$B$232) -> 0.55242603 | H73: =(Deviation_sequence!$B$233 + 0.5 *Deviation_sequence!$B$232) / (Deviation_sequence!H73 + 0.5 * Deviation_sequence!$B$232) -> 0.51496664 | I73: =(Deviation_sequence!$B$233 + 0.5 *Deviation_sequence!$B$232) / (Deviation_sequence!I73 + 0.5 * Deviation_sequence!$B$232) -> 0.5597281 | ... M73: =(Deviation_sequence!$B$233 + 0.5 *Deviation_sequence!$B$232) / (Deviation_sequence!M73 + 0.5 * Deviation_sequence!$B$232) -> 0.54539673 | O73: =AVERAGE(B73:M73) -> 0.52706078
A74: Bharti Airtel Ltd | B74: =(Deviation_sequence!$B$233 + 0.5 *Deviation_sequence!$B$232) / (Deviation_sequence!B74 + 0.5 * Deviation_sequence!$B$232) -> 0.47779618 | C74: =(Deviation_sequence!$B$233 + 0.5 *Deviation_sequence!$B$232) / (Deviation_sequence!C74 + 0.5 * Deviation_sequence!$B$232) -> 0.9025362 | D74: =(Deviation_sequence!$B$233 + 0.5 *Deviation_sequence!$B$232) / (Deviation_sequence!D74 + 0.5 * Deviation_sequence!$B$232) -> 0.68327288 | E74: =(Deviation_sequence!$B$233 + 0.5 *Deviation_sequence!$B$232) / (Deviation_sequence!E74 + 0.5 * Deviation_sequence!$B$232) -> 0.83097369 | F74: =(Deviation_sequence!$B$233 + 0.5 *Deviation_sequence!$B$232) / (Deviation_sequence!F74 + 0.5 * Deviation_sequence!$B$232) -> 0.97653405 | G74: =(Deviation_sequence!$B$233 + 0.5 *Deviation_sequence!$B$232) / (Deviation_sequence!G74 + 0.5 * Deviation_sequence!$B$232) -> 0.94801323 | H74: =(Deviation_sequence!$B$233 + 0.5 *Deviation_sequence!$B$232) / (Deviation_sequence!H74 + 0.5 * Deviation_sequence!$B$232) -> 0.91958481 | I74: =(Deviation_sequence!$B$233 + 0.5 *Deviation_sequence!$B$232) / (Deviation_sequence!I74 + 0.5 * Deviation_sequence!$B$232) -> 0.98359986 | ... M74: =(Deviation_sequence!$B$233 + 0.5 *Deviation_sequence!$B$232) / (Deviation_sequence!M74 + 0.5 * Deviation_sequence!$B$232) -> 0.87207046 | O74: =AVERAGE(B74:M74) -> 0.83475251
A75: HCL Technologies Ltd | B75: =(Deviation_sequence!$B$233 + 0.5 *Deviation_sequence!$B$232) / (Deviation_sequence!B75 + 0.5 * Deviation_sequence!$B$232) -> 0.54065017 | C75: =(Deviation_sequence!$B$233 + 0.5 *Deviation_sequence!$B$232) / (Deviation_sequence!C75 + 0.5 * Deviation_sequence!$B$232) -> 0.56701153 | D75: =(Deviation_sequence!$B$233 + 0.5 *Deviation_sequence!$B$232) / (Deviation_sequence!D75 + 0.5 * Deviation_sequence!$B$232) -> 0.54171695 | E75: =(Deviation_sequence!$B$233 + 0.5 *Deviation_sequence!$B$232) / (Deviation_sequence!E75 + 0.5 * Deviation_sequence!$B$232) -> 0.53104792 | F75: =(Deviation_sequence!$B$233 + 0.5 *Deviation_sequence!$B$232) / (Deviation_sequence!F75 + 0.5 * Deviation_sequence!$B$232) -> 0.58339122 | G75: =(Deviation_sequence!$B$233 + 0.5 *Deviation_sequence!$B$232) / (Deviation_sequence!G75 + 0.5 * Deviation_sequence!$B$232) -> 0.51580385 | H75: =(Deviation_sequence!$B$233 + 0.5 *Deviation_sequence!$B$232) / (Deviation_sequence!H75 + 0.5 * Deviation_sequence!$B$232) -> 0.51170931 | I75: =(Deviation_sequence!$B$233 + 0.5 *Deviation_sequence!$B$232) / (Deviation_sequence!I75 + 0.5 * Deviation_sequence!$B$232) -> 0.50405308 | ... M75: =(Deviation_sequence!$B$233 + 0.5 *Deviation_sequence!$B$232) / (Deviation_sequence!M75 + 0.5 * Deviation_sequence!$B$232) -> 0.47869615 | O75: =AVERAGE(B75:M75) -> 0.5188943
A76: HDFC Bank Ltd | B76: =(Deviation_sequence!$B$233 + 0.5 *Deviation_sequence!$B$232) / (Deviation_sequence!B76 + 0.5 * Deviation_sequence!$B$232) -> 0.4369887 | C76: =(Deviation_sequence!$B$233 + 0.5 *Deviation_sequence!$B$232) / (Deviation_sequence!C76 + 0.5 * Deviation_sequence!$B$232) -> 0.41702376 | D76: =(Deviation_sequence!$B$233 + 0.5 *Deviation_sequence!$B$232) / (Deviation_sequence!D76 + 0.5 * Deviation_sequence!$B$232) -> 0.38521905 | E76: =(Deviation_sequence!$B$233 + 0.5 *Deviation_sequence!$B$232) / (Deviation_sequence!E76 + 0.5 * Deviation_sequence!$B$232) -> 0.36887003 | F76: =(Deviation_sequence!$B$233 + 0.5 *Deviation_sequence!$B$232) / (Deviation_sequence!F76 + 0.5 * Deviation_sequence!$B$232) -> 0.41103938 | G76: =(Deviation_sequence!$B$233 + 0.5 *Deviation_sequence!$B$232) / (Deviation_sequence!G76 + 0.5 * Deviation_sequence!$B$232) -> 0.41957743 | H76: =(Deviation_sequence!$B$233 + 0.5 *Deviation_sequence!$B$232) / (Deviation_sequence!H76 + 0.5 * Deviation_sequence!$B$232) -> 0.45106435 | I76: =(Deviation_sequence!$B$233 + 0.5 *Deviation_sequence!$B$232) / (Deviation_sequence!I76 + 0.5 * Deviation_sequence!$B$232) -> 0.44693194 | ... M76: =(Deviation_sequence!$B$233 + 0.5 *Deviation_sequence!$B$232) / (Deviation_sequence!M76 + 0.5 * Deviation_sequence!$B$232) -> 0.45898628 | O76: =AVERAGE(B76:M76) -> 0.43066284
A77: Hindustan Unilever Ltd | B77: =(Deviation_sequence!$B$233 + 0.5 *Deviation_sequence!$B$232) / (Deviation_sequence!B77 + 0.5 * Deviation_sequence!$B$232) -> 0.50474523 | C77: =(Deviation_sequence!$B$233 + 0.5 *Deviation_sequence!$B$232) / (Deviation_sequence!C77 + 0.5 * Deviation_sequence!$B$232) -> 0.50343344 | D77: =(Deviation_sequence!$B$233 + 0.5 *Deviation_sequence!$B$232) / (Deviation_sequence!D77 + 0.5 * Deviation_sequence!$B$232) -> 0.51601794 | E77: =(Deviation_sequence!$B$233 + 0.5 *Deviation_sequence!$B$232) / (Deviation_sequence!E77 + 0.5 * Deviation_sequence!$B$232) -> 0.49663357 | F77: =(Deviation_sequence!$B$233 + 0.5 *Deviation_sequence!$B$232) / (Deviation_sequence!F77 + 0.5 * Deviation_sequence!$B$232) -> 0.50541759 | G77: =(Deviation_sequence!$B$233 + 0.5 *Deviation_sequence!$B$232) / (Deviation_sequence!G77 + 0.5 * Deviation_sequence!$B$232) -> 0.51497991 | H77: =(Deviation_sequence!$B$233 + 0.5 *Deviation_sequence!$B$232) / (Deviation_sequence!H77 + 0.5 * Deviation_sequence!$B$232) -> 0.5396858 | I77: =(Deviation_sequence!$B$233 + 0.5 *Deviation_sequence!$B$232) / (Deviation_sequence!I77 + 0.5 * Deviation_sequence!$B$232) -> 0.55910792 | ... M77: =(Deviation_sequence!$B$233 + 0.5 *Deviation_sequence!$B$232) / (Deviation_sequence!M77 + 0.5 * Deviation_sequence!$B$232) -> 0.57877378 | O77: =AVERAGE(B77:M77) -> 0.53641276
A78: ICICI Bank Ltd | B78: =(Deviation_sequence!$B$233 + 0.5 *Deviation_sequence!$B$232) / (Deviation_sequence!B78 + 0.5 * Deviation_sequence!$B$232) -> 0.37011864 | C78: =(Deviation_sequence!$B$233 + 0.5 *Deviation_sequence!$B$232) / (Deviation_sequence!C78 + 0.5 * Deviation_sequence!$B$232) -> 0.37924808 | D78: =(Deviation_sequence!$B$233 + 0.5 *Deviation_sequence!$B$232) / (Deviation_sequence!D78 + 0.5 * Deviation_sequence!$B$232) -> 0.37746365 | E78: =(Deviation_sequence!$B$233 + 0.5 *Deviation_sequence!$B$232) / (Deviation_sequence!E78 + 0.5 * Deviation_sequence!$B$232) -> 0.39112826 | F78: =(Deviation_sequence!$B$233 + 0.5 *Deviation_sequence!$B$232) / (Deviation_sequence!F78 + 0.5 * Deviation_sequence!$B$232) -> 0.44516387 | G78: =(Deviation_sequence!$B$233 + 0.5 *Deviation_sequence!$B$232) / (Deviation_sequence!G78 + 0.5 * Deviation_sequence!$B$232) -> 0.56262187 | H78: =(Deviation_sequence!$B$233 + 0.5 *Deviation_sequence!$B$232) / (Deviation_sequence!H78 + 0.5 * Deviation_sequence!$B$232) -> 0.72563713 | I78: =(Deviation_sequence!$B$233 + 0.5 *Deviation_sequence!$B$232) / (Deviation_sequence!I78 + 0.5 * Deviation_sequence!$B$232) -> 0.54670493 | ... M78: =(Deviation_sequence!$B$233 + 0.5 *Deviation_sequence!$B$232) / (Deviation_sequence!M78 + 0.5 * Deviation_sequence!$B$232) -> 0.42534525 | O78: =AVERAGE(B78:M78) -> 0.4675037
A79: Infosys Ltd | B79: =(Deviation_sequence!$B$233 + 0.5 *Deviation_sequence!$B$232) / (Deviation_sequence!B79 + 0.5 * Deviation_sequence!$B$232) -> 0.51512247 | C79: =(Deviation_sequence!$B$233 + 0.5 *Deviation_sequence!$B$232) / (Deviation_sequence!C79 + 0.5 * Deviation_sequence!$B$232) -> 0.50474196 | D79: =(Deviation_sequence!$B$233 + 0.5 *Deviation_sequence!$B$232) / (Deviation_sequence!D79 + 0.5 * Deviation_sequence!$B$232) -> 0.5017901 | E79: =(Deviation_sequence!$B$233 + 0.5 *Deviation_sequence!$B$232) / (Deviation_sequence!E79 + 0.5 * Deviation_sequence!$B$232) -> 0.49794135 | F79: =(Deviation_sequence!$B$233 + 0.5 *Deviation_sequence!$B$232) / (Deviation_sequence!F79 + 0.5 * Deviation_sequence!$B$232) -> 0.50067568 | G79: =(Deviation_sequence!$B$233 + 0.5 *Deviation_sequence!$B$232) / (Deviation_sequence!G79 + 0.5 * Deviation_sequence!$B$232) -> 0.47899266 | H79: =(Deviation_sequence!$B$233 + 0.5 *Deviation_sequence!$B$232) / (Deviation_sequence!H79 + 0.5 * Deviation_sequence!$B$232) -> 0.48886351 | I79: =(Deviation_sequence!$B$233 + 0.5 *Deviation_sequence!$B$232) / (Deviation_sequence!I79 + 0.5 * Deviation_sequence!$B$232) -> 0.4302515 | ... M79: =(Deviation_sequence!$B$233 + 0.5 *Deviation_sequence!$B$232) / (Deviation_sequence!M79 + 0.5 * Deviation_sequence!$B$232) -> 0.4504788 | O79: =AVERAGE(B79:M79) -> 0.47404655
... A96: UltraTech Cement Ltd | B96: =(Deviation_sequence!$B$233 + 0.5 *Deviation_sequence!$B$232) / (Deviation_sequence!B96 + 0.5 * Deviation_sequence!$B$232) -> 0.70377576 | C96: =(Deviation_sequence!$B$233 + 0.5 *Deviation_sequence!$B$232) / (Deviation_sequence!C96 + 0.5 * Deviation_sequence!$B$232) -> 0.65786343 | D96: =(Deviation_sequence!$B$233 + 0.5 *Deviation_sequence!$B$232) / (Deviation_sequence!D96 + 0.5 * Deviation_sequence!$B$232) -> 0.70508643 | E96: =(Deviation_sequence!$B$233 + 0.5 *Deviation_sequence!$B$232) / (Deviation_sequence!E96 + 0.5 * Deviation_sequence!$B$232) -> 0.5524128 | F96: =(Deviation_sequence!$B$233 + 0.5 *Deviation_sequence!$B$232) / (Deviation_sequence!F96 + 0.5 * Deviation_sequence!$B$232) -> 0.63286043 | G96: =(Deviation_sequence!$B$233 + 0.5 *Deviation_sequence!$B$232) / (Deviation_sequence!G96 + 0.5 * Deviation_sequence!$B$232) -> 0.55523377 | H96: =(Deviation_sequence!$B$233 + 0.5 *Deviation_sequence!$B$232) / (Deviation_sequence!H96 + 0.5 * Deviation_sequence!$B$232) -> 0.76169649 | I96: =(Deviation_sequence!$B$233 + 0.5 *Deviation_sequence!$B$232) / (Deviation_sequence!I96 + 0.5 * Deviation_sequence!$B$232) -> 0.71372908 | ... M96: =(Deviation_sequence!$B$233 + 0.5 *Deviation_sequence!$B$232) / (Deviation_sequence!M96 + 0.5 * Deviation_sequence!$B$232) -> 0.64725409 | O96: =AVERAGE(B96:M96) -> 0.65922044
N97: ratio score | O97: =AVERAGE(O68:O96) -> 0.59957823
A100: Price to BV | B100: (P/B)2025 | C100: (P/B)2024 | D100: (P/B)2023 | E100: (P/B)2022 | F100: (P/B)2021 | G100: (P/B)2020 | H100: (P/B)2019 | I100: (P/B)2018 | J100: (P/B)2017 | K100: (P/B)2016 | L100: (P/B)2015 | M100: (P/B)2014
A101: Adani Ports and Special Economic Zone Ltd | B101: =(Deviation_sequence!$B$233 + 0.5 *Deviation_sequence!$B$232) / (Deviation_sequence!B101 + 0.5 * Deviation_sequence!$B$232) -> 0.38521752 | C101: =(Deviation_sequence!$B$233 + 0.5 *Deviation_sequence!$B$232) / (Deviation_sequence!C101 + 0.5 * Deviation_sequence!$B$232) -> 0.43858572 | D101: =(Deviation_sequence!$B$233 + 0.5 *Deviation_sequence!$B$232) / (Deviation_sequence!D101 + 0.5 * Deviation_sequence!$B$232) -> 0.36896016 | E101: =(Deviation_sequence!$B$233 + 0.5 *Deviation_sequence!$B$232) / (Deviation_sequence!E101 + 0.5 * Deviation_sequence!$B$232) -> 0.39520019 | F101: =(Deviation_sequence!$B$233 + 0.5 *Deviation_sequence!$B$232) / (Deviation_sequence!F101 + 0.5 * Deviation_sequence!$B$232) -> 0.43294626 | G101: =(Deviation_sequence!$B$233 + 0.5 *Deviation_sequence!$B$232) / (Deviation_sequence!G101 + 0.5 * Deviation_sequence!$B$232) -> 0.35067042 | H101: =(Deviation_sequence!$B$233 + 0.5 *Deviation_sequence!$B$232) / (Deviation_sequence!H101 + 0.5 * Deviation_sequence!$B$232) -> 0.37750399 | I101: =(Deviation_sequence!$B$233 + 0.5 *Deviation_sequence!$B$232) / (Deviation_sequence!I101 + 0.5 * Deviation_sequence!$B$232) -> 0.38113779 | ... M101: =(Deviation_sequence!$B$233 + 0.5 *Deviation_sequence!$B$232) / (Deviation_sequence!M101 + 0.5 * Deviation_sequence!$B$232) -> 0.40468841 | O101: =AVERAGE(B101:M101) -> 0.39624185
A102: Asian Paints Ltd | B102: =(Deviation_sequence!$B$233 + 0.5 *Deviation_sequence!$B$232) / (Deviation_sequence!B102 + 0.5 * Deviation_sequence!$B$232) -> 0.57372986 | C102: =(Deviation_sequence!$B$233 + 0.5 *Deviation_sequence!$B$232) / (Deviation_sequence!C102 + 0.5 * Deviation_sequence!$B$232) -> 0.73315146 | D102: =(Deviation_sequence!$B$233 + 0.5 *Deviation_sequence!$B$232) / (Deviation_sequence!D102 + 0.5 * Deviation_sequence!$B$232) -> 0.86651217 | E102: =(Deviation_sequence!$B$233 + 0.5 *Deviation_sequence!$B$232) / (Deviation_sequence!E102 + 0.5 * Deviation_sequence!$B$232) -> 0.96768948 | F102: =(Deviation_sequence!$B$233 + 0.5 *Deviation_sequence!$B$232) / (Deviation_sequence!F102 + 0.5 * Deviation_sequence!$B$232) -> 0.93833674 | G102: =(Deviation_sequence!$B$233 + 0.5 *Deviation_sequence!$B$232) / (Deviation_sequence!G102 + 0.5 * Deviation_sequence!$B$232) -> 0.82273779 | H102: =(Deviation_sequence!$B$233 + 0.5 *Deviation_sequence!$B$232) / (Deviation_sequence!H102 + 0.5 * Deviation_sequence!$B$232) -> 0.79200675 | I102: =(Deviation_sequence!$B$233 + 0.5 *Deviation_sequence!$B$232) / (Deviation_sequence!I102 + 0.5 * Deviation_sequence!$B$232) -> 0.63683653 | ... M102: =(Deviation_sequence!$B$233 + 0.5 *Deviation_sequence!$B$232) / (Deviation_sequence!M102 + 0.5 * Deviation_sequence!$B$232) -> 0.65554569 | O102: =AVERAGE(B102:M102) -> 0.76839826
A103: AXIS Bank Ltd | B103: =(Deviation_sequence!$B$233 + 0.5 *Deviation_sequence!$B$232) / (Deviation_sequence!B103 + 0.5 * Deviation_sequence!$B$232) -> 0.35535398 | C103: =(Deviation_sequence!$B$233 + 0.5 *Deviation_sequence!$B$232) / (Deviation_sequence!C103 + 0.5 * Deviation_sequence!$B$232) -> 0.3619101 | D103: =(Deviation_sequence!$B$233 + 0.5 *Deviation_sequence!$B$232) / (Deviation_sequence!D103 + 0.5 * Deviation_sequence!$B$232) -> 0.36181333 | E103: =(Deviation_sequence!$B$233 + 0.5 *Deviation_sequence!$B$232) / (Deviation_sequence!E103 + 0.5 * Deviation_sequence!$B$232) -> 0.35817558 | F103: =(Deviation_sequence!$B$233 + 0.5 *Deviation_sequence!$B$232) / (Deviation_sequence!F103 + 0.5 * Deviation_sequence!$B$232) -> 0.371921 | G103: =(Deviation_sequence!$B$233 + 0.5 *Deviation_sequence!$B$232) / (Deviation_sequence!G103 + 0.5 * Deviation_sequence!$B$232) -> 0.33681796 | H103: =(Deviation_sequence!$B$233 + 0.5 *Deviation_sequence!$B$232) / (Deviation_sequence!H103 + 0.5 * Deviation_sequence!$B$232) -> 0.38144727 | I103: =(Deviation_sequence!$B$233 + 0.5 *Deviation_sequence!$B$232) / (Deviation_sequence!I103 + 0.5 * Deviation_sequence!$B$232) -> 0.35864901 | ... M103: =(Deviation_sequence!$B$233 + 0.5 *Deviation_sequence!$B$232) / (Deviation_sequence!M103 + 0.5 * Deviation_sequence!$B$232) -> 0.35920076 | O103: =AVERAGE(B103:M103) -> 0.36194014
A104: Bajaj Finserv Ltd | B104: =(Deviation_sequence!$B$233 + 0.5 *Deviation_sequence!$B$232) / (Deviation_sequence!B104 + 0.5 * Deviation_sequence!$B$232) -> 0.40007771 | C104: =(Deviation_sequence!$B$233 + 0.5 *Deviation_sequence!$B$232) / (Deviation_sequence!C104 + 0.5 * Deviation_sequence!$B$232) -> 0.40098131 | D104: =(Deviation_sequence!$B$233 + 0.5 *Deviation_sequence!$B$232) / (Deviation_sequence!D104 + 0.5 * Deviation_sequence!$B$232) -> 0.39022681 | E104: =(Deviation_sequence!$B$233 + 0.5 *Deviation_sequence!$B$232) / (Deviation_sequence!E104 + 0.5 * Deviation_sequence!$B$232) -> 0.46160038 | F104: =(Deviation_sequence!$B$233 + 0.5 *Deviation_sequence!$B$232) / (Deviation_sequence!F104 + 0.5 * Deviation_sequence!$B$232) -> 0.41706601 | G104: =(Deviation_sequence!$B$233 + 0.5 *Deviation_sequence!$B$232) / (Deviation_sequence!G104 + 0.5 * Deviation_sequence!$B$232) -> 0.35868247 | H104: =(Deviation_sequence!$B$233 + 0.5 *Deviation_sequence!$B$232) / (Deviation_sequence!H104 + 0.5 * Deviation_sequence!$B$232) -> 0.4097705 | I104: =(Deviation_sequence!$B$233 + 0.5 *Deviation_sequence!$B$232) / (Deviation_sequence!I104 + 0.5 * Deviation_sequence!$B$232) -> 0.39538796 | ... M104: =(Deviation_sequence!$B$233 + 0.5 *Deviation_sequence!$B$232) / (Deviation_sequence!M104 + 0.5 * Deviation_sequence!$B$232) -> 0.34892839 | O104: =AVERAGE(B104:M104) -> 0.3938547
A105: Bajaj Finance Ltd | B105: =(Deviation_sequence!$B$233 + 0.5 *Deviation_sequence!$B$232) / (Deviation_sequence!B105 + 0.5 * Deviation_sequence!$B$232) -> 0.426764 | C105: =(Deviation_sequence!$B$233 + 0.5 *Deviation_sequence!$B$232) / (Deviation_sequence!C105 + 0.5 * Deviation_sequence!$B$232) -> 0.43029768 | D105: =(Deviation_sequence!$B$233 + 0.5 *Deviation_sequence!$B$232) / (Deviation_sequence!D105 + 0.5 * Deviation_sequence!$B$232) -> 0.42672942 | E105: =(Deviation_sequence!$B$233 + 0.5 *Deviation_sequence!$B$232) / (Deviation_sequence!E105 + 0.5 * Deviation_sequence!$B$232) -> 0.54647539 | F105: =(Deviation_sequence!$B$233 + 0.5 *Deviation_sequence!$B$232) / (Deviation_sequence!F105 + 0.5 * Deviation_sequence!$B$232) -> 0.52327802 | G105: =(Deviation_sequence!$B$233 + 0.5 *Deviation_sequence!$B$232) / (Deviation_sequence!G105 + 0.5 * Deviation_sequence!$B$232) -> 0.38935733 | H105: =(Deviation_sequence!$B$233 + 0.5 *Deviation_sequence!$B$232) / (Deviation_sequence!H105 + 0.5 * Deviation_sequence!$B$232) -> 0.51818108 | I105: =(Deviation_sequence!$B$233 + 0.5 *Deviation_sequence!$B$232) / (Deviation_sequence!I105 + 0.5 * Deviation_sequence!$B$232) -> 0.44167909 | ... M105: =(Deviation_sequence!$B$233 + 0.5 *Deviation_sequence!$B$232) / (Deviation_sequence!M105 + 0.5 * Deviation_sequence!$B$232) -> 0.36917623 | O105: =AVERAGE(B105:M105) -> 0.4469687
A106: Bharat Electronics Ltd | B106: =(Deviation_sequence!$B$233 + 0.5 *Deviation_sequence!$B$232) / (Deviation_sequence!B106 + 0.5 * Deviation_sequence!$B$232) -> 0.58070298 | C106: =(Deviation_sequence!$B$233 + 0.5 *Deviation_sequence!$B$232) / (Deviation_sequence!C106 + 0.5 * Deviation_sequence!$B$232) -> 0.52960391 | D106: =(Deviation_sequence!$B$233 + 0.5 *Deviation_sequence!$B$232) / (Deviation_sequence!D106 + 0.5 * Deviation_sequence!$B$232) -> 0.41870361 | E106: =(Deviation_sequence!$B$233 + 0.5 *Deviation_sequence!$B$232) / (Deviation_sequence!E106 + 0.5 * Deviation_sequence!$B$232) -> 0.40506467 | F106: =(Deviation_sequence!$B$233 + 0.5 *Deviation_sequence!$B$232) / (Deviation_sequence!F106 + 0.5 * Deviation_sequence!$B$232) -> 0.38231806 | G106: =(Deviation_sequence!$B$233 + 0.5 *Deviation_sequence!$B$232) / (Deviation_sequence!G106 + 0.5 * Deviation_sequence!$B$232) -> 0.3527672 | H106: =(Deviation_sequence!$B$233 + 0.5 *Deviation_sequence!$B$232) / (Deviation_sequence!H106 + 0.5 * Deviation_sequence!$B$232) -> 0.3562298 | I106: =(Deviation_sequence!$B$233 + 0.5 *Deviation_sequence!$B$232) / (Deviation_sequence!I106 + 0.5 * Deviation_sequence!$B$232) -> 0.39332516 | ... M106: =(Deviation_sequence!$B$233 + 0.5 *Deviation_sequence!$B$232) / (Deviation_sequence!M106 + 0.5 * Deviation_sequence!$B$232) -> 0.3483167 | O106: =AVERAGE(B106:M106) -> 0.41312454
A107: Bharti Airtel Ltd | B107: =(Deviation_sequence!$B$233 + 0.5 *Deviation_sequence!$B$232) / (Deviation_sequence!B107 + 0.5 * Deviation_sequence!$B$232) -> 0.47458986 | C107: =(Deviation_sequence!$B$233 + 0.5 *Deviation_sequence!$B$232) / (Deviation_sequence!C107 + 0.5 * Deviation_sequence!$B$232) -> 0.46637174 | D107: =(Deviation_sequence!$B$233 + 0.5 *Deviation_sequence!$B$232) / (Deviation_sequence!D107 + 0.5 * Deviation_sequence!$B$232) -> 0.40057831 | E107: =(Deviation_sequence!$B$233 + 0.5 *Deviation_sequence!$B$232) / (Deviation_sequence!E107 + 0.5 * Deviation_sequence!$B$232) -> 0.4454657 | F107: =(Deviation_sequence!$B$233 + 0.5 *Deviation_sequence!$B$232) / (Deviation_sequence!F107 + 0.5 * Deviation_sequence!$B$232) -> 0.4073229 | G107: =(Deviation_sequence!$B$233 + 0.5 *Deviation_sequence!$B$232) / (Deviation_sequence!G107 + 0.5 * Deviation_sequence!$B$232) -> 0.38206225 | H107: =(Deviation_sequence!$B$233 + 0.5 *Deviation_sequence!$B$232) / (Deviation_sequence!H107 + 0.5 * Deviation_sequence!$B$232) -> 0.351605 | I107: =(Deviation_sequence!$B$233 + 0.5 *Deviation_sequence!$B$232) / (Deviation_sequence!I107 + 0.5 * Deviation_sequence!$B$232) -> 0.36452659 | ... M107: =(Deviation_sequence!$B$233 + 0.5 *Deviation_sequence!$B$232) / (Deviation_sequence!M107 + 0.5 * Deviation_sequence!$B$232) -> 0.3619732 | O107: =AVERAGE(B107:M107) -> 0.39710061
A108: HCL Technologies Ltd | B108: =(Deviation_sequence!$B$233 + 0.5 *Deviation_sequence!$B$232) / (Deviation_sequence!B108 + 0.5 * Deviation_sequence!$B$232) -> 0.43267491 | C108: =(Deviation_sequence!$B$233 + 0.5 *Deviation_sequence!$B$232) / (Deviation_sequence!C108 + 0.5 * Deviation_sequence!$B$232) -> 0.44118774 | D108: =(Deviation_sequence!$B$233 + 0.5 *Deviation_sequence!$B$232) / (Deviation_sequence!D108 + 0.5 * Deviation_sequence!$B$232) -> 0.39785052 | E108: =(Deviation_sequence!$B$233 + 0.5 *Deviation_sequence!$B$232) / (Deviation_sequence!E108 + 0.5 * Deviation_sequence!$B$232) -> 0.41428475 | F108: =(Deviation_sequence!$B$233 + 0.5 *Deviation_sequence!$B$232) / (Deviation_sequence!F108 + 0.5 * Deviation_sequence!$B$232) -> 0.42080458 | G108: =(Deviation_sequence!$B$233 + 0.5 *Deviation_sequence!$B$232) / (Deviation_sequence!G108 + 0.5 * Deviation_sequence!$B$232) -> 0.35779443 | H108: =(Deviation_sequence!$B$233 + 0.5 *Deviation_sequence!$B$232) / (Deviation_sequence!H108 + 0.5 * Deviation_sequence!$B$232) -> 0.38436796 | I108: =(Deviation_sequence!$B$233 + 0.5 *Deviation_sequence!$B$232) / (Deviation_sequence!I108 + 0.5 * Deviation_sequence!$B$232) -> 0.38664797 | ... M108: =(Deviation_sequence!$B$233 + 0.5 *Deviation_sequence!$B$232) / (Deviation_sequence!M108 + 0.5 * Deviation_sequence!$B$232) -> 0.43110492 | O108: =AVERAGE(B108:M108) -> 0.40580852
A109: HDFC Bank Ltd | B109: =(Deviation_sequence!$B$233 + 0.5 *Deviation_sequence!$B$232) / (Deviation_sequence!B109 + 0.5 * Deviation_sequence!$B$232) -> 0.37322962 | C109: =(Deviation_sequence!$B$233 + 0.5 *Deviation_sequence!$B$232) / (Deviation_sequence!C109 + 0.5 * Deviation_sequence!$B$232) -> 0.36312546 | D109: =(Deviation_sequence!$B$233 + 0.5 *Deviation_sequence!$B$232) / (Deviation_sequence!D109 + 0.5 * Deviation_sequence!$B$232) -> 0.37834661 | E109: =(Deviation_sequence!$B$233 + 0.5 *Deviation_sequence!$B$232) / (Deviation_sequence!E109 + 0.5 * Deviation_sequence!$B$232) -> 0.37921089 | F109: =(Deviation_sequence!$B$233 + 0.5 *Deviation_sequence!$B$232) / (Deviation_sequence!F109 + 0.5 * Deviation_sequence!$B$232) -> 0.40326581 | G109: =(Deviation_sequence!$B$233 + 0.5 *Deviation_sequence!$B$232) / (Deviation_sequence!G109 + 0.5 * Deviation_sequence!$B$232) -> 0.36358547 | H109: =(Deviation_sequence!$B$233 + 0.5 *Deviation_sequence!$B$232) / (Deviation_sequence!H109 + 0.5 * Deviation_sequence!$B$232) -> 0.39804744 | I109: =(Deviation_sequence!$B$233 + 0.5 *Deviation_sequence!$B$232) / (Deviation_sequence!I109 + 0.5 * Deviation_sequence!$B$232) -> 0.4068146 | ... M109: =(Deviation_sequence!$B$233 + 0.5 *Deviation_sequence!$B$232) / (Deviation_sequence!M109 + 0.5 * Deviation_sequence!$B$232) -> 0.39578664 | O109: =AVERAGE(B109:M109) -> 0.38704484
A110: Hindustan Unilever Ltd | B110: =(Deviation_sequence!$B$233 + 0.5 *Deviation_sequence!$B$232) / (Deviation_sequence!B110 + 0.5 * Deviation_sequence!$B$232) -> 0.55509082 | C110: =(Deviation_sequence!$B$233 + 0.5 *Deviation_sequence!$B$232) / (Deviation_sequence!C110 + 0.5 * Deviation_sequence!$B$232) -> 0.53662599 | D110: =(Deviation_sequence!$B$233 + 0.5 *Deviation_sequence!$B$232) / (Deviation_sequence!D110 + 0.5 * Deviation_sequence!$B$232) -> 0.61266446 | E110: =(Deviation_sequence!$B$233 + 0.5 *Deviation_sequence!$B$232) / (Deviation_sequence!E110 + 0.5 * Deviation_sequence!$B$232) -> 0.51593519 | F110: =(Deviation_sequence!$B$233 + 0.5 *Deviation_sequence!$B$232) / (Deviation_sequence!F110 + 0.5 * Deviation_sequence!$B$232) -> 0.60471272 | G110: =(Deviation_sequence!$B$233 + 0.5 *Deviation_sequence!$B$232) / (Deviation_sequence!G110 + 0.5 * Deviation_sequence!$B$232) -> 0.95463204 | H110: =(Deviation_sequence!$B$233 + 0.5 *Deviation_sequence!$B$232) / (Deviation_sequence!H110 + 0.5 * Deviation_sequence!$B$232) -> 0.96045921 | I110: =(Deviation_sequence!$B$233 + 0.5 *Deviation_sequence!$B$232) / (Deviation_sequence!I110 + 0.5 * Deviation_sequence!$B$232) -> 0.94121114 | ... M110: =(Deviation_sequence!$B$233 + 0.5 *Deviation_sequence!$B$232) / (Deviation_sequence!M110 + 0.5 * Deviation_sequence!$B$232) -> 0.95034269 | O110: =AVERAGE(B110:M110) -> 0.79684572
A111: ICICI Bank Ltd | B111: =(Deviation_sequence!$B$233 + 0.5 *Deviation_sequence!$B$232) / (Deviation_sequence!B111 + 0.5 * Deviation_sequence!$B$232) -> 0.3779846 | C111: =(Deviation_sequence!$B$233 + 0.5 *Deviation_sequence!$B$232) / (Deviation_sequence!C111 + 0.5 * Deviation_sequence!$B$232) -> 0.37772223 | D111: =(Deviation_sequence!$B$233 + 0.5 *Deviation_sequence!$B$232) / (Deviation_sequence!D111 + 0.5 * Deviation_sequence!$B$232) -> 0.37584787 | E111: =(Deviation_sequence!$B$233 + 0.5 *Deviation_sequence!$B$232) / (Deviation_sequence!E111 + 0.5 * Deviation_sequence!$B$232) -> 0.37561881 | F111: =(Deviation_sequence!$B$233 + 0.5 *Deviation_sequence!$B$232) / (Deviation_sequence!F111 + 0.5 * Deviation_sequence!$B$232) -> 0.37834332 | G111: =(Deviation_sequence!$B$233 + 0.5 *Deviation_sequence!$B$232) / (Deviation_sequence!G111 + 0.5 * Deviation_sequence!$B$232) -> 0.35169157 | H111: =(Deviation_sequence!$B$233 + 0.5 *Deviation_sequence!$B$232) / (Deviation_sequence!H111 + 0.5 * Deviation_sequence!$B$232) -> 0.36984314 | I111: =(Deviation_sequence!$B$233 + 0.5 *Deviation_sequence!$B$232) / (Deviation_sequence!I111 + 0.5 * Deviation_sequence!$B$232) -> 0.35455494 | ... M111: =(Deviation_sequence!$B$233 + 0.5 *Deviation_sequence!$B$232) / (Deviation_sequence!M111 + 0.5 * Deviation_sequence!$B$232) -> 0.3606016 | O111: =AVERAGE(B111:M111) -> 0.3657181
A112: Infosys Ltd | B112: =(Deviation_sequence!$B$233 + 0.5 *Deviation_sequence!$B$232) / (Deviation_sequence!B112 + 0.5 * Deviation_sequence!$B$232) -> 0.44629568 | C112: =(Deviation_sequence!$B$233 + 0.5 *Deviation_sequence!$B$232) / (Deviation_sequence!C112 + 0.5 * Deviation_sequence!$B$232) -> 0.45217303 | D112: =(Deviation_sequence!$B$233 + 0.5 *Deviation_sequence!$B$232) / (Deviation_sequence!D112 + 0.5 * Deviation_sequence!$B$232) -> 0.45984898 | E112: =(Deviation_sequence!$B$233 + 0.5 *Deviation_sequence!$B$232) / (Deviation_sequence!E112 + 0.5 * Deviation_sequence!$B$232) -> 0.56654495 | F112: =(Deviation_sequence!$B$233 + 0.5 *Deviation_sequence!$B$232) / (Deviation_sequence!F112 + 0.5 * Deviation_sequence!$B$232) -> 0.49321536 | G112: =(Deviation_sequence!$B$233 + 0.5 *Deviation_sequence!$B$232) / (Deviation_sequence!G112 + 0.5 * Deviation_sequence!$B$232) -> 0.38876141 | H112: =(Deviation_sequence!$B$233 + 0.5 *Deviation_sequence!$B$232) / (Deviation_sequence!H112 + 0.5 * Deviation_sequence!$B$232) -> 0.41334422 | I112: =(Deviation_sequence!$B$233 + 0.5 *Deviation_sequence!$B$232) / (Deviation_sequence!I112 + 0.5 * Deviation_sequence!$B$232) -> 0.38826889 | ... M112: =(Deviation_sequence!$B$233 + 0.5 *Deviation_sequence!$B$232) / (Deviation_sequence!M112 + 0.5 * Deviation_sequence!$B$232) -> 0.39684998 | O112: =AVERAGE(B112:M112) -> 0.43308195
... A129: UltraTech Cement Ltd | B129: =(Deviation_sequence!$B$233 + 0.5 *Deviation_sequence!$B$232) / (Deviation_sequence!B129 + 0.5 * Deviation_sequence!$B$232) -> 0.40629303 | C129: =(Deviation_sequence!$B$233 + 0.5 *Deviation_sequence!$B$232) / (Deviation_sequence!C129 + 0.5 * Deviation_sequence!$B$232) -> 0.40650082 | D129: =(Deviation_sequence!$B$233 + 0.5 *Deviation_sequence!$B$232) / (Deviation_sequence!D129 + 0.5 * Deviation_sequence!$B$232) -> 0.39375189 | E129: =(Deviation_sequence!$B$233 + 0.5 *Deviation_sequence!$B$232) / (Deviation_sequence!E129 + 0.5 * Deviation_sequence!$B$232) -> 0.3842375 | F129: =(Deviation_sequence!$B$233 + 0.5 *Deviation_sequence!$B$232) / (Deviation_sequence!F129 + 0.5 * Deviation_sequence!$B$232) -> 0.41535634 | G129: =(Deviation_sequence!$B$233 + 0.5 *Deviation_sequence!$B$232) / (Deviation_sequence!G129 + 0.5 * Deviation_sequence!$B$232) -> 0.3606647 | H129: =(Deviation_sequence!$B$233 + 0.5 *Deviation_sequence!$B$232) / (Deviation_sequence!H129 + 0.5 * Deviation_sequence!$B$232) -> 0.38591932 | I129: =(Deviation_sequence!$B$233 + 0.5 *Deviation_sequence!$B$232) / (Deviation_sequence!I129 + 0.5 * Deviation_sequence!$B$232) -> 0.38970637 | ... M129: =(Deviation_sequence!$B$233 + 0.5 *Deviation_sequence!$B$232) / (Deviation_sequence!M129 + 0.5 * Deviation_sequence!$B$232) -> 0.38512765 | O129: =AVERAGE(B129:M129) -> 0.3933994
N130: ratio a | O130: =AVERAGE(O101:O129) -> 0.44467551
A133: Price to Earng | B133: (P/E)2025 | C133: (P/E)2024 | D133: (P/E)2023 | E133: (P/E)2022 | F133: (P/E)2021 | G133: (P/E)2020 | H133: (P/E)2019 | I133: (P/E)2018 | J133: (P/E)2017 | K133: (P/E)2016 | L133: (P/E)2015 | M133: (P/E)2014
A134: Adani Ports and Special Economic Zone Ltd | B134: =(Deviation_sequence!$B$233 + 0.5 *Deviation_sequence!$B$232) / (Deviation_sequence!B134 + 0.5 * Deviation_sequence!$B$232) -> 0.37665845 | C134: =(Deviation_sequence!$B$233 + 0.5 *Deviation_sequence!$B$232) / (Deviation_sequence!C134 + 0.5 * Deviation_sequence!$B$232) -> 0.43713263 | D134: =(Deviation_sequence!$B$233 + 0.5 *Deviation_sequence!$B$232) / (Deviation_sequence!D134 + 0.5 * Deviation_sequence!$B$232) -> 0.38442646 | E134: =(Deviation_sequence!$B$233 + 0.5 *Deviation_sequence!$B$232) / (Deviation_sequence!E134 + 0.5 * Deviation_sequence!$B$232) -> 0.41310747 | F134: =(Deviation_sequence!$B$233 + 0.5 *Deviation_sequence!$B$232) / (Deviation_sequence!F134 + 0.5 * Deviation_sequence!$B$232) -> 0.42661443 | G134: =(Deviation_sequence!$B$233 + 0.5 *Deviation_sequence!$B$232) / (Deviation_sequence!G134 + 0.5 * Deviation_sequence!$B$232) -> 0.35375863 | H134: =(Deviation_sequence!$B$233 + 0.5 *Deviation_sequence!$B$232) / (Deviation_sequence!H134 + 0.5 * Deviation_sequence!$B$232) -> 0.37585039 | I134: =(Deviation_sequence!$B$233 + 0.5 *Deviation_sequence!$B$232) / (Deviation_sequence!I134 + 0.5 * Deviation_sequence!$B$232) -> 0.37547748 | ... M134: =(Deviation_sequence!$B$233 + 0.5 *Deviation_sequence!$B$232) / (Deviation_sequence!M134 + 0.5 * Deviation_sequence!$B$232) -> 0.38741873 | O134: =AVERAGE(B134:M134) -> 0.39004629
A135: Asian Paints Ltd | B135: =(Deviation_sequence!$B$233 + 0.5 *Deviation_sequence!$B$232) / (Deviation_sequence!B135 + 0.5 * Deviation_sequence!$B$232) -> 0.40772573 | C135: =(Deviation_sequence!$B$233 + 0.5 *Deviation_sequence!$B$232) / (Deviation_sequence!C135 + 0.5 * Deviation_sequence!$B$232) -> 0.4608966 | D135: =(Deviation_sequence!$B$233 + 0.5 *Deviation_sequence!$B$232) / (Deviation_sequence!D135 + 0.5 * Deviation_sequence!$B$232) -> 0.51391831 | E135: =(Deviation_sequence!$B$233 + 0.5 *Deviation_sequence!$B$232) / (Deviation_sequence!E135 + 0.5 * Deviation_sequence!$B$232) -> 0.7357752 | F135: =(Deviation_sequence!$B$233 + 0.5 *Deviation_sequence!$B$232) / (Deviation_sequence!F135 + 0.5 * Deviation_sequence!$B$232) -> 0.60352351 | G135: =(Deviation_sequence!$B$233 + 0.5 *Deviation_sequence!$B$232) / (Deviation_sequence!G135 + 0.5 * Deviation_sequence!$B$232) -> 0.49821638 | H135: =(Deviation_sequence!$B$233 + 0.5 *Deviation_sequence!$B$232) / (Deviation_sequence!H135 + 0.5 * Deviation_sequence!$B$232) -> 0.53803696 | I135: =(Deviation_sequence!$B$233 + 0.5 *Deviation_sequence!$B$232) / (Deviation_sequence!I135 + 0.5 * Deviation_sequence!$B$232) -> 0.47028757 | ... M135: =(Deviation_sequence!$B$233 + 0.5 *Deviation_sequence!$B$232) / (Deviation_sequence!M135 + 0.5 * Deviation_sequence!$B$232) -> 0.44164455 | O135: =AVERAGE(B135:M135) -> 0.50821281
